Workbook

Sheet CBR_pullDB
A1: Pull Database - follow KBMF source
A3: MDP Area Name | B3: Persist Table Name | C3: Test Status | D3: Remark | E3: Action | F3: status CBR
A4: dgtl_fctrng | B4: persist_dgtl_fctrng.dgtl_fctrng_v_purref | C4: Passed
A5: dgtl_fctrng | B5: persist_dgtl_fctrng.dgtl_fctrng_v_clientdebtor
A6: dgtl_fctrng | B6: persist_dgtl_fctrng.dgtl_fctrng_v_product | C6: Passed
A7: dgtl_fctrng | B7: persist_dgtl_fctrng.dgtl_fctrng_v_company
A8: dgtl_fctrng | B8: persist_dgtl_fctrng.dgtl_fctrng_v_clientlimit
A9: dgtl_fctrng | B9: persist_dgtl_fctrng.dgtl_fctrng_v_cis | C9: Passed
A10: dgtl_fctrng | B10: persist_dgtl_fctrng.dgtl_fctrng_v_interestspread | C10: Passed
A11: scf | B11: persist_scf.scf_vw_sct_book_loan
A12: scf | B12: persist_scf.scf_vw_rdt_scf_cl
A13: scf | B13: persist_scf.scf_vw_cm_fee_structure | C13: Failed | D13: Data file (47) / KBMF (37) / CBR EBAN (37) ['strstep', 'strchargefeedate', 'strremark', 'strfeecodebahtnet', 'decfeeamtsbahtnet', 'decfeeamtdbahtnet', 'strchargefeeforbahtnet', 'strfeetypebahtnet', 'strefftdatebahtnet', 'stractiveflagbahtnet'] | E13: EBAN
A14: scf | B14: persist_scf.scf_vw_scm_acct | C14: Passed
A15: scf | B15: persist_scf.scf_trading
A16: scf | B16: persist_scf.scf_customer | E16: ACN field dup
A17: scf | B17: persist_scf.scf_product_map | C17: Passed
A18: scf | B18: persist_scf.scf_vw_rdt_scf_cl_acct | C18: Passed
A19: scf | B19: persist_scf.scf_trading_acct | E19: ACN field dup
A20: ud | B20: persist_ud.ud_vw_t_su_sub_uh_ful
A21: ud | B21: persist_ud.ud_vw_kgroup_sidetexttbl
A22: ud | B22: persist_ud.ud_vw_fi_fnd_inf_ful
A23: ud | B23: persist_ud.ud_vw_flt_rl_sub_bal_enq | C23: Failed | D23: Data file 16 columns / KBMF 16 / CBR EBAN 15 columns - app_date | E23: ACN app_date >> src_pos_dt
A24: ud | B24: persist_ud.ud_vw_t_uh_uh_ful
A25: ud | B25: persist_ud.ud_vw_flt_div_pmt_inc
A26: ud | B26: persist_ud.ud_vw_transactionext
A27: ud | B27: persist_ud.ud_vw_transactioneodext
A28: ud | B28: persist_ud.ud_vw_flt_dp_div_cert_inc

Sheet UAT Test
A1: Area Name | B1: Persist Table Name | C1: Integration Approach | D1: SIT Status | E1: pos_dt | F1: SIT issue | G1: CBR revise | H1: Issues | I1: Note | J1: Owner | K1: Batch2 | L1: Batch3 | M1: passed
A2: gts | B2: persist_gts.gts_dbttnrel | C2: Plan B: Source File (EBAN) | D2: Not Start | E2: 2024-03-20 | F2: Empty file | H2: Empty file | I2: source (EBAN) | J2: P'Fon | K2: =ISNUMBER(MATCH(B2,Batch!A:A,0)) -> FALSE | L2: =ISNUMBER(MATCH(B2,Batch!B:B,0)) -> TRUE | M2: =ISNUMBER(MATCH(B2,passed!A:A,0)) -> FALSE
A3: kplus | B3: persist_kplus.kplus_view_jmobileacctcard_log | C3: Plan B: EBAN Extraction File (Push) | D3: Not Start | E3: 45363 | F3: [1-April] EBAN confirmed that on EBAN production didn't have null value for fields ''relateacctcard' and 'mobileno' Test result : TS08 will be failed [28-Mar] EBAN confirmed that on EBAN production didn't have null value for 'mobileno' TS08: Mandatory null ['relateacctcard', 'mobileno'] | G3: Pending : relateacctcard (AR_ID EBAN set null) // Action: Data source sent with encrypt then CBR to update spec | H3: New Requirement (Decrypt some record) Mandatory null | I3: [1-April] Source (EBAN) CBR | J3: Keaw | K3: =ISNUMBER(MATCH(B3,Batch!A:A,0)) -> FALSE | L3: =ISNUMBER(MATCH(B3,Batch!B:B,0)) -> TRUE | M3: =ISNUMBER(MATCH(B3,passed!A:A,0)) -> FALSE
A4: trade_na | B4: persist_trade_na.trade_na_lcr070 | C4: Plan B: Source File (EBAN) | D4: Not Start | F4: [28-Mar] data in date column is not correct as format => Pending source to confirm date data [26-Mar] Mandatory null ['lcacno', 'lclsrt', 'lcddte', 'lcinfg', 'lccndt', 'lcrvdt', 'lcspty', 'lcrspd'] CBR incorrect date format - ['lcvdte','lcddte'] Spec - yyyyMMdd data file - yyMMdd TS12 unknown date format - ['lccndt', 'lcrvdt'] => Pending source to confirm date data Source send all null, suspect that it might be wrong format as the above 2 field | G4: [28-Mar] Updated date format ['lcvdte','lcddte'] yyMMdd to be as data file => Fixed [25-Mar] Update source datasize number (added precision) => Fixed | H4: Mismatch source data format Mandatory null | I4: source (EBAN) | J4: Kaew | K4: =ISNUMBER(MATCH(B4,Batch!A:A,0)) -> FALSE | L4: =ISNUMBER(MATCH(B4,Batch!B:B,0)) -> TRUE | M4: =ISNUMBER(MATCH(B4,passed!A:A,0)) -> FALSE
A5: pcb_loan | B5: persist_pcb_loan.pcb_loan_common_product_type | C5: Plan B: Source File (EBAN) | D5: Not Start | F5: [1-April] fw target Wed 3-April [27-Mar] Framework need enhancement on header or tailor record has column more than body record | H5: Framework | I5: Framework need enhances | J5: FW | K5: =ISNUMBER(MATCH(B5,Batch!A:A,0)) -> FALSE | L5: =ISNUMBER(MATCH(B5,Batch!B:B,0)) -> TRUE | M5: =ISNUMBER(MATCH(B5,passed!A:A,0)) -> FALSE
A6: cardlink | B6: persist_cardlink.cardlink_kb1dh005_kbbcrd | C6: Plan B: Source File (DIH) | D6: Not Start | F6: [27-Mar] source 74| raw 71 | H6: Mismatch source data layout | I6: source | J6: Kaew | K6: =ISNUMBER(MATCH(B6,Batch!A:A,0)) -> FALSE | L6: =ISNUMBER(MATCH(B6,Batch!B:B,0)) -> TRUE | M6: =ISNUMBER(MATCH(B6,passed!A:A,0)) -> FALSE
A7: cardlink | B7: persist_cardlink.cardlink_kb1dh003_cpbcus | C7: Plan B: Source File (DIH) | D7: Not Start | F7: [27-Mar] source 113| raw 111 | H7: Mismatch source data layout | I7: source | J7: Kaew | K7: =ISNUMBER(MATCH(B7,Batch!A:A,0)) -> FALSE | L7: =ISNUMBER(MATCH(B7,Batch!B:B,0)) -> TRUE | M7: =ISNUMBER(MATCH(B7,passed!A:A,0)) -> FALSE
A8: cardlink | B8: persist_cardlink.cardlink_kb1dh006_kbbcus | C8: Plan B: Source File (DIH) | D8: Not Start | F8: [27-Mar] source 35| raw 28 | H8: Mismatch source data layout | I8: source | J8: Kaew | K8: =ISNUMBER(MATCH(B8,Batch!A:A,0)) -> FALSE | L8: =ISNUMBER(MATCH(B8,Batch!B:B,0)) -> TRUE | M8: =ISNUMBER(MATCH(B8,passed!A:A,0)) -> FALSE
A9: cardlink | B9: persist_cardlink.cardlink_kb1dh031_cc1d583b | C9: Plan B: Source File (EBAN) | D9: Not Start | F9: [27-Mar] Source is fixed length file. Config is set to be delimited | G9: delimited | H9: ACN | I9: [1-April] CBR | J9: Kaew M | K9: =ISNUMBER(MATCH(B9,Batch!A:A,0)) -> FALSE | L9: =ISNUMBER(MATCH(B9,Batch!B:B,0)) -> TRUE | M9: =ISNUMBER(MATCH(B9,passed!A:A,0)) -> FALSE
A10: cardlink | B10: persist_cardlink.cardlink_kb1dh007_cpahf | C10: Plan B: Source File (DIH) | D10: Not Start | F10: [27-Mar] source 21 | raw 20 | H10: Mismatch source data layout | I10: source | J10: Kaew | K10: =ISNUMBER(MATCH(B10,Batch!A:A,0)) -> FALSE | L10: =ISNUMBER(MATCH(B10,Batch!B:B,0)) -> TRUE | M10: =ISNUMBER(MATCH(B10,passed!A:A,0)) -> FALSE
A11: cardlink | B11: persist_cardlink.cardlink_kb1dh011_cc1d2027 | C11: Plan B: Source File (DIH) | D11: Not Start | F11: [27-Mar] Fixed length mapping is not correct, ref - INGT_SIT_0073 https://kasikornbankgroup.sharepoint.com/:x:/s/DocumentRepository/Data%20-%20Analytics/EVNQm3Jxo0xBlN_XYjolql0Bsq4FIiqlOg11xdBTKDqPqQ?e=BCxCeG | G11: offset | H11: Mismatch source data format | I11: [1-April] CBR | J11: Kaew | K11: =ISNUMBER(MATCH(B11,Batch!A:A,0)) -> FALSE | L11: =ISNUMBER(MATCH(B11,Batch!B:B,0)) -> TRUE | M11: =ISNUMBER(MATCH(B11,passed!A:A,0)) -> FALSE
A12: dgtl_fctrng | B12: persist_dgtl_fctrng.dgtl_fctrng_v_company | C12: Plan B: Pull DB | D12: Not Start | E12: 45372 | F12: Mismatch data layout - Data source 85 | CBR EBAN 65| KBMF 78 (field in KBMF mostly not match with data source) >> agreed to align with EBAN CBR 65 fields (diff 20 fields) Data source schema mismatches with the target table, missing the columns (data file not have): shortname, regaddr1, regaddr2, regaddr3, regzip, contactaddr1, contactaddr2, contactaddr3, contactzip, taxaddr1, taxaddr2, taxaddr3, taxzip, tel, fax, email, website, officer1, telo1, officer2, telo2, taxid, regid, regdate, regcap, paidcap, mbankcode, mbankname, mbranchcode, mbranchname, macctno, macctname, bankcode, bankname, branchcode, branchname, acctno, acctname, rbankcode, rbankname, rbranchcode, rbranchname, racctno, racctname, product, marketing, controllimit, agrno, agrdate, admissionfee, interestcode, interestspread, minfee, penalty, penaltyrate, repaymentday, recourse | G12: [28-Mar] EBAN team to recheck CBR file (เนื่องจาก column ต่างกันเยอะเกินไป) [28-Mar] Updated CBR MDP to align with CBR EBAN = 65 Pending to confirm 1. อิงตาม CBR ไม่มี date format ให้อ้างอิง => สามารถอิงจาก datafile ได้ไหม 2. มี field ใน CBR - 2 field อยู่รวมกันเช่น ApproveDate ApproveTime => ถ้าแยกคอลัมน์จะไม่ทราบ datasize/datatype สามารถอิงจาก datafile ได้ไหม [22-Mar] EBAN team confirmed to align table structure by CBR EBAN 65 fields (diff with data 20 fields) | H12: Mismatch source data layout | I12: [1 April] init spec | J12: Kaew | K12: =ISNUMBER(MATCH(B12,Batch!A:A,0)) -> FALSE | L12: =ISNUMBER(MATCH(B12,Batch!B:B,0)) -> TRUE | M12: =ISNUMBER(MATCH(B12,passed!A:A,0)) -> FALSE
A13: gts | B13: persist_gts.gts_kbgt_loan_outstanding | C13: Plan B: Source File (EBAN) | D13: Passed | E13: 45378 | F13: [1-Apr] EBAN confirmed that on EBAN production have null value for fields 'center_code', 'nxt_int_pymt_dt', 'ppymt_f' Test result : TS08 will be failed TS08: Mandatory null ['maturity_date', 'due_date', 'center_code', 'nxt_int_pymt_dt', 'ppymt_f'] Mismatch data layout (data file no header) Data source 159 /KBMF 159/CBR EBAN 157 Update CBR MDP to Align with KBMF | G13: [28-Mar] Updated CBR to align with new KBMF from EBAN team 159 fields [27-Mar] EBAN send new version of KBMF (KBMF-Batch_NTF_Loan_Outstanding_DIH_v0.0.36_20240322) | H13: Passed | K13: =ISNUMBER(MATCH(B13,Batch!A:A,0)) -> TRUE | L13: =ISNUMBER(MATCH(B13,Batch!B:B,0)) -> FALSE | M13: =ISNUMBER(MATCH(B13,passed!A:A,0)) -> TRUE
A14: gts | B14: persist_gts.gts_kbgt_limit_allocated | C14: Plan B: Source File (EBAN) | D14: Not Start | F14: Mismatch data layout with spec (data file incorrect sequence) - data file no header - column seq 21 = updated_date | G14: [1-Apr] - Enhance TS05: NUMERIC_10,7 - EBAN team provided new KBMF => Update CBR as new KBMF [28-Mar] Pending EBAN Team to update new CBR check ใน CBR EBAN seq21 = issue_date, seq22 = update_date | H14: Mismatch source data layout | I14: [1 April] Investigate | J14: Tee | K14: =ISNUMBER(MATCH(B14,Batch!A:A,0)) -> FALSE | L14: =ISNUMBER(MATCH(B14,Batch!B:B,0)) -> TRUE | M14: =ISNUMBER(MATCH(B14,passed!A:A,0)) -> FALSE
A15: kplus | B15: persist_kplus.kplus_jmobileactlog_log | C15: Plan B: EBAN Extraction File (Push) | D15: Ready to execute | F15: Mismatch data layout - Data source 31| CBR EBAN(Ref) 26| KBMF 26 [29-Mar] EBAN confirmed to use CBR_V_MB_ACTN_LOG_v.1.8.xlsx (Tab: Request Field source 509) and exclude 5 additional field by using full column name from KBMF EBAN IN Src column name LogID|TranDateTime|TranDesc|MobileNo|MobileOperator|CurrentAccountNo|SavingAccountNo|CardNoEncrypt|CardType|Language|OTP|PIN|UpgradeFlag|ThirdFundTransferFlag|ProductCode|Channel|Location|UserName|ResponseCode|Remark|UpdateType|OldUpdateValue|NewUpdateValue|IPAddress|Latitude|Longitude|AdditionalData1|AdditionalData2|AdditionalData3|AdditionalData4|AdditionalData5 ValueError: Data source schema mismatches with the target table, missing the columns: cardno | G15: [29-Mar Saranchai S.] Completed Revise CBR [29-Mar] EBAN confirmed to use CBR_V_MB_ACTN_LOG_v.1.8.xlsx (Tab: Request Field source 509) | H15: Mismatch source data layout | K15: =ISNUMBER(MATCH(B15,Batch!A:A,0)) -> FALSE | L15: =ISNUMBER(MATCH(B15,Batch!B:B,0)) -> TRUE | M15: =ISNUMBER(MATCH(B15,passed!A:A,0)) -> FALSE
A16: kplus | B16: persist_kplus.kplus_actlog_qlocal | C16: Plan B: EBAN Extraction File (Push) | D16: Not Start | F16: Mismatch data layout - Data source 31| CBR EBAN(Ref) 26| KBMF 26 [29-Mar] EBAN pending to confirm using CBR_V_MB_ACTN_LOG_v.1.8.xlsx (Tab: Request Field source xxx) and include 5 additional field by using full column name from KBMF EBAN IN Mismatch data layout src 31/ raw 26/ persist 26 Src column name LogID|TranDateTime|TranDesc|MobileNo|MobileOperator|CurrentAccountNo|SavingAccountNo|CardNoEncrypt|CardType|Language|OTP|PIN|UpgradeFlag|ThirdFundTransferFlag|ProductCode|Channel|Location|UserName|ResponseCode|Remark|UpdateType|OldUpdateValue|NewUpdateValue|IPAddress|Latitude|Longitude|AdditionalData1|AdditionalData2|AdditionalData3|AdditionalData4|AdditionalData5 TS08: Mandatory null ['logid'] ValueError: Data source schema mismatches with the target table, missing the columns: cardno | G16: [28-Mar Saranchai S.] Pending P' Jo to confirm CBR reference Revise CBR: add column AdditionalData1,AdditionalData2,AdditionalData3,AdditionalData4,AdditionalData5 | H16: Mismatch source data layout + Mandatory null | I16: source (EBAN) | J16: Kaew | K16: =ISNUMBER(MATCH(B16,Batch!A:A,0)) -> FALSE | L16: =ISNUMBER(MATCH(B16,Batch!B:B,0)) -> TRUE | M16: =ISNUMBER(MATCH(B16,passed!A:A,0)) -> FALSE
A17: ks | B17: persist_ks.ks_fundportfolio | C17: Plan B: Source File (EBAN) | D17: Ready to execute | E17: 45268 | F17: [29-Mar] TS04: column name change src_pos_dt | G17: Due to the column name change from as_of_dt to src_pos_dt Test result : TS04 will be failed | H17: Passed | K17: =ISNUMBER(MATCH(B17,Batch!A:A,0)) -> TRUE | L17: =ISNUMBER(MATCH(B17,Batch!B:B,0)) -> FALSE | M17: =ISNUMBER(MATCH(B17,passed!A:A,0)) -> FALSE
A18: mx | B18: persist_mx.mx_src_murx_deal_ar | C18: Plan B: Source File (EBAN) | D18: Not Start | E18: 45351 | F18: [29-Mar Warm last message] TS04 Error column name posn_dt -> src_pos_dt TS11 Change logic to convert persist decimal to double -> error TS12 persist re-ingest date field still 1400 Source 125/ spec 42 (data file no header) - incorrect CBR spec provided | G18: [1 Apr] TS4,TS11,TS12 failed -Sum record [28-Mar] Updated date format (yyyyMMdd) to be aligned with data file [22-Mar] Update CBE Foundateion (Reference : CBR_VP_CMB_DEAL_AR_DTL_MO_v0.1) Aligned with source and CBR EBAN 125 Fields | H18: Mismatch source data layout | I18: [1 April] Investigate | J18: Tee | K18: =ISNUMBER(MATCH(B18,Batch!A:A,0)) -> FALSE | L18: =ISNUMBER(MATCH(B18,Batch!B:B,0)) -> TRUE | M18: =ISNUMBER(MATCH(B18,passed!A:A,0)) -> FALSE
A19: pcb_dep | B19: persist_pcb_dep.pcb_dep_extrate1 | C19: Plan B: Source File (EBAN) | D19: Ready to execute | E19: 2024-03-27 | F19: [1 Apr] All passed : No need to enhance Thai encode [27-Mar] ValueError: invalid literal for int() with base 10: 'FZ0001' File has no header and footer record, but config set header and footer | G19: [28 Mar] EBAN team confirmed to remove header, tailor label | J19: No need to enhance Thai encode | K19: =ISNUMBER(MATCH(B19,Batch!A:A,0)) -> FALSE | L19: =ISNUMBER(MATCH(B19,Batch!B:B,0)) -> TRUE | M19: =ISNUMBER(MATCH(B19,passed!A:A,0)) -> FALSE
A20: pcb_dep | B20: persist_pcb_dep.pcb_dep_deptxn_db | C20: Plan B: EBAN Extraction File (Push) | D20: Passed | E20: 2024-03-19 | F20: TS12 All week-based patterns are unsupported since Spark 3.0, detected: e, Please use the SQL function EXTRACT instead | G20: [28-Mar] Updated CBR as per new version of CBR EBAN (Fixed Timestamp datasize) and EBAN confirmed timestamp format as 2024-03-24 00:00:00.0 [25-Mar] EBAN confirmed Update Datatype : ORIG_SRC_STM_ID smallint to int | H20: Passed | J20: M (Thai encode) | K20: =ISNUMBER(MATCH(B20,Batch!A:A,0)) -> TRUE | L20: =ISNUMBER(MATCH(B20,Batch!B:B,0)) -> FALSE | M20: =ISNUMBER(MATCH(B20,passed!A:A,0)) -> TRUE
A21: scf | B21: persist_scf.scf_customer | C21: Plan B: Pull DB | D21: Failed | E21: 2024-03-26 | F21: [28-Mar Tee] Source columns: 63 raw DDL columns: 60 - ['strcustaxid', 'strkbankaut', 'strcustype'] ----------------------------------------------------------------------- Mismatch data layout - Data source 63 |CBR EBAN 60 | KBMF (spec) 50 decfeeamt, decbalfeeamt, strlastfeedate, strpersoncont, strvostrocode, strmappingglno, strrmcode, strrmname, strsegment, strspokeid, strcustaxid, strkbankaut, strcustype TS04 Failed TS05 Failed TS12 Failed INGT_SIT_0063 : field ซ้ำ | G21: [28-Mar Saranchai S.] Completed Revise CBR [26-Mar] EBAN Team agreed to align table structure by CBR EBAN (diff with data 3 fields) | H21: Mismatch source data layout | I21: extraction config pull DB | J21: M | K21: =ISNUMBER(MATCH(B21,Batch!A:A,0)) -> FALSE | L21: =ISNUMBER(MATCH(B21,Batch!B:B,0)) -> TRUE | M21: =ISNUMBER(MATCH(B21,passed!A:A,0)) -> FALSE
A22: scf | B22: persist_scf.scf_vw_trading_acct | C22: Plan B: Pull DB | D22: Failed | F22: [27-Mar] Diff 3 fields from datafile (stroverdrawflg, strflagtype, strbankcode) Mismatch data layout - Data source 18 / raw 15 / persist 15 - CBR 15, KBMF 15 (CBR and KBMF are the same) | G22: [28-Mar] EBAN Team confirmed to align table structure by CBR EBAN (diff with data 3 fields) Use same KBMF (KBMF-(460)-SCM_TRADING_ACCT) | H22: Mismatch source data layout | I22: extraction config pull DB | J22: M | K22: =ISNUMBER(MATCH(B22,Batch!A:A,0)) -> FALSE | L22: =ISNUMBER(MATCH(B22,Batch!B:B,0)) -> TRUE | M22: =ISNUMBER(MATCH(B22,passed!A:A,0)) -> FALSE
A23: trade_na | B23: persist_trade_na.trade_na_src_eximar | C23: Plan B: Source File (EBAN) | D23: Not Start | E23: 45077 | F23: [28-Mar Tee] Ingestion Success TS08 Mandatory null The following mandatory column(s) contain null value: ['bill_cyc_id', 'blc_code_id', 'call_dt', 'put_dt', 'call_prc', 'put_prc', 'cc_tp_id', 'cls_bal_amt', 'clt_amt', 'clt_tp', 'cmpd_frq', 'ctr_sign_dt', 'cost_cntr', 'cntpr_nm', 'nxt_pnp_pymt_amt', 'nxt_int_pymt_amt', 'crn_stmt_bal', 'bsn_code_id', 'ip_id', 'cst_tp_id', 'dept_no', 'exn_dep_amt', 'grc_prd', 'hld_ac', 'hld_bal_amt', 'ar_hld_tp_id', 'prch_sale_ind', 'rcv_pay_ind', 'issu_dt', 'ivsm_tp', 'issur_nm', 'last_rprc_dt', 'ar_pps_tp_id', 'mtm_val', 'orig_pymt_amt', 'opn_bal_amt', 'clc_int_stop_dt', 'prd_flr_rate', 'prd_cap_rate', 'prev_stmt_bal', 'rate_cap', 'rate_flr', 'rprc_sprd_rate', 'rvrs_acr_int_dt', 'sp_itnl_rtg', 'tris_itnl_rtg', 'fitch_itnl_rtg', 'moodys_itnl_rtg', 'scr_nm', 'ln_clsfd_bot', 'tsr_rate_end_dt', 'tsr_rate', 'tsr_rate_tp_id', 'ppymt_bal_amt', 'ppymt_dt', 'ppymt_f', 'lmt_amt_rng', 'pct_non_rvl', 'ac_ofcr', 'crn_rate_fix', 'exn_mo_f', 'fwd_tp_code', 'npl_dt', 'orig_admn_rate', 'setl_dt', 'val_dt', 'yld_to_mat', 'pymt_due_dt', 'ln_clsfd', 'ac_ofcr_pd_f', 'cst_seg_id', 'ppn_dt', 'ppn_tm', 'src_stm_id', 'sub_product'] TS12 All week-based patterns are unsupported since Spark 3.0, detected: e, Please use the SQL function EXTRACT instead [28-Mar] Fixed init raw ( added record type) | H23: Mandatory null | I23: source (EBAN) | J23: P'Fon | K23: =ISNUMBER(MATCH(B23,Batch!A:A,0)) -> FALSE | L23: =ISNUMBER(MATCH(B23,Batch!B:B,0)) -> TRUE | M23: =ISNUMBER(MATCH(B23,passed!A:A,0)) -> FALSE
A24: ud | B24: persist_ud.ud_vw_t_su_sub_uh_ful | C24: Plan B: Pull DB | D24: Not Start | E24: 45379 | F24: missing the columns: src_pos_dt | G24: [29-Mar] CBR + Iinit + spec mapping (Fixed) : Updated date, timestamp format yyyy-MM-dd HH:mm:ss and yyyy-MM-dd HH:mm:ss.SSSSSS to be aligned with source data file and change to timestamp for all date in target table | H24: Mismatch source data format | I24: [1 April] Investigate | J24: Tee | K24: =ISNUMBER(MATCH(B24,Batch!A:A,0)) -> FALSE | L24: =ISNUMBER(MATCH(B24,Batch!B:B,0)) -> TRUE | M24: =ISNUMBER(MATCH(B24,passed!A:A,0)) -> FALSE
A25: ud | B25: persist_ud.ud_vw_kgroup_sidetexttbl | C25: Plan B: Pull DB | D25: Not Start | E25: 45379 | F25: [25-Mar] INCONSISTENT_BEHAVIOR_CROSS_VERSION.PARSE_DATETIME_BY_NEW_PARSER [21-Mar] src_pos_dt => Fixed | G25: [29-Mar] CBR + Iinit + spec mapping (Fixed) : Updated date, timestamp format yyyy-MM-dd HH:mm:ss and yyyy-MM-dd HH:mm:ss.SSSSSS to be aligned with source data file and change to timestamp for all date in target table | H25: Mismatch source data format | I25: [1 April] Investigate | J25: Tee | K25: =ISNUMBER(MATCH(B25,Batch!A:A,0)) -> FALSE | L25: =ISNUMBER(MATCH(B25,Batch!B:B,0)) -> TRUE | M25: =ISNUMBER(MATCH(B25,passed!A:A,0)) -> FALSE
A26: ud | B26: persist_ud.ud_vw_fi_fnd_inf_ful | C26: Plan B: Pull DB | D26: Not Start | E26: 45379 | F26: [29-Mar Tee] Detecting extra columns ['min_bal_amount'] in source dataframe compared to target database mdpuat.raw_ud.ud_vw_fi_fnd_inf_ful Data source 64 | CBR 63 |KBMF 64 | Diff 1 fields (<min_bal_amount>) [25-Mar] INCONSISTENT_BEHAVIOR_CROSS_VERSION.PARSE_DATETIME_BY_NEW_PARSER [21-Mar] src_pos_dt => Fixed | G26: [29-Mar] CBR + Iinit + spec mapping (Fixed) : Updated date, timestamp format yyyy-MM-dd HH:mm:ss and yyyy-MM-dd HH:mm:ss.SSSSSS to be aligned with source data file and change to timestamp for all date in target table | H26: Mismatch source data format | I26: [1-April] CBR | J26: Kaew | K26: =ISNUMBER(MATCH(B26,Batch!A:A,0)) -> FALSE | L26: =ISNUMBER(MATCH(B26,Batch!B:B,0)) -> TRUE | M26: =ISNUMBER(MATCH(B26,passed!A:A,0)) -> FALSE
A27: ud | B27: persist_ud.ud_vw_t_uh_uh_ful | C27: Plan B: Pull DB | D27: Not Start | E27: 45379 | F27: [25-Mar] INCONSISTENT_BEHAVIOR_CROSS_VERSION.PARSE_DATETIME_BY_NEW_PARSER | G27: [29-Mar] CBR + Iinit + spec mapping (Fixed) : Updated date, timestamp format yyyy-MM-dd HH:mm:ss and yyyy-MM-dd HH:mm:ss.SSSSSS to be aligned with source data file and change to timestamp for all date in target table | H27: Mismatch source data format | I27: [1 April] Investigate | J27: Tee | K27: =ISNUMBER(MATCH(B27,Batch!A:A,0)) -> FALSE | L27: =ISNUMBER(MATCH(B27,Batch!B:B,0)) -> TRUE | M27: =ISNUMBER(MATCH(B27,passed!A:A,0)) -> FALSE
A28: scf | B28: persist_scf.scf_vw_sct_book_loan | C28: Plan B: Pull DB | D28: Not Start | F28: [29-Mar] incorrect date format in cbr ['dtecreatedate', 'dteupddate'] => Pending EBAN to confirm on date format dtecreatedate from yyyy-MM-dd HH:mm:ss.sss -> yyyy-MM-dd HH:mm:ss.SSSSSS dteupddate inconsistent date format - yyyy-MM-dd HH:mm:ss.SSSSSS, yyyy-MM-dd HH:mm:ss => To align with data file [28-Mar Tee] Ingestion Success Mismatch data layout - Data source 96 / CBR spec 66 / KBMF 56 | G28: [1-Apr] EBAN team confirmed to use - 'dteupdate', 'dtecreatedate' = yyyy-MM-dd HH:mm:ss.SSSSSS [29Mar] 'dteupddate' data ส่งมา 2 format มีทั้ง yyyy-MM-dd HH:mm:ss และ yyyy-MM-dd HH:mm:ss.SSSSSS จาก spec จะเป็น format yyyy-MM-dd HH:mm:ss.SSS [28-Mar Saranchai S.] Completed Revise 96 fields | H28: Mismatch source data layout | I28: [1-April] CBR spec mapping | J28: Kaew | K28: =ISNUMBER(MATCH(B28,Batch!A:A,0)) -> FALSE | L28: =ISNUMBER(MATCH(B28,Batch!B:B,0)) -> TRUE | M28: =ISNUMBER(MATCH(B28,passed!A:A,0)) -> FALSE
A29: scf | B29: persist_scf.scf_trading | C29: Plan B: Pull DB | D29: Ready to execute | E29: 45377 | F29: Mismatch data layout - Data source 73 / CBR spec 66 / KBMF 73 - To update CBR MDP to be aligned with KBMF 73 | G29: [29-Mar] Updated CBR as new KBMF from EBAN (KBMF-(460)-SCM_TRADING (1)) | H29: Mismatch source data layout | K29: =ISNUMBER(MATCH(B29,Batch!A:A,0)) -> FALSE | L29: =ISNUMBER(MATCH(B29,Batch!B:B,0)) -> TRUE | M29: =ISNUMBER(MATCH(B29,passed!A:A,0)) -> FALSE
A30: pcb_dep | B30: persist_pcb_dep.pcb_dep_cb2d0005_odencitd_sam | C30: Plan B: Source File (EBAN) - fix length | D30: Passed | E30: 2024-03-26 | F30: [27-Mar] extra column 'filler' from fixed length mapping [28-Mar] To add filler in init raw | H30: Passed | J30: M (Thai encode) | K30: =ISNUMBER(MATCH(B30,Batch!A:A,0)) -> TRUE | L30: =ISNUMBER(MATCH(B30,Batch!B:B,0)) -> FALSE | M30: =ISNUMBER(MATCH(B30,passed!A:A,0)) -> TRUE
A31: cardlink | B31: persist_cardlink.cardlink_kb1dh002_cpbcrd | C31: Plan B: Source File (DIH) | D31: Not Start | F31: [29-Mar] source 465| raw 466 Data source xx | CBR xx |KBMF xx | [Fixed] 2 hours processed, needs upsize also | H31: Mismatch source data layout | I31: [1-April] CBR | J31: Kaew | K31: =ISNUMBER(MATCH(B31,Batch!A:A,0)) -> FALSE | L31: =ISNUMBER(MATCH(B31,Batch!B:B,0)) -> TRUE | M31: =ISNUMBER(MATCH(B31,passed!A:A,0)) -> FALSE
A32: ud | B32: persist_ud.ud_vw_flt_div_pmt_inc | C32: Plan B: Pull DB | D32: Not Start | E32: 45379 | F32: [28-Mar Tee] Schema is already correct, format in ingest spec is not correct yet. Ex. of Date data: 2024-03-19 00:00:00, Timestamp data: 2024-03-15 01:12:55.605384 | G32: [29-Mar] CBR + Iinit + spec mapping (Fixed) : Updated date, timestamp format yyyy-MM-dd HH:mm:ss and yyyy-MM-dd HH:mm:ss.SSSSSS to be aligned with source data file and change to timestamp for all date in target table Update MDP CBR align from KBMF data xx/ KBMF 32 / CBR 32 (sequence is different between CBR and KBMF) [27-Mar] Update CBR to align with KBMF source and fixed init, spec | H32: Mismatch source data layout | I32: [1 April] Investigate | J32: Tee | K32: =ISNUMBER(MATCH(B32,Batch!A:A,0)) -> FALSE | L32: =ISNUMBER(MATCH(B32,Batch!B:B,0)) -> TRUE | M32: =ISNUMBER(MATCH(B32,passed!A:A,0)) -> FALSE
A33: cardlink | B33: persist_cardlink.cardlink_kb1dh019_cc1t377 | C33: Plan B: Source File (EBAN) | D33: Not Start | F33: [28-Mar] Missing mandatory field in cbr [27-Mar] Done | G33: Mandatory = O btw to check CBR EBAN (source) | H33: Missing mandatory field | I33: [1-April] CBR | J33: Kaew | K33: =ISNUMBER(MATCH(B33,Batch!A:A,0)) -> FALSE | L33: =ISNUMBER(MATCH(B33,Batch!B:B,0)) -> TRUE | M33: =ISNUMBER(MATCH(B33,passed!A:A,0)) -> FALSE
A34: cardlink | B34: persist_cardlink.cardlink_kb1dh038_cc1d5012 | C34: Plan B: Source File (EBAN) | D34: Not Start | F34: [28-Mar] Missing mandatory field in cbr [27-Mar] Done | G34: Mandatory = O btw to check CBR EBAN (source) | H34: Missing mandatory field | I34: [1-April] CBR | J34: Kaew | K34: =ISNUMBER(MATCH(B34,Batch!A:A,0)) -> FALSE | L34: =ISNUMBER(MATCH(B34,Batch!B:B,0)) -> TRUE | M34: =ISNUMBER(MATCH(B34,passed!A:A,0)) -> FALSE
A35: cardlink | B35: persist_cardlink.cardlink_kb1dh013_eptrans | C35: Plan B: Source File (DIH) | D35: Not Start | F35: [28-Mar Tee] invalid literal for int() with base 10: '53|' -> fixed length mapping for footer is not correct - INGT_SIT_0076 Fixed length data, but delimiter at footer ? [27-Mar] UnicodeError [28-Mar M] Implement Encoding to job config for ANSI | G35: Offset btw to check CBR EBAN (source) | H35: Unicode | I35: [1-April] CBR fixed length mapping | J35: Kaew M | K35: =ISNUMBER(MATCH(B35,Batch!A:A,0)) -> FALSE | L35: =ISNUMBER(MATCH(B35,Batch!B:B,0)) -> TRUE | M35: =ISNUMBER(MATCH(B35,passed!A:A,0)) -> FALSE
A36: cardlink | B36: persist_cardlink.cardlink_kb1dh017_cpamt | C36: Plan B: Source File (EBAN) | D36: Not Start | E36: 45378 | F36: [28-Mar] TS08: Mandatory null ['dh017_cmt_card_nmbr'] [27-Mar] UnicodeError [28-Mar M] Implement Encoding to job config for ANSI [28-Mar Tee] Ingestion success | H36: Unicode Mandatory null | I36: source (EBAN) | J36: P'Fon | K36: =ISNUMBER(MATCH(B36,Batch!A:A,0)) -> FALSE | L36: =ISNUMBER(MATCH(B36,Batch!B:B,0)) -> TRUE | M36: =ISNUMBER(MATCH(B36,passed!A:A,0)) -> FALSE
A37: cardlink | B37: persist_cardlink.cardlink_kb1dh018_cpsrptt | C37: Plan B: Source File (EBAN) | D37: Not Start | F37: [1-Apr Tee] multiple encoding char for multiple files [27-Mar] UnicodeError | H37: Unicode | I37: Unicode | J37: M | K37: =ISNUMBER(MATCH(B37,Batch!A:A,0)) -> FALSE | L37: =ISNUMBER(MATCH(B37,Batch!B:B,0)) -> TRUE | M37: =ISNUMBER(MATCH(B37,passed!A:A,0)) -> FALSE
A38: cardlink | B38: persist_cardlink.cardlink_kb1dh014_cc1dmpgl | C38: Plan B: Source File (DIH) | D38: Not Start | F38: [28-Mar Tee] fixed length mapping for footer is not correct - INGT_SIT_0077 Fixed length data, but delimiter at footer ? [27-Mar] UnicodeError [28-Mar M] Implement Encoding to job config for ANSI | H38: Unicode | I38: [1-April] CBR fixed length mapping | J38: Kaew M | K38: =ISNUMBER(MATCH(B38,Batch!A:A,0)) -> FALSE | L38: =ISNUMBER(MATCH(B38,Batch!B:B,0)) -> TRUE | M38: =ISNUMBER(MATCH(B38,passed!A:A,0)) -> FALSE
A39: fxb | B39: persist_fxb.fxb_midrate_kbank | C39: Plan B: Source File (DIH) | D39: Not Start | E39: 2024-03-13 2024-03-14 | F39: [29-Mar Tee] Rerun job success with PKs and remove upd_tms from raw [28 Mar -M] - Fixed config update PK List to Job config [27Mar] incremental file failed with no primary key [26 Mar] rerun with incremental = initial error Control File Record Count 232 is not equal to spark dataframe record count 229 [25 Mar - warm] - to rerun wiht incremental = initial ( also lpm_as400) DependencyCheckError: Failed dependency checking: The job is not ready due to failures in prerequisite jobs. ingest_fxb_midrate_kbank_d - 2024-03-12 (Delta) Initial file 232 records | G39: [1 April] Due to the columns 'record_type', 'filler_1', 'filler_2' will stored and present only in raw Test result : TS03 will be failed [27 Mar] source confirmed to Updated primary key fields "underlying currency", "base currency" | H39: Missing Primary Key | I39: [1 April] Investigate | J39: Tee | K39: =ISNUMBER(MATCH(B39,Batch!A:A,0)) -> FALSE | L39: =ISNUMBER(MATCH(B39,Batch!B:B,0)) -> TRUE | M39: =ISNUMBER(MATCH(B39,passed!A:A,0)) -> FALSE
A40: lec | B40: persist_lec.lec_lecp_lec3d18 | C40: Plan B: Source File (EBAN) | D40: Passed | E40: 43910 | F40: [28-Mar Tee] ingestion success -fw log control file count = None -CBR have filler column -Data no filler -Raw no filler column [28-Mar - M] Updated fixed_length_mapping | H40: Passed | K40: =ISNUMBER(MATCH(B40,Batch!A:A,0)) -> TRUE | L40: =ISNUMBER(MATCH(B40,Batch!B:B,0)) -> FALSE | M40: =ISNUMBER(MATCH(B40,passed!A:A,0)) -> TRUE
A41: ud | B41: persist_ud.ud_ka_fundcode | C41: Plan B: Source File (EBAN) | D41: Not Start | E41: 45379 | F41: [28-Mar Tee] raw DDL column name should be same as source column name when source header column flag is "Y", ingestion spec also; => Pending to confirm with source (rectype and rcrd_tp) [27-Mar] Extraction config and ingestion config are not correct. Date is specified in filename. Should be KA_FundCode_YYYYMMDD.txt [29-Mar M] Update diffrent filter columns (transform_to_raw_task) now | I41: [1 April] Investigate | J41: Tee | K41: =ISNUMBER(MATCH(B41,Batch!A:A,0)) -> FALSE | L41: =ISNUMBER(MATCH(B41,Batch!B:B,0)) -> TRUE | M41: =ISNUMBER(MATCH(B41,passed!A:A,0)) -> FALSE
A42: ud | B42: persist_ud.ud_privatefund_balance | C42: Plan B: Source File (EBAN) | D42: Not Start | E42: 45379 | F42: [28-Mar Tee] Data file does not have header column flag, but header is specified => CBR Fixed [27-Mar] Extraction config and ingestion config are not correct. Date is specified in filename. Should be PrivateFund_Balance_YYYYMMDD.txt [28-Mar] Update file name both extraction config , job config [29-Mar M] Update columns name flag to False (N) | I42: [1 April] Investigate | J42: Tee | K42: =ISNUMBER(MATCH(B42,Batch!A:A,0)) -> FALSE | L42: =ISNUMBER(MATCH(B42,Batch!B:B,0)) -> TRUE | M42: =ISNUMBER(MATCH(B42,passed!A:A,0)) -> FALSE
A43: cardlink | B43: persist_cardlink.cardlink_kb1dh037_cpccpf_p | C43: Plan B: Source File (EBAN) | D43: Not Start | F43: File does not exist for transferred | H43: Empty file | I43: source (EBAN) | J43: P'Fon | K43: =ISNUMBER(MATCH(B43,Batch!A:A,0)) -> FALSE | L43: =ISNUMBER(MATCH(B43,Batch!B:B,0)) -> TRUE | M43: =ISNUMBER(MATCH(B43,passed!A:A,0)) -> FALSE
A44: cardlink | B44: persist_cardlink.cardlink_kb1dh001_cp1t170_01 | C44: Plan B: Source File (DIH) | D44: Not Start | F44: Changed to KAS layout | H44: KAS layout | I44: KAS layout | K44: =ISNUMBER(MATCH(B44,Batch!A:A,0)) -> FALSE | L44: =ISNUMBER(MATCH(B44,Batch!B:B,0)) -> FALSE | M44: =ISNUMBER(MATCH(B44,passed!A:A,0)) -> FALSE
A45: cardlink | B45: persist_cardlink.cardlink_kb1dh032_addtype | C45: Plan B: Source File (DIH) | D45: Not Start | F45: Changed to KAS layout | H45: KAS layout | I45: KAS layout | K45: =ISNUMBER(MATCH(B45,Batch!A:A,0)) -> FALSE | L45: =ISNUMBER(MATCH(B45,Batch!B:B,0)) -> FALSE | M45: =ISNUMBER(MATCH(B45,passed!A:A,0)) -> FALSE
A46: cardlink | B46: persist_cardlink.cardlink_la10s_oatkn | C46: Plan B: Source File (EBAN) | D46: Not Start | F46: Changed to KAS layout | H46: KAS layout | I46: KAS layout | K46: =ISNUMBER(MATCH(B46,Batch!A:A,0)) -> FALSE | L46: =ISNUMBER(MATCH(B46,Batch!B:B,0)) -> FALSE | M46: =ISNUMBER(MATCH(B46,passed!A:A,0)) -> FALSE
A47: cardlink | B47: persist_cardlink.cardlink_kb1dh037_cptcpf_p | C47: Plan B: Source File (EBAN) | D47: Not Start | F47: File does not exist for transferred | H47: Empty file | I47: source (EBAN) | J47: P'Fon | K47: =ISNUMBER(MATCH(B47,Batch!A:A,0)) -> FALSE | L47: =ISNUMBER(MATCH(B47,Batch!B:B,0)) -> TRUE | M47: =ISNUMBER(MATCH(B47,passed!A:A,0)) -> FALSE
A48: cardlink | B48: persist_cardlink.cardlink_kb1dh045_cc1d289g | C48: Plan B: Source File (EBAN) | D48: Not Start | F48: [29-Mar] CBR does not have mandatory flag [28-Mar Tee] ingestion success but pending upsize cluster [27-Mar] Control-M set wrong job config path | G48: Mandatory = O btw to check CBR EBAN (source) | H48: Control-M | I48: [1-April] CBR | J48: Kaew | K48: =ISNUMBER(MATCH(B48,Batch!A:A,0)) -> FALSE | L48: =ISNUMBER(MATCH(B48,Batch!B:B,0)) -> TRUE | M48: =ISNUMBER(MATCH(B48,passed!A:A,0)) -> FALSE
A49: cardlink | B49: persist_cardlink.cardlink_kb1dh028_ccixpt | C49: Plan B: Source File (EBAN) | D49: Not Start | F49: Changed to KAS layout | H49: KAS layout | I49: KAS layout | K49: =ISNUMBER(MATCH(B49,Batch!A:A,0)) -> FALSE | L49: =ISNUMBER(MATCH(B49,Batch!B:B,0)) -> FALSE | M49: =ISNUMBER(MATCH(B49,passed!A:A,0)) -> FALSE
A50: cardlink | B50: persist_cardlink.cardlink_kb1dh029_ccatabla | C50: Plan B: Source File (EBAN) | D50: Not Start | F50: Changed to KAS layout | H50: KAS layout | I50: KAS layout | K50: =ISNUMBER(MATCH(B50,Batch!A:A,0)) -> FALSE | L50: =ISNUMBER(MATCH(B50,Batch!B:B,0)) -> FALSE | M50: =ISNUMBER(MATCH(B50,passed!A:A,0)) -> FALSE
A51: cardlink | B51: persist_cardlink.cardlink_kb1dh030_cuptran | C51: Plan B: Source File (EBAN) | D51: Not Start | F51: Changed to KAS layout | H51: KAS layout | I51: KAS layout | K51: =ISNUMBER(MATCH(B51,Batch!A:A,0)) -> FALSE | L51: =ISNUMBER(MATCH(B51,Batch!B:B,0)) -> FALSE | M51: =ISNUMBER(MATCH(B51,passed!A:A,0)) -> FALSE
A52: cardlink | B52: persist_cardlink.cardlink_kb1dh012_cpcah | C52: Plan B: Source File (EBAN) | D52: Not Start | F52: Changed to KAS layout | H52: KAS layout | I52: KAS layout | K52: =ISNUMBER(MATCH(B52,Batch!A:A,0)) -> FALSE | L52: =ISNUMBER(MATCH(B52,Batch!B:B,0)) -> FALSE | M52: =ISNUMBER(MATCH(B52,passed!A:A,0)) -> FALSE
A53: cardlink | B53: persist_cardlink.cardlink_kb1dh020_cc1d582d | C53: Plan B: Source File (EBAN) | D53: Not Start | F53: Changed to KAS layout | H53: KAS layout | I53: KAS layout | K53: =ISNUMBER(MATCH(B53,Batch!A:A,0)) -> FALSE | L53: =ISNUMBER(MATCH(B53,Batch!B:B,0)) -> FALSE | M53: =ISNUMBER(MATCH(B53,passed!A:A,0)) -> FALSE
A54: cardlink | B54: persist_cardlink.cardlink_kb1dh021_cc1d582s | C54: Plan B: Source File (EBAN) | D54: Not Start | F54: Changed to KAS layout | H54: KAS layout | I54: KAS layout | K54: =ISNUMBER(MATCH(B54,Batch!A:A,0)) -> FALSE | L54: =ISNUMBER(MATCH(B54,Batch!B:B,0)) -> FALSE | M54: =ISNUMBER(MATCH(B54,passed!A:A,0)) -> FALSE
A55: cardlink | B55: persist_cardlink.cardlink_kb1dh022_oadcc32 | C55: Plan B: Source File (EBAN) | D55: Not Start | F55: Changed to KAS layout | H55: KAS layout | I55: KAS layout | K55: =ISNUMBER(MATCH(B55,Batch!A:A,0)) -> FALSE | L55: =ISNUMBER(MATCH(B55,Batch!B:B,0)) -> FALSE | M55: =ISNUMBER(MATCH(B55,passed!A:A,0)) -> FALSE
A56: cardlink | B56: persist_cardlink.cardlink_kb1dh024_cc1d560 | C56: Plan B: Source File (EBAN) | D56: Not Start | F56: Changed to KAS layout | H56: KAS layout | I56: KAS layout | K56: =ISNUMBER(MATCH(B56,Batch!A:A,0)) -> FALSE | L56: =ISNUMBER(MATCH(B56,Batch!B:B,0)) -> FALSE | M56: =ISNUMBER(MATCH(B56,passed!A:A,0)) -> FALSE
A57: cardlink | B57: persist_cardlink.cardlink_kb1dh025_cpcah | C57: Plan B: Source File (EBAN) | D57: Not Start | F57: [28-Mar Tee] Need upsize cluster again | G57: [1 Apr] Fatal error: The Python kernel is unresponsive in Test Notebook | H57: Cluster size (out of mem) | I57: [1 April] Investigate | J57: Tee | K57: =ISNUMBER(MATCH(B57,Batch!A:A,0)) -> FALSE | L57: =ISNUMBER(MATCH(B57,Batch!B:B,0)) -> TRUE | M57: =ISNUMBER(MATCH(B57,passed!A:A,0)) -> FALSE
A58: dgtl_fctrng | B58: persist_dgtl_fctrng.dgtl_fctrng_v_clientdebtor | C58: Plan B: Pull DB | D58: Not Start | E58: 45372 | F58: [1 April] TS05, TS11 failed [27-Mar] Control file is correct, need to find way to read source | I58: [1 April] Investigate | J58: Tee | K58: =ISNUMBER(MATCH(B58,Batch!A:A,0)) -> FALSE | L58: =ISNUMBER(MATCH(B58,Batch!B:B,0)) -> TRUE | M58: =ISNUMBER(MATCH(B58,passed!A:A,0)) -> FALSE
A59: gts | B59: persist_gts.gts_kbgt_cont_outstanding | C59: Plan B: Source File (EBAN) | D59: Failed | E59: 2024-03-27 | F59: [29-Mar Tee] Detecting extra columns ['_c157', '_c158'] in source dataframe compared to target database mdpuat.raw_gts.gts_kbgt_cont_outstanding [28-Mar Tee] orig_admn_rate is missing from ingestion spec => Fixed Mismatch data layout (data file no header) Data source 159 /CBR EBAN 157 / KBMF 163 >> check column EBAN prod (156) diff 'header3' | G59: [1-April] To check updated KBMF (159 fields) 'SRC_SYSTEM' [25-Mar] EBAN team confirmed to align spec from CBR 157 fields ('header3' >> rec_type) | H59: Mismatch source data layout | I59: [1 April] init spec | J59: Kaew | K59: =ISNUMBER(MATCH(B59,Batch!A:A,0)) -> FALSE | L59: =ISNUMBER(MATCH(B59,Batch!B:B,0)) -> TRUE | M59: =ISNUMBER(MATCH(B59,passed!A:A,0)) -> FALSE
A60: scf | B60: persist_scf.scf_vw_cm_fee_structure | C60: Plan B: Pull DB | D60: Failed | E60: 45371 | F60: [28-Mar] TS03, 04, 12 Failed To Update CBR field INTPERIODDAYS => decimal(3,0) to smallint(3) TBD Spec with EBAN TS03: num col mismatch - data source(47) / KBMF (37) / CBR EBAN (37) ['strstep', 'strchargefeedate', 'strremark', 'strfeecodebahtnet', 'decfeeamtsbahtnet', 'decfeeamtdbahtnet', 'strchargefeeforbahtnet', 'strfeetypebahtnet', 'strefftdatebahtnet', 'stractiveflagbahtnet'] TS04: col name mismatch | G60: [27-Mar] KBMF source and CBR EBAN are in the same layout [21-Mar] EBAN Team agreed to align table structure by CBR EBAN (diff with data 10 fields) | H60: Mismatch source data layout | I60: extraction config pull DB | J60: M | K60: =ISNUMBER(MATCH(B60,Batch!A:A,0)) -> FALSE | L60: =ISNUMBER(MATCH(B60,Batch!B:B,0)) -> TRUE | M60: =ISNUMBER(MATCH(B60,passed!A:A,0)) -> FALSE
A61: ud | B61: persist_ud.ud_vw_transactionext | C61: Plan B: Pull DB | D61: Not Start | E61: 45379 | F61: [25-Mar] INCONSISTENT_BEHAVIOR_CROSS_VERSION.PARSE_DATETIME_BY_NEW_PARSER [21-Mar] src_pos_dt => Fixed | G61: [29-Mar] CBR + Iinit + spec mapping (Fixed) : Updated date, timestamp format yyyy-MM-dd HH:mm:ss and yyyy-MM-dd HH:mm:ss.SSSSSS to be aligned with source data file and change to timestamp for all date in target table | H61: Mismatch source data format | I61: [1 April] Investigate | J61: Tee | K61: =ISNUMBER(MATCH(B61,Batch!A:A,0)) -> FALSE | L61: =ISNUMBER(MATCH(B61,Batch!B:B,0)) -> TRUE | M61: =ISNUMBER(MATCH(B61,passed!A:A,0)) -> FALSE
A62: ud | B62: persist_ud.ud_vw_transactioneodext | C62: Plan B: Pull DB | D62: Not Start | E62: 45379 | F62: [25-Mar] INCONSISTENT_BEHAVIOR_CROSS_VERSION.PARSE_DATETIME_BY_NEW_PARSER [21-Mar] src_pos_dt => Fixed | G62: [29-Mar] CBR + Iinit + spec mapping (Fixed) : Updated date, timestamp format yyyy-MM-dd HH:mm:ss and yyyy-MM-dd HH:mm:ss.SSSSSS to be aligned with source data file and change to timestamp for all date in target table | H62: Mismatch source data format | I62: [1 April] Investigate | J62: Tee | K62: =ISNUMBER(MATCH(B62,Batch!A:A,0)) -> FALSE | L62: =ISNUMBER(MATCH(B62,Batch!B:B,0)) -> TRUE | M62: =ISNUMBER(MATCH(B62,passed!A:A,0)) -> FALSE
A63: cardlink | B63: persist_cardlink.cardlink_kb1dh023_lbpttrn | C63: Plan B: Source File (EBAN) | D63: Passed | F63: [27-Mar] Done | H63: Passed | K63: =ISNUMBER(MATCH(B63,Batch!A:A,0)) -> TRUE | L63: =ISNUMBER(MATCH(B63,Batch!B:B,0)) -> FALSE | M63: =ISNUMBER(MATCH(B63,passed!A:A,0)) -> TRUE
A64: cardlink | B64: persist_cardlink.cardlink_kb1dh039_ccnd5012 | C64: Plan B: Source File (EBAN) | D64: Not Start | F64: [28-Mar] incorrect CBR column name dh039_trans_dest_amt and dh039_retrvl_ref_nbr are in the same cell for both source and target [27-Mar] Done | H64: Mismatch source data layout | I64: [1-April] CBR | J64: Kaew | K64: =ISNUMBER(MATCH(B64,Batch!A:A,0)) -> FALSE | L64: =ISNUMBER(MATCH(B64,Batch!B:B,0)) -> TRUE | M64: =ISNUMBER(MATCH(B64,passed!A:A,0)) -> FALSE
A65: cardlink | B65: persist_cardlink.cardlink_lb1dh002_lbcrd | C65: Plan B: Source File (DIH) | D65: Not Start | E65: 2024-03-26 | F65: [28-Mar] Missing mandatory field in cbr [27-Mar] Done | G65: Mandatory = O btw to check CBR EBAN (source) | H65: Mismatch source data layout | I65: [1-April] CBR | J65: Kaew | K65: =ISNUMBER(MATCH(B65,Batch!A:A,0)) -> FALSE | L65: =ISNUMBER(MATCH(B65,Batch!B:B,0)) -> TRUE | M65: =ISNUMBER(MATCH(B65,passed!A:A,0)) -> FALSE
A66: ks | B66: persist_ks.ks_fundmaster | C66: Plan B: Source File (EBAN) | D66: Passed | E66: 45268 | F66: [29-Mar] TS04: column name change src_pos_dt | G66: Due to the column name change from as_of_dt to src_pos_dt Test result : TS04 will be failed | H66: Passed | K66: =ISNUMBER(MATCH(B66,Batch!A:A,0)) -> TRUE | L66: =ISNUMBER(MATCH(B66,Batch!B:B,0)) -> FALSE | M66: =ISNUMBER(MATCH(B66,passed!A:A,0)) -> TRUE
A67: ks | B67: persist_ks.ks_custprofile | C67: Plan B: Source File (EBAN) | D67: Ready to execute | E67: 45268 | F67: [1-April] - Due to the column name change from 'as_of_d't to 'src_pos_dt' Test result : TS04 will be failed - EBAN confirmed that on EBAN production didn't have null value for field 'card_id' Test result : TS08 will be failed [29-Mar] TS04: column name change src_pos_dt TS:08 Mandatory null ['card_id'] [27-Mar] Source timestamp data sent milliseconds, but timestamp format is yyyy-MM-dd HH:mm:ss. Using yyyy-MM-dd HH:mm:ss.SSSSSS instead ref - INGT_SIT_0074 https://kasikornbankgroup.sharepoint.com/:x:/s/DocumentRepository/Data%20-%20Analytics/EVNQm3Jxo0xBlN_XYjolql0Bsq4FIiqlOg11xdBTKDqPqQ?e=BCxCeG | G67: [28-Mar] EBAN confirmed to align date format with datafile yyyy-MM-dd HH:mm:ss.SSSSSS | H67: Passed | K67: =ISNUMBER(MATCH(B67,Batch!A:A,0)) -> TRUE | L67: =ISNUMBER(MATCH(B67,Batch!B:B,0)) -> FALSE | M67: =ISNUMBER(MATCH(B67,passed!A:A,0)) -> FALSE
A68: pcb_loan | B68: persist_pcb_loan.pcb_loan_common_account_info | C68: Plan B: Source File (EBAN) | D68: Not Start | E68: 2024-03-20 | F68: [28-Mar] TS08: Mandatory null ['coa_rspl_cntr_pnp', 'coa_fnc_pnp', 'ac_adr1', 'tfr_br', 'resch_flg', 'ren_code'] [27-Mar] Ingestion success 1. Mismatch data layout (no header column) - Data source 162/ CBR EBAN Spec 161 / KBMF 162 2. Mandatory null ['coa_rspl_cntr_pnp', 'coa_fnc_pnp', 'ac_adr1', 'tfr_br', 'resch_flg', 'ren_code'] [27-Mar] Ingestion success | G68: [27-Mar] Updated CBR to align with KBMF source and fixed init raw [26-Mar] Align with KBMF source (added filler to the last column) | H68: Mismatch source data layout Mandatory null Unicode | I68: pending re-order for Thai encode | J68: M (Thai encode) | K68: =ISNUMBER(MATCH(B68,Batch!A:A,0)) -> FALSE | L68: =ISNUMBER(MATCH(B68,Batch!B:B,0)) -> TRUE | M68: =ISNUMBER(MATCH(B68,passed!A:A,0)) -> FALSE
A69: kplus | B69: persist_kplus.kplus_view_jmobile_log | C69: Plan B: EBAN Extraction File (Push) | D69: Passed | E69: 2024-03-25 | F69: TS04: source send col name with encrypt TS05: tinyint -> tinyint? ValueError: Data source schema mismatches with the target table, missing the columns: registeredcardno [28-Mar] Rerun success | G69: [28-Mar] Revised datatype from tinyint to smallint in Target table | H69: Passed | K69: =ISNUMBER(MATCH(B69,Batch!A:A,0)) -> TRUE | L69: =ISNUMBER(MATCH(B69,Batch!B:B,0)) -> FALSE | M69: =ISNUMBER(MATCH(B69,passed!A:A,0)) -> TRUE
A70: cardlink_acq | B70: persist_cardlink_acq.cardlink_acq_ci1d1166_crdhd | C70: Plan B: Source File (DIH) | D70: Passed | E70: 45377 | F70: TS08 Mandatory null ['issuedate', 'firstyearfee'] [28-Mar] EBAN confirmed that on EBAN production have null value for fields 'issuedate' Test result : TS08 will be failed | H70: Passed | K70: =ISNUMBER(MATCH(B70,Batch!A:A,0)) -> TRUE | L70: =ISNUMBER(MATCH(B70,Batch!B:B,0)) -> FALSE | M70: =ISNUMBER(MATCH(B70,passed!A:A,0)) -> TRUE
A71: cardlink_acq | B71: persist_cardlink_acq.cardlink_acq_ci1d1178_crdreg | C71: Plan B: Source File (EBAN) | D71: Failed | E71: 45371 | F71: TS08 Mandatory null ['issuedate', 'firstyearfee'] | H71: Mandatory null | I71: pending re-order for Thai encode | J71: M | K71: =ISNUMBER(MATCH(B71,Batch!A:A,0)) -> FALSE | L71: =ISNUMBER(MATCH(B71,Batch!B:B,0)) -> TRUE | M71: =ISNUMBER(MATCH(B71,passed!A:A,0)) -> FALSE
A72: cardlink_acq | B72: persist_cardlink_acq.cardlink_acq_ci1d1167_cardtype | C72: Plan B: Source File (DIH) | D72: Passed | E72: 2024-03-20 | H72: Passed | K72: =ISNUMBER(MATCH(B72,Batch!A:A,0)) -> FALSE | L72: =ISNUMBER(MATCH(B72,Batch!B:B,0)) -> FALSE | M72: =ISNUMBER(MATCH(B72,passed!A:A,0)) -> TRUE
A73: dgtl_fctrng | B73: persist_dgtl_fctrng.dgtl_fctrng_fact_acct | C73: Plan B: Source File (EBAN) | D73: Not Start | E73: 43580 | F73: [1-April] - To enhance TS05 : number(10) >> expected_result bigint - To enhance TS11: sum record - EBAN confirmed that on EBAN production have null value for fields 'last_int_pymt_dt', 'last_pnp_pymt_dt', 'nxt_int_pymt_dt' Test result : TS08 will be failed [26 Mar] TS08 Mandatory null ['last_int_pymt_dt', 'last_pnp_pymt_dt', 'nxt_int_pymt_dt'] [Fixed] INGT_SIT_0062: A column or function parameter with name `dpd-prin` cannot be resolved | H73: Mandatory null | I73: [1 April] Investigate | J73: Tee | K73: =ISNUMBER(MATCH(B73,Batch!A:A,0)) -> FALSE | L73: =ISNUMBER(MATCH(B73,Batch!B:B,0)) -> TRUE | M73: =ISNUMBER(MATCH(B73,passed!A:A,0)) -> FALSE
A74: dgtl_fctrng | B74: persist_dgtl_fctrng.dgtl_fctrng_v_purref | C74: Plan B: Pull DB | D74: Passed | E74: 2024-03-20 | H74: Passed | K74: =ISNUMBER(MATCH(B74,Batch!A:A,0)) -> FALSE | L74: =ISNUMBER(MATCH(B74,Batch!B:B,0)) -> FALSE | M74: =ISNUMBER(MATCH(B74,passed!A:A,0)) -> TRUE
A75: dgtl_fctrng | B75: persist_dgtl_fctrng.dgtl_fctrng_v_product | C75: Plan B: Pull DB | D75: Passed | E75: 2024-03-20 | H75: Passed | K75: =ISNUMBER(MATCH(B75,Batch!A:A,0)) -> FALSE | L75: =ISNUMBER(MATCH(B75,Batch!B:B,0)) -> FALSE | M75: =ISNUMBER(MATCH(B75,passed!A:A,0)) -> TRUE
A76: dgtl_fctrng | B76: persist_dgtl_fctrng.dgtl_fctrng_v_clientlimit | C76: Plan B: Pull DB | D76: Passed | E76: 2024-03-20 | F76: Primary Key Duplicate ['orgcode', 'clientcode', 'startdate', 'seq'] [25-Mar] Source confirmed add PK for 'limittype' | G76: [25-Mar] Source confirmed add PK for 'limittype' | H76: Passed | K76: =ISNUMBER(MATCH(B76,Batch!A:A,0)) -> FALSE | L76: =ISNUMBER(MATCH(B76,Batch!B:B,0)) -> FALSE | M76: =ISNUMBER(MATCH(B76,passed!A:A,0)) -> TRUE
A77: dgtl_fctrng | B77: persist_dgtl_fctrng.dgtl_fctrng_v_cis | C77: Plan B: Pull DB | D77: Passed | E77: 2024-03-20 | H77: Passed | K77: =ISNUMBER(MATCH(B77,Batch!A:A,0)) -> FALSE | L77: =ISNUMBER(MATCH(B77,Batch!B:B,0)) -> FALSE | M77: =ISNUMBER(MATCH(B77,passed!A:A,0)) -> TRUE
A78: dgtl_fctrng | B78: persist_dgtl_fctrng.dgtl_fctrng_v_interestspread | C78: Plan B: Pull DB | D78: Passed | E78: 2024-03-20 | F78: float column display 0.00 in test vs 0 in sql | H78: Passed | K78: =ISNUMBER(MATCH(B78,Batch!A:A,0)) -> FALSE | L78: =ISNUMBER(MATCH(B78,Batch!B:B,0)) -> FALSE | M78: =ISNUMBER(MATCH(B78,passed!A:A,0)) -> TRUE
A79: fcd | B79: persist_fcd.fcd_ar | C79: Plan B: Source File (EBAN) | D79: Passed | E79: 45371 | F79: [27 Mar] TS05 datatype 9(11)V9(5) แปลงเป็นdecimal16,2 หรือ decimal 16,5 - fixed Data source 68 / CBR 67 / KBMF 68 TS03: count col mismatch TS04: col name mismatch TS12: thai encoder - from source | G79: [27-Mar] Updated CBR to decimal 16,5 and fixed init, spec [25-Mar] EBAN confirmed to align spec from KBMF 68 fields | H79: Unicode | K79: =ISNUMBER(MATCH(B79,Batch!A:A,0)) -> TRUE | L79: =ISNUMBER(MATCH(B79,Batch!B:B,0)) -> FALSE | M79: =ISNUMBER(MATCH(B79,passed!A:A,0)) -> TRUE
A80: gts | B80: persist_gts.gts_kbgt_limit | C80: Plan B: Source File (EBAN) | D80: Passed | E80: 45370 | F80: TS08:Mandatory null ['facility_description', 'approverid', 'makerid'] [25-Mar] EBAN confirmed that on prodution don't have null value for all field | H80: Passed | K80: =ISNUMBER(MATCH(B80,Batch!A:A,0)) -> FALSE | L80: =ISNUMBER(MATCH(B80,Batch!B:B,0)) -> FALSE | M80: =ISNUMBER(MATCH(B80,passed!A:A,0)) -> TRUE
A81: gts | B81: persist_gts.gts_dbtl4xl6 | C81: Plan B: Source File (EBAN) | D81: Passed | E81: 2024-03-20 | H81: Passed | K81: =ISNUMBER(MATCH(B81,Batch!A:A,0)) -> FALSE | L81: =ISNUMBER(MATCH(B81,Batch!B:B,0)) -> FALSE | M81: =ISNUMBER(MATCH(B81,passed!A:A,0)) -> TRUE
A82: hris | B82: persist_hris.hris_staff_accnt_vw | C82: Plan B: Source File (EBAN) | D82: Passed | E82: 2024-03-26 | F82: [27-Mar] AssertionError: Control File Record Count 20789 is not equal to spark dataframe record count 20788 [26 Mar] extraction error แก้ extraction config , job config, CBR จาก hris_staff_accnt_vw_YYYYMMDD.txt เป็น extraction config : HRIS_STAFF_ACCNT_{{ptn_yyyy}}{{ptn_mm}}{{ptn_dd}}.* CBR: HRIS_STAFF_ACCNT_YYYYMMDD.txt [27Mar] -Fixed both extraction and job config about name extraction config : HRIS_STAFF_ACCNT_{{ptn_yyyy}}{{ptn_mm}}{{ptn_dd}}.* CBR: HRIS_STAFF_ACCNT_YYYYMMDD.txt - Fixed Columns name flag Y ->> N | G82: [26 Mar] CBR updated Column Name Flag from "Y" to "N" to CBR_Ingestion_hris_staff_accnt_vw_v02_00_00 | H82: Passed | K82: =ISNUMBER(MATCH(B82,Batch!A:A,0)) -> TRUE | L82: =ISNUMBER(MATCH(B82,Batch!B:B,0)) -> FALSE | M82: =ISNUMBER(MATCH(B82,passed!A:A,0)) -> TRUE
A83: kplus | B83: persist_kplus.kplus_view_balancealertreglog_log | C83: Plan B: EBAN Extraction File (Push) | D83: Passed | E83: 43318 | H83: Passed | K83: =ISNUMBER(MATCH(B83,Batch!A:A,0)) -> FALSE | L83: =ISNUMBER(MATCH(B83,Batch!B:B,0)) -> FALSE | M83: =ISNUMBER(MATCH(B83,passed!A:A,0)) -> TRUE
A84: kplus | B84: persist_kplus.kplus_jmobiletranloghd | C84: Plan B: EBAN Extraction File (Push) | D84: Failed | E84: 45376 | F84: [2 Apr] Spec format : yyyy-MM-dd HH:mm:ss.SSS Data source: - datetime : yyyy-MM-dd HH:mm:ss - duedate : yyyy-MM-dd HH:mm:ss and 'NULL' value field: datetime, duedate ที่ persist view แสดงเป็น 1400-01-01 00:00:00.000 | H84: Mismatch source data format | I84: source (EBAN) | J84: P'Fon | K84: =ISNUMBER(MATCH(B84,Batch!A:A,0)) -> FALSE | L84: =ISNUMBER(MATCH(B84,Batch!B:B,0)) -> TRUE | M84: =ISNUMBER(MATCH(B84,passed!A:A,0)) -> FALSE
A85: kplus | B85: persist_kplus.kplus_view_simbankbankinfo_log | C85: Plan B: EBAN Extraction File (Push) | D85: Passed | E85: 45361 | F85: SUCCESS - 2024-03-10 | H85: Passed | K85: =ISNUMBER(MATCH(B85,Batch!A:A,0)) -> FALSE | L85: =ISNUMBER(MATCH(B85,Batch!B:B,0)) -> FALSE | M85: =ISNUMBER(MATCH(B85,passed!A:A,0)) -> TRUE
A86: lpm_wrtoff | B86: persist_lpm_wrtoff.lpm_wrtoff_pscp_wo_wo1d04h_sam | C86: Plan B: Source File (EBAN) | D86: Not Start | F86: Pending enhance file .SAM | H86: Unicode | I86: [1 April] Investigate | J86: Tee | K86: =ISNUMBER(MATCH(B86,Batch!A:A,0)) -> FALSE | L86: =ISNUMBER(MATCH(B86,Batch!B:B,0)) -> FALSE | M86: =ISNUMBER(MATCH(B86,passed!A:A,0)) -> FALSE
A87: mx | B87: persist_mx.mx_mktevent | C87: Plan B: Source File (EBAN) | D87: Passed | E87: 45314 | H87: Passed | K87: =ISNUMBER(MATCH(B87,Batch!A:A,0)) -> FALSE | L87: =ISNUMBER(MATCH(B87,Batch!B:B,0)) -> FALSE | M87: =ISNUMBER(MATCH(B87,passed!A:A,0)) -> TRUE
A88: mx | B88: persist_mx.mx_mmlivemat | C88: Plan B: Source File (EBAN) | D88: Passed | E88: 2024-03-21 | F88: prinamt - inconsistant floating point ( decimal type) Source 42/ spec 41 (data file no header) >> Add field 'ctpy_full_name' => Fixed | H88: Passed | K88: =ISNUMBER(MATCH(B88,Batch!A:A,0)) -> FALSE | L88: =ISNUMBER(MATCH(B88,Batch!B:B,0)) -> FALSE | M88: =ISNUMBER(MATCH(B88,passed!A:A,0)) -> TRUE
A89: mx | B89: persist_mx.mx_report_limit_ctp_funded_forint | C89: Plan B: Source File (EBAN) | D89: Passed | E89: 45370 | H89: Passed | K89: =ISNUMBER(MATCH(B89,Batch!A:A,0)) -> FALSE | L89: =ISNUMBER(MATCH(B89,Batch!B:B,0)) -> FALSE | M89: =ISNUMBER(MATCH(B89,passed!A:A,0)) -> TRUE
A90: mx | B90: persist_mx.mx_report_limit_pse_forint | C90: Plan B: Source File (EBAN) | D90: Passed | E90: 45370 | H90: Passed | K90: =ISNUMBER(MATCH(B90,Batch!A:A,0)) -> FALSE | L90: =ISNUMBER(MATCH(B90,Batch!B:B,0)) -> FALSE | M90: =ISNUMBER(MATCH(B90,passed!A:A,0)) -> TRUE
A91: mx | B91: persist_mx.mx_report_limit_se_forint | C91: Plan B: Source File (EBAN) | D91: Passed | E91: 45370 | H91: Passed | K91: =ISNUMBER(MATCH(B91,Batch!A:A,0)) -> FALSE | L91: =ISNUMBER(MATCH(B91,Batch!B:B,0)) -> FALSE | M91: =ISNUMBER(MATCH(B91,passed!A:A,0)) -> TRUE
A92: mx | B92: persist_mx.mx_reset_lp_ctp_funded_forint | C92: Plan B: Source File (EBAN) | D92: Passed | E92: 45370 | F92: Mandatory null ['counterparty_staus'] | H92: Passed | K92: =ISNUMBER(MATCH(B92,Batch!A:A,0)) -> FALSE | L92: =ISNUMBER(MATCH(B92,Batch!B:B,0)) -> FALSE | M92: =ISNUMBER(MATCH(B92,passed!A:A,0)) -> TRUE
A93: mx | B93: persist_mx.mx_reset_mplcde_forint | C93: Plan B: Source File (EBAN) | D93: Passed | E93: 45370 | F93: Mandatory null ['counterparty_staus'] | H93: Passed | K93: =ISNUMBER(MATCH(B93,Batch!A:A,0)) -> FALSE | L93: =ISNUMBER(MATCH(B93,Batch!B:B,0)) -> FALSE | M93: =ISNUMBER(MATCH(B93,passed!A:A,0)) -> TRUE
A94: mx | B94: persist_mx.mx_limiteffective | C94: Plan B: Source File (EBAN) | D94: Passed | E94: 45370 | H94: Passed | K94: =ISNUMBER(MATCH(B94,Batch!A:A,0)) -> FALSE | L94: =ISNUMBER(MATCH(B94,Batch!B:B,0)) -> FALSE | M94: =ISNUMBER(MATCH(B94,passed!A:A,0)) -> TRUE
A95: pcb_dep | B95: persist_pcb_dep.pcb_dep_src_pf_ar_sa_dly | C95: Plan B: Source File (EBAN) | D95: Not Start | F95: Mandatory null ['pcb_int_idnx', 'tax_owner'] [25-Mar] EBAN confirmed that on prodution have null value for field 'pcb_int_idnx' TS12: thai encoding - from source - order 2024-03-24 | H95: Mandatory null | I95: pending re-order for Thai encode | J95: M (Thai encode) | K95: =ISNUMBER(MATCH(B95,Batch!A:A,0)) -> FALSE | L95: =ISNUMBER(MATCH(B95,Batch!B:B,0)) -> TRUE | M95: =ISNUMBER(MATCH(B95,passed!A:A,0)) -> FALSE
A96: pcb_dep | B96: persist_pcb_dep.pcb_dep_src_pf_ar_ca_dly | C96: Plan B: Source File (EBAN) | D96: Not Start | F96: TS08: Mandatory null ['cls_dt', 'bsn_code_id', 'psbk_no', 'neg_cmpd_frq_unit', 'eff_int_rate_tp_id'] TS12: thai encoding - from source - order 2024-03-24 | H96: Mandatory null | I96: pending re-order for Thai encode | J96: M (Thai encode) | K96: =ISNUMBER(MATCH(B96,Batch!A:A,0)) -> FALSE | L96: =ISNUMBER(MATCH(B96,Batch!B:B,0)) -> TRUE | M96: =ISNUMBER(MATCH(B96,passed!A:A,0)) -> FALSE
A97: pcb_dep | B97: persist_pcb_dep.pcb_dep_src_pf_ar_fx_dly | C97: Plan B: Source File (EBAN) | D97: Failed | E97: 2024-03-20 | F97: TS12: thai encoding - from source - order 2024-03-24 [25 Mar 24 Warm] - All format DATE, TIMESTAMP incorrect Spec - timestamp : yyyy-MM-dd HH:mm:ss Data : yyyyMMdd [Kate] - Check Data : ภาษาไทย Eban สามารถแสดงผลได้ตามปกติ - TC12 : Field src_pos_dt,opn_dt,eff_dt,mat_dt,last_cst_avy_dt,last_int_pymt_dt แสดงปี คศ เป็น 1400-01-01T00:00:00+07:00 | G97: [26-Mar] EBAN Team agreed to refer spec for date datatype as data source (Convert spec from timestamp to date yyyyMMdd) | H97: Mismatch source data format | I97: pending re-order for Thai encode | J97: M (Thai encode) | K97: =ISNUMBER(MATCH(B97,Batch!A:A,0)) -> FALSE | L97: =ISNUMBER(MATCH(B97,Batch!B:B,0)) -> TRUE | M97: =ISNUMBER(MATCH(B97,passed!A:A,0)) -> FALSE
A98: pcb_dep | B98: persist_pcb_dep.pcb_dep_src_pf_ar_sf_dly | C98: Plan B: Source File (EBAN) | D98: Failed | E98: 2024-03-20 | F98: TS12: thai encoding - from source - order 2024-03-24 | H98: Unicode | I98: pending re-order for Thai encode | J98: M (Thai encode) | K98: =ISNUMBER(MATCH(B98,Batch!A:A,0)) -> FALSE | L98: =ISNUMBER(MATCH(B98,Batch!B:B,0)) -> TRUE | M98: =ISNUMBER(MATCH(B98,passed!A:A,0)) -> FALSE
A99: pcb_dep | B99: persist_pcb_dep.pcb_dep_src_pf_txn_mis_eft_dly | C99: Plan B: Source File (EBAN) | D99: Not Start | F99: TS08: Mandatory null ['fm_ar_id', 'txn_tel_fee', 'fm_ar_domc_br_no', 'fm_coa_pd_ftr_code', 'eft_chk_nbr'] TS12: thai encoding - from source - order 2024-03-24 | H99: Mandatory null | I99: pending re-order for Thai encode | J99: M (Thai encode) | K99: =ISNUMBER(MATCH(B99,Batch!A:A,0)) -> FALSE | L99: =ISNUMBER(MATCH(B99,Batch!B:B,0)) -> TRUE | M99: =ISNUMBER(MATCH(B99,passed!A:A,0)) -> FALSE
A100: pcb_dep | B100: persist_pcb_dep.pcb_dep_cls500029 | C100: Plan B: Source File (EBAN) | D100: Not Start | F100: [1 April] All TS passed; except TS12 Thai language [28-Mar] No header and footer, but header and footer are specified in job config => Source to confirm Control File Record Count is not equal to spark dataframe record count [1-April M] Fixed jobconfig (header/tailer) | H100: Mismatch source data layout | I100: pending re-order for Thai encode | J100: M (Thai encode) | K100: =ISNUMBER(MATCH(B100,Batch!A:A,0)) -> FALSE | L100: =ISNUMBER(MATCH(B100,Batch!B:B,0)) -> TRUE | M100: =ISNUMBER(MATCH(B100,passed!A:A,0)) -> FALSE
...

Sheet Detail1
A1: Details for Count of Persist Table Name - Note: Framework need enhances, Batch3: TRUE
A3: Area Name | B3: Persist Table Name | C3: Integration Approach | D3: SIT Status | E3: pos_dt | F3: SIT issue | G3: CBR revise | H3: Issues | I3: Note | J3: Owner | K3: Batch2 | L3: Batch3 | M3: passed
A4: pcb_loan | B4: persist_pcb_loan.pcb_loan_common_product_type | C4: Plan B: Source File (EBAN) | D4: Not Start | F4: [1-April] fw target Wed 3-April [27-Mar] Framework need enhancement on header or tailor record has column more than body record | H4: Framework | I4: Framework need enhances | J4: FW | K4: FALSE | L4: TRUE | M4: FALSE

Sheet Detail2
A1: Details for Count of Persist Table Name - Note: [1 April] Investigate, Batch3: TRUE
A3: Area Name | B3: Persist Table Name | C3: Integration Approach | D3: SIT Status | E3: pos_dt | F3: SIT issue | G3: CBR revise | H3: Issues | I3: Note | J3: Owner | K3: Batch2 | L3: Batch3 | M3: passed
A4: ud | B4: persist_ud.ud_vw_flt_dp_div_cert_inc | C4: Plan B: Pull DB | D4: Not Start | E4: 45379 | F4: TS05: datatype mismatch TS12: date and timestamp field - All format DATE, TIMESTAMP incorrect Spec : yyyyMMdd HHmmss Data : yyyy-MM-dd HH:mm:ss, yyyy-MM-dd HH:mm:ss.SSSSSS | G4: [28-Mar] Updated Data Type+ Format for Target table for 4 fields to Timestamp - effective_date_of_transfer - extraction_date - dividend_processing_date - bookclosingdate | H4: Mismatch source data format | I4: [1 April] Investigate | J4: Tee | K4: FALSE | L4: TRUE | M4: FALSE
A5: dgtl_fctrng | B5: persist_dgtl_fctrng.dgtl_fctrng_fact_acct | C5: Plan B: Source File (EBAN) | D5: Not Start | E5: 43580 | F5: [1-April] - To enhance TS05 : number(10) >> expected_result bigint - To enhance TS11: sum record - EBAN confirmed that on EBAN production have null value for fields 'last_int_pymt_dt', 'last_pnp_pymt_dt', 'nxt_int_pymt_dt' Test result : TS08 will be failed [26 Mar] TS08 Mandatory null ['last_int_pymt_dt', 'last_pnp_pymt_dt', 'nxt_int_pymt_dt'] [Fixed] INGT_SIT_0062: A column or function parameter with name `dpd-prin` cannot be resolved | H5: Mandatory null | I5: [1 April] Investigate | J5: Tee | K5: FALSE | L5: TRUE | M5: FALSE
A6: ud | B6: persist_ud.ud_vw_transactioneodext | C6: Plan B: Pull DB | D6: Not Start | E6: 45379 | F6: [25-Mar] INCONSISTENT_BEHAVIOR_CROSS_VERSION.PARSE_DATETIME_BY_NEW_PARSER [21-Mar] src_pos_dt => Fixed | G6: [29-Mar] CBR + Iinit + spec mapping (Fixed) : Updated date, timestamp format yyyy-MM-dd HH:mm:ss and yyyy-MM-dd HH:mm:ss.SSSSSS to be aligned with source data file and change to timestamp for all date in target table | H6: Mismatch source data format | I6: [1 April] Investigate | J6: Tee | K6: FALSE | L6: TRUE | M6: FALSE
A7: ud | B7: persist_ud.ud_vw_transactionext | C7: Plan B: Pull DB | D7: Not Start | E7: 45379 | F7: [25-Mar] INCONSISTENT_BEHAVIOR_CROSS_VERSION.PARSE_DATETIME_BY_NEW_PARSER [21-Mar] src_pos_dt => Fixed | G7: [29-Mar] CBR + Iinit + spec mapping (Fixed) : Updated date, timestamp format yyyy-MM-dd HH:mm:ss and yyyy-MM-dd HH:mm:ss.SSSSSS to be aligned with source data file and change to timestamp for all date in target table | H7: Mismatch source data format | I7: [1 April] Investigate | J7: Tee | K7: FALSE | L7: TRUE | M7: FALSE
A8: dgtl_fctrng | B8: persist_dgtl_fctrng.dgtl_fctrng_v_clientdebtor | C8: Plan B: Pull DB | D8: Not Start | E8: 45372 | F8: [1 April] TS05, TS11 failed [27-Mar] Control file is correct, need to find way to read source | I8: [1 April] Investigate | J8: Tee | K8: FALSE | L8: TRUE | M8: FALSE
A9: cardlink | B9: persist_cardlink.cardlink_kb1dh025_cpcah | C9: Plan B: Source File (EBAN) | D9: Not Start | F9: [28-Mar Tee] Need upsize cluster again | G9: [1 Apr] Fatal error: The Python kernel is unresponsive in Test Notebook | H9: Cluster size (out of mem) | I9: [1 April] Investigate | J9: Tee | K9: FALSE | L9: TRUE | M9: FALSE
A10: ud | B10: persist_ud.ud_privatefund_balance | C10: Plan B: Source File (EBAN) | D10: Not Start | E10: 45379 | F10: [28-Mar Tee] Data file does not have header column flag, but header is specified => CBR Fixed [27-Mar] Extraction config and ingestion config are not correct. Date is specified in filename. Should be PrivateFund_Balance_YYYYMMDD.txt [28-Mar] Update file name both extraction config , job config [29-Mar M] Update columns name flag to False (N) | I10: [1 April] Investigate | J10: Tee | K10: FALSE | L10: TRUE | M10: FALSE
A11: ud | B11: persist_ud.ud_ka_fundcode | C11: Plan B: Source File (EBAN) | D11: Not Start | E11: 45379 | F11: [28-Mar Tee] raw DDL column name should be same as source column name when source header column flag is "Y", ingestion spec also; => Pending to confirm with source (rectype and rcrd_tp) [27-Mar] Extraction config and ingestion config are not correct. Date is specified in filename. Should be KA_FundCode_YYYYMMDD.txt [29-Mar M] Update diffrent filter columns (transform_to_raw_task) now | I11: [1 April] Investigate | J11: Tee | K11: FALSE | L11: TRUE | M11: FALSE
A12: fxb | B12: persist_fxb.fxb_midrate_kbank | C12: Plan B: Source File (DIH) | D12: Not Start | E12: 2024-03-13 2024-03-14 | F12: [29-Mar Tee] Rerun job success with PKs and remove upd_tms from raw [28 Mar -M] - Fixed config update PK List to Job config [27Mar] incremental file failed with no primary key [26 Mar] rerun with incremental = initial error Control File Record Count 232 is not equal to spark dataframe record count 229 [25 Mar - warm] - to rerun wiht incremental = initial ( also lpm_as400) DependencyCheckError: Failed dependency checking: The job is not ready due to failures in prerequisite jobs. ingest_fxb_midrate_kbank_d - 2024-03-12 (Delta) Initial file 232 records | G12: [1 April] Due to the columns 'record_type', 'filler_1', 'filler_2' will stored and present only in raw Test result : TS03 will be failed [27 Mar] source confirmed to Updated primary key fields "underlying currency", "base currency" | H12: Missing Primary Key | I12: [1 April] Investigate | J12: Tee | K12: FALSE | L12: TRUE | M12: FALSE
A13: ud | B13: persist_ud.ud_vw_flt_div_pmt_inc | C13: Plan B: Pull DB | D13: Not Start | E13: 45379 | F13: [28-Mar Tee] Schema is already correct, format in ingest spec is not correct yet. Ex. of Date data: 2024-03-19 00:00:00, Timestamp data: 2024-03-15 01:12:55.605384 | G13: [29-Mar] CBR + Iinit + spec mapping (Fixed) : Updated date, timestamp format yyyy-MM-dd HH:mm:ss and yyyy-MM-dd HH:mm:ss.SSSSSS to be aligned with source data file and change to timestamp for all date in target table Update MDP CBR align from KBMF data xx/ KBMF 32 / CBR 32 (sequence is different between CBR and KBMF) [27-Mar] Update CBR to align with KBMF source and fixed init, spec | H13: Mismatch source data layout | I13: [1 April] Investigate | J13: Tee | K13: FALSE | L13: TRUE | M13: FALSE
A14: ud | B14: persist_ud.ud_vw_t_uh_uh_ful | C14: Plan B: Pull DB | D14: Not Start | E14: 45379 | F14: [25-Mar] INCONSISTENT_BEHAVIOR_CROSS_VERSION.PARSE_DATETIME_BY_NEW_PARSER | G14: [29-Mar] CBR + Iinit + spec mapping (Fixed) : Updated date, timestamp format yyyy-MM-dd HH:mm:ss and yyyy-MM-dd HH:mm:ss.SSSSSS to be aligned with source data file and change to timestamp for all date in target table | H14: Mismatch source data format | I14: [1 April] Investigate | J14: Tee | K14: FALSE | L14: TRUE | M14: FALSE
A15: ud | B15: persist_ud.ud_vw_kgroup_sidetexttbl | C15: Plan B: Pull DB | D15: Not Start | E15: 45379 | F15: [25-Mar] INCONSISTENT_BEHAVIOR_CROSS_VERSION.PARSE_DATETIME_BY_NEW_PARSER [21-Mar] src_pos_dt => Fixed | G15: [29-Mar] CBR + Iinit + spec mapping (Fixed) : Updated date, timestamp format yyyy-MM-dd HH:mm:ss and yyyy-MM-dd HH:mm:ss.SSSSSS to be aligned with source data file and change to timestamp for all date in target table | H15: Mismatch source data format | I15: [1 April] Investigate | J15: Tee | K15: FALSE | L15: TRUE | M15: FALSE
A16: gts | B16: persist_gts.gts_kbgt_limit_allocated | C16: Plan B: Source File (EBAN) | D16: Not Start | F16: Mismatch data layout with spec (data file incorrect sequence) - data file no header - column seq 21 = updated_date | G16: [1-Apr] - Enhance TS05: NUMERIC_10,7 - EBAN team provided new KBMF => Update CBR as new KBMF [28-Mar] Pending EBAN Team to update new CBR check ใน CBR EBAN seq21 = issue_date, seq22 = update_date | H16: Mismatch source data layout | I16: [1 April] Investigate | J16: Tee | K16: FALSE | L16: TRUE | M16: FALSE
A17: ud | B17: persist_ud.ud_vw_t_su_sub_uh_ful | C17: Plan B: Pull DB | D17: Not Start | E17: 45379 | F17: missing the columns: src_pos_dt | G17: [29-Mar] CBR + Iinit + spec mapping (Fixed) : Updated date, timestamp format yyyy-MM-dd HH:mm:ss and yyyy-MM-dd HH:mm:ss.SSSSSS to be aligned with source data file and change to timestamp for all date in target table | H17: Mismatch source data format | I17: [1 April] Investigate | J17: Tee | K17: FALSE | L17: TRUE | M17: FALSE
A18: mx | B18: persist_mx.mx_src_murx_deal_ar | C18: Plan B: Source File (EBAN) | D18: Not Start | E18: 45351 | F18: [29-Mar Warm last message] TS04 Error column name posn_dt -> src_pos_dt TS11 Change logic to convert persist decimal to double -> error TS12 persist re-ingest date field still 1400 Source 125/ spec 42 (data file no header) - incorrect CBR spec provided | G18: [1 Apr] TS4,TS11,TS12 failed -Sum record [28-Mar] Updated date format (yyyyMMdd) to be aligned with data file [22-Mar] Update CBE Foundateion (Reference : CBR_VP_CMB_DEAL_AR_DTL_MO_v0.1) Aligned with source and CBR EBAN 125 Fields | H18: Mismatch source data layout | I18: [1 April] Investigate | J18: Tee | K18: FALSE | L18: TRUE | M18: FALSE
A22: persist_gts.gts_kbgt_limit_allocated | B22: =ISNUMBER(MATCH(A22,Table1[Persist Table Name],0)) -> TRUE
A23: persist_mx.mx_src_murx_deal_ar | B23: =ISNUMBER(MATCH(A23,Table1[Persist Table Name],0)) -> TRUE
A24: persist_ud.ud_vw_t_su_sub_uh_ful | B24: =ISNUMBER(MATCH(A24,Table1[Persist Table Name],0)) -> TRUE
A25: persist_ud.ud_vw_kgroup_sidetexttbl | B25: =ISNUMBER(MATCH(A25,Table1[Persist Table Name],0)) -> TRUE
A26: persist_ud.ud_vw_t_uh_uh_ful | B26: =ISNUMBER(MATCH(A26,Table1[Persist Table Name],0)) -> TRUE
A27: persist_ud.ud_vw_flt_div_pmt_inc | B27: =ISNUMBER(MATCH(A27,Table1[Persist Table Name],0)) -> TRUE
A28: persist_fxb.fxb_midrate_kbank | B28: =ISNUMBER(MATCH(A28,Table1[Persist Table Name],0)) -> TRUE
A29: persist_ud.ud_ka_fundcode | B29: =ISNUMBER(MATCH(A29,Table1[Persist Table Name],0)) -> TRUE
A30: persist_ud.ud_privatefund_balance | B30: =ISNUMBER(MATCH(A30,Table1[Persist Table Name],0)) -> TRUE
A31: persist_cardlink.cardlink_kb1dh025_cpcah | B31: =ISNUMBER(MATCH(A31,Table1[Persist Table Name],0)) -> TRUE
A32: persist_dgtl_fctrng.dgtl_fctrng_v_clientdebtor | B32: =ISNUMBER(MATCH(A32,Table1[Persist Table Name],0)) -> TRUE
A33: persist_ud.ud_vw_transactionext | B33: =ISNUMBER(MATCH(A33,Table1[Persist Table Name],0)) -> TRUE
... A37: persist_ud.ud_vw_flt_dp_div_cert_inc | B37: =ISNUMBER(MATCH(A37,Table1[Persist Table Name],0)) -> TRUE

Sheet Status
A1: Batch3 | B1: TRUE | E1: Batch3 | F1: TRUE
A3: SIT Status | B3: Issues | C3: Count of Persist Table Name | E3: Note | F3: Count of Persist Table Name
A4: Not Start | B4: Missing Primary Key | C4: 1 | E4: [1 April] Investigate | F4: 15 | H4: ACN
B5: ACN | C5: 1 | E5: [1 April] init spec | F5: 2 | H5: EBAN
B6: Cluster size (out of mem) | C6: 1 | E6: [1-April] CBR fixed length mapping | F6: 2
B7: Control-M | C7: 1 | E7: [1-April] CBR spec mapping | F7: 1
B8: Empty file | C8: 3 | E8: [1-April] CBR | F8: 9
B9: Framework | C9: 1 | E9: [1-April] Source (EBAN) CBR | F9: 1 | G9: -1 file Kplus (pending Key) | H9: ACN
B10: Mandatory null | C10: 6 | E10: extraction config pull DB | F10: 3 | H10: ACN
B11: Mismatch source data format | C11: 8 | E11: Framework need enhances | F11: 1 | H11: ACN
B12: Mismatch source data format Mandatory null | C12: 1 | E12: pending re-order for Thai encode | F12: 14 | H12: ACN
B13: Mismatch source data layout | C13: 13 | E13: source | F13: 4 | H13: ACN
B14: Mismatch source data layout + Mandatory null | C14: 1 | E14: source (EBAN) | F14: 8 | H14: ACN
B15: Missing mandatory field | C15: 2 | E15: Unicode | F15: 1
B16: New Requirement (Decrypt some record) Mandatory null | C16: 1 | E16: (blank) | F16: 3 | G16: + 1 file Kplus (pending Key)
B17: (blank) | C17: 3 | E17: Grand Total | F17: 64 | H17: ACN
B18: Unicode | C18: 4 | H18: ACN
B19: Unicode Mandatory null | C19: 1 | H19: ACN
B20: Mismatch source data layout Mandatory null Unicode | C20: 1
A21: Not Start Total | C21: 49
A22: Ready to execute | B22: Mismatch source data layout | C22: 2
B23: (blank) | C23: 1
A24: Ready to execute Total | C24: 3
A25: Failed | B25: Mandatory null | C25: 1
B26: Mismatch source data format | C26: 2
B27: Mismatch source data layout | C27: 4
B28: Unicode | C28: 5
A29: Failed Total | C29: 12
A30: Grand Total | C30: 64

Sheet passed
A1: persist_dgtl_fctrng.dgtl_fctrng_v_clientlimit
A2: persist_dgtl_fctrng.dgtl_fctrng_v_cis
A3: persist_rmst.rmst_customer
A4: persist_fcd.fcd_ar
A5: persist_mx.mx_mktevent
A6: persist_mx.mx_mmlivemat
A7: persist_mx.mx_report_limit_ctp_funded_forint
A8: persist_mx.mx_report_limit_pse_forint
A9: persist_mx.mx_report_limit_se_forint
A10: persist_mx.mx_reset_lp_ctp_funded_forint
A11: persist_mx.mx_reset_mplcde_forint
A12: persist_mx.mx_limiteffective
... A88: persist_scf.scf_vw_rdt_scf_cl_acct

Sheet Batch
A1: Batch2 | B1: Batch3
A2: persist_fcd.fcd_ar | B2: persist_mx.mx_src_murx_deal_ar
A3: persist_gts.gts_kbgt_loan_outstanding | B3: persist_gts.gts_kbgt_cont_outstanding
A4: persist_pcb_dep.pcb_dep_cb2d0005_odencitd_sam | B4: persist_gts.gts_dbttnrel
A5: persist_pcb_loan.pcb_loan_common_transaction_file | B5: persist_gts.gts_kbgt_limit_allocated
A6: persist_cardlink.cardlink_kb1dh023_lbpttrn | B6: persist_pcb_dep.pcb_dep_src_pf_ar_sa_dly
A7: persist_cardlink_acq.cardlink_acq_ci1d1166_crdhd | B7: persist_pcb_dep.pcb_dep_src_pf_ar_ca_dly
A8: persist_hris.hris_staff_accnt_vw | B8: persist_pcb_dep.pcb_dep_src_pf_ar_fx_dly
A9: persist_ks.ks_fundmaster | B9: persist_pcb_dep.pcb_dep_src_pf_ar_sf_dly
A10: persist_ks.ks_fundportfolio | B10: persist_pcb_dep.pcb_dep_extrate1
A11: persist_ks.ks_custprofile | B11: persist_pcb_dep.pcb_dep_src_pf_txn_mis_eft_dly
A12: persist_lec.lec_lecp_lec3d18 | B12: persist_pcb_dep.pcb_dep_cls500029
... A16: persist_ud.ud_vw_flt_rl_sub_bal_enq | B16: persist_pcb_loan.pcb_loan_common_market_code
B17: persist_pcb_loan.pcb_loan_common_rate_type
B18: persist_pcb_loan.pcb_loan_common_product_type
B19: persist_pcb_loan.pcb_loan_common_sub_type
B20: persist_pcb_loan.pcb_loan_common_loan_purpose_table
B21: persist_trade_na.trade_na_lcr070
B22: persist_trade_na.trade_na_src_eximar
B23: persist_cardlink.cardlink_kb1dh013_eptrans
B24: persist_cardlink.cardlink_kb1dh045_cc1d289g
B25: persist_cardlink.cardlink_kb1dh002_cpbcrd
B26: persist_cardlink.cardlink_kb1dh005_kbbcrd
B27: persist_cardlink.cardlink_kb1dh039_ccnd5012
B28: persist_cardlink.cardlink_kb1dh017_cpamt
... B65: persist_ud.ud_vw_flt_dp_div_cert_inc

Sheet Summary
A3: Issues | B3: Count of Persist Table Name | D3: All | E3: 179
A4: Missing Primary Key | B4: 1 | D4: PlanA | E4: 52
A5: ACN | B5: 2 | D5: PlanB | E5: 117
A6: Cluster size (out of mem) | B6: 1 | D6: issue | E6: 68
A7: Control-M | B7: 1 | D7: Pull DB | E7: 25
A8: Empty file | B8: 3
A9: extraction config | B9: 1 | D9: EBAN-IN | E9: 10
A10: Framework | B10: 1
A11: Incorrect spec from EBAN | B11: 1 | D11: Integration Approach | E11: Plan B: Pull DB
A12: KAS layout | B12: 11
A13: Mandatory null | B13: 13 | D13: Issues | E13: Count of Persist Table Name
A14: Mismatch source data format | B14: 12 | D14: extraction config | E14: 1
A15: Mismatch source data format Mandatory null | B15: 1 | D15: Mandatory null | E15: 1
A16: Mismatch source data layout | B16: 24 | D16: Mismatch source data format | E16: 8
A17: Mismatch source data layout + Mandatory null | B17: 1 | D17: Mismatch source data layout | E17: 8
A18: Mismatch source data layout Mandatory null UnicodeDecode | B18: 1 | D18: Pass | E18: 7
A19: Missing mandatory field | B19: 2 | D19: Grand Total | E19: 25
A20: New Requirement (Decrypt some record) Mandatory null | B20: 1
A21: Pass | B21: 7
A22: passed | B22: 1
A23: UnicodeDecode | B23: 9
A24: UnicodeDecode Mandatory null | B24: 1
A25: (blank) | B25: 20
A26: Grand Total | B26: 115
A30: Owner | B30: Count of Persist Table Name
A31: Fon | B31: 10
A32: FW | B32: 1
A33: Kaew | B33: 16
A34: M | B34: 3
A35: P'Fon | B35: 9
A36: Tee | B36: 7
A37: (blank) | B37: 66
A38: Kaew M | B38: 3
A39: Grand Total | B39: 115

Sheet Thai encoding
A1: MDP Area Name | B1: Persist Table Name | C1: Source File name | D1: Integration Approach | E1: enconding
A2: mx | B2: persist_mx.mx_report_limit_ctp_funded_forint | C2: =VLOOKUP(B2,Sheet1!B:C,2,FALSE) -> Report_Limit_Ctp_Funded_ForInt_YYYYMMDD.txt | D2: Plan B: Source File (EBAN) | E2: UTF8
A3: mx | B3: persist_mx.mx_report_limit_pse_forint | C3: =VLOOKUP(B3,Sheet1!B:C,2,FALSE) -> Report_Limit_PSE_ForInt_YYYYMMDD.txt | D3: Plan B: Source File (EBAN) | E3: UTF8
A4: mx | B4: persist_mx.mx_report_limit_se_forint | C4: =VLOOKUP(B4,Sheet1!B:C,2,FALSE) -> Report_Limit_SE_ForInt_YYYYMMDD.txt | D4: Plan B: Source File (EBAN) | E4: UTF8
A5: mx | B5: persist_mx.mx_reset_lp_ctp_funded_forint | C5: =VLOOKUP(B5,Sheet1!B:C,2,FALSE) -> Reset_LP_Ctp_Funded_ForInt_YYYYMMDD.txt | D5: Plan B: Source File (EBAN) | E5: UTF8
A6: mx | B6: persist_mx.mx_reset_mplcde_forint | C6: =VLOOKUP(B6,Sheet1!B:C,2,FALSE) -> Reset_MPLCDE_ForInt_YYYYMMDD.txt | D6: Plan B: Source File (EBAN) | E6: UTF8
A7: pcb_dep | B7: persist_pcb_dep.pcb_dep_src_pf_ar_sa_dly | C7: =VLOOKUP(B7,Sheet1!B:C,2,FALSE) -> src_pf_ar_sa_dly_yyyymmdd.txt | D7: Plan B: Source File (EBAN) | E7: ANSI | F7: UTF8
A8: pcb_dep | B8: persist_pcb_dep.pcb_dep_src_pf_ar_ca_dly | C8: =VLOOKUP(B8,Sheet1!B:C,2,FALSE) -> src_pf_ar_ca_dly_yyyymmdd.txt | D8: Plan B: Source File (EBAN) | E8: ANSI
A9: pcb_dep | B9: persist_pcb_dep.pcb_dep_src_pf_ar_fx_dly | C9: =VLOOKUP(B9,Sheet1!B:C,2,FALSE) -> src_pf_ar_fx_dly_yyyymmdd.txt | D9: Plan B: Source File (EBAN) | E9: ANSI
A10: pcb_dep | B10: persist_pcb_dep.pcb_dep_src_pf_ar_sf_dly | C10: =VLOOKUP(B10,Sheet1!B:C,2,FALSE) -> src_pf_ar_sf_dly_yyyymmdd.txt | D10: Plan B: Source File (EBAN) | E10: ANSI
A11: pcb_dep | B11: persist_pcb_dep.pcb_dep_src_pf_txn_mis_eft_dly | C11: =VLOOKUP(B11,Sheet1!B:C,2,FALSE) -> src_pf_txn_mis_eft_dly_yyyymmdd.txt | D11: Plan B: Source File (EBAN) | E11: ANSI
A12: pcb_dep | B12: persist_pcb_dep.pcb_dep_cls500029 | C12: =VLOOKUP(B12,Sheet1!B:C,2,FALSE) -> cls500029_yyyymmdd.txt | D12: Plan B: Source File (EBAN) | E12: ANSI
A13: pcb_dep | B13: persist_pcb_dep.pcb_dep_src_pf_ar_ca_cr_inf_dly | C13: =VLOOKUP(B13,Sheet1!B:C,2,FALSE) -> SRC_PF_AR_CA_CR_INF_DLY_yyyymmdd.txt | D13: Plan B: Source File (EBAN) - fix length | E13: ANSI
A14: pcb_loan | B14: persist_pcb_loan.pcb_loan_common_market_code | C14: =VLOOKUP(B14,Sheet1!B:C,2,FALSE) -> Common_Market_Code_YYYYMMDD.txt | D14: Plan B: Source File (EBAN) | E14: ANSI
A15: pcb_loan | B15: persist_pcb_loan.pcb_loan_common_sub_type | C15: =VLOOKUP(B15,Sheet1!B:C,2,FALSE) -> Common_Sub_Type.txt | D15: Plan B: Source File (EBAN) | E15: ANSI
A16: pcb_loan | B16: persist_pcb_loan.pcb_loan_common_loan_purpose_table | C16: =VLOOKUP(B16,Sheet1!B:C,2,FALSE) -> Common_Loan_Purpose_Table_yyyymmdd.txt | D16: Plan B: Source File (EBAN) | E16: ANSI
A17: pcb_loan | B17: persist_pcb_loan.pcb_loan_common_rate_type | E17: ANSI
A18: cardlink_acq | B18: persist_cardlink_acq.cardlink_acq_ci1d1166_crdhd | C18: =VLOOKUP(B18,Sheet1!B:C,2,FALSE) -> CPACP.DIH.CI1D1166.CRDHD.Dddmmyy.TXT | D18: Plan B: Source File (DIH) | E18: TIS-620
A19: cardlink_acq | B19: persist_cardlink_acq.cardlink_acq_ci1d1178_crdreg | C19: =VLOOKUP(B19,Sheet1!B:C,2,FALSE) -> CPACP.DIH.CI1D1178.CRDREG.Dddmmyy.TXT | D19: Plan B: Source File (EBAN) | E19: TIS-620
A20: fcd | B20: persist_fcd.fcd_ar | C20: =VLOOKUP(B20,Sheet1!B:C,2,FALSE) -> FCD_AR_YYYYMMDD.txt | D20: Plan B: Source File (EBAN) | E20: ANSI
A21: cardlink | B21: persist_cardlink.cardlink_kb1dh013_eptrans | C21: =VLOOKUP(B21,Sheet1!B:C,2,FALSE) -> CPACP.DIH.KB1DH013.EPTRANS.Dddmmyy.txt
A22: cardlink | B22: persist_cardlink.cardlink_kb1dh017_cpamt | C22: =VLOOKUP(B22,Sheet1!B:C,2,FALSE) -> CPACP.DIH.KB1DH017.CPAMT.Dddmmyy.TXT
A23: cardlink | B23: persist_cardlink.cardlink_kb1dh018_cpsrptt | C23: =VLOOKUP(B23,Sheet1!B:C,2,FALSE) -> CPACP.DIH.KB1DH018.CPSRPTT.Dddmmyy.TXT
A24: cardlink | B24: persist_cardlink.cardlink_kb1dh014_cc1dmpgl | C24: =VLOOKUP(B24,Sheet1!B:C,2,FALSE) -> CPACP.DIH.KB1DH014.CC1DMPGL.Dddmmyy

Sheet Sheet1
A1: MDP Area Name | B1: Persist Table Name | C1: Source File name/Table name
A2: cis | B2: persist_cis.cis_ipxar | C2: CIS_IPXAR_YYYYMMDD.txt
A3: cis | B3: persist_cis.cis_ip | C3: CIS_IP_YYYYMMDD.txt
A4: cis | B4: persist_cis.cis_ar | C4: CIS_AR_YYYYMMDD.txt
A5: cis | B5: persist_cis.cis_relar | C5: CIS_RELAR_YYYYMMDD.txt
A6: cis | B6: persist_cis.cis_doctp | C6: CIS_DOCTP_YYYYMMDD.txt
A7: cis | B7: persist_cis.cis_cntreltp | C7: CIS_CNTRELTP_YYYYMMDD.txt
A8: cis | B8: persist_cis.cis_ipxcontact | C8: CIS_IPXCONTACT_YYYYMMDD.txt
A9: cis | B9: persist_cis.cis_conttp | C9: CIS_CONTTP_YYYYMMDD.txt
A10: cis | B10: persist_cis.cis_continfo | C10: CIS_CONTINFO_YYYYMMDD.txt
A11: cis | B11: persist_cis.cis_idv | C11: CIS_IDV_YYYYMMDD.txt
A12: cis | B12: persist_cis.cis_org | C12: CIS_ORG_YYYYMMDD.txt
... A167: ud | B167: persist_ud.ud_vw_flt_dp_div_cert_inc | C167: ud_vw_flt_dp_div_cert_inc_YYYYMMDD.txt

Sheet KAS
A1: File name/Table name | B1: Target Schema Name | C1: Target Table Name (Persist) | J1: cc
A2: CPACP.DIH.KB1DH028.CCIXPT.Dddmmyy.TXT | B2: persist_cardlink | C2: cardlink_kb1dh028_ccixpt | D2: =B2&"."&C2 -> persist_cardlink.cardlink_kb1dh028_ccixpt | H2: =ISNUMBER(MATCH(D2,K:K,0)) -> TRUE | J2: =ISNUMBER(MATCH(K2,D:D,0)) -> FALSE | K2: persist_cardlink.cardlink_kb1dh005_kbbcrd
A3: CPACP.DIH.KB1DH029.CCATABLA.Dddmmyy.TXT | B3: persist_cardlink | C3: cardlink_kb1dh029_ccatabla | D3: =B3&"."&C3 -> persist_cardlink.cardlink_kb1dh029_ccatabla | H3: =ISNUMBER(MATCH(D3,K:K,0)) -> TRUE | J3: =ISNUMBER(MATCH(K3,D:D,0)) -> FALSE | K3: persist_cardlink.cardlink_kb1dh003_cpbcus
A4: CPACP.DIH.KB1DH030.CUPTRAN.Dddmmyy.TXT | B4: persist_cardlink | C4: cardlink_kb1dh030_cuptran | D4: =B4&"."&C4 -> persist_cardlink.cardlink_kb1dh030_cuptran | H4: =ISNUMBER(MATCH(D4,K:K,0)) -> TRUE | J4: =ISNUMBER(MATCH(K4,D:D,0)) -> FALSE | K4: persist_cardlink.cardlink_kb1dh006_kbbcus
A5: CPACP.DIH.KB1DH001.CP1T170.Dddmmyy.TXT | B5: persist_cardlink | C5: cardlink_kb1dh001_cp1t170_01 | D5: =B5&"."&C5 -> persist_cardlink.cardlink_kb1dh001_cp1t170_01 | H5: =ISNUMBER(MATCH(D5,K:K,0)) -> TRUE | J5: =ISNUMBER(MATCH(K5,D:D,0)) -> FALSE | K5: persist_cardlink.cardlink_kb1dh031_cc1d583b
A6: CPACP.DIH.KB1DH012.CPCAH.Dddmmyy | B6: persist_cardlink | C6: cardlink_kb1dh012_cpcah | D6: =B6&"."&C6 -> persist_cardlink.cardlink_kb1dh012_cpcah | H6: =ISNUMBER(MATCH(D6,K:K,0)) -> TRUE | J6: =ISNUMBER(MATCH(K6,D:D,0)) -> FALSE | K6: persist_cardlink.cardlink_kb1dh007_cpahf
A7: CPACP.DIH.KB1DH020.CC1D582D.Dddmmyy.TXT | B7: persist_cardlink | C7: cardlink_kb1dh020_cc1d582d | D7: =B7&"."&C7 -> persist_cardlink.cardlink_kb1dh020_cc1d582d | H7: =ISNUMBER(MATCH(D7,K:K,0)) -> TRUE | J7: =ISNUMBER(MATCH(K7,D:D,0)) -> FALSE | K7: persist_cardlink.cardlink_kb1dh011_cc1d2027
A8: CPACP.DIH.KB1DH021.CC1D582S.Dddmmyy.TXT | B8: persist_cardlink | C8: cardlink_kb1dh021_cc1d582s | D8: =B8&"."&C8 -> persist_cardlink.cardlink_kb1dh021_cc1d582s | H8: =ISNUMBER(MATCH(D8,K:K,0)) -> TRUE | J8: =ISNUMBER(MATCH(K8,D:D,0)) -> FALSE | K8: persist_cardlink.cardlink_kb1dh002_cpbcrd
A9: CPACP.DIH.KB1DH022.OADCC32.Dddmmyy.TXT | B9: persist_cardlink | C9: cardlink_kb1dh022_oadcc32 | D9: =B9&"."&C9 -> persist_cardlink.cardlink_kb1dh022_oadcc32 | H9: =ISNUMBER(MATCH(D9,K:K,0)) -> TRUE | J9: =ISNUMBER(MATCH(K9,D:D,0)) -> FALSE | K9: persist_cardlink.cardlink_kb1dh019_cc1t377
A10: CPACP.DIH.KB1DH024.CC1D560.Dddmmyy.TXT | B10: persist_cardlink | C10: cardlink_kb1dh024_cc1d560 | D10: =B10&"."&C10 -> persist_cardlink.cardlink_kb1dh024_cc1d560 | H10: =ISNUMBER(MATCH(D10,K:K,0)) -> TRUE | J10: =ISNUMBER(MATCH(K10,D:D,0)) -> FALSE | K10: persist_cardlink.cardlink_kb1dh038_cc1d5012
A11: CPACP.DIH.KB1DH032.ADDTYPE | B11: persist_cardlink | C11: cardlink_kb1dh032_addtype | D11: =B11&"."&C11 -> persist_cardlink.cardlink_kb1dh032_addtype | H11: =ISNUMBER(MATCH(D11,K:K,0)) -> TRUE | J11: =ISNUMBER(MATCH(K11,D:D,0)) -> FALSE | K11: persist_cardlink.cardlink_kb1dh013_eptrans
A12: CPACP.LA10S.OATKN.OUTBOUND | B12: persist_cardlink | C12: cardlink_la10s_oatkn | D12: =B12&"."&C12 -> persist_cardlink.cardlink_la10s_oatkn | H12: =ISNUMBER(MATCH(D12,K:K,0)) -> TRUE | J12: =ISNUMBER(MATCH(K12,D:D,0)) -> FALSE | K12: persist_cardlink.cardlink_kb1dh017_cpamt
A13: CPACP.DIH.KB1DH001.CP1T170.Dddmmyy.TXT | B13: persist_cardlink | C13: cardlink_kb1dh001_cp1t170_02 | D13: =B13&"."&C13 -> persist_cardlink.cardlink_kb1dh001_cp1t170_02 | H13: =ISNUMBER(MATCH(D13,K:K,0)) -> FALSE | J13: =ISNUMBER(MATCH(K13,D:D,0)) -> FALSE | K13: persist_cardlink.cardlink_kb1dh018_cpsrptt
... A16: CPACP.DIH.KB1DH010.OADCTF.DDDMMYY | B16: persist_cardlink | C16: cardlink_kb1dh010_oadctf | D16: =B16&"."&C16 -> persist_cardlink.cardlink_kb1dh010_oadctf | H16: =ISNUMBER(MATCH(D16,K:K,0)) -> FALSE | J16: =ISNUMBER(MATCH(K16,D:D,0)) -> TRUE | K16: persist_cardlink.cardlink_kb1dh001_cp1t170_01
J17: =ISNUMBER(MATCH(K17,D:D,0)) -> TRUE | K17: persist_cardlink.cardlink_kb1dh032_addtype
J18: =ISNUMBER(MATCH(K18,D:D,0)) -> TRUE | K18: persist_cardlink.cardlink_la10s_oatkn
J19: =ISNUMBER(MATCH(K19,D:D,0)) -> FALSE | K19: persist_cardlink.cardlink_kb1dh037_cptcpf_p
J20: =ISNUMBER(MATCH(K20,D:D,0)) -> FALSE | K20: persist_cardlink.cardlink_kb1dh045_cc1d289g
J21: =ISNUMBER(MATCH(K21,D:D,0)) -> TRUE | K21: persist_cardlink.cardlink_kb1dh028_ccixpt
J22: =ISNUMBER(MATCH(K22,D:D,0)) -> TRUE | K22: persist_cardlink.cardlink_kb1dh029_ccatabla
J23: =ISNUMBER(MATCH(K23,D:D,0)) -> TRUE | K23: persist_cardlink.cardlink_kb1dh030_cuptran
J24: =ISNUMBER(MATCH(K24,D:D,0)) -> TRUE | K24: persist_cardlink.cardlink_kb1dh012_cpcah
J25: =ISNUMBER(MATCH(K25,D:D,0)) -> TRUE | K25: persist_cardlink.cardlink_kb1dh020_cc1d582d
J26: =ISNUMBER(MATCH(K26,D:D,0)) -> TRUE | K26: persist_cardlink.cardlink_kb1dh021_cc1d582s
J27: =ISNUMBER(MATCH(K27,D:D,0)) -> TRUE | K27: persist_cardlink.cardlink_kb1dh022_oadcc32
J28: =ISNUMBER(MATCH(K28,D:D,0)) -> TRUE | K28: persist_cardlink.cardlink_kb1dh024_cc1d560
... J32: =ISNUMBER(MATCH(K32,D:D,0)) -> FALSE | K32: persist_cardlink.cardlink_lb1dh002_lbcrd

Sheet Run Job status
A1: MDP Area Name | B1: Source File name/Table name | C1: POS_DATE | D1: STATUS EXTRACTION | E1: STATUS RUNJOB | F1: LINKED | G1: REMAKED | I1: In Progress
A2: cis | B2: cis_addr | C2: 45376 | D2: Passed | E2: Passed | I2: Passed | L2: Count of Source File name/Table name | M2: STATUS RUNJOB
A3: cis | B3: cis_ar | C3: 45376 | D3: Passed | E3: Passed | I3: Failed | L3: MDP Area Name | M3: Failed | N3: In Progress | O3: Passed | P3: Grand Total
A4: cis | B4: cis_cntreltp | C4: 45376 | D4: Passed | E4: Passed | L4: ccms | O4: 4 | P4: 4
A5: cis | B5: cis_continfo | C5: 45376 | D5: Passed | E5: Passed | L5: cis | O5: 17 | P5: 17
A6: cis | B6: cis_conttp | C6: 45376 | D6: Passed | E6: Passed | L6: csm | M6: 3 | O6: 14 | P6: 17
A7: cis | B7: cis_dntcnt | C7: 45376 | D7: Passed | E7: Passed | L7: fcd | O7: 1 | P7: 1
A8: cis | B8: cis_doctp | C8: 45376 | D8: Passed | E8: Passed | L8: gts | N8: 4 | O8: 2 | P8: 6
A9: cis | B9: cis_histsegm | C9: 45376 | D9: Passed | E9: Passed | L9: lpm-as400 | M9: 2 | N9: 8 | P9: 10
A10: cis | B10: cis_idv | C10: 45376 | D10: Passed | E10: Passed | L10: mx | N10: 1 | O10: 8 | P10: 9
A11: cis | B11: cis_ip | C11: 45376 | D11: Passed | E11: Passed | L11: pcb_dep | N11: 8 | O11: 3 | P11: 11
A12: cis | B12: cis_ipsegment | C12: 45376 | D12: Passed | E12: Passed | L12: pcb_loan | N12: 7 | O12: 2 | P12: 9
A13: cis | B13: cis_ipxaddr | C13: 45376 | D13: Passed | E13: Passed | L13: rdm | O13: 12 | P13: 12
A14: cis | B14: cis_ipxar | C14: 45376 | D14: Passed | E14: Passed | L14: rmst | M14: 1 | P14: 1
A15: cis | B15: cis_ipxcontact | C15: 45376 | D15: Passed | E15: Passed | L15: lpm-wrtoff | N15: 1 | P15: 1
A16: cis | B16: cis_org | C16: 45376 | D16: Passed | E16: Passed | L16: cardlink | M16: 1 | N16: 34 | P16: 35
A17: cis | B17: cis_othdoc | C17: 45376 | D17: Passed | E17: Passed | L17: cardlink_acq | M17: 2 | O17: 1 | P17: 3
A18: cis | B18: cis_relar | C18: 45376 | D18: Passed | E18: Passed | L18: hris | O18: 1 | P18: 1
A19: csm | B19: csm_action | C19: 45376 | D19: Passed | E19: Passed | L19: hrcrc | N19: 1 | P19: 1
A20: csm | B20: csm_channel | C20: 45376 | D20: Passed | E20: Passed | L20: lec | O20: 1 | P20: 1
A21: csm | B21: csm_company | C21: 45376 | D21: Passed | E21: Passed | L21: kplus | N21: 3 | O21: 4 | P21: 7
A22: csm | B22: csm_custxformxconsent | C22: 45376 | D22: Passed | E22: Passed | L22: dgtl_fctrng | N22: 3 | O22: 5 | P22: 8
A23: csm | B23: csm_custxformxconsentderived | C23: 45376 | D23: Passed | E23: Failed | F23: https://adb-1225054441296002.2.azuredatabricks.net/?o=1225054441296002#job/847414196180011/run/208058610995029 | G23: Failed dependency checking: The job is not ready due to failures in prerequisite jobs. | L23: scf | N23: 3 | O23: 6 | P23: 9
A24: csm | B24: csm_custxformxconsentderivedlog | C24: 45376 | D24: Passed | E24: Failed | F24: https://adb-1225054441296002.2.azuredatabricks.net/?o=1225054441296002#job/847414196180011/run/677383381515210 | G24: Failed dependency checking: The job is not ready due to failures in prerequisite jobs. | L24: ud | N24: 10 | O24: 1 | P24: 11
A25: csm | B25: csm_custxformxconsentlog | C25: 45376 | D25: Passed | E25: Failed | F25: https://adb-1225054441296002.2.azuredatabricks.net/?o=1225054441296002#job/847414196180011/run/11022580495261 | G25: Failed dependency checking: The job is not ready due to failures in prerequisite jobs. | L25: ks | N25: 3 | P25: 3
A26: csm | B26: csm_downstreamconfig | C26: 45376 | D26: Passed | E26: Passed | L26: trade_na | N26: 2 | P26: 2
A27: csm | B27: csm_downstreamrules | C27: 45376 | D27: Passed | E27: Passed | L27: fxb | N27: 1 | P27: 1
A28: csm | B28: csm_formconsent | C28: 45376 | D28: Passed | E28: Passed | L28: Grand Total | M28: 9 | N28: 89 | O28: 82 | P28: 180
A29: csm | B29: csm_formxappr | C29: 45376 | D29: Passed | E29: Passed
A30: csm | B30: csm_formxcontent | C30: 45376 | D30: Passed | E30: Passed
A31: csm | B31: csm_originateproductcoa | C31: 45376 | D31: Passed | E31: Passed
A32: csm | B32: csm_originateproductnoncoa | C32: 45376 | D32: Passed | E32: Passed
A33: csm | B33: csm_product | C33: 45376 | D33: Passed | E33: Passed
A34: csm | B34: csm_purpose | C34: 45376 | D34: Passed | E34: Passed
A35: csm | B35: csm_receivertype | C35: 45376 | D35: Passed | E35: Passed
A36: rdm | B36: rdm_card_tp_cd | C36: 45376 | D36: Passed | E36: Passed
A37: rdm | B37: rdm_cst_ctf_tp_cd | C37: 45376 | D37: Passed | E37: Passed
A38: rdm | B38: rdm_cst_idv_incm_seg_cd | C38: 45376 | D38: Passed | E38: Passed
A39: rdm | B39: rdm_cst_ip_lgl_stc_tp_cd | C39: 45376 | D39: Passed | E39: Passed
A40: rdm | B40: rdm_cst_mar_st_cd | C40: 45376 | D40: Passed | E40: Passed
... A51: ccms | B51: ccms_bp772n1_cardholder_purge | C51: 45366 | D51: Passed | E51: Passed
A52: lpm-as400 | B52: lpm_x_ip_rel | C52: 45121 | D52: Passed | E52: Failed | F52: https://adb-1225054441296002.2.azuredatabricks.net/?o=1225054441296002#job/847414196180011/run/500508920364717 https://adb-1225054441296002.2.azuredatabricks.net/?o=1225054441296002#job/847414196180011/run/500508920364717 | G52: Failed dependency checking: The job is not ready due to failures in prerequisite jobs.
A53: lpm-as400 | B53: lpm_x_ip_rel | C53: 45122 | D53: Passed | E53: Failed | F53: https://adb-1225054441296002.2.azuredatabricks.net/?o=1225054441296002#job/847414196180011/run/69449439651921 | G53: Failed dependency checking: The job is not ready due to failures in prerequisite jobs.
A54: lpm-as400 | B54: lpm_as400_ar_clss_qly_m | D54: In Progress | E54: In Progress
A55: lpm-as400 | B55: lpm_as400_ar_wrtof_rcv_m | D55: In Progress | E55: In Progress
A56: lpm-as400 | B56: lpm_as400_lmt_ar_inf_bfr_wrtof_d | D56: In Progress | E56: In Progress
A57: lpm-as400 | B57: lpm_as400_lmt_inf_bfr_wrtof_d | D57: In Progress | E57: In Progress
A58: lpm-as400 | B58: lpm_as400_ln_card_clss_prvn_m | D58: In Progress | E58: In Progress
A59: lpm-as400 | B59: lpm_as400_ln_cntg_clss_prvn_bfr_wrtof_m | D59: In Progress | E59: In Progress
A60: lpm-as400 | B60: lpm_as400_ln_cntg_clss_prvn_m | D60: In Progress | E60: In Progress
A61: lpm-as400 | B61: lpm_as400_ln_cntg_dmmy_clss_prvn_m | D61: In Progress | E61: In Progress
A62: lpm-wrtoff | B62: lpm_wrtoff_pscp_wo_wo1d04h_sam_m | D62: In Progress | E62: In Progress
A63: rmst | B63: SalesSmart_Customer | C63: 45376 | D63: Passed | E63: Failed | F63: https://adb-1225054441296002.2.azuredatabricks.net/jobs/209860476102323/runs/278703411266153?o=1225054441296002 | G63: Failed dependency checking: The job is not ready due to failures in prerequisite jobs.
A64: mx | B64: mx_limiteffective | C64: 45370 | D64: Passed | E64: Passed
A65: mx | B65: mx_mktevent | C65: 45370 | D65: Passed | E65: Passed
A66: mx | B66: mx_mmlivemat | C66: 45370 | D66: Passed | E66: Passed
A67: mx | B67: mx_report_limit_ctp_funded_forint | C67: 45370 | D67: Passed | E67: Passed
A68: mx | B68: mx_report_limit_pse_forint | C68: 45370 | D68: Passed | E68: Passed
A69: mx | B69: mx_report_limit_se_forint | C69: 45370 | D69: Passed | E69: Passed
A70: mx | B70: mx_reset_lp_ctp_funded_forint | C70: 45370 | D70: Passed | E70: Passed
A71: mx | B71: mx_reset_mplcde_forint | C71: 45370 | D71: Passed | E71: Passed
A72: mx | B72: mx_src_murx_deal_ar | D72: In Progress | E72: In Progress
A73: fcd | B73: fcd_ar | C73: 45371 | D73: Passed | E73: Passed
A74: gts | B74: gts_dbtl4xl6 | C74: 45372 | D74: Passed | E74: Passed
A75: gts | B75: gts_dbttnrel | C75: 45372 | D75: Passed | E75: Passed
A76: gts | B76: gts_kbgt_cont_outstanding | D76: In Progress | E76: In Progress
A77: gts | B77: gts_kbgt_limit_allocated | D77: In Progress | E77: In Progress
A78: gts | B78: gts_kbgt_limit | C78: 45370 | D78: Passed | E78: Passed
A79: gts | B79: gts_kbgt_loan_outstanding | C79: 45378 | D79: Passed | E79: Passed
A80: pcb_dep | B80: pcb_dep_cb2d0005_odencitd_sam | C80: 45377 | D80: Passed | E80: Passed
A81: pcb_dep | B81: pcb_dep_cls500029 | D81: In Progress | E81: In Progress
A82: pcb_dep | B82: pcb_dep_deptxn_db | D82: In Progress | E82: In Progress
A83: pcb_dep | B83: pcb_dep_extrate1 | C83: 45377 | D83: Passed | E83: Passed
A84: pcb_dep | B84: pcb_dep_src_pf_ar_ca_cr_inf_dly | D84: In Progress | E84: In Progress
A85: pcb_dep | B85: pcb_dep_src_pf_ar_ca_dly | D85: In Progress | E85: In Progress
A86: pcb_dep | B86: pcb_dep_src_pf_ar_ca_limit_dly | C86: 45371 | D86: Passed | E86: Passed
A87: pcb_dep | B87: pcb_dep_src_pf_ar_fx_dly | D87: In Progress | E87: In Progress
A88: pcb_dep | B88: pcb_dep_src_pf_ar_sa_dly | D88: In Progress | E88: In Progress
A89: pcb_dep | B89: pcb_dep_src_pf_ar_sf_dly | D89: In Progress | E89: In Progress
A90: pcb_dep | B90: pcb_dep_src_pf_txn_mis_eft_dly | D90: In Progress | E90: In Progress
A91: pcb_loan | B91: pcb_loan_common_account_info | D91: In Progress | E91: In Progress
A92: pcb_loan | B92: pcb_loan_common_account_tier_by_time | C92: 45371 | D92: Passed | E92: Passed
A93: pcb_loan | B93: pcb_loan_common_limit_info | D93: In Progress | E93: In Progress
A94: pcb_loan | B94: pcb_loan_common_loan_purpose_table | D94: In Progress | E94: In Progress
A95: pcb_loan | B95: pcb_loan_common_market_code | D95: In Progress | E95: In Progress
A96: pcb_loan | B96: pcb_loan_common_product_type | D96: In Progress | E96: In Progress
A97: pcb_loan | B97: pcb_loan_common_rate_type | D97: In Progress | E97: In Progress
A98: pcb_loan | B98: pcb_loan_common_sub_type | D98: In Progress | E98: In Progress
A99: pcb_loan | B99: pcb_loan_common_transaction_file | C99: 45371 | D99: Passed | E99: Passed
A100: cardlink | B100: cardlink_kb1dh001_cp1t170_s | D100: In Progress | E100: In Progress
A101: cardlink | B101: cardlink_kb1dh002_cp1t170_s | D101: In Progress | E101: In Progress
A102: cardlink | B102: cardlink_kb1dh002_cpbcrd | D102: In Progress | E102: In Progress
A103: cardlink | B103: cardlink_kb1dh003_cpbcus | D103: In Progress | E103: In Progress
A104: cardlink | B104: cardlink_kb1dh005_kbbcrd | D104: In Progress | E104: In Progress
A105: cardlink | B105: cardlink_kb1dh006_kbbcus | D105: In Progress | E105: In Progress
A106: cardlink | B106: cardlink_kb1dh007_cpahf | D106: In Progress | E106: In Progress
A107: cardlink | B107: cardlink_kb1dh011_cc1d2027 | D107: In Progress | E107: In Progress
A108: cardlink | B108: cardlink_kb1dh012_cpcah_m | D108: In Progress | E108: In Progress
A109: cardlink | B109: cardlink_kb1dh013_eptrans | C109: 45378 | D109: Passed | E109: Failed | F109: Run of Ingestion_Framework of mdp-framework-1.5.0 - Databricks (azuredatabricks.net) | G109: utf-8' codec can't decode byte 0xa8 in position 3947: invalid start byte
A110: cardlink | B110: cardlink_kb1dh014_cc1dmpgl | D110: In Progress | E110: In Progress
...

Sheet Sheet2
D1: Control checker task | M1: Normal
M2: Sample File
D3: Normal | E3: นับรวม header ไม่รวม tailor | F3: นับรวม tailor ไม่รวม header | G3: นับรวม header และ tailor
C4: Source | D4: Count of body (20) | E4: Count of body (20) + adjust_source (1) | F4: Count of body (20) + adjust_source (1) | G4: Count of body (20) + adjust_source (2) | M4: Header: | N4: 20240327|2|3|4
C5: Control | D5: Count of control (20) | E5: Count of control (21) | F5: Count of control (21) | G5: Count of control (22) | M5: Body: | N5: count: 20
M6: Tailor: | N6: 20240327|20|3|4
M10: Header: | N10: 20240327|21|3|4
M11: Body: | N11: count: 20 | O11: + adjust_source(1)
