Workbook
Name _56F9DC9755BA473782653E2940F9FormId: "OT154DkJbUmxKRmO3ZFv6wT4ob2Jv5lBseHwcjzz9GdUNVlVQkpaNDdQU0Q5VDhNNFBaUjFOVEJQWSQlQCN0PWcu"
Name _56F9DC9755BA473782653E2940F9ResponseSheet: "Form1"
Name _56F9DC9755BA473782653E2940F9SourceDocId: "{20cff37e-62ca-453c-88e4-ce2eb7538031}"
Name actual: #REF!
Name Analyze1: [3]FIT_GAP!$D$8:$D$10
Name AppInDate: #REF!
Name Application_Acronym_List: '[4]5.Reference Values'!$B:$B
Name Apply_Auto_Ingestion: #REF!
Name Cash_beginning: #REF!
Name Cash_Minimum: #REF!
Name ColumnTitle1: [5]!CashLog[[#Headers],[Date]]
Name Company_name: #REF!
Name Cycle: [6]FixVar!$G$2:$G$8
Name data: OFFSET('[7]Branch Staff'!#REF!,0,0,COUNTA('[7]Branch Staff'!#REF!)-1,COUNTA('[7]Branch Staff'!$A$1:$IV$1))
Name Datum_teller: #REF!
Name Datum_Teller_cash_Reconciliation: #REF!
Name Display_Week: #REF!
Name ExtraCredit: #REF!
Name f: #REF!
Name Fruit: #REF!
Name Grace: #REF!
Name Grace_Bi_Weekly_Installments: #REF!
Name Grace_Months: #REF!
Name IQ_CH: 110000
Name IQ_CQ: 5000
Name IQ_CY: 10000
Name IQ_DAILY: 500000
Name IQ_FH: 100000
Name IQ_FQ: 500
Name IQ_FY: 1000
Name IQ_LTM: 2000
Name IQ_MONTH: 15000
Name IQ_NTM: 6000
Name IQ_WEEK: 50000
Name IQ_YTD: 3000
Name Items: #REF!
Name k: [9]FixVar!$G$2:$G$8
Name LIST: #REF!
Name Meat: #REF!
Name MoreFruit: #REF!
Name MoreItem: #REF!
Name MoreItems: #REF!
Name Print_Area1: #REF!
Name Print_Area2: #REF!
Name Project_Start: #REF!
Name Promotional_Installments: #REF!
Name Report: #REF!
Name Start_Date: #REF!
Name STATUS1: [6]FixVar!$R$2:$R$5
Name SUMExtraCredit: #REF!
Name SUMIF: #REF!
Name SUMIFExtraCredit: #REF!
Name Total: #REF!
Name valuevx: 42.314159

Sheet Version Control
B2: Version | C2: Date | D2: Description | E2: By | R2: Pending Confirm
B3: v00_00_01 | C3: 45268 | D3: Initial | E3: Chonnikan C. | R3: Confirmed
B4: v00_00_02 | C4: 45280 | D4: Updated "Batch 1 - Ingestion Inventory " sheet to only include files/tables required by curation requirement scope Added "Batch 2 - Ingestion Inventory" sheet for files/tables to be cut-off for ingestion team on 27-Dec-2023 | E4: Nonthapatr S. | R4: Pending to provide
B5: v00_00_02 | C5: 45294 | D5: Updated information for Batch 1,2 - KBMF File Reference (From EBAN provided for PlanB) - Table Specification | E5: Chonnikan C. | R5: N/A
B6: v00_00_02 | C6: 45310 | D6: Added 2 tables to Batch 4: - SCM_PRODUCT_MAP - VW_RDT_SCF_CL_ACCT | E6: Nonthapatr S.
B7: v00_00_02 | C7: 45317 | D7: Item removed from scope: - CPACP.DIH.CI1D1166.CRDHD.D.DIH_ENC.TXT (Source: Cardlink TPN) | E7: Thanapol M.
B8: v00_00_03 | C8: 45321 | D8: Added 2 tables to Batch 2 - src_pf_ar_ca_limit_dly_yyyymmdd.txt - common_transaction file.txt | E8: Chonnikan C.
B9: v00_00_04 | C9: 45357 | D9: Updated source table name - GTS (New-Trade): from DBTL4xL10 to DBTL4xL6 Cancelled 3 tables - CPACP.DIH.KB1DH004.CPBMER.Dddmmyy.txt - CPACP.DIH.KB1DH010.OADCTF.DDDMMYY - CPACP.DIH.KB1DH009.KBBMER.DDDMMYY | E9: Tanatchporn S. Chonnikan C.
B10: v00_00_05 | C10: 45363 | D10: Cancelled : DTEADM.VW_STD_INS_EOD_INC (table :ud_vw_std_ins_eod_inc) | E10: Chonnikan C.

Sheet Batch1
A1: View | B1: Column | C1: Desc | D1: Remark | E1: Fix1 | F1: Target | H1: Unique | J1: Status
A2: v_pcb_dep_src_pf_ar_sa_dly | B2: pos_dt | H2: Record Type | J2: clmn_nm_blnk | K2: =_xlfn.CONCAT(COUNTBLANK(B2:B2227)," Field") -> 283 Field
A3: v_pcb_dep_src_pf_ar_sa_dly | B3: rec_tp | C3: Record Type | H3: Account Number | J3: Completed | K3: 20 Doc
A4: v_pcb_dep_src_pf_ar_sa_dly | B4: acct_num | C4: Account Number | H4: Source Position Date
A5: v_pcb_dep_src_pf_ar_sa_dly | B5: src_pos_dt | C5: Source Position Date | H5: Account Name in Thai
A6: v_pcb_dep_src_pf_ar_sa_dly | B6: acct_nm_in_thai | C6: Account Name in Thai | H6: Account Name in English
A7: v_pcb_dep_src_pf_ar_sa_dly | B7: acct_nm_in_eng | C7: Account Name in English | H7: Account Open Date
A8: v_pcb_dep_src_pf_ar_sa_dly | B8: acct_open_dt | C8: Account Open Date | H8: Account Close Date
A9: v_pcb_dep_src_pf_ar_sa_dly | B9: acct_cls_dt | C9: Account Close Date | H9: Account Status Code
A10: v_pcb_dep_src_pf_ar_sa_dly | B10: acct_st_cd | C10: Account Status Code | H10: Customer Classification Type Code
A11: v_pcb_dep_src_pf_ar_sa_dly | B11: cst_cl_tp_cd | C11: Customer Classification Type Code | H11: Business Sector Code
A12: v_pcb_dep_src_pf_ar_sa_dly | B12: bsn_sect_cd | C12: Business Sector Code | H12: Branch Code
A13: v_pcb_dep_src_pf_ar_sa_dly | B13: br_cd | C13: Branch Code | H13: Currency Code
A14: v_pcb_dep_src_pf_ar_sa_dly | B14: ccy_cd | C14: Currency Code | H14: Outstanding Balance Amount
A15: v_pcb_dep_src_pf_ar_sa_dly | B15: otsnd_bal_amt | C15: Outstanding Balance Amount | H15: Open Balance Amount
... A42: v_pcb_dep_src_pf_ar_sa_dly | B42: hold_bal_amt | C42: Hold Balance Amount | H42: Change E-Saving Current Date
A43: v_pcb_dep_src_pf_ar_sa_dly | C43: Change E-Saving Current Date | H43: Change E-Saving Current Timestamp
A44: v_pcb_dep_src_pf_ar_sa_dly | C44: Change E-Saving Current Timestamp | H44: Change E-Saving Device Number
A45: v_pcb_dep_src_pf_ar_sa_dly | C45: Change E-Saving Device Number | H45: Change E-Saving Service Branch Code
A46: v_pcb_dep_src_pf_ar_sa_dly | C46: Change E-Saving Service Branch Code | H46: E-Saving Account Flag
A47: v_pcb_dep_src_pf_ar_sa_dly | C47: E-Saving Account Flag | H47: Profile Interest Deposit Number
A48: v_pcb_dep_src_pf_ar_sa_dly | B48: prfl_int_dep_num | C48: Profile Interest Deposit Number | H48: Accumulate Interest Paid Amount
A49: v_pcb_dep_src_pf_ar_sa_dly | B49: accum_int_paid_amt | C49: Accumulate Interest Paid Amount | H49: Previous Year Interest Paid Amount
A50: v_pcb_dep_src_pf_ar_sa_dly | B50: pyr_int_paid_amt | C50: Previous Year Interest Paid Amount | H50: Year-To-Date Interest Paid Amount
A51: v_pcb_dep_src_pf_ar_sa_dly | B51: yr_to_dt_int_paid_amt | C51: Year-To-Date Interest Paid Amount | H51: Backup Withholding Flag
A52: v_pcb_dep_src_pf_ar_sa_dly | C52: Backup Withholding Flag | H52: Previous Year Backup Withholding Paid Amount
A53: v_pcb_dep_src_pf_ar_sa_dly | C53: Previous Year Backup Withholding Paid Amount | H53: Year-To-Date Backup Withholding Paid Amount
A54: v_pcb_dep_src_pf_ar_sa_dly | C54: Year-To-Date Backup Withholding Paid Amount | H54: Tax Owner Customer Identification Number
A55: v_pcb_dep_src_pf_ar_sa_dly | B55: tax_ownr_cst_id_num | C55: Tax Owner Customer Identification Number | H55: Interest Withholding Calculation Method
A56: v_pcb_dep_src_pf_ar_sa_dly | B56: int_wthld_cal_mthd | C56: Interest Withholding Calculation Method | H56: Tax Key
A57: v_pcb_dep_src_pf_ar_sa_dly | B57: tax_key | C57: Tax Key | H57: Surety Account Flag
A58: v_pcb_dep_src_pf_ar_sa_dly | C58: Surety Account Flag | H58: Block Code
A59: v_pcb_dep_src_pf_ar_sa_dly | B59: block_cd | C59: Block Code | H59: Debit or Credit Allowable code
A60: v_pcb_dep_src_pf_ar_sa_dly | C60: Debit or Credit Allowable code | H60: Tax Identification Number
A61: v_pcb_dep_src_pf_ar_sa_dly | B61: tax_id_num | C61: Tax Identification Number | H61: customer identification number
A62: v_pcb_dep_src_pf_ar_sa_dly | B62: cst_id_num | C62: customer identification number | H62: Principal Amount
A63: v_pcb_dep_src_pf_ar_sa_dly | B63: load_tms | H63: Positive Interest Payment Frequency
A64: v_pcb_dep_src_pf_ar_sa_dly | B64: src_sys_id | H64: Positive Interest Payment Frequency Unit
A65: v_pcb_dep_src_pf_ar_sa_dly | B65: ptn_yyyy | H65: Negative Interest Payment Frequency
A66: v_pcb_dep_src_pf_ar_sa_dly | B66: ptn_mm | H66: Negative Interest Payment Frequency Unit
A67: v_pcb_dep_src_pf_ar_sa_dly | B67: ptn_dd | H67: Last Positive Interest Payment Date
A68: v_pcb_dep_src_pf_ar_ca_dly | B68: pos_dt | H68: Next Positive Interest Payment Date
A69: v_pcb_dep_src_pf_ar_ca_dly | B69: rec_tp | C69: Record Type | H69: Last Negative Interest Payment Date
A70: v_pcb_dep_src_pf_ar_ca_dly | B70: src_pos_dt | C70: Source Position Date | H70: Next Negative Interest Payment Date
A71: v_pcb_dep_src_pf_ar_ca_dly | B71: acct_num | C71: Account Number | H71: Positive Compounded Interest Frequency
A72: v_pcb_dep_src_pf_ar_ca_dly | B72: acct_nm_in_thai | C72: Account Name in Thai | H72: Positive Compounded Interest Frequency Unit
A73: v_pcb_dep_src_pf_ar_ca_dly | B73: acct_nm_in_eng | C73: Account Name in English | H73: Negative Compounded Interest Frequency
A74: v_pcb_dep_src_pf_ar_ca_dly | B74: acct_open_dt | C74: Account Open Date | H74: Negative Compounded Interest Frequency Unit
A75: v_pcb_dep_src_pf_ar_ca_dly | B75: acct_cls_dt | C75: Account Close Date | H75: Positive Current Interest Rate
A76: v_pcb_dep_src_pf_ar_ca_dly | B76: acct_st_cd | C76: Account Status Code | H76: Positive Interest Rate Effective Date
A77: v_pcb_dep_src_pf_ar_ca_dly | B77: cst_cl_tp_cd | C77: Customer Classification Type Code | H77: Positive Interest Rate End Date
A78: v_pcb_dep_src_pf_ar_ca_dly | B78: bsn_sect_cd | C78: Business Sector Code | H78: Negative Current Interest Rate
A79: v_pcb_dep_src_pf_ar_ca_dly | B79: br_cd | C79: Branch Code | H79: Negative Interest Rate Effective Date
A80: v_pcb_dep_src_pf_ar_ca_dly | B80: ccy_cd | C80: Currency Code | H80: Negative Interest Rate End Date
... A103: v_pcb_dep_src_pf_ar_ca_dly | B103: postv_crrnt_int_rate | C103: Positive Current Interest Rate | H103: Interest Withholding Tax Calculation Method
A104: v_pcb_dep_src_pf_ar_ca_dly | B104: postv_int_rate_eff_dt | C104: Positive Interest Rate Effective Date | E104: postv_int_rate_eff_dt | H104: Sub Account Number
A105: v_pcb_dep_src_pf_ar_ca_dly | B105: postv_int_rate_end_dt | C105: Positive Interest Rate End Date | H105: Account Name in English
A106: v_pcb_dep_src_pf_ar_ca_dly | B106: neg_crrnt_int_rate | C106: Negative Current Interest Rate | H106: Account Closed Date
A107: v_pcb_dep_src_pf_ar_ca_dly | B107: neg_int_rate_eff_dt | C107: Negative Interest Rate Effective Date | E107: neg_int_rate_eff_dt | H107: Effective Date
A108: v_pcb_dep_src_pf_ar_ca_dly | B108: neg_int_rate_end_dt | C108: Negative Interest Rate End Date | H108: Maturity Date
A109: v_pcb_dep_src_pf_ar_ca_dly | B109: crrnt_int_rate_tp_cd | C109: Current Interest Rate Type Code | H109: Customer Classified Type Code
A110: v_pcb_dep_src_pf_ar_ca_dly | B110: int_rate_tp_cd | C110: Interest Rate Type Code | H110: Interest Calculation Status
A111: v_pcb_dep_src_pf_ar_ca_dly | B111: crrnt_sprd_int_rate | C111: Current Spread Interest Rate | H111: Account Term Period
A112: v_pcb_dep_src_pf_ar_ca_dly | B112: acru_int_paybl_amt | C112: Accrued Interest Payable Amount | H112: Account Term Period Unit
A113: v_pcb_dep_src_pf_ar_ca_dly | B113: acru_int_amt | C113: Accrued Interest Amount | H113: Extend Term Flag
A114: v_pcb_dep_src_pf_ar_ca_dly | B114: rvrs_acru_int_amt | C114: Reverse Accrued Interest Amount | H114: Backup Withholding Tax Flag
A115: v_pcb_dep_src_pf_ar_ca_dly | B115: memo_acru_int_amt | C115: Memo Accrued Interest Amount | H115: Rollover Account Number
A116: v_pcb_dep_src_pf_ar_ca_dly | B116: int_paid_amt | C116: Interest Paid Amount | H116: Transfer Interest Account Number
A117: v_pcb_dep_src_pf_ar_ca_dly | B117: int_cal_st_cd | C117: Interest Calculation Status Code | H117: Maturity Transfer Account Number
A118: v_pcb_dep_src_pf_ar_ca_dly | B118: coa_acct_cd | C118: COA Account Code | H118: Blocked Code
A119: v_pcb_dep_src_pf_ar_ca_dly | B119: coa_pd_cd | C119: COA Product Code | H119: Current Date
... A132: v_pcb_dep_src_pf_ar_ca_dly | B132: frst_cntrct_crrnt_int_rate_tp_cd | C132: First Contract Current Interest Rate Type Code | H132: Channel Number
A133: v_pcb_dep_src_pf_ar_ca_dly | B133: frst_lmt_seq_eff_dt | C133: First Limit Sequence Effective Date | E133: frst_lmt_seq_eff_dt | H133: Sender Account Number
A134: v_pcb_dep_src_pf_ar_ca_dly | B134: frst_lmt_seq_amt | C134: First Limit Sequence Amount | H134: Recipient Account Number
A135: v_pcb_dep_src_pf_ar_ca_dly | B135: acct_pps_tp_cd | C135: Account Purpose Type Code | H135: Inter Zone Number
A136: v_pcb_dep_src_pf_ar_ca_dly | B136: int_indx_cd | C136: Interest Index Code | H136: Transaction Amount
A137: v_pcb_dep_src_pf_ar_ca_dly | B137: accum_int_paid_amt | C137: Accumulate Interest Paid Amount | H137: Commission Amount
A138: v_pcb_dep_src_pf_ar_ca_dly | B138: pyr_int_paid_amt | C138: Previous Year Interest Paid Amount | H138: Telephone Fee Amount
A139: v_pcb_dep_src_pf_ar_ca_dly | B139: yr_to_dt_int_paid_amt | C139: Year-To-Date Interest Paid Amount | H139: Actual Transaction Amount
A140: v_pcb_dep_src_pf_ar_ca_dly | C140: Backup Withholding Flag | H140: Waive Fee Amount
A141: v_pcb_dep_src_pf_ar_ca_dly | C141: Previous Year Backup Withholding Tax Paid Amount | H141: Sender Service Branch Number
A142: v_pcb_dep_src_pf_ar_ca_dly | C142: Year-To-Date Backup Withholding Tax Paid Amount | H142: Recipient Domicile Branch Number
A143: v_pcb_dep_src_pf_ar_ca_dly | B143: tax_ownr_cst_id_num | C143: Tax Owner Customer Identification Number | H143: Sender Account Branch Number
A144: v_pcb_dep_src_pf_ar_ca_dly | B144: int_wthld_tax_cal_mthd | C144: Interest Withholding Tax Calculation Method | H144: Sender Account Product Type Code
A145: v_pcb_dep_src_pf_ar_ca_dly | B145: tax_key | C145: Tax Key | H145: Recipient Account Product Type Code
A146: v_pcb_dep_src_pf_ar_ca_dly | C146: Surety Account Flag | H146: Sender Account Product Feature Code
A147: v_pcb_dep_src_pf_ar_ca_dly | B147: block_cd | C147: Block Code | H147: Recipient Account Product Feature Code
A148: v_pcb_dep_src_pf_ar_ca_dly | C148: Debit or Credit Allowable Code | H148: Recipient Account Name in Thai
A149: v_pcb_dep_src_pf_ar_ca_dly | B149: tax_id_num | C149: Tax Identification Number | H149: Recipient Account Name in English
A150: v_pcb_dep_src_pf_ar_ca_dly | B150: cst_id_num | C150: customer Identification Number | H150: Sender Customer Name
A151: v_pcb_dep_src_pf_ar_ca_dly | B151: load_tms | H151: User Number
A152: v_pcb_dep_src_pf_ar_ca_dly | B152: src_sys_id | H152: Operation Type
A153: v_pcb_dep_src_pf_ar_ca_dly | B153: ptn_yyyy | H153: Cheque Number
A154: v_pcb_dep_src_pf_ar_ca_dly | B154: ptn_mm | H154: Cheque Bank Code
A155: v_pcb_dep_src_pf_ar_ca_dly | B155: ptn_dd | H155: Classification Scheme Type Code
A156: v_pcb_dep_src_pf_ar_fx_dly | B156: pos_dt | H156: Classification Scheme Number
A157: v_pcb_dep_src_pf_ar_fx_dly | B157: rec_tp | C157: Record Type | H157: Classification Number
A158: v_pcb_dep_src_pf_ar_fx_dly | B158: sub_acct_num | C158: Sub Account Number | H158: Parent Classification Number
A159: v_pcb_dep_src_pf_ar_fx_dly | B159: acct_num | C159: Account Number | H159: Classification Name in English
A160: v_pcb_dep_src_pf_ar_fx_dly | B160: src_pos_dt | C160: Source Position Date | H160: Classification Name in Thai
...

Sheet Batch2lot1
A1: View Name | B1: Column Name | C1: Column Name | E1: Description | F1: Mandatory | G1: Data Type | H1: Data Size | I1: Confidential Data | J1: Transformation Rules | K1: T Seq. | L1: Table Name | M1: Column Name | Q1: Status
A2: v_pcb_loan_common_limit_info | B2: pos_dt | C2: pos_dt | F2: M | G2: date | H2: 8 | J2: Direct Move | K2: 1 | L2: pcb_loan_common_limit_info | M2: pos_dt | Q2: clmn_nm_blnk | R2: =_xlfn.CONCAT(COUNTBLANK(B2:B3469)," Field") -> 198 Field
A3: v_pcb_loan_common_limit_info | B3: rec_tp | D3: rec_tp | E3: Record Type | F3: M | G3: alphanumeric | H3: 1 | J3: Direct Move | K3: 2 | L3: pcb_loan_common_limit_info | M3: rec_type | Q3: Completed | R3: 19 Doc
A4: v_pcb_loan_common_limit_info | B4: lmt_acct_num | D4: lmt_acct_num | E4: Limit Account Number | F4: M | G4: string | H4: 19 | J4: Direct Move | K4: 3 | L4: pcb_loan_common_limit_info | M4: lmt_ac_ar_id
A5: v_pcb_loan_common_limit_info | B5: prfl_acct_num | D5: prfl_acct_num | E5: Profile Account Number | F5: M | G5: string | H5: 12 | J5: Direct Move | K5: 4 | L5: pcb_loan_common_limit_info | M5: prfl_ac_ar_id
A6: v_pcb_loan_common_limit_info | B6: root_commit_acct_num | D6: root_commit_acct_num | E6: Root Commitment Account Number | F6: M | G6: string | H6: 19 | J6: Direct Move | K6: 5 | L6: pcb_loan_common_limit_info | M6: root_ac_ar_id
A7: v_pcb_loan_common_limit_info | B7: lmt_nm_in_thai | D7: lmt_nm_in_thai | E7: Limit Name in Thai | F7: M | G7: string | H7: 180 | J7: Direct Move | K7: 6 | L7: pcb_loan_common_limit_info | M7: ar_nm_th
A8: v_pcb_loan_common_limit_info | B8: lmt_nm_in_eng | D8: lmt_nm_in_eng | E8: Limit Name in English | F8: O | G8: string | H8: 180 | J8: Direct Move | K8: 7 | L8: pcb_loan_common_limit_info | M8: ar_nm_eng
A9: v_pcb_loan_common_limit_info | B9: cst_tp_cd | D9: cst_tp_cd | E9: Customer Type Code | F9: M | G9: string | H9: 5 | J9: Direct Move | K9: 8 | L9: pcb_loan_common_limit_info | M9: cst_typ_id
A10: v_pcb_loan_common_limit_info | B10: kbnk_bsn_cd | D10: kbnk_bsn_cd | E10: Kbank Business Code | F10: O | G10: string | H10: 9 | J10: Direct Move | K10: 9 | L10: pcb_loan_common_limit_info | M10: bsn_code_id
A11: v_pcb_loan_common_limit_info | B11: acct_pps_tp_cd | D11: acct_pps_tp_cd | E11: Account Purpose Type Code | F11: O | G11: string | H11: 3 | J11: Direct Move | K11: 10 | L11: pcb_loan_common_limit_info | M11: loan_pps_typ_id
A12: v_pcb_loan_common_limit_info | B12: cntrct_dt | D12: cntrct_dt | E12: Contract Date | F12: M | G12: date | H12: 10 | J12: Direct Move | K12: 11 | L12: pcb_loan_common_limit_info | M12: ctr_dt
A13: v_pcb_loan_common_limit_info | B13: eff_dt | D13: eff_dt | E13: Effective Date | F13: M | G13: date | H13: 10 | J13: Direct Move | K13: 12 | L13: pcb_loan_common_limit_info | M13: eff_dt
A14: v_pcb_loan_common_limit_info | B14: mat_dt | D14: mat_dt | E14: Maturity Date | F14: M | G14: date | H14: 10 | J14: Direct Move | K14: 13 | L14: pcb_loan_common_limit_info | M14: lmt_end_dt
A15: v_pcb_loan_common_limit_info | B15: acct_st | D15: acct_st | E15: Account Status | F15: M | G15: string | H15: 1 | J15: Direct Move | K15: 14 | L15: pcb_loan_common_limit_info | M15: ac_sts_id
... A31: v_pcb_loan_common_limit_info | B31: use_lmt_amt | D31: use_lmt_amt | E31: Used Limit Amount | F31: M | G31: decimal | H31: 17 | J31: Direct Move | K31: 30 | L31: pcb_loan_common_limit_info | M31: used_lmt
A32: v_pcb_loan_common_limit_info | E32: ESR Amount | F32: M | G32: decimal | H32: 17 | J32: Direct Move | K32: 31 | L32: pcb_loan_common_limit_info | M32: esr
A33: v_pcb_loan_common_limit_info | B33: unuse_lmt_amt | D33: unuse_lmt_amt | E33: Unused Limit Amount | F33: M | G33: decimal | H33: 17 | J33: Direct Move | K33: 32 | L33: pcb_loan_common_limit_info | M33: unused_lmt
A34: v_pcb_loan_common_limit_info | B34: avl_lmt_amt | D34: avl_lmt_amt | E34: Available Limit Amount | F34: M | G34: decimal | H34: 17 | J34: Direct Move | K34: 33 | L34: pcb_loan_common_limit_info | M34: avl_lmt
A35: v_pcb_loan_common_limit_info | B35: hold_amt | D35: hold_amt | E35: Holding Amount | F35: O | G35: decimal | H35: 17 | J35: Direct Move | K35: 34 | L35: pcb_loan_common_limit_info | M35: hold_amt
A36: v_pcb_loan_common_limit_info | B36: li_idv_f | D36: li_idv_f | E36: LI Individual Flag | F36: M | G36: smallint | H36: 1 | J36: Direct Move | K36: 35 | L36: pcb_loan_common_limit_info | M36: li_idv_flg
A37: v_pcb_loan_common_limit_info | E37: CIS Number | F37: M | G37: bigint | H37: 10 | J37: Direct Move | K37: 36 | L37: pcb_loan_common_limit_info | M37: cis_id
A38: v_pcb_loan_common_limit_info | B38: tot_li_amt | D38: tot_li_amt | E38: Total LI Amount | F38: O | G38: decimal | H38: 17 | J38: Direct Move | K38: 37 | L38: pcb_loan_common_limit_info | M38: tot_li_amt
A39: v_pcb_loan_common_limit_info | B39: tot_dr_amt | D39: tot_dr_amt | E39: Total Debit Amount | F39: O | G39: decimal | H39: 17 | J39: Direct Move | K39: 38 | L39: pcb_loan_common_limit_info | M39: tot_dr_amt
A40: v_pcb_loan_common_limit_info | B40: crrnt_int_rate_tp_cd | D40: crrnt_int_rate_tp_cd | E40: Current Interest Rate Type Code | F40: O | G40: string | H40: 3 | J40: Direct Move | K40: 39 | L40: pcb_loan_common_limit_info | M40: eff_int_rate_typ_id
A41: v_pcb_loan_common_limit_info | B41: crrnt_sprd_int_rate_sign | D41: crrnt_sprd_int_rate_sign | E41: Current Spread Interest Rate Sign | F41: O | G41: string | H41: 1 | J41: Direct Move | K41: 40 | L41: pcb_loan_common_limit_info | M41: eff_sprd_int_sign
A42: v_pcb_loan_common_limit_info | B42: crrnt_sprd_int_rate_pct | D42: crrnt_sprd_int_rate_pct | E42: Current Spread Interest Rate Percentage | F42: O | G42: decimal | H42: 8 | J42: Direct Move | K42: 41 | L42: pcb_loan_common_limit_info | M42: eff_sprd_int_rate
A43: v_pcb_loan_common_limit_info | B43: max_day | D43: max_day | E43: Max Day | F43: O | G43: smallint | H43: 4 | J43: Direct Move | K43: 42 | L43: pcb_loan_common_limit_info | M43: max_days
A44: v_pcb_loan_common_limit_info | B44: dedct_acct_num | D44: dedct_acct_num | E44: Deduction Account Number | F44: O | G44: string | H44: 10 | J44: Direct Move | K44: 43 | L44: pcb_loan_common_limit_info | M44: refr_ddcn_ac
A45: v_pcb_loan_common_limit_info | B45: dep_acct_num | D45: dep_acct_num | E45: Deposit Account Number | F45: O | G45: string | H45: 10 | J45: Direct Move | K45: 44 | L45: pcb_loan_common_limit_info | M45: rel_ac_ar_id
A46: v_pcb_loan_common_limit_info | B46: dep_sub_acct_num | D46: dep_sub_acct_num | E46: Deposit Sub Account Number | F46: O | G46: string | H46: 3 | J46: Direct Move | K46: 45 | L46: pcb_loan_common_limit_info | M46: rel_ac_ar_id_sub
A47: v_pcb_loan_common_limit_info | B47: dep_acct_crrnt_sprd_rate_pct | D47: dep_acct_crrnt_sprd_rate_pct | E47: Deposit Account Current Spread Rate Percentage | F47: O | G47: decimal | H47: 8 | J47: Direct Move | K47: 46 | L47: pcb_loan_common_limit_info | M47: rel_ac_sign_sprd
A48: v_pcb_loan_common_limit_info | B48: cr_prgm_cd | D48: cr_prgm_cd | E48: Credit Program Code | F48: O | G48: string | H48: 40 | J48: Direct Move | K48: 47 | L48: pcb_loan_common_limit_info | M48: cr_prog
A49: v_pcb_loan_common_limit_info | B49: appl_id_num | D49: appl_id_num | E49: Application Identification Number | F49: O | G49: string | H49: 50 | J49: Direct Move | K49: 48 | L49: pcb_loan_common_limit_info | M49: kcps_app_id
... A51: v_pcb_loan_common_limit_info | B51: fillr | D51: fillr | E51: Filler | F51: O | G51: string | H51: 183 | J51: Direct Move | K51: 50 | L51: pcb_loan_common_limit_info | M51: filler
A52: v_pcb_loan_common_limit_info | B52: load_tms | C52: load_tms | F52: M | G52: timestamp | H52: 26 | J52: Direct Move | K52: 51 | L52: pcb_loan_common_limit_info | M52: load_tms
A53: v_pcb_loan_common_limit_info | B53: src_sys_id | C53: src_sys_id | F53: M | G53: string | H53: 10 | J53: Direct Move | K53: 52 | L53: pcb_loan_common_limit_info | M53: src_sys_id
A54: v_pcb_loan_common_limit_info | B54: ptn_yyyy | C54: ptn_yyyy | F54: M | G54: string | H54: 4 | J54: Direct Move | K54: 53 | L54: pcb_loan_common_limit_info | M54: ptn_yyyy
A55: v_pcb_loan_common_limit_info | B55: ptn_mm | C55: ptn_mm | F55: M | G55: string | H55: 2 | J55: Direct Move | K55: 54 | L55: pcb_loan_common_limit_info | M55: ptn_mm
A56: v_pcb_loan_common_limit_info | B56: ptn_dd | C56: ptn_dd | F56: M | G56: string | H56: 2 | J56: Direct Move | K56: 55 | L56: pcb_loan_common_limit_info | M56: ptn_dd
A57: v_pcb_loan_common_market_code | B57: pos_dt | C57: pos_dt | F57: M | G57: date | H57: 8 | J57: Direct Move | K57: 1 | L57: pcb_loan_common_market_code | M57: pos_dt
A58: v_pcb_loan_common_market_code | B58: rec_tp | D58: rec_tp | E58: Record Type | F58: M | G58: alphanumeric | H58: 1 | J58: Direct Move | K58: 2 | L58: pcb_loan_common_market_code | M58: rec_type
A59: v_pcb_loan_common_market_code | B59: pd_grp_cd | D59: pd_grp_cd | E59: Product Group Code | F59: M | G59: string | H59: 4 | J59: Direct Move | K59: 3 | L59: pcb_loan_common_market_code | M59: pd_grp
A60: v_pcb_loan_common_market_code | B60: pd_tp_cd | D60: pd_tp_cd | E60: Product Type Code | F60: M | G60: string | H60: 4 | J60: Direct Move | K60: 4 | L60: pcb_loan_common_market_code | M60: pd_typ
A61: v_pcb_loan_common_market_code | B61: pd_sub_tp_cd | D61: pd_sub_tp_cd | E61: Product Sub Type Code | F61: M | G61: string | H61: 5 | J61: Direct Move | K61: 5 | L61: pcb_loan_common_market_code | M61: sub_typ_code
A62: v_pcb_loan_common_market_code | B62: mkt_cd | D62: mkt_cd | E62: Market Code | F62: M | G62: string | H62: 5 | J62: Direct Move | K62: 6 | L62: pcb_loan_common_market_code | M62: mkt_code
A63: v_pcb_loan_common_market_code | B63: mkt_desc | D63: mkt_desc | E63: Market Description | F63: M | G63: string | H63: 120 | J63: Direct Move | K63: 7 | L63: pcb_loan_common_market_code | M63: mkt_code_dsc
A64: v_pcb_loan_common_market_code | B64: pd_catg_tp_cd | D64: pd_catg_tp_cd | E64: Product Category Type Code | F64: M | G64: string | H64: 2 | J64: Direct Move | K64: 8 | L64: pcb_loan_common_market_code | M64: pd_cgy
A65: v_pcb_loan_common_market_code | B65: max_lmt_of_mkt_cd | D65: max_lmt_of_mkt_cd | E65: Max Limit of Market Code | F65: M | G65: decimal | H65: 17,2 | J65: Direct Move | K65: 9 | L65: pcb_loan_common_market_code | M65: mx_lmt
A66: v_pcb_loan_common_market_code | B66: load_tms | C66: load_tms | F66: M | G66: timestamp | H66: 26 | J66: Direct Move | K66: 10 | L66: pcb_loan_common_market_code | M66: load_tms
A67: v_pcb_loan_common_market_code | B67: src_sys_id | C67: src_sys_id | F67: M | G67: string | H67: 10 | J67: Direct Move | K67: 11 | L67: pcb_loan_common_market_code | M67: src_sys_id
A68: v_pcb_loan_common_market_code | B68: ptn_yyyy | C68: ptn_yyyy | F68: M | G68: string | H68: 4 | J68: Direct Move | K68: 12 | L68: pcb_loan_common_market_code | M68: ptn_yyyy
A69: v_pcb_loan_common_market_code | B69: ptn_mm | C69: ptn_mm | F69: M | G69: string | H69: 2 | J69: Direct Move | K69: 13 | L69: pcb_loan_common_market_code | M69: ptn_mm
A70: v_pcb_loan_common_market_code | B70: ptn_dd | C70: ptn_dd | F70: M | G70: string | H70: 2 | J70: Direct Move | K70: 14 | L70: pcb_loan_common_market_code | M70: ptn_dd
A71: v_pcb_loan_common_rate_type | B71: pos_dt | C71: pos_dt | F71: M | G71: date | H71: 8 | J71: Direct Move | K71: 1 | L71: pcb_loan_common_rate_type | M71: pos_dt
A72: v_pcb_loan_common_rate_type | B72: rec_tp | D72: rec_tp | E72: Record Type | F72: M | G72: alphanumeric | H72: 1 | J72: Direct Move | K72: 2 | L72: pcb_loan_common_rate_type | M72: rec_type
A73: v_pcb_loan_common_rate_type | B73: orig_int_rate_tp_cd | D73: orig_int_rate_tp_cd | E73: Origin Interest Rate Type Code | F73: M | G73: string | H73: 3 | J73: Direct Move | K73: 3 | L73: pcb_loan_common_rate_type | M73: int_idnx
A74: v_pcb_loan_common_rate_type | B74: mgrt_int_rate_tp_cd | D74: mgrt_int_rate_tp_cd | E74: Migrated Interest Rate Type Code | F74: M | G74: string | H74: 20 | J74: Direct Move | K74: 4 | L74: pcb_loan_common_rate_type | M74: pcb_int_idnx
A75: v_pcb_loan_common_rate_type | B75: int_rate_tp_desc | D75: int_rate_tp_desc | E75: Interest Rate Type Description | F75: M | G75: string | H75: 50 | J75: Direct Move | K75: 5 | L75: pcb_loan_common_rate_type | M75: int_dsc
A76: v_pcb_loan_common_rate_type | B76: int_indx_tp_cd | D76: int_indx_tp_cd | E76: Interest Index Type Code | F76: M | G76: string | H76: 1 | J76: Direct Move | K76: 6 | L76: pcb_loan_common_rate_type | M76: int_idnx_tp
A77: v_pcb_loan_common_rate_type | B77: crrnt_int_rate_pct | D77: crrnt_int_rate_pct | E77: Current Interest Rate Percentage | F77: M | G77: decimal | H77: 3,5 | J77: Direct Move | K77: 7 | L77: pcb_loan_common_rate_type | M77: eff_int_rate
A78: v_pcb_loan_common_rate_type | B78: cntrct_sprd_f | D78: cntrct_sprd_f | E78: Contract Spread Flag | F78: M | G78: string | H78: 1 | J78: Direct Move | K78: 8 | L78: pcb_loan_common_rate_type | M78: ctr_sprd_flg
A79: v_pcb_loan_common_rate_type | B79: strt_dt | D79: strt_dt | E79: Start Date | F79: M | G79: date | H79: 8 | J79: Direct Move | K79: 9 | L79: pcb_loan_common_rate_type | M79: start_dt
A80: v_pcb_loan_common_rate_type | B80: end_dt | D80: end_dt | E80: End Date | F80: M | G80: date | H80: 8 | J80: Direct Move | K80: 10 | L80: pcb_loan_common_rate_type | M80: end_dt
A81: v_pcb_loan_common_rate_type | B81: int_tp_cd | D81: int_tp_cd | E81: Interest Type Code | F81: O | G81: smallint | H81: 1 | J81: Direct Move | K81: 11 | L81: pcb_loan_common_rate_type | M81: rate_type
A82: v_pcb_loan_common_rate_type | B82: ccy_cd | D82: ccy_cd | E82: Currency Code | F82: O | G82: string | H82: 3 | J82: Direct Move | K82: 12 | L82: pcb_loan_common_rate_type | M82: ccy_code
A83: v_pcb_loan_common_rate_type | B83: indx_sub_catg | D83: indx_sub_catg | E83: Index Sub Category | F83: O | G83: string | H83: 6 | J83: Direct Move | K83: 13 | L83: pcb_loan_common_rate_type | M83: sub_category
A84: v_pcb_loan_common_rate_type | B84: tenor_cd | D84: tenor_cd | E84: Tenor Code | F84: O | G84: string | H84: 10 | J84: Direct Move | K84: 14 | L84: pcb_loan_common_rate_type | M84: tenor
A85: v_pcb_loan_common_rate_type | B85: cal_back_priod | D85: cal_back_priod | E85: Calculation Back Period | F85: O | G85: smallint | H85: 3 | J85: Direct Move | K85: 15 | L85: pcb_loan_common_rate_type | M85: cal_back_period
A86: v_pcb_loan_common_rate_type | B86: load_tms | C86: load_tms | F86: M | G86: timestamp | H86: 26 | J86: Direct Move | K86: 16 | L86: pcb_loan_common_rate_type | M86: load_tms
A87: v_pcb_loan_common_rate_type | B87: src_sys_id | C87: src_sys_id | F87: M | G87: string | H87: 10 | J87: Direct Move | K87: 17 | L87: pcb_loan_common_rate_type | M87: src_sys_id
A88: v_pcb_loan_common_rate_type | B88: ptn_yyyy | C88: ptn_yyyy | F88: M | G88: string | H88: 4 | J88: Direct Move | K88: 18 | L88: pcb_loan_common_rate_type | M88: ptn_yyyy
A89: v_pcb_loan_common_rate_type | B89: ptn_mm | C89: ptn_mm | F89: M | G89: string | H89: 2 | J89: Direct Move | K89: 19 | L89: pcb_loan_common_rate_type | M89: ptn_mm
A90: v_pcb_loan_common_rate_type | B90: ptn_dd | C90: ptn_dd | F90: M | G90: string | H90: 2 | J90: Direct Move | K90: 20 | L90: pcb_loan_common_rate_type | M90: ptn_dd
A91: v_pcb_loan_common_account_tier_by_time | B91: pos_dt | C91: pos_dt | F91: M | G91: date | H91: 8 | J91: Direct Move | K91: 1 | L91: pcb_loan_common_account_tier_by_time | M91: pos_dt
A92: v_pcb_loan_common_account_tier_by_time | B92: mgrt_acct_num | D92: mgrt_acct_num | E92: Migrated Account Number | F92: M | G92: string | H92: 19 | J92: Direct Move | K92: 2 | L92: pcb_loan_common_account_tier_by_time | M92: ac_ar_id
A93: v_pcb_loan_common_account_tier_by_time | B93: acct_num | D93: acct_num | E93: Account Number | F93: M | G93: string | H93: 12 | J93: Direct Move | K93: 3 | L93: pcb_loan_common_account_tier_by_time | M93: prfl_ac_ar_id
A94: v_pcb_loan_common_account_tier_by_time | B94: eff_dt | D94: eff_dt | E94: Effective Date | F94: M | G94: date | H94: 8 | J94: Direct Move | K94: 4 | L94: pcb_loan_common_account_tier_by_time | M94: eff_dt
A95: v_pcb_loan_common_account_tier_by_time | B95: end_dt | D95: end_dt | E95: End Date | F95: O | G95: date | H95: 8 | J95: Direct Move | K95: 5 | L95: pcb_loan_common_account_tier_by_time | M95: end_dt
A96: v_pcb_loan_common_account_tier_by_time | B96: int_rate_indx | D96: int_rate_indx | E96: Interest Rate Index | F96: M | G96: string | H96: 3 | J96: Direct Move | K96: 6 | L96: pcb_loan_common_account_tier_by_time | M96: int_idnx
A97: v_pcb_loan_common_account_tier_by_time | B97: int_sign | D97: int_sign | E97: Interest Sign | F97: O | G97: string | H97: 1 | J97: Direct Move | K97: 7 | L97: pcb_loan_common_account_tier_by_time | M97: int_rate_sign
A98: v_pcb_loan_common_account_tier_by_time | B98: sprd_rate_pct | D98: sprd_rate_pct | E98: Spread Rate Percentage | F98: O | G98: decimal | H98: 8,5 | J98: Direct Move | K98: 8 | L98: pcb_loan_common_account_tier_by_time | M98: int_rate_sprd
A99: v_pcb_loan_common_account_tier_by_time | B99: crrnt_int_rate_tp_cd | D99: crrnt_int_rate_tp_cd | E99: Current Interest Rate Type Code | F99: M | G99: string | H99: 20 | J99: Direct Move | K99: 9 | L99: pcb_loan_common_account_tier_by_time | M99: eff_int_rate_typ_prfl
A100: v_pcb_loan_common_account_tier_by_time | B100: load_tms | C100: load_tms | F100: M | G100: timestamp | H100: 26 | J100: Direct Move | K100: 10 | L100: pcb_loan_common_account_tier_by_time | M100: load_tms
A101: v_pcb_loan_common_account_tier_by_time | B101: src_sys_id | C101: src_sys_id | F101: M | G101: string | H101: 10 | J101: Direct Move | K101: 11 | L101: pcb_loan_common_account_tier_by_time | M101: src_sys_id
A102: v_pcb_loan_common_account_tier_by_time | B102: ptn_yyyy | C102: ptn_yyyy | F102: M | G102: string | H102: 4 | J102: Direct Move | K102: 12 | L102: pcb_loan_common_account_tier_by_time | M102: ptn_yyyy
A103: v_pcb_loan_common_account_tier_by_time | B103: ptn_mm | C103: ptn_mm | F103: M | G103: string | H103: 2 | J103: Direct Move | K103: 13 | L103: pcb_loan_common_account_tier_by_time | M103: ptn_mm
A104: v_pcb_loan_common_account_tier_by_time | B104: ptn_dd | C104: ptn_dd | F104: M | G104: string | H104: 2 | J104: Direct Move | K104: 14 | L104: pcb_loan_common_account_tier_by_time | M104: ptn_dd
A105: v_pcb_dep_cb2d0005_odencitd_sam | B105: pos_dt | C105: pos_dt | F105: M | G105: date | H105: 8 | J105: Direct Move | K105: 1 | L105: pcb_dep_cb2d0005_odencitd_sam | M105: pos_dt
A106: v_pcb_dep_cb2d0005_odencitd_sam | B106: ca_acct_num | D106: ca_acct_num | E106: CA Account Number | F106: M | G106: string | H106: 10 | J106: Direct Move | K106: 2 | L106: pcb_dep_cb2d0005_odencitd_sam | M106: ar_id
A107: v_pcb_dep_cb2d0005_odencitd_sam | E107: OD/ENC/ITD Limit Account Number | F107: M | G107: string | H107: 10 | J107: Direct Move | K107: 3 | L107: pcb_dep_cb2d0005_odencitd_sam | M107: lmt_ar_id
A108: v_pcb_dep_cb2d0005_odencitd_sam | B108: domc_br_num | D108: domc_br_num | E108: Domicile Branch Number | F108: M | G108: string | H108: 4 | J108: Direct Move | K108: 4 | L108: pcb_dep_cb2d0005_odencitd_sam | M108: domc_br_no
A109: v_pcb_dep_cb2d0005_odencitd_sam | B109: crrnt_lmt_sign | D109: crrnt_lmt_sign | E109: Current Limit Sign | F109: M | G109: string | H109: 1 | J109: Direct Move | K109: 5 | L109: pcb_dep_cb2d0005_odencitd_sam | M109: crn_lmt_sign
A110: v_pcb_dep_cb2d0005_odencitd_sam | B110: crrnt_lmt_amt | D110: crrnt_lmt_amt | E110: Current Limit Amount | F110: M | G110: decimal | H110: 15,2 | J110: Direct Move | K110: 6 | L110: pcb_dep_cb2d0005_odencitd_sam | M110: crn_lmt_amt
A111: v_pcb_dep_cb2d0005_odencitd_sam | B111: enc_usg_lmt_sign | D111: enc_usg_lmt_sign | E111: ENC Usage Limit Sign | F111: O | G111: string | H111: 1 | J111: Direct Move | K111: 7 | L111: pcb_dep_cb2d0005_odencitd_sam | M111: drvd_lmt_sign
A112: v_pcb_dep_cb2d0005_odencitd_sam | B112: enc_usg_lmt_by_dep_chq | D112: enc_usg_lmt_by_dep_chq | E112: ENC Usage Limit by Deposit Cheque | F112: O | G112: decimal | H112: 15,2 | J112: Direct Move | K112: 8 | L112: pcb_dep_cb2d0005_odencitd_sam | M112: drvd_lmt_amt
A113: v_pcb_dep_cb2d0005_odencitd_sam | B113: use_lmt_sign | D113: use_lmt_sign | E113: Used Limit Sign | F113: O | G113: string | H113: 1 | J113: Direct Move | K113: 9 | L113: pcb_dep_cb2d0005_odencitd_sam | M113: utlz_lmt_sign
A114: v_pcb_dep_cb2d0005_odencitd_sam | B114: use_lmt_amt | D114: use_lmt_amt | E114: Used Limit Amount | F114: O | G114: decimal | H114: 15,2 | J114: Direct Move | K114: 10 | L114: pcb_dep_cb2d0005_odencitd_sam | M114: utlz_lmt_amt
A115: v_pcb_dep_cb2d0005_odencitd_sam | B115: otsnd_bal_sign | D115: otsnd_bal_sign | E115: Outstanding Balance Sign | F115: O | G115: string | H115: 1 | J115: Direct Move | K115: 11 | L115: pcb_dep_cb2d0005_odencitd_sam | M115: otsnd_sign
A116: v_pcb_dep_cb2d0005_odencitd_sam | B116: otsnd_bal_amt | D116: otsnd_bal_amt | E116: Outstanding Balance Amount | F116: O | G116: decimal | H116: 15,2 | J116: Direct Move | K116: 12 | L116: pcb_dep_cb2d0005_odencitd_sam | M116: otsnd_bal
...

Sheet Batch2lot2
A1: View Name | B1: Column Name | C1: sys+Column Name+add filler | D1: Column | E1: Key | F1: Description | G1: Mandatory | H1: Data Type | I1: Data Size | J1: Confidential Data | K1: Transformation Rules | L1: T Seq. | M1: Table Name | N1: Column Name | R1: Status
A2: v_gts_kbgt_cont_outstanding | B2: pos_dt | C2: pos_dt | E2: =VLOOKUP(F2,[13]abbr_btch2lot2!A:B,2,FALSE) -> #N/A | G2: M | H2: date | I2: 8 | K2: Direct Move | L2: 1 | M2: gts_kbgt_cont_outstanding | N2: pos_dt | R2: clmn_nm_blnk | S2: =_xlfn.CONCAT(COUNTBLANK(C2:C3469)," Field") -> 585 Field
A3: v_gts_kbgt_cont_outstanding | C3: acct_num | D3: acct_num | E3: =VLOOKUP(F3,[13]abbr_btch2lot2!A:B,2,FALSE) -> 1 | F3: Account Number | G3: M | H3: string | I3: 15 | K3: Direct Move | L3: 2 | M3: gts_kbgt_cont_outstanding | N3: trade_ref | R3: Completed | S3: 5 Doc
A4: v_gts_kbgt_cont_outstanding | C4: mgrt_acct_num | D4: mgrt_acct_num | E4: =VLOOKUP(F4,[13]abbr_btch2lot2!A:B,2,FALSE) -> 2 | F4: Migrated Account Number | G4: O | H4: string | I4: 15 | K4: Direct Move | L4: 3 | M4: gts_kbgt_cont_outstanding | N4: old_traderef
A5: v_gts_kbgt_cont_outstanding | E5: =VLOOKUP(F5,[13]abbr_btch2lot2!A:B,2,FALSE) -> 3 | F5: CIS Number | G5: M | H5: string | I5: 10 | K5: Direct Move | L5: 4 | M5: gts_kbgt_cont_outstanding | N5: cis_id
A6: v_gts_kbgt_cont_outstanding | C6: fclty_cd | D6: fclty_cd | E6: =VLOOKUP(F6,[13]abbr_btch2lot2!A:B,2,FALSE) -> 4 | F6: Facility Code | G6: O | H6: string | I6: 11 | K6: Direct Move | L6: 5 | M6: gts_kbgt_cont_outstanding | N6: facility_id
A7: v_gts_kbgt_cont_outstanding | C7: lmt_cd | D7: lmt_cd | E7: =VLOOKUP(F7,[13]abbr_btch2lot2!A:B,2,FALSE) -> 5 | F7: Limit Code | G7: O | H7: string | I7: 19 | K7: Direct Move | L7: 6 | M7: gts_kbgt_cont_outstanding | N7: limit_id
A8: v_gts_kbgt_cont_outstanding | C8: fclty_lvl | D8: fclty_lvl | E8: =VLOOKUP(F8,[13]abbr_btch2lot2!A:B,2,FALSE) -> 6 | F8: Facility Level | G8: O | H8: string | I8: 1 | K8: Direct Move | L8: 7 | M8: gts_kbgt_cont_outstanding | N8: facility_level
A9: v_gts_kbgt_cont_outstanding | C9: lvl_6_lmt_cd | D9: lvl_6_lmt_cd | E9: =VLOOKUP(F9,[13]abbr_btch2lot2!A:B,2,FALSE) -> 7 | F9: Level 6 Limit Code | G9: O | H9: string | I9: 19 | K9: Direct Move | L9: 8 | M9: gts_kbgt_cont_outstanding | N9: l6_limit_id
A10: v_gts_kbgt_cont_outstanding | C10: issu_dt | D10: issu_dt | E10: =VLOOKUP(F10,[13]abbr_btch2lot2!A:B,2,FALSE) -> 8 | F10: Issue Date | G10: M | H10: date | I10: 10 | K10: Direct Move | L10: 9 | M10: gts_kbgt_cont_outstanding | N10: issue_date
A11: v_gts_kbgt_cont_outstanding | C11: eff_dt | D11: eff_dt | E11: =VLOOKUP(F11,[13]abbr_btch2lot2!A:B,2,FALSE) -> 9 | F11: Effective Date | G11: M | H11: date | I11: 10 | K11: Direct Move | L11: 10 | M11: gts_kbgt_cont_outstanding | N11: eff_date
A12: v_gts_kbgt_cont_outstanding | C12: mat_dt | D12: mat_dt | E12: =VLOOKUP(F12,[13]abbr_btch2lot2!A:B,2,FALSE) -> 10 | F12: Maturity Date | G12: M | H12: date | I12: 10 | K12: Direct Move | L12: 11 | M12: gts_kbgt_cont_outstanding | N12: maturity-date
A13: v_gts_kbgt_cont_outstanding | C13: due_dt | D13: due_dt | E13: =VLOOKUP(F13,[13]abbr_btch2lot2!A:B,2,FALSE) -> 11 | F13: Due Date | G13: M | H13: date | I13: 10 | K13: Direct Move | L13: 12 | M13: gts_kbgt_cont_outstanding | N13: due-date
A14: v_gts_kbgt_cont_outstanding | C14: cls_dt | D14: cls_dt | E14: =VLOOKUP(F14,[13]abbr_btch2lot2!A:B,2,FALSE) -> 12 | F14: Close Date | G14: O | H14: date | I14: 10 | K14: Direct Move | L14: 13 | M14: gts_kbgt_cont_outstanding | N14: close_date
A15: v_gts_kbgt_cont_outstanding | C15: acct_st | D15: acct_st | E15: =VLOOKUP(F15,[13]abbr_btch2lot2!A:B,2,FALSE) -> 13 | F15: Account Status | G15: O | H15: string | I15: 1 | K15: Direct Move | L15: 14 | M15: gts_kbgt_cont_outstanding | N15: status
A16: v_gts_kbgt_cont_outstanding | C16: tenor | D16: tenor | E16: =VLOOKUP(F16,[13]abbr_btch2lot2!A:B,2,FALSE) -> 14 | F16: Tenor | G16: M | H16: decimal | I16: 5,0 | K16: Direct Move | L16: 15 | M16: gts_kbgt_cont_outstanding | N16: term
A17: v_gts_kbgt_cont_outstanding | C17: tenor_unit | D17: tenor_unit | E17: =VLOOKUP(F17,[13]abbr_btch2lot2!A:B,2,FALSE) -> 15 | F17: Tenor Unit | G17: M | H17: string | I17: 1 | K17: Direct Move | L17: 16 | M17: gts_kbgt_cont_outstanding | N17: term_unit
A18: v_gts_kbgt_cont_outstanding | C18: ccy_cd | D18: ccy_cd | E18: =VLOOKUP(F18,[13]abbr_btch2lot2!A:B,2,FALSE) -> 16 | F18: Currency Code | G18: M | H18: string | I18: 3 | K18: Direct Move | L18: 17 | M18: gts_kbgt_cont_outstanding | N18: ccy_code
A19: v_gts_kbgt_cont_outstanding | C19: orig_pnp_amt_in_orig_ccy | D19: orig_pnp_amt_in_orig_ccy | E19: =VLOOKUP(F19,[13]abbr_btch2lot2!A:B,2,FALSE) -> 17 | F19: Original Principal Amount in Original Currency | G19: M | H19: decimal | I19: 18,2 | K19: Direct Move | L19: 18 | M19: gts_kbgt_cont_outstanding | N19: prin_org_amount_ccy
A20: v_gts_kbgt_cont_outstanding | C20: orig_pnp_amt_in_thb | D20: orig_pnp_amt_in_thb | E20: =VLOOKUP(F20,[13]abbr_btch2lot2!A:B,2,FALSE) -> 18 | F20: Original Principal Amount in Thai Baht | G20: M | H20: decimal | I20: 18,2 | K20: Direct Move | L20: 19 | M20: gts_kbgt_cont_outstanding | N20: prin_org_amount_thb
A21: v_gts_kbgt_cont_outstanding | C21: crrnt_orig_pnp_amt_in_orig_ccy | D21: crrnt_orig_pnp_amt_in_orig_ccy | E21: =VLOOKUP(F21,[13]abbr_btch2lot2!A:B,2,FALSE) -> 19 | F21: Current Original Principal Amount in Original Currency | G21: M | H21: decimal | I21: 18,2 | K21: Direct Move | L21: 20 | M21: gts_kbgt_cont_outstanding | N21: prin_cur_amount_ccy
A22: v_gts_kbgt_cont_outstanding | C22: crrnt_orig_pnp_amt_in_thb | D22: crrnt_orig_pnp_amt_in_thb | E22: =VLOOKUP(F22,[13]abbr_btch2lot2!A:B,2,FALSE) -> 20 | F22: Current Original Principal Amount in Thai Baht | G22: M | H22: decimal | I22: 18,2 | K22: Direct Move | L22: 21 | M22: gts_kbgt_cont_outstanding | N22: prin_cur_amount_thb
A23: v_gts_kbgt_cont_outstanding | C23: dly_acru_int_amt_in_orig_ccy | D23: dly_acru_int_amt_in_orig_ccy | E23: =VLOOKUP(F23,[13]abbr_btch2lot2!A:B,2,FALSE) -> 21 | F23: Daily Accrued Interest amount in Original Currency | G23: M | H23: decimal | I23: 18,2 | K23: Direct Move | L23: 22 | M23: gts_kbgt_cont_outstanding | N23: int_daily_accru_ccy
A24: v_gts_kbgt_cont_outstanding | C24: dly_acru_int_amt_in_thb | D24: dly_acru_int_amt_in_thb | E24: =VLOOKUP(F24,[13]abbr_btch2lot2!A:B,2,FALSE) -> 22 | F24: Daily Accrued Interest amount in Thai Baht | G24: M | H24: decimal | I24: 18,2 | K24: Direct Move | L24: 23 | M24: gts_kbgt_cont_outstanding | N24: int_daily_accru_thb
A25: v_gts_kbgt_cont_outstanding | C25: rmain_acru_int_in_orig_ccy | D25: rmain_acru_int_in_orig_ccy | E25: =VLOOKUP(F25,[13]abbr_btch2lot2!A:B,2,FALSE) -> 23 | F25: Remain Accrued Interest in Original Currency | G25: M | H25: decimal | I25: 18,2 | K25: Direct Move | L25: 24 | M25: gts_kbgt_cont_outstanding | N25: int_remain_amount_ccy
A26: v_gts_kbgt_cont_outstanding | C26: rmain_acru_int_in_thb | D26: rmain_acru_int_in_thb | E26: =VLOOKUP(F26,[13]abbr_btch2lot2!A:B,2,FALSE) -> 24 | F26: Remain Accrued Interest in Thai Baht | G26: M | H26: decimal | I26: 18,2 | K26: Direct Move | L26: 25 | M26: gts_kbgt_cont_outstanding | N26: int_remain_amount_thb
A27: v_gts_kbgt_cont_outstanding | C27: discnt_amt_in_orig_ccy | D27: discnt_amt_in_orig_ccy | E27: =VLOOKUP(F27,[13]abbr_btch2lot2!A:B,2,FALSE) -> 25 | F27: Discount Amount in Original Currency | G27: O | H27: decimal | I27: 18,2 | K27: Direct Move | L27: 26 | M27: gts_kbgt_cont_outstanding | N27: disc_amount_ccy
A28: v_gts_kbgt_cont_outstanding | C28: discnt_amt_in_thb | D28: discnt_amt_in_thb | E28: =VLOOKUP(F28,[13]abbr_btch2lot2!A:B,2,FALSE) -> 26 | F28: Discount Amount in Thai Baht | G28: O | H28: decimal | I28: 18,2 | K28: Direct Move | L28: 27 | M28: gts_kbgt_cont_outstanding | N28: disc_amount_thb
A29: v_gts_kbgt_cont_outstanding | C29: amtz_amt_in_orig_ccy | D29: amtz_amt_in_orig_ccy | E29: =VLOOKUP(F29,[13]abbr_btch2lot2!A:B,2,FALSE) -> 27 | F29: Amortized amount in Original Currency | G29: O | H29: decimal | I29: 18,2 | K29: Direct Move | L29: 28 | M29: gts_kbgt_cont_outstanding | N29: amrz_amount_ccy
A30: v_gts_kbgt_cont_outstanding | C30: amtz_amt_in_thb | D30: amtz_amt_in_thb | E30: =VLOOKUP(F30,[13]abbr_btch2lot2!A:B,2,FALSE) -> 28 | F30: Amortized amount in Thai Baht | G30: O | H30: decimal | I30: 18,2 | K30: Direct Move | L30: 29 | M30: gts_kbgt_cont_outstanding | N30: amrz_amount_thb
... A41: v_gts_kbgt_cont_outstanding | C41: tot_unpaid_fee_amt_in_thb | D41: tot_unpaid_fee_amt_in_thb | E41: =VLOOKUP(F41,[13]abbr_btch2lot2!A:B,2,FALSE) -> 39 | F41: Total Unpaid Fee amount in Thai Baht | G41: M | H41: decimal | I41: 18,2 | K41: Direct Move | L41: 40 | M41: gts_kbgt_cont_outstanding | N41: unpaid_fee_thb
A42: v_gts_kbgt_cont_outstanding | C42: last_paymt_dt | D42: last_paymt_dt | E42: =VLOOKUP(F42,[13]abbr_btch2lot2!A:B,2,FALSE) -> 40 | F42: Last Payment Date | G42: O | H42: date | I42: 10 | K42: Direct Move | L42: 41 | M42: gts_kbgt_cont_outstanding | N42: date_of_last_payment
A43: v_gts_kbgt_cont_outstanding | C43: last_paymt_amt_in_orig_ccy | D43: last_paymt_amt_in_orig_ccy | E43: =VLOOKUP(F43,[13]abbr_btch2lot2!A:B,2,FALSE) -> 41 | F43: Last Payment Amount in Original Currency | G43: O | H43: decimal | I43: 18,2 | K43: Direct Move | L43: 42 | M43: gts_kbgt_cont_outstanding | N43: amt_last_payment_ccy
A44: v_gts_kbgt_cont_outstanding | C44: last_paymt_amt_in_thb | D44: last_paymt_amt_in_thb | E44: =VLOOKUP(F44,[13]abbr_btch2lot2!A:B,2,FALSE) -> 42 | F44: Last Payment Amount in Thai Baht | G44: O | H44: decimal | I44: 18,2 | K44: Direct Move | L44: 43 | M44: gts_kbgt_cont_outstanding | N44: amt_last_payment_thb
A45: v_gts_kbgt_cont_outstanding | C45: accum_paymt_amt_in_orig_ccy | D45: accum_paymt_amt_in_orig_ccy | E45: =VLOOKUP(F45,[13]abbr_btch2lot2!A:B,2,FALSE) -> 43 | F45: Accumulate Payment Amount in Original Currency | G45: O | H45: bigint | I45: 18 | K45: Direct Move | L45: 44 | M45: gts_kbgt_cont_outstanding | N45: amt_accum_payment_ccy
A46: v_gts_kbgt_cont_outstanding | C46: accum_paymt_amt_in_thb | D46: accum_paymt_amt_in_thb | E46: =VLOOKUP(F46,[13]abbr_btch2lot2!A:B,2,FALSE) -> 44 | F46: Accumulate Payment Amount in Thai Baht | G46: O | H46: bigint | I46: 18 | K46: Direct Move | L46: 45 | M46: gts_kbgt_cont_outstanding | N46: amt_accum_payment_thb
A47: v_gts_kbgt_cont_outstanding | C47: mid_rate | D47: mid_rate | E47: =VLOOKUP(F47,[13]abbr_btch2lot2!A:B,2,FALSE) -> 45 | F47: Mid Rate | G47: M | H47: decimal | I47: 11,7 | K47: Direct Move | L47: 46 | M47: gts_kbgt_cont_outstanding | N47: mid_rate
A48: v_gts_kbgt_cont_outstanding | C48: crrnt_int_rate | D48: crrnt_int_rate | E48: =VLOOKUP(F48,[13]abbr_btch2lot2!A:B,2,FALSE) -> 46 | F48: Current Interest Rate | G48: M | H48: decimal | I48: 9,7 | K48: Direct Move | L48: 47 | M48: gts_kbgt_cont_outstanding | N48: eff_rate
A49: v_gts_kbgt_cont_outstanding | C49: rate_tp_cd | D49: rate_tp_cd | E49: =VLOOKUP(F49,[13]abbr_btch2lot2!A:B,2,FALSE) -> 47 | F49: Rate Type Code | G49: M | H49: string | I49: 3 | K49: Direct Move | L49: 48 | M49: gts_kbgt_cont_outstanding | N49: rate_type
A50: v_gts_kbgt_cont_outstanding | C50: sign | D50: sign | E50: =VLOOKUP(F50,[13]abbr_btch2lot2!A:B,2,FALSE) -> 48 | F50: Sign | G50: O | H50: string | I50: 1 | K50: Direct Move | L50: 49 | M50: gts_kbgt_cont_outstanding | N50: sign
A51: v_gts_kbgt_cont_outstanding | C51: sprd_rate | D51: sprd_rate | E51: =VLOOKUP(F51,[13]abbr_btch2lot2!A:B,2,FALSE) -> 49 | F51: Spread Rate | G51: O | H51: decimal | I51: 9,7 | K51: Direct Move | L51: 50 | M51: gts_kbgt_cont_outstanding | N51: spread_rate
A52: v_gts_kbgt_cont_outstanding | C52: int_late_chrg_rate | D52: int_late_chrg_rate | E52: =VLOOKUP(F52,[13]abbr_btch2lot2!A:B,2,FALSE) -> 50 | F52: Interest Late Charge Rate | G52: O | H52: decimal | I52: 9,7 | K52: Direct Move | L52: 51 | M52: gts_kbgt_cont_outstanding | N52: int_late_chg_rate
A53: v_gts_kbgt_cont_outstanding | C53: max_rate | D53: max_rate | E53: =VLOOKUP(F53,[13]abbr_btch2lot2!A:B,2,FALSE) -> 51 | F53: Max Rate | G53: M | H53: decimal | I53: 9,7 | K53: Direct Move | L53: 52 | M53: gts_kbgt_cont_outstanding | N53: max_rate
A54: v_gts_kbgt_cont_outstanding | C54: int_paymt_frq | D54: int_paymt_frq | E54: =VLOOKUP(F54,[13]abbr_btch2lot2!A:B,2,FALSE) -> 52 | F54: Interest Payment Frequency | G54: M | H54: smallint | I54: 1 | K54: Direct Move | L54: 53 | M54: gts_kbgt_cont_outstanding | N54: int_pay_type
A55: v_gts_kbgt_cont_outstanding | C55: kbnk_pd_cd | D55: kbnk_pd_cd | E55: =VLOOKUP(F55,[13]abbr_btch2lot2!A:B,2,FALSE) -> 53 | F55: Kbank Product Code | G55: M | H55: integer | I55: 9 | K55: Direct Move | L55: 54 | M55: gts_kbgt_cont_outstanding | N55: kbank_product_code
A56: v_gts_kbgt_cont_outstanding | C56: ln_tp_cd | D56: ln_tp_cd | E56: =VLOOKUP(F56,[13]abbr_btch2lot2!A:B,2,FALSE) -> 54 | F56: Loan Type Code | G56: O | H56: string | I56: 1 | K56: Direct Move | L56: 55 | M56: gts_kbgt_cont_outstanding | N56: type_of_loan
A57: v_gts_kbgt_cont_outstanding | C57: rvrs_f | D57: rvrs_f | E57: =VLOOKUP(F57,[13]abbr_btch2lot2!A:B,2,FALSE) -> 55 | F57: Reverse Flag | G57: M | H57: smallint | I57: 1 | K57: Direct Move | L57: 56 | M57: gts_kbgt_cont_outstanding | N57: reverse_flag
A58: v_gts_kbgt_cont_outstanding | C58: rvrs_dt | D58: rvrs_dt | E58: =VLOOKUP(F58,[13]abbr_btch2lot2!A:B,2,FALSE) -> 56 | F58: Reverse Date | G58: O | H58: date | I58: 10 | K58: Direct Move | L58: 57 | M58: gts_kbgt_cont_outstanding | N58: reverse_date
A59: v_gts_kbgt_cont_outstanding | C59: day_pass_due_pnp | D59: day_pass_due_pnp | E59: =VLOOKUP(F59,[13]abbr_btch2lot2!A:B,2,FALSE) -> 57 | F59: Days Pass Due Principle | G59: O | H59: smallint | I59: 5 | K59: Direct Move | L59: 58 | M59: gts_kbgt_cont_outstanding | N59: dpd-prin
A60: v_gts_kbgt_cont_outstanding | C60: day_pass_due_int | D60: day_pass_due_int | E60: =VLOOKUP(F60,[13]abbr_btch2lot2!A:B,2,FALSE) -> 58 | F60: Days Pass Due Interest | G60: O | H60: smallint | I60: 5 | K60: Direct Move | L60: 59 | M60: gts_kbgt_cont_outstanding | N60: dpd-int
A61: v_gts_kbgt_cont_outstanding | C61: day_pass_due_bot | D61: day_pass_due_bot | E61: =VLOOKUP(F61,[13]abbr_btch2lot2!A:B,2,FALSE) -> 59 | F61: Days Pass Due BOT | G61: O | H61: smallint | I61: 5 | K61: Direct Move | L61: 60 | M61: gts_kbgt_cont_outstanding | N61: dpd-bot
A62: v_gts_kbgt_cont_outstanding | C62: day_pass_due_strt_dt | D62: day_pass_due_strt_dt | E62: =VLOOKUP(F62,[13]abbr_btch2lot2!A:B,2,FALSE) -> 60 | F62: Days Pass Due Start Date | G62: O | H62: date | I62: 10 | K62: Direct Move | L62: 61 | M62: gts_kbgt_cont_outstanding | N62: dpd_start_date
A63: v_gts_kbgt_cont_outstanding | C63: ovdue_amt_in_orig_ccy | D63: ovdue_amt_in_orig_ccy | E63: =VLOOKUP(F63,[13]abbr_btch2lot2!A:B,2,FALSE) -> 61 | F63: Overdue amount in Original Currency | G63: O | H63: decimal | I63: 18,2 | K63: Direct Move | L63: 62 | M63: gts_kbgt_cont_outstanding | N63: overdue_amount_ccy
A64: v_gts_kbgt_cont_outstanding | C64: ovdue_amt_in_thb | D64: ovdue_amt_in_thb | E64: =VLOOKUP(F64,[13]abbr_btch2lot2!A:B,2,FALSE) -> 62 | F64: Overdue amount in Thai Baht | G64: O | H64: decimal | I64: 18,2 | K64: Direct Move | L64: 63 | M64: gts_kbgt_cont_outstanding | N64: overdue_amount_thb
A65: v_gts_kbgt_cont_outstanding | E65: =VLOOKUP(F65,[13]abbr_btch2lot2!A:B,2,FALSE) -> 63 | F65: DDC Account Number | G65: O | H65: bigint | I65: 10 | K65: Direct Move | L65: 64 | M65: gts_kbgt_cont_outstanding | N65: regis_repay_dda
A66: v_gts_kbgt_cont_outstanding | C66: brwr_tp_cd | D66: brwr_tp_cd | E66: =VLOOKUP(F66,[13]abbr_btch2lot2!A:B,2,FALSE) -> 64 | F66: Borrower Type Code | G66: M | H66: string | I66: 1 | K66: Direct Move | L66: 65 | M66: gts_kbgt_cont_outstanding | N66: borrower_type
A67: v_gts_kbgt_cont_outstanding | C67: grc_priod_f | D67: grc_priod_f | E67: =VLOOKUP(F67,[13]abbr_btch2lot2!A:B,2,FALSE) -> 65 | F67: Grace Period Flag | G67: M | H67: string | I67: 1 | K67: Direct Move | L67: 66 | M67: gts_kbgt_cont_outstanding | N67: grace_flag
A68: v_gts_kbgt_cont_outstanding | C68: grc_priod_strt_dt | D68: grc_priod_strt_dt | E68: =VLOOKUP(F68,[13]abbr_btch2lot2!A:B,2,FALSE) -> 66 | F68: Grace period Start Date | G68: O | H68: date | I68: 10 | K68: Direct Move | L68: 67 | M68: gts_kbgt_cont_outstanding | N68: grace_start_date
A69: v_gts_kbgt_cont_outstanding | C69: grc_priod_end_dt | D69: grc_priod_end_dt | E69: =VLOOKUP(F69,[13]abbr_btch2lot2!A:B,2,FALSE) -> 67 | F69: Grace period End Date | G69: O | H69: date | I69: 10 | K69: Direct Move | L69: 68 | M69: gts_kbgt_cont_outstanding | N69: grace_end_date
A70: v_gts_kbgt_cont_outstanding | C70: rc_cd | D70: rc_cd | E70: =VLOOKUP(F70,[13]abbr_btch2lot2!A:B,2,FALSE) -> 68 | F70: RC Code | G70: M | H70: string | I70: 5 | K70: Direct Move | L70: 69 | M70: gts_kbgt_cont_outstanding | N70: center-code
A71: v_gts_kbgt_cont_outstanding | C71: coa_lgl_entity_cd_for_pnp | D71: coa_lgl_entity_cd_for_pnp | E71: =VLOOKUP(F71,[13]abbr_btch2lot2!A:B,2,FALSE) -> 69 | F71: COA Legal Entity Code for Principle | G71: M | H71: smallint | I71: 3 | K71: Direct Move | L71: 70 | M71: gts_kbgt_cont_outstanding | N71: prin_coa_lgl_ent
A72: v_gts_kbgt_cont_outstanding | C72: coa_rc_for_pnp | D72: coa_rc_for_pnp | E72: =VLOOKUP(F72,[13]abbr_btch2lot2!A:B,2,FALSE) -> 70 | F72: COA Responsibility Centre for Principle | G72: M | H72: smallint | I72: 5 | K72: Direct Move | L72: 71 | M72: gts_kbgt_cont_outstanding | N72: prin_coa_rspl_cntr
A73: v_gts_kbgt_cont_outstanding | E73: =VLOOKUP(F73,[13]abbr_btch2lot2!A:B,2,FALSE) -> 71 | F73: COA OGL Account Number for Principle | G73: M | H73: integer | I73: 7 | K73: Direct Move | L73: 72 | M73: gts_kbgt_cont_outstanding | N73: prin_coa_ac
A74: v_gts_kbgt_cont_outstanding | C74: coa_func_cd_for_pnp | D74: coa_func_cd_for_pnp | E74: =VLOOKUP(F74,[13]abbr_btch2lot2!A:B,2,FALSE) -> 72 | F74: COA Function Code for Principle | G74: M | H74: smallint | I74: 1 | K74: Direct Move | L74: 73 | M74: gts_kbgt_cont_outstanding | N74: prin_coa_fnc
A75: v_gts_kbgt_cont_outstanding | C75: coa_line_of_bsn_for_pnp | D75: coa_line_of_bsn_for_pnp | E75: =VLOOKUP(F75,[13]abbr_btch2lot2!A:B,2,FALSE) -> 73 | F75: COA Line of Business for Principle | G75: M | H75: smallint | I75: 3 | K75: Direct Move | L75: 74 | M75: gts_kbgt_cont_outstanding | N75: prin_coa_line_of_bsn
A76: v_gts_kbgt_cont_outstanding | C76: coa_pd_cd_for_pnp | D76: coa_pd_cd_for_pnp | E76: =VLOOKUP(F76,[13]abbr_btch2lot2!A:B,2,FALSE) -> 74 | F76: COA Product Code for Principle | G76: M | H76: integer | I76: 6 | K76: Direct Move | L76: 75 | M76: gts_kbgt_cont_outstanding | N76: prin_coa_pd
A77: v_gts_kbgt_cont_outstanding | E77: =VLOOKUP(F77,[13]abbr_btch2lot2!A:B,2,FALSE) -> 75 | F77: COA Inter Company Code for Principle | G77: M | H77: smallint | I77: 3 | K77: Direct Move | L77: 76 | M77: gts_kbgt_cont_outstanding | N77: prin_coa_intco
A78: v_gts_kbgt_cont_outstanding | E78: =VLOOKUP(F78,[13]abbr_btch2lot2!A:B,2,FALSE) -> 76 | F78: COA Intra Company Code for Principle | G78: M | H78: smallint | I78: 5 | K78: Direct Move | L78: 77 | M78: gts_kbgt_cont_outstanding | N78: prin_coa_inrco
A79: v_gts_kbgt_cont_outstanding | C79: coa_prj_cd_for_pnp | D79: coa_prj_cd_for_pnp | E79: =VLOOKUP(F79,[13]abbr_btch2lot2!A:B,2,FALSE) -> 77 | F79: COA Project Code for Principle | G79: M | H79: smallint | I79: 4 | K79: Direct Move | L79: 78 | M79: gts_kbgt_cont_outstanding | N79: prin_coa_prj
A80: v_gts_kbgt_cont_outstanding | C80: coa_futr_use_1_cd_for_pnp | D80: coa_futr_use_1_cd_for_pnp | E80: =VLOOKUP(F80,[13]abbr_btch2lot2!A:B,2,FALSE) -> 78 | F80: COA Future Use 1 Code for Principle | G80: M | H80: integer | I80: 7 | K80: Direct Move | L80: 79 | M80: gts_kbgt_cont_outstanding | N80: prin_coa_futr_used1
A81: v_gts_kbgt_cont_outstanding | C81: coa_futr_use_2_cd_for_pnp | D81: coa_futr_use_2_cd_for_pnp | E81: =VLOOKUP(F81,[13]abbr_btch2lot2!A:B,2,FALSE) -> 79 | F81: COA Future Use 2 Code for Principle | G81: M | H81: smallint | I81: 4 | K81: Direct Move | L81: 80 | M81: gts_kbgt_cont_outstanding | N81: prin_coa_futr_used2
A82: v_gts_kbgt_cont_outstanding | C82: coa_pd_ftr_cd_for_pnp | D82: coa_pd_ftr_cd_for_pnp | E82: =VLOOKUP(F82,[13]abbr_btch2lot2!A:B,2,FALSE) -> 80 | F82: COA Product Feature Code for Principle | G82: M | H82: integer | I82: 9 | K82: Direct Move | L82: 81 | M82: gts_kbgt_cont_outstanding | N82: prin_coa_pd_ftr_code
A83: v_gts_kbgt_cont_outstanding | C83: coa_lgl_entity_cd_for_acru_int | D83: coa_lgl_entity_cd_for_acru_int | E83: =VLOOKUP(F83,[13]abbr_btch2lot2!A:B,2,FALSE) -> 81 | F83: COA Legal Entity Code for Accrued Interest | G83: M | H83: smallint | I83: 3 | K83: Direct Move | L83: 82 | M83: gts_kbgt_cont_outstanding | N83: accu_int_coa_lgl_ent
A84: v_gts_kbgt_cont_outstanding | C84: coa_rc_for_acru_int | D84: coa_rc_for_acru_int | E84: =VLOOKUP(F84,[13]abbr_btch2lot2!A:B,2,FALSE) -> 82 | F84: COA Responsibility Centre for Accrued Interest | G84: M | H84: smallint | I84: 5 | K84: Direct Move | L84: 83 | M84: gts_kbgt_cont_outstanding | N84: accu_int_coa_rspl_cntr
A85: v_gts_kbgt_cont_outstanding | E85: =VLOOKUP(F85,[13]abbr_btch2lot2!A:B,2,FALSE) -> 83 | F85: COA OGL Account Number for Accrued Interest | G85: M | H85: integer | I85: 7 | K85: Direct Move | L85: 84 | M85: gts_kbgt_cont_outstanding | N85: accu_int_coa_ac
A86: v_gts_kbgt_cont_outstanding | C86: coa_func_cd_for_acru_int | D86: coa_func_cd_for_acru_int | E86: =VLOOKUP(F86,[13]abbr_btch2lot2!A:B,2,FALSE) -> 84 | F86: COA Function Code for Accrued Interest | G86: M | H86: smallint | I86: 1 | K86: Direct Move | L86: 85 | M86: gts_kbgt_cont_outstanding | N86: accu_int_coa_fnc
A87: v_gts_kbgt_cont_outstanding | C87: coa_line_of_bsn_for_acru_int | D87: coa_line_of_bsn_for_acru_int | E87: =VLOOKUP(F87,[13]abbr_btch2lot2!A:B,2,FALSE) -> 85 | F87: COA Line of Business for Accrued Interest | G87: M | H87: smallint | I87: 3 | K87: Direct Move | L87: 86 | M87: gts_kbgt_cont_outstanding | N87: accu_int_coa_line_of_bsn
A88: v_gts_kbgt_cont_outstanding | C88: coa_pd_cd_for_acru_int | D88: coa_pd_cd_for_acru_int | E88: =VLOOKUP(F88,[13]abbr_btch2lot2!A:B,2,FALSE) -> 86 | F88: COA Product Code for Accrued Interest | G88: M | H88: integer | I88: 6 | K88: Direct Move | L88: 87 | M88: gts_kbgt_cont_outstanding | N88: accu_int_coa_pd
A89: v_gts_kbgt_cont_outstanding | E89: =VLOOKUP(F89,[13]abbr_btch2lot2!A:B,2,FALSE) -> 87 | F89: COA Inter Company Code for Accrued Interest | G89: M | H89: smallint | I89: 3 | K89: Direct Move | L89: 88 | M89: gts_kbgt_cont_outstanding | N89: accu_int_coa_intco
A90: v_gts_kbgt_cont_outstanding | E90: =VLOOKUP(F90,[13]abbr_btch2lot2!A:B,2,FALSE) -> 88 | F90: COA Intra Company Code for Accrued Interest | G90: M | H90: smallint | I90: 5 | K90: Direct Move | L90: 89 | M90: gts_kbgt_cont_outstanding | N90: accu_int_coa_inrco
A91: v_gts_kbgt_cont_outstanding | C91: coa_prj_cd_for_acru_int | D91: coa_prj_cd_for_acru_int | E91: =VLOOKUP(F91,[13]abbr_btch2lot2!A:B,2,FALSE) -> 89 | F91: COA Project Code for Accrued Interest | G91: M | H91: smallint | I91: 4 | K91: Direct Move | L91: 90 | M91: gts_kbgt_cont_outstanding | N91: accu_int_coa_prj
A92: v_gts_kbgt_cont_outstanding | C92: coa_futr_use_1_cd_for_acru_int | D92: coa_futr_use_1_cd_for_acru_int | E92: =VLOOKUP(F92,[13]abbr_btch2lot2!A:B,2,FALSE) -> 90 | F92: COA Future Use 1 Code for Accrued Interest | G92: M | H92: integer | I92: 7 | K92: Direct Move | L92: 91 | M92: gts_kbgt_cont_outstanding | N92: accu_int_coa_futr_used1
A93: v_gts_kbgt_cont_outstanding | C93: coa_futr_use_2_cd_for_acru_int | D93: coa_futr_use_2_cd_for_acru_int | E93: =VLOOKUP(F93,[13]abbr_btch2lot2!A:B,2,FALSE) -> 91 | F93: COA Future Use 2 Code for Accrued Interest | G93: M | H93: smallint | I93: 4 | K93: Direct Move | L93: 92 | M93: gts_kbgt_cont_outstanding | N93: accu_int_coa_futr_used2
A94: v_gts_kbgt_cont_outstanding | C94: coa_pd_ftr_cd_for_acru_int | D94: coa_pd_ftr_cd_for_acru_int | E94: =VLOOKUP(F94,[13]abbr_btch2lot2!A:B,2,FALSE) -> 92 | F94: COA Product Feature Code for Accrued Interest | G94: M | H94: integer | I94: 9 | K94: Direct Move | L94: 93 | M94: gts_kbgt_cont_outstanding | N94: accu_int_coa_pd_ftr_code
A95: v_gts_kbgt_cont_outstanding | C95: coa_lgl_entity_cd_for_rvrs_acru_int | D95: coa_lgl_entity_cd_for_rvrs_acru_int | E95: =VLOOKUP(F95,[13]abbr_btch2lot2!A:B,2,FALSE) -> 93 | F95: COA Legal Entity Code for Reverse Accrued Interest | G95: O | H95: smallint | I95: 3 | K95: Direct Move | L95: 94 | M95: gts_kbgt_cont_outstanding | N95: rev_int_coa_lgl_ent
A96: v_gts_kbgt_cont_outstanding | C96: coa_rc_for_rvrs_acru_int | D96: coa_rc_for_rvrs_acru_int | E96: =VLOOKUP(F96,[13]abbr_btch2lot2!A:B,2,FALSE) -> 94 | F96: COA Responsibility Centre for Reverse Accrued Interest | G96: O | H96: smallint | I96: 5 | K96: Direct Move | L96: 95 | M96: gts_kbgt_cont_outstanding | N96: rev_int_coa_rspl_cntr
A97: v_gts_kbgt_cont_outstanding | E97: =VLOOKUP(F97,[13]abbr_btch2lot2!A:B,2,FALSE) -> 95 | F97: COA OGL Account Number for Reverse Accrued Interest | G97: O | H97: integer | I97: 7 | K97: Direct Move | L97: 96 | M97: gts_kbgt_cont_outstanding | N97: rev_int_coa_ac
A98: v_gts_kbgt_cont_outstanding | C98: coa_func_cd_for_rvrs_acru_int | D98: coa_func_cd_for_rvrs_acru_int | E98: =VLOOKUP(F98,[13]abbr_btch2lot2!A:B,2,FALSE) -> 96 | F98: COA Function Code for Reverse Accrued Interest | G98: O | H98: smallint | I98: 1 | K98: Direct Move | L98: 97 | M98: gts_kbgt_cont_outstanding | N98: rev_int_coa_fnc
A99: v_gts_kbgt_cont_outstanding | C99: coa_line_of_bsn_for_rvrs_acru_int | D99: coa_line_of_bsn_for_rvrs_acru_int | E99: =VLOOKUP(F99,[13]abbr_btch2lot2!A:B,2,FALSE) -> 97 | F99: COA Line of Business for Reverse Accrued Interest | G99: O | H99: smallint | I99: 3 | K99: Direct Move | L99: 98 | M99: gts_kbgt_cont_outstanding | N99: rev_int_coa_line_of_bsn
A100: v_gts_kbgt_cont_outstanding | C100: coa_pd_cd_for_rvrs_acru_int | D100: coa_pd_cd_for_rvrs_acru_int | E100: =VLOOKUP(F100,[13]abbr_btch2lot2!A:B,2,FALSE) -> 98 | F100: COA Product Code for Reverse Accrued Interest | G100: O | H100: integer | I100: 6 | K100: Direct Move | L100: 99 | M100: gts_kbgt_cont_outstanding | N100: rev_int_coa_pd
A101: v_gts_kbgt_cont_outstanding | E101: =VLOOKUP(F101,[13]abbr_btch2lot2!A:B,2,FALSE) -> 99 | F101: COA Inter Company Code for Reverse Accrued Interest | G101: O | H101: smallint | I101: 3 | K101: Direct Move | L101: 100 | M101: gts_kbgt_cont_outstanding | N101: rev_int_coa_intco
A102: v_gts_kbgt_cont_outstanding | E102: =VLOOKUP(F102,[13]abbr_btch2lot2!A:B,2,FALSE) -> 100 | F102: COA Intra Company Code for Reverse Accrued Interest | G102: O | H102: smallint | I102: 5 | K102: Direct Move | L102: 101 | M102: gts_kbgt_cont_outstanding | N102: rev_int_coa_inrco
A103: v_gts_kbgt_cont_outstanding | C103: coa_prj_cd_for_rvrs_acru_int | D103: coa_prj_cd_for_rvrs_acru_int | E103: =VLOOKUP(F103,[13]abbr_btch2lot2!A:B,2,FALSE) -> 101 | F103: COA Project Code for Reverse Accrued Interest | G103: O | H103: smallint | I103: 4 | K103: Direct Move | L103: 102 | M103: gts_kbgt_cont_outstanding | N103: rev_int_coa_prj
A104: v_gts_kbgt_cont_outstanding | C104: coa_futr_use_1_cd_for_rvrs_acru_int | D104: coa_futr_use_1_cd_for_rvrs_acru_int | E104: =VLOOKUP(F104,[13]abbr_btch2lot2!A:B,2,FALSE) -> 102 | F104: COA Future Use 1 Code for Reverse Accrued Interest | G104: O | H104: integer | I104: 7 | K104: Direct Move | L104: 103 | M104: gts_kbgt_cont_outstanding | N104: rev_int_coa_futr_used1
A105: v_gts_kbgt_cont_outstanding | C105: coa_futr_use_2_cd_for_rvrs_acru_int | D105: coa_futr_use_2_cd_for_rvrs_acru_int | E105: =VLOOKUP(F105,[13]abbr_btch2lot2!A:B,2,FALSE) -> 103 | F105: COA Future Use 2 Code for Reverse Accrued Interest | G105: O | H105: smallint | I105: 4 | K105: Direct Move | L105: 104 | M105: gts_kbgt_cont_outstanding | N105: rev_int_coa_futr_used2
A106: v_gts_kbgt_cont_outstanding | C106: coa_pd_ftr_cd_for_rvrs_acru_int | D106: coa_pd_ftr_cd_for_rvrs_acru_int | E106: =VLOOKUP(F106,[13]abbr_btch2lot2!A:B,2,FALSE) -> 104 | F106: COA Product Feature Code for Reverse Accrued Interest | G106: O | H106: integer | I106: 9 | K106: Direct Move | L106: 105 | M106: gts_kbgt_cont_outstanding | N106: rev_int_coa_pd_ftr_code
A107: v_gts_kbgt_cont_outstanding | C107: coa_lgl_entity_cd_for_memo_acru_int | D107: coa_lgl_entity_cd_for_memo_acru_int | E107: =VLOOKUP(F107,[13]abbr_btch2lot2!A:B,2,FALSE) -> 105 | F107: COA Legal Entity Code for Memo Accrued Interest | G107: O | H107: smallint | I107: 3 | K107: Direct Move | L107: 106 | M107: gts_kbgt_cont_outstanding | N107: memo_coa_lgl_ent
A108: v_gts_kbgt_cont_outstanding | C108: coa_rc_for_memo_acru_int | D108: coa_rc_for_memo_acru_int | E108: =VLOOKUP(F108,[13]abbr_btch2lot2!A:B,2,FALSE) -> 106 | F108: COA Responsibility Centre for Memo Accrued Interest | G108: O | H108: smallint | I108: 5 | K108: Direct Move | L108: 107 | M108: gts_kbgt_cont_outstanding | N108: memo_coa_rspl_cntr
A109: v_gts_kbgt_cont_outstanding | E109: =VLOOKUP(F109,[13]abbr_btch2lot2!A:B,2,FALSE) -> 107 | F109: COA OGL Account Number for Memo Accrued Interest | G109: O | H109: integer | I109: 7 | K109: Direct Move | L109: 108 | M109: gts_kbgt_cont_outstanding | N109: memo_coa_ac
A110: v_gts_kbgt_cont_outstanding | C110: coa_func_cd_for_memo_acru_int | D110: coa_func_cd_for_memo_acru_int | E110: =VLOOKUP(F110,[13]abbr_btch2lot2!A:B,2,FALSE) -> 108 | F110: COA Function Code for Memo Accrued Interest | G110: O | H110: smallint | I110: 1 | K110: Direct Move | L110: 109 | M110: gts_kbgt_cont_outstanding | N110: memo_coa_fnc
...

Sheet Batch 1
A1: =COUNTA(A3:A949) -> 37
A2: No | B2: Batch | C2: System | D2: File name/Table name | E2: EBAN/DIH | F2: KBMF File Reference | G2: CBR EBAN File Reference | H2: Status
A3: 1 | B3: Batch 1 | C3: PCB-Deposit | D3: src_pf_ar_sa_dly_yyyymmdd.txt | E3: EBAN
A4: 2 | B4: Batch 1 | C4: PCB-Deposit | D4: src_pf_ar_ca_dly_yyyymmdd.txt | E4: EBAN
A5: 3 | B5: Batch 1 | C5: PCB-Deposit | D5: src_pf_ar_fx_dly_yyyymmdd.txt | E5: EBAN
A6: 4 | B6: Batch 1 | C6: PCB-Deposit | D6: src_pf_ar_sf_dly_yyyymmdd.txt | E6: EBAN
A7: 5 | B7: Batch 1 | C7: PCB-Deposit | D7: PCB_DIH_ExtRATE1_YYYYMMDD.txt | E7: EBAN
A8: 6 | B8: Batch 1 | C8: PCB-Deposit | D8: Common_Market_Code.txt | E8: EBAN
A9: 7 | B9: Batch 1 | C9: PCB-Lending | D9: Common_Account_Info_YYYYMMDD.txt | E9: EBAN
A10: 8 | B10: Batch 1 | C10: PCB-Lending | D10: Common_Limit_Info_YYYYMMDD.txt | E10: EBAN
A11: 9 | B11: Batch 1 | C11: PCB-Lending | D11: Account_Defer_Interest_YYYYMMDD.txt | E11: EBAN
A12: 10 | B12: Batch 1 | C12: PCB-Lending | D12: Common_Rate_Type.txt | E12: EBAN
A13: 11 | B13: Batch 1 | C13: PCB-Lending | D13: Common_Billing_Detail_yyyymmdd.txt | E13: EBAN
A14: 12 | B14: Batch 1 | C14: PCB-Lending | D14: Common_Billing_yyyymmdd.txt | E14: EBAN
... A39: 37 | B39: Batch 1 | C39: PCB-Lending | D39: Bene_Product_Type_YYYYMMDD.txt | E39: EBAN

Sheet Batch 2 - Old
A1: 404
A2: No | B2: Batch | C2: System | D2: Plan | E2: File name/Table name | F2: EBAN/DIH | G2: KBMF File Reference | H2: CBR File Reference | I2: Status
A3: 1 | B3: Batch 2 | C3: K PLUS | D3: Plan B | E3: View_JMobileActLog_Log | F3: EBAN | H3: CBR_V_MB_ACTN_LOG_v.1.8
A4: 2 | B4: Batch 2 | C4: K PLUS | D4: Plan B | E4: View_JMobile_Log | F4: EBAN | H4: CBR_V_MB_PLUS_IP_MSTR_V.0.13
A5: 3 | B5: Batch 2 | C5: K PLUS | D5: Plan B | E5: View_JMobileAcctCard_Log | F5: EBAN | H5: CBR_V_MB_PLUS_IP_X_AR_REL_v0.5
A6: 4 | B6: Batch 2 | C6: LPM-AS/400​ | D6: Plan B | E6: LMD23400 | F6: EBAN | H6: CBR_VP_LPM_LMT_AR_INF_BFR_WRTOF_v0.5
A7: 5 | B7: Batch 2 | C7: LPM-AS/400​ | D7: Plan B | E7: L01D070 | F7: EBAN | H7: CBR_V_LPM_AR_WRTOF_RCV_v0.9.xlsx
A8: 6 | B8: Batch 2 | C8: LPM-AS/400​ | D8: Plan B | E8: L01W769 | F8: EBAN | H8: CBR_VP_LPM_LN_CNTG_DMMY_CLSS_PRVN_v0.19
A9: 7 | B9: Batch 2 | C9: LPM-AS/400​ | D9: Plan B | E9: L01W181 | F9: EBAN | H9: CBR_VP_LPM_LN_CARD_CLSS_PRVN_v0.18
A10: 8 | B10: Batch 2 | C10: LPM-AS/400​ | D10: Plan B | E10: L01W909 | F10: EBAN | H10: CBR_VP_LPM_LN_CNTG_CLSS_PRVN_v0.18
A11: 9 | B11: Batch 2 | C11: LPM-AS/400​ | D11: Plan B | E11: L01D027 | F11: EBAN | H11: CBR_VP_LPM_AR_CLSS_QLY_v.0.8
A12: 10 | B12: Batch 2 | C12: LPM-AS/400​ | D12: Plan B | E12: L01D003 | F12: EBAN | H12: CBR_VP_LPM_AR_INF_v0.14
A13: 11 | B13: Batch 2 | C13: LPM-AS/400​ | D13: Plan B | E13: LMD24000 | F13: EBAN | H13: CBR_VP_LPM_LMT_AR_INF_v0.11
A14: 12 | B14: Batch 2 | C14: LPM-AS/400​ | D14: Plan B | E14: DRD07200-HIST-TDR-ACCT-FILE | F14: EBAN | H14: CBR_VP_LPM_AR_TDR_TRCK
... A45: 43 | B45: Batch 2 | C45: LPM-TDR | D45: Plan B | E45: CT1D408A_YYYYMMDD.txt | F45: EBAN | H45: CBR_VP_TDR_AR_RESHD_v1.1
A46: 44 | B46: Batch 2 | C46: Trade-Navigator | D46: Plan B | E46: RDT_SCF_CL_ACCT_NAL_yyyymmdd.txt | F46: EBAN
A47: 45 | B47: Batch 2 | C47: Trade-Navigator | D47: Plan B | E47: LCR070_YYYYMMDD.txt | F47: EBAN
A48: 46 | B48: Batch 2 | C48: Trade-Navigator | D48: Plan B | E48: SRC_EXIMAR_YYYYMMDD.TXT | F48: EBAN
A49: 47 | B49: Batch 2 | C49: Trade-Navigator | D49: Plan B | E49: BASEL_YYYYMMDD.txt | F49: EBAN
A50: 48 | B50: Batch 2 | C50: Trade-Navigator | D50: Plan B | E50: EB059F_YYYYMMDD.TXT | F50: EBAN
A51: 49 | B51: Batch 2 | C51: Trade-Navigator | D51: Plan B | E51: AML_YYYYMMDD.txt | F51: EBAN
A52: 50 | B52: Batch 2 | C52: Trade-Navigator | D52: Plan B | E52: LPM030_YYYYMMDD.TXT | F52: EBAN
A53: 51 | B53: Batch 2 | C53: Trade-Navigator | D53: Plan B | E53: src_trdna_txn_trd_fnc_yyyymmdd.txt | F53: EBAN
A54: 52 | B54: Batch 2 | C54: Trade-Navigator | D54: Plan B | E54: LAP040F_YYYYMM.txt | F54: EBAN
A55: 53 | B55: Batch 2 | C55: Trade-Navigator | D55: Plan B | E55: CT1D364_yyyymm.txt | F55: EBAN
A56: 54 | B56: Batch 2 | C56: Trade-Navigator | D56: Plan B | E56: LCR071_YYYYMMDD.txt | F56: EBAN
A57: 55 | B57: Batch 2 | C57: Trade-Navigator | D57: Plan B | E57: daily_turn_over_yyyymmdd.txt | F57: EBAN
... A184: 182 | B184: Batch 2 | C184: UD | D184: Plan B | E184: VW_TRANSACTIONEXT | F184: EBAN
A185: 183 | B185: Batch 2 | C185: CIS | D185: Plan A | E185: MQ_AR_IPXAR
A186: 184 | B186: Batch 2 | C186: CIS | D186: Plan A | E186: MQ_DIH_ARXCONTACT
A187: 185 | B187: Batch 2 | C187: CIS | D187: Plan A | E187: V_RELAR
A188: 186 | B188: Batch 2 | C188: CIS | D188: Plan A | E188: MQ_ARXAR
A189: 187 | B189: Batch 2 | C189: CIS | D189: Plan A | E189: V_CNTCHNNL
A190: 188 | B190: Batch 2 | C190: CIS | D190: Plan A | E190: V_CNTPDDMN
A191: 189 | B191: Batch 2 | C191: CIS | D191: Plan A | E191: V_CNTPURPS
A192: 190 | B192: Batch 2 | C192: CIS | D192: Plan A | E192: MQ_DNTCNT
A193: 191 | B193: Batch 2 | C193: CIS | D193: Plan A | E193: V_DOCTP
A194: 192 | B194: Batch 2 | C194: CIS | D194: Plan A | E194: V_IPMERGE
A195: 193 | B195: Batch 2 | C195: CIS | D195: Plan A | E195: MQ_DIH_OTHDOC
A196: 194 | B196: Batch 2 | C196: CIS | D196: Plan A | E196: V_CNTRELTP
... A209: 207 | B209: Batch 2 | C209: CIS | D209: Plan A | E209: CRIFLDSTM
A210: 208 | B210: Batch 2 | C210: FCD | D210: Plan B | E210: FCD_AR_YYYYMMDD.txt | F210: EBAN
A211: 209 | B211: Batch 2 | C211: CSM | D211: Plan A | E211: CSM_CUSTXFORMXCONSENT_YYYYMMDD.TXT | F211: N/A | H211: CBR_V_CNSNT_FORM_KBNK_V0.7.xlsx
A212: 210 | B212: Batch 2 | C212: CSM | D212: Plan A | E212: CSM_FORMXAPPR_YYYYMMDD.TXT | F212: N/A | H212: CBR_VP_CNSNT_FORM_DTL_V0.1.xlsx
A213: 211 | B213: Batch 2 | C213: CSM | D213: Plan A | E213: CSM_CHANNEL_YYYYMMDD.TXT | F213: N/A | H213: CBR_VP_CNSNT_CNL_CD_v.0.1.xlsx
A214: 212 | B214: Batch 2 | C214: CSM | D214: Plan A | E214: CSM_ORIGINATEPRODUCTCOA_YYYYMMDD.TXT | F214: N/A
A215: 213 | B215: Batch 2 | C215: CSM | D215: Plan A | E215: CSM_ORIGINATEPRODUCTNONCOA_YYYYMMDD.TXT | F215: N/A | H215: CBR_VP_CNSNT_ORIG_NON_COA_PD_CD_v.0.2.xlsx
A216: 214 | B216: Batch 2 | C216: CSM | D216: Plan A | E216: CSM_PURPOSE_YYYYMMDD.TXT | F216: N/A | H216: CBR_VP_CNSNT_PPS_CD_v.0.1.xlsx
A217: 215 | B217: Batch 2 | C217: CSM | D217: Plan A | E217: CSM_COMPANY_YYYYMMDD.TXT | F217: N/A | H217: CBR_VP_CNSNT_CO_CD_v.0.2.xlsx
A218: 216 | B218: Batch 2 | C218: CSM | D218: Plan A | E218: CSM_RECEIVERTYPE_YYYYMMDD.TXT | F218: N/A
A219: 217 | B219: Batch 2 | C219: CSM | D219: Plan A | E219: CSM_FORMCONSENT_YYYYMMDD.TXT | F219: N/A
A220: 218 | B220: Batch 2 | C220: CSM | D220: Plan A | E220: CSM_FORMXCONTENT_YYYYMMDD.TXT | F220: N/A
A221: 219 | B221: Batch 2 | C221: RDM | D221: Plan B | E221: mdm.CST_IP_LGL_STC_TP_CD | F221: EBAN | H221: CBR_V_IP_LGL_STC_TP_CD_v.0.5
A222: 220 | B222: Batch 2 | C222: RDM | D222: Plan B | E222: mdm.CST_NAT_CD | F222: EBAN | H222: CBR_V_NAT_CD_v0.7
A223: 221 | B223: Batch 2 | C223: RDM | D223: Plan B | E223: mdm.CST_MAR_ST_CD | F223: EBAN | H223: CBR_V_MAR_ST_CD_v0.8
A224: 222 | B224: Batch 2 | C224: RDM | D224: Plan B | E224: mdm.CST_CTF_TP_CD | F224: EBAN | H224: CBR_V_CTF_TP_CD_v.0.7
A225: 223 | B225: Batch 2 | C225: RDM | D225: Plan B | E225: mdm.CST_OCP_CD | F225: EBAN | H225: CBR_V_OCP_CD_V0.4_PRD
A226: 224 | B226: Batch 2 | C226: RDM | D226: Plan B | E226: mdm.CST_PROF_CD | F226: EBAN | H226: CBR_EBAN_V_PROF_CD_V0.7
A227: 225 | B227: Batch 2 | C227: RDM | D227: Plan B | E227: mdm.CST_IDV_INCM_SEG_CD | F227: EBAN | H227: CBR_V_IDV_INCM_SEG_CD_v.1.0
A228: 226 | B228: Batch 2 | C228: RDM | D228: Plan B | E228: mdm.CARD_TP_CD | F228: EBAN | H228: CBR_EBAN_V_CC_TP_CD_v1.0
A229: 227 | B229: Batch 2 | C229: RDM | D229: Plan B | E229: VC_IDY_CL_CD | F229: DIH | H229: CBR_EBAN_VC_REFR_IDY_CL_CD_v2.2.xlsx
A230: 228 | B230: Batch 2 | C230: RDM | D230: Plan B | E230: mdm.CST_SEG_CD | F230: EBAN | H230: CBR_V_SEG_CD_v1.2
A231: 229 | B231: Batch 2 | C231: RDM | D231: Plan B | E231: mdm.CST_CTY_CD | F231: EBAN | H231: CBR_V_CTY_CD_v.0.8
A232: 230 | B232: Batch 2 | C232: RDM | D232: Plan B | E232: mdm.PCB_TLR_ID | F232: EBAN
A233: 231 | B233: Batch 2 | C233: RDM | D233: Plan B | E233: mdm.PCB_TXN_CD | F233: EBAN
A234: 232 | B234: Batch 2 | C234: RDM | D234: Plan B | E234: mdm.IDY_SEG_CD | F234: EBAN | H234: CBR_VP_IDY_SEG_CD_v0.1
A235: 233 | B235: Batch 2 | C235: RDM | D235: Plan B | E235: mdm.CST_TTL_CD | F235: EBAN | H235: CBR_V_TTL_CD_v0.6
A236: 234 | B236: Batch 2 | C236: RDM | D236: Plan B | E236: mdm.CST_POS_CD | F236: EBAN | H236: CBR_V_POS_CD_v1.1
A237: 235 | B237: Batch 2 | C237: RDM | D237: Plan B | E237: mdm.CST_ORD_REV_SEG_CD | F237: EBAN | H237: CBR_V_ORG_REV_SEG_CD_v0.9
A238: 236 | B238: Batch 2 | C238: RDM | D238: Plan B | E238: mdm.CST_IP_REL_TP_CD | F238: EBAN | H238: CBR_V_IP_REL_TP_CD_v.1.1
A239: 237 | B239: Batch 2 | C239: RDM | D239: Plan B | E239: mdm.CST_IP_LGL_STC_TP_X_TTL_REL | F239: EBAN | H239: CBR_V_IP_LGL_STC_TP_X_TTL_REL_v.0.2 CBR_V_IP_LGL_STC_TP_X_TAX_REL_v.0.2
A240: 238 | B240: Batch 2 | C240: RDM | D240: Plan B | E240: mdm.CST_ADR_MSTR | F240: EBAN | H240: CBR_V_ADR_MSTR_V0.3
A241: 239 | B241: Batch 2 | C241: RDM | D241: Plan B | E241: mdm.CNRLCRM_REG_COA_PD | F241: EBAN | H241: CBR_EBAN_VP_REFR_REG_COA_PD_v0.2
A242: 240 | B242: Batch 2 | C242: RDM | D242: Plan B | E242: mdm.IDY_RSK_IND | F242: EBAN | H242: CBR_EBAN_VP_REFR_IDY_RSK_IND_V0.2
A243: 241 | B243: Batch 2 | C243: RDM | D243: Plan B | E243: mdm.IDY_POLCY_RSK_IND | F243: EBAN | H243: CBR_EBAN_VP_REFR_IDY_POLCY_RSK_IND_V0.2
A244: 242 | B244: Batch 2 | C244: RDM | D244: Plan B | E244: IDY_PROV_INC | F244: DIH | H244: CBR_EBAN_VP_REFR_IDY_CL_PROV_IMP_V.03
A245: 243 | B245: Batch 2 | C245: RDM | D245: Plan B | E245: CST_OCP_X_PROF_REL | F245: DIH | H245: CBR_EBAN_VP_OCP_X_PROF_REL_V0.6
... A248: 246 | B248: Batch 2 | C248: RDM | D248: Plan B | E248: mdm.CST_OCP_GRP_CD | F248: EBAN | H248: CBR_EBAN_V_OCP_GRP_CD_V0.4

Sheet Source Inventory
M1: …/inbound/source_file/mdp/<Source System>/<env>/<file name> | O1: abfss://inbound@stmdpsea<env>in001.dfs.core.windows.net/<database> / <table> / <partitions>​
A2: # | B2: Business Area | C2: source system name | D2: System Name | E2: Abbr src_sys | F2: src_sys_id | G2: Source Status | H2: KBMF Approach | I2: Action | J2: Plan | K2: Case | L2: Remark | M2: Target Folder on Landing Zone VM | N2: path on cloud | O2: adls on cloud
A3: 1 | B3: Deposit | C3: Profile Core Banking - Deposit | D3: PCB-Deposit | E3: pcb_dep | F3: 668 | G3: Group 1 | H3: EBAN | I3: Fon to follow up | J3: Plan B | K3: Source operation to extract file to EBAN landing zone | M3: ="/datasource/inbound/source_file/mdp/"&E3&"/" -> /datasource/inbound/source_file/mdp/pcb_dep/ | N3: ="/inbound/source_file/mdp/"&E3&"/" -> /inbound/source_file/mdp/pcb_dep/ | O3: ="abfss://inbound@stmdpsea<env>in001.dfs.core.windows.net/source_file/mdp/"&E3&"/" -> abfss://inbound@stmdpsea<env>in001.dfs.core.windows.net/source_file/mdp/pcb_dep/
A4: 2 | B4: Credit | C4: Profile Core Banking - Lending | D4: PCB-Lending | E4: pcb_loan | F4: 668.08 | G4: Group 1 | H4: EBAN | I4: Fon to follow up | J4: Plan B | K4: Source operation to extract file to EBAN landing zone | M4: ="/datasource/inbound/source_file/mdp/"&E4&"/" -> /datasource/inbound/source_file/mdp/pcb_loan/ | N4: ="/inbound/source_file/mdp/"&E4&"/" -> /inbound/source_file/mdp/pcb_loan/ | O4: ="abfss://inbound@stmdpsea<env>in001.dfs.core.windows.net/source_file/mdp/"&E4&"/" -> abfss://inbound@stmdpsea<env>in001.dfs.core.windows.net/source_file/mdp/pcb_loan/
A5: 3 | B5: LPM | C5: LPM ON AS/400 | D5: LPM-AS/400​ | E5: lpm_as400 | F5: 75 | G5: Group 1 | H5: EBAN | I5: Fon to follow up | J5: Plan B | K5: Direct Access | L5: Case 3: KBMF from Source this Friday | M5: ="/datasource/inbound/source_file/mdp/"&E5&"/" -> /datasource/inbound/source_file/mdp/lpm_as400/ | N5: ="/inbound/source_file/mdp/"&E5&"/" -> /inbound/source_file/mdp/lpm_as400/ | O5: ="abfss://inbound@stmdpsea<env>in001.dfs.core.windows.net/source_file/mdp/"&E5&"/" -> abfss://inbound@stmdpsea<env>in001.dfs.core.windows.net/source_file/mdp/lpm_as400/
A6: 4 | B6: FCD | C6: Foreign Currency Profile - FCD | D6: FCD | E6: fcd | F6: 640 | G6: Group 1 | H6: EBAN | I6: Fon to follow up | J6: Plan B | K6: Source operation to extract file to EBAN landing zone | M6: ="/datasource/inbound/source_file/mdp/"&E6&"/" -> /datasource/inbound/source_file/mdp/fcd/ | N6: ="/inbound/source_file/mdp/"&E6&"/" -> /inbound/source_file/mdp/fcd/ | O6: ="abfss://inbound@stmdpsea<env>in001.dfs.core.windows.net/source_file/mdp/"&E6&"/" -> abfss://inbound@stmdpsea<env>in001.dfs.core.windows.net/source_file/mdp/fcd/
A7: 5 | B7: Customer Demographic | C7: Customer Information System | D7: CIS | E7: cis | F7: 176 | G7: Group 2.1 | H7: Source | I7: Received existing KBMF (22-Dec:14) Pending new KBMF | J7: Plan A | M7: ="/datasource/inbound/source_file/mdp/"&E7&"/" -> /datasource/inbound/source_file/mdp/cis/ | N7: ="/inbound/source_file/mdp/"&E7&"/" -> /inbound/source_file/mdp/cis/ | O7: ="abfss://inbound@stmdpsea<env>in001.dfs.core.windows.net/source_file/mdp/"&E7&"/" -> abfss://inbound@stmdpsea<env>in001.dfs.core.windows.net/source_file/mdp/cis/
A8: 6 | B8: Customer Consent | C8: Consent Management System | D8: CSM | E8: csm | F8: 780 | G8: Group 2.2 | H8: Source | I8: Received existing KBMF (22-Dec:17) Pending new KBMF | J8: Plan A | L8: pending ~2 files | M8: ="/datasource/inbound/source_file/mdp/"&E8&"/" -> /datasource/inbound/source_file/mdp/csm/ | N8: ="/inbound/source_file/mdp/"&E8&"/" -> /inbound/source_file/mdp/csm/ | O8: ="abfss://inbound@stmdpsea<env>in001.dfs.core.windows.net/source_file/mdp/"&E8&"/" -> abfss://inbound@stmdpsea<env>in001.dfs.core.windows.net/source_file/mdp/csm/
A9: 7 | B9: KPLUS | C9: KPLUS | D9: K PLUS | E9: kplus | F9: 509 | G9: Group 2.3 | H9: EBAN | I9: Fon to follow up | J9: Plan B | K9: Direct Access | L9: Case 3: KBMF from Source | M9: ="/datasource/inbound/source_file/mdp/"&E9&"/" -> /datasource/inbound/source_file/mdp/kplus/ | N9: ="/inbound/source_file/mdp/"&E9&"/" -> /inbound/source_file/mdp/kplus/ | O9: ="abfss://inbound@stmdpsea<env>in001.dfs.core.windows.net/source_file/mdp/"&E9&"/" -> abfss://inbound@stmdpsea<env>in001.dfs.core.windows.net/source_file/mdp/kplus/
A10: 8 | B10: Trade | C10: Trade Finance - Trade Navigator | D10: Trade-Navigator | E10: trade_na | F10: 451 | G10: Group 2.3 | H10: EBAN | I10: Fon to follow up | J10: Plan B | K10: Source operation to extract file to EBAN landing zone | M10: ="/datasource/inbound/source_file/mdp/"&E10&"/" -> /datasource/inbound/source_file/mdp/trade_na/ | N10: ="/inbound/source_file/mdp/"&E10&"/" -> /inbound/source_file/mdp/trade_na/ | O10: ="abfss://inbound@stmdpsea<env>in001.dfs.core.windows.net/source_file/mdp/"&E10&"/" -> abfss://inbound@stmdpsea<env>in001.dfs.core.windows.net/source_file/mdp/trade_na/
A11: 9 | B11: Trade | C11: New-Trade | D11: New-Trade | E11: gts | F11: 735 | G11: Group 2.3 | H11: EBAN | I11: Fon to follow up | J11: Plan B | K11: Source operation to extract file to EBAN landing zone | M11: ="/datasource/inbound/source_file/mdp/"&E11&"/" -> /datasource/inbound/source_file/mdp/gts/ | N11: ="/inbound/source_file/mdp/"&E11&"/" -> /inbound/source_file/mdp/gts/ | O11: ="abfss://inbound@stmdpsea<env>in001.dfs.core.windows.net/source_file/mdp/"&E11&"/" -> abfss://inbound@stmdpsea<env>in001.dfs.core.windows.net/source_file/mdp/gts/
A12: 10 | B12: Supply Chain | C12: Supply Chain | D12: Supply Chain | E12: scf | F12: 460 | G12: Group 2.3 | H12: EBAN/DIH | I12: Fon to follow up | J12: Plan B | K12: - Direct Access '- Source operation to extract file to EBAN landing zone | L12: pending ~2 files Case 3: KBMF from Source | M12: ="/datasource/inbound/source_file/mdp/"&E12&"/" -> /datasource/inbound/source_file/mdp/scf/ | N12: ="/inbound/source_file/mdp/"&E12&"/" -> /inbound/source_file/mdp/scf/ | O12: ="abfss://inbound@stmdpsea<env>in001.dfs.core.windows.net/source_file/mdp/"&E12&"/" -> abfss://inbound@stmdpsea<env>in001.dfs.core.windows.net/source_file/mdp/scf/
A13: 11 | B13: Factoring | C13: Factoring | D13: Factoring | E13: dgtl_fctrng | F13: 754 | G13: Group 2.3 | H13: EBAN | I13: Fon to follow up | J13: Plan B | K13: - Direct Access - Source operation to extract file to EBAN landing zone | L13: TBC - Timezone and charset Case 2: File - KBMF From EBAN Case 3: View - KBMF From Source | M13: ="/datasource/inbound/source_file/mdp/"&E13&"/" -> /datasource/inbound/source_file/mdp/dgtl_fctrng/ | N13: ="/inbound/source_file/mdp/"&E13&"/" -> /inbound/source_file/mdp/dgtl_fctrng/ | O13: ="abfss://inbound@stmdpsea<env>in001.dfs.core.windows.net/source_file/mdp/"&E13&"/" -> abfss://inbound@stmdpsea<env>in001.dfs.core.windows.net/source_file/mdp/dgtl_fctrng/
A14: 12 | B14: MM/ REPO | C14: Murex | D14: Murex | E14: mx | F14: 590 | G14: Group 2.3 | H14: EBAN | I14: Fon to follow up | J14: Plan B | K14: Source operation to extract file to EBAN landing zone | M14: ="/datasource/inbound/source_file/mdp/"&E14&"/" -> /datasource/inbound/source_file/mdp/mx/ | N14: ="/inbound/source_file/mdp/"&E14&"/" -> /inbound/source_file/mdp/mx/ | O14: ="abfss://inbound@stmdpsea<env>in001.dfs.core.windows.net/source_file/mdp/"&E14&"/" -> abfss://inbound@stmdpsea<env>in001.dfs.core.windows.net/source_file/mdp/mx/
A15: 13 | B15: Fund | C15: Unit Dealing | D15: UD | E15: ud | F15: 607 | G15: Group 2.3 | H15: EBAN/DIH | I15: Fon to follow up | J15: Plan B | K15: - Direct Access - Source operation to extract file to EBAN landing zone | L15: Case 2: File - KBMF From EBAN Case 3: View - KBMF From Source | M15: ="/datasource/inbound/source_file/mdp/"&E15&"/" -> /datasource/inbound/source_file/mdp/ud/ | N15: ="/inbound/source_file/mdp/"&E15&"/" -> /inbound/source_file/mdp/ud/ | O15: ="abfss://inbound@stmdpsea<env>in001.dfs.core.windows.net/source_file/mdp/"&E15&"/" -> abfss://inbound@stmdpsea<env>in001.dfs.core.windows.net/source_file/mdp/ud/
A16: 14 | B16: Fund | D16: KS | E16: ks | F16: KS | G16: Group 2.3 | H16: EBAN/DIH | I16: Fon to follow up | J16: Plan B | M16: ="/datasource/inbound/source_file/mdp/"&E16&"/" -> /datasource/inbound/source_file/mdp/ks/ | N16: ="/inbound/source_file/mdp/"&E16&"/" -> /inbound/source_file/mdp/ks/ | O16: ="abfss://inbound@stmdpsea<env>in001.dfs.core.windows.net/source_file/mdp/"&E16&"/" -> abfss://inbound@stmdpsea<env>in001.dfs.core.windows.net/source_file/mdp/ks/
A17: 15 | B17: Master of Code Description | C17: Reference Data Management | D17: RDM | E17: rdm | F17: 655 | G17: Group 2.3 | H17: EBAN/DIH | I17: Fon to follow up | J17: Plan A | L17: Changed to Plan A Both control file and tailor | M17: ="/datasource/inbound/source_file/mdp/dih/" -> /datasource/inbound/source_file/mdp/dih/ | N17: ="/inbound/source_file/mdp/dih/" -> /inbound/source_file/mdp/dih/ | O17: ="abfss://inbound@stmdpsea<env>in001.dfs.core.windows.net/source_file/mdp/dih/" -> abfss://inbound@stmdpsea<env>in001.dfs.core.windows.net/source_file/mdp/dih/
A18: 16 | B18: Write off for Lending | C18: LPM-WriteOff | D18: LPM-WriteOff | E18: lpm_wrtoff | F18: 235 | G18: Group 1 | H18: EBAN | I18: Fon to follow up | J18: Plan B | K18: Source operation to extract file to EBAN landing zone | M18: ="/datasource/inbound/source_file/mdp/"&E18&"/" -> /datasource/inbound/source_file/mdp/lpm_wrtoff/ | N18: ="/inbound/source_file/mdp/"&E18&"/" -> /inbound/source_file/mdp/lpm_wrtoff/ | O18: ="abfss://inbound@stmdpsea<env>in001.dfs.core.windows.net/source_file/mdp/"&E18&"/" -> abfss://inbound@stmdpsea<env>in001.dfs.core.windows.net/source_file/mdp/lpm_wrtoff/
A19: 17 | B19: Legal status for Lending​ | C19: LEC - BAD BANK | D19: LEC​ | E19: lec | F19: 72 | G19: Group 1 | H19: EBAN | I19: Fon to follow up | J19: Plan B | K19: Source operation to extract file to EBAN landing zone | M19: ="/datasource/inbound/source_file/mdp/"&E19&"/" -> /datasource/inbound/source_file/mdp/lec/ | N19: ="/inbound/source_file/mdp/"&E19&"/" -> /inbound/source_file/mdp/lec/ | O19: ="abfss://inbound@stmdpsea<env>in001.dfs.core.windows.net/source_file/mdp/"&E19&"/" -> abfss://inbound@stmdpsea<env>in001.dfs.core.windows.net/source_file/mdp/lec/
A20: 18 | B20: CC/ XPC | C20: CardLink | D20: Cardlink | E20: cardlink | F20: 268 | G20: Group 1.2 | H20: Source | I20: Received existing KBMF (22-Dec:8) Pending new KBMF | J20: Plan A | L20: MQ, Not provide control file | M20: ="/datasource/inbound/source_file/mdp/"&E20&"/" -> /datasource/inbound/source_file/mdp/cardlink/ | N20: ="/inbound/source_file/mdp/"&E20&"/" -> /inbound/source_file/mdp/cardlink/ | O20: ="abfss://inbound@stmdpsea<env>in001.dfs.core.windows.net/source_file/mdp/"&E20&"/" -> abfss://inbound@stmdpsea<env>in001.dfs.core.windows.net/source_file/mdp/cardlink/
A21: 19 | B21: Debit Card​ | C21: CardLink (TPN) | D21: Cardlink(TPN​) | E21: cardlink_acq | F21: 268.01 | G21: Group 1.2 | H21: Source | I21: Name helps to follow up | J21: Plan A | L21: Not provide control file | M21: ="/datasource/inbound/source_file/mdp/"&E21&"/" -> /datasource/inbound/source_file/mdp/cardlink_acq/ | N21: ="/inbound/source_file/mdp/"&E21&"/" -> /inbound/source_file/mdp/cardlink_acq/ | O21: ="abfss://inbound@stmdpsea<env>in001.dfs.core.windows.net/source_file/mdp/"&E21&"/" -> abfss://inbound@stmdpsea<env>in001.dfs.core.windows.net/source_file/mdp/cardlink_acq/
A22: 20 | B22: Customer RM Segment | C22: Sales Smart | D22: RMST | E22: rmst | F22: 723 | G22: Group 2.2 | H22: Source | I22: Name helps to follow up | J22: Plan A | L22: Sales Smart will sent KBMF by 12-Jan (As agreed in WS) | M22: ="/datasource/inbound/source_file/mdp/"&E22&"/" -> /datasource/inbound/source_file/mdp/rmst/ | N22: ="/inbound/source_file/mdp/"&E22&"/" -> /inbound/source_file/mdp/rmst/ | O22: ="abfss://inbound@stmdpsea<env>in001.dfs.core.windows.net/source_file/mdp/"&E22&"/" -> abfss://inbound@stmdpsea<env>in001.dfs.core.windows.net/source_file/mdp/rmst/
A23: 21 | B23: Debit Card​ | C23: Centralized Card Management System | D23: CCMS​ | E23: ccms | F23: 772 | G23: Group 2.2 | H23: Source | I23: Name helps to follow up | J23: Plan A | M23: ="/datasource/inbound/source_file/mdp/"&E23&"/" -> /datasource/inbound/source_file/mdp/ccms/ | N23: ="/inbound/source_file/mdp/"&E23&"/" -> /inbound/source_file/mdp/ccms/ | O23: ="abfss://inbound@stmdpsea<env>in001.dfs.core.windows.net/source_file/mdp/"&E23&"/" -> abfss://inbound@stmdpsea<env>in001.dfs.core.windows.net/source_file/mdp/ccms/
A24: 22 | B24: Exchange Rate​ | C24: FX at booth | D24: FXBOOTH​ | E24: fxb | F24: 745 | G24: Group 2.3 | I24: Fon to follow up | J24: Plan B | L24: ผ่านทาง DIH | M24: ="/datasource/inbound/source_file/mdp/"&E24&"/" -> /datasource/inbound/source_file/mdp/fxb/ | N24: ="/inbound/source_file/mdp/"&E24&"/" -> /inbound/source_file/mdp/fxb/ | O24: ="abfss://inbound@stmdpsea<env>in001.dfs.core.windows.net/source_file/mdp/"&E24&"/" -> abfss://inbound@stmdpsea<env>in001.dfs.core.windows.net/source_file/mdp/fxb/
A25: 23 | C25: HRMIS-Centralized RC | D25: HRCRC | E25: hrcrc | F25: 497 | M25: ="/datasource/inbound/source_file/mdp/"&E25&"/" -> /datasource/inbound/source_file/mdp/hrcrc/ | N25: ="/inbound/source_file/mdp/"&E25&"/" -> /inbound/source_file/mdp/hrcrc/ | O25: ="abfss://inbound@stmdpsea<env>in001.dfs.core.windows.net/source_file/mdp/"&E25&"/" -> abfss://inbound@stmdpsea<env>in001.dfs.core.windows.net/source_file/mdp/hrcrc/
A26: 24 | B26: KBANK VS KBANK-Group | C26: HRIS | D26: HRIS | E26: hris | F26: 506 | M26: ="/datasource/inbound/source_file/mdp/"&E26&"/" -> /datasource/inbound/source_file/mdp/hris/ | N26: ="/inbound/source_file/mdp/"&E26&"/" -> /inbound/source_file/mdp/hris/ | O26: ="abfss://inbound@stmdpsea<env>in001.dfs.core.windows.net/source_file/mdp/"&E26&"/" -> abfss://inbound@stmdpsea<env>in001.dfs.core.windows.net/source_file/mdp/hris/

Sheet Technical Source Inventory
A1: 0 | B1: 0 | C1: 0 | D1: 0 | E1: 0 | F1: 0 | G1: 0 | H1: 0 | I1: 0 | J1: 0 | K1: 0 | L1: 0 | M1: 0 | N1: 0 | O1: 0
A2: # | B2: Business Area | C2: source system name | D2: Abbr src_sys | E2: System Name | F2: Count Summary | G2: Source Status | H2: KBMF Approach | I2: Action | J2: Note for Baseline 1 | K2: Plan | L2: Extraction Cases | M2: Case | N2: Remark | O2: KBMF Status | P2: Workshop Status | Q2: Access status | R2: Integration Status | S2: Pending Action | T2: Plan | U2: FW Extraction Case | V2: File Type | W2: Control File Type | X2: Environments | Y2: Database Type | Z2: Authentication | AA2: Availability | AB2: Timezone | AC2: Charset | AD2: Extraction Method | AE2: Extraction Size | AF2: Extraction Size Limit | AG2: Encryption | AH2: Parallel Extraction
A3: 1 | B3: Deposit | C3: Profile Core Banking - Deposit | D3: PCB_DEP | E3: PCB-Deposit | F3: 5 | G3: Group 1 | H3: EBAN | I3: Fon to follow up | J3: 45273 | K3: Plan B | L3: Push | M3: Source operation to extract file to EBAN landing zone | N3: 0 | O3: Received | P3: Pending | S3: Test extraction framework on DEV | T3: Plan B | U3: Pull File (EBAN LANDING)
A4: 2 | B4: Credit | C4: Profile Core Banking - Lending | D4: PCB_LOAN | E4: PCB-Lending | F4: 5 | G4: Group 1 | H4: EBAN | I4: Fon to follow up | J4: 45273 | K4: Plan B | L4: Push | M4: Source operation to extract file to EBAN landing zone | N4: 0 | O4: Received | P4: Pending | S4: Test extraction framework on DEV | T4: Plan B | U4: Pull File (EBAN LANDING)
A5: 3 | B5: LPM | C5: LPM ON AS/400 | D5: LPM_AS400 | E5: LPM-AS/400​ | F5: 7 | G5: Group 1 | H5: EBAN | I5: Fon to follow up | J5: 45280 | K5: Plan B | L5: Pull | M5: Direct Access | N5: Case 3: KBMF from Source this Friday | O5: In Progress | P5: Pending | S5: To get approval for pulling EBAN's DB | T5: Plan B | U5: Pull File (EBAN IN)
A6: 4 | B6: FCD | C6: Foreign Currency Profile - FCD | D6: FCD | E6: FCD | F6: 1 | G6: Group 1 | H6: EBAN | I6: Fon to follow up | J6: 45280 | K6: Plan B | L6: Push | M6: Source operation to extract file to EBAN landing zone | N6: 0 | O6: Received | P6: Pending | S6: Test extraction framework on DEV | T6: Plan B | U6: Pull File (EBAN LANDING)
A7: 5 | B7: Customer Demographic | C7: Customer Information System | D7: CIS | E7: CIS | F7: 16 | G7: Group 2.1 | H7: Source | I7: Received existing KBMF (22-Dec:14) Pending new KBMF | J7: 45280 | K7: Plan A | L7: Push | M7: 0 | N7: 0 | O7: In Progress | P7: Started | S7: ACN to confirm the on-prem VM's path | T7: Plan A | U7: Push File | V7: Text | W7: Control File | AD7: Initial - Full Dump On-going - Delta | AE7: 300M-600M records
A8: 6 | B8: Customer Consent | C8: Consent Management System | D8: CSM | E8: CSM | F8: 10 | G8: Group 2.2 | H8: Source | I8: Received existing KBMF (22-Dec:17) Pending new KBMF | J8: 45280 | K8: Plan A | L8: Push | M8: 0 | N8: pending ~2 files | O8: In Progress | P8: Started | S8: ACN to confirm the on-prem VM's path | T8: Plan A | U8: Push File | V8: Text | W8: Control File
A9: 7 | B9: KPLUS | C9: KPLUS | D9: KPLUS | E9: K PLUS | F9: 3 | G9: Group 2.3 | H9: EBAN | I9: Fon to follow up | J9: 45280 | K9: Plan B | L9: Pull | M9: Direct Access | N9: Case 3: KBMF from Source | O9: In Progress | P9: Pending | S9: Test extraction framework on DEV | T9: Plan B | U9: Pull File (EBAN LANDING)
A10: 8 | B10: Trade | C10: Trade Finance - Trade Navigator | D10: TRADE_NA | E10: Trade-Navigator | F10: 2 | G10: Group 2.3 | H10: EBAN | I10: Fon to follow up | J10: 45280 | K10: Plan B | L10: Push | M10: Source operation to extract file to EBAN landing zone | N10: 0 | O10: Received | P10: Pending | S10: Test extraction framework on DEV | T10: Plan B | U10: Pull File (EBAN LANDING)
A11: 9 | B11: Trade | C11: New-Trade | D11: GTS | E11: New-Trade | F11: 2 | G11: Group 2.3 | H11: EBAN | I11: Fon to follow up | J11: 45280 | K11: Plan B | L11: Push | M11: Source operation to extract file to EBAN landing zone | N11: 0 | O11: In Progress | P11: Pending | S11: Test extraction framework on DEV | T11: Plan B | U11: Pull File (EBAN LANDING)
A12: 10 | B12: Supply Chain | C12: Supply Chain | D12: SCF | E12: Supply Chain | F12: 6 | G12: Group 2.3 | H12: EBAN/DIH | I12: Fon to follow up | J12: 45280 | K12: Plan B | L12: Pull and Push | M12: - Direct Access '- Source operation to extract file to EBAN landing zone | N12: pending ~2 files Case 3: KBMF from Source | O12: Received | P12: Started | S12: To attend solution&architect session for source pulling confirmation | T12: Plan B | U12: Pull Database | X12: SIT/ UAT/ PRD | Y12: SQL Server 2016 | Z12: User/ Password - obtained | AA12: After 8:00 PM | AB12: UTC+7 | AC12: Pending | AF12: None | AG12: None | AH12: Available
A13: 11 | B13: Factoring | C13: Factoring | D13: DGTL_FCTRNG | E13: Factoring | F13: 2 | G13: Group 2.3 | H13: EBAN | I13: Fon to follow up | J13: 45280 | K13: Plan B | L13: Pull and Push | M13: - Direct Access - Source operation to extract file to EBAN landing zone | N13: TBC - Timezone and charset Case 2: File - KBMF From EBAN Case 3: View - KBMF From Source | O13: In Progress | P13: Started | S13: To request firewall and user/password for source DB access | T13: Plan B | U13: Pull Database | X13: DEV/ SIT/ UAT/ PRD | Y13: SQL Server 2016 | Z13: User/ Password | AA13: Pending | AB13: SE Asia Standard Time | AC13: Thai_CI_AS | AF13: None | AG13: Test - Masked Prod - None | AH13: Available
A14: 12 | E14: Factoring | S14: Test extraction framework on DEV | T14: Plan B | U14: Pull File (EBAN LANDING)
A15: 12 | B15: MM/ REPO | C15: Murex | D15: MX | E15: Murex | F15: 2 | G15: Group 2.3 | H15: EBAN | I15: Fon to follow up | J15: 45280 | K15: Plan B | L15: Push | M15: Source operation to extract file to EBAN landing zone | N15: 0 | O15: Received | P15: Pending | S15: Test extraction framework on DEV | T15: Plan B | U15: Pull File (EBAN LANDING)
A16: 13 | B16: KBANK VS KBANK-Group | C16: HRIS | D16: HRIS | E16: HRIS | F16: 1 | G16: Group 2.3 | H16: EBAN | I16: Fon to follow up | J16: 45280 | K16: Plan B | L16: Push | M16: Source operation to extract file to EBAN landing zone | N16: 0 | O16: Pending to provide | P16: Pending | S16: Test extraction framework on DEV | T16: Plan B | U16: Pull File (EBAN LANDING)
A17: 14 | D17: UD | E17: UD | S17: Test extraction framework on DEV | T17: Plan B | U17: Pull File (EBAN LANDING)
A18: 15 | B18: Fund | C18: Unit Dealing | D18: UD | E18: UD | F18: 8 | G18: Group 2.3 | H18: EBAN/DIH | I18: Fon to follow up | J18: 45280 | K18: Plan B | L18: Pull and Push | M18: - Direct Access - Source operation to extract file to EBAN landing zone | N18: Case 2: File - KBMF From EBAN Case 3: View - KBMF From Source | O18: Pending to provide | P18: Started | S18: To request firewall and user/password for source DB access | T18: Plan B | U18: Pull Database | X18: SIT/UAT (CTE2/3) not separated PRD | Y18: Oracle SQL 2011 | Z18: User/ Password | AA18: After 5:00 AM | AB18: UTC+7 | AC18: ASCII (UTF-8 might be available) | AF18: None | AG18: Test - Masked Prod - None | AH18: Not Available
A19: 16 | B19: Master of Code Description | C19: Reference Data Management | D19: RDM | E19: RDM | F19: 11 | G19: Group 2.3 | H19: EBAN/DIH | I19: Fon to follow up | J19: 45280 | K19: Plan A | L19: Push | M19: 0 | N19: Changed to Plan A Both control file and tailor | O19: In Progress | P19: Started | S19: ACN to confirm the on-prem VM's path | T19: Plan A | U19: Push File (DIH) | V19: Text | W19: Pending
A20: 17 | B20: Write off for Lending | C20: LPM-WriteOff | D20: LPM_WRTOFF | E20: LPM-WriteOff | F20: 1 | G20: Group 1 | H20: EBAN | I20: Fon to follow up | J20: 45287 | K20: Plan B | L20: Push | M20: Source operation to extract file to EBAN landing zone | N20: 0 | O20: Pending to provide | P20: Pending | S20: Test extraction framework on DEV | T20: Plan B | U20: Pull File (EBAN LANDING)
A21: 18 | B21: Legal status for Lending​ | C21: LEC - BAD BANK | D21: LEC | E21: LEC​ | F21: 1 | G21: Group 1 | H21: EBAN | I21: Fon to follow up | J21: 45287 | K21: Plan B | L21: Push | M21: Source operation to extract file to EBAN landing zone | N21: 0 | O21: Pending to provide | P21: Pending | S21: Test extraction framework on DEV | T21: Plan B | U21: Pull File (EBAN LANDING)
A22: 19 | B22: CC/ XPC | C22: CardLink | D22: CARDLINK | E22: Cardlink | F22: 11 | G22: Group 1.2 | H22: Source | I22: Received existing KBMF (22-Dec:8) Pending new KBMF | J22: 45287 | K22: Plan A | L22: Push | M22: 0 | N22: MQ, Not provide control file | O22: Pending to provide | P22: Started | S22: Workshop for MQ's topic subscription Friday 2024-01-19 *To discuss consuming from streaming hub | T22: Plan A | U22: Pull File | V22: (Cardlink JCB) Streaming - Kafka
A23: 20 | D23: CARDLINK | E23: Cardlink | S23: *Pending | T23: Plan B | U23: Pull EBAN File
A24: 21 | B24: Debit Card​ | C24: CardLink (TPN) | D24: CARDLINK_ACQ | E24: Cardlink(TPN​) | F24: 4 | G24: Group 1.2 | H24: Source | I24: Name helps to follow up | J24: 45287 | K24: Plan A | L24: Push | M24: 0 | N24: Not provide control file | O24: Pending to provide | P24: Started | S24: ACN to confirm the on-prem VM's path | T24: Plan A | U24: Pull File | V24: Mainframe
A25: 22 | B25: Customer RM Segment | C25: Sales Smart | D25: RMST | E25: RMST | F25: 1 | G25: Group 2.2 | H25: Source | I25: Name helps to follow up | J25: 45287 | K25: Plan A | L25: Push | M25: 0 | N25: Sales Smart will sent KBMF by 12-Jan (As agreed in WS) | O25: Pending to provide | P25: Started | S25: ACN to confirm the on-prem VM's path | T25: Plan A | U25: Push File
A26: 23 | B26: Debit Card​ | C26: Centralized Card Management System | D26: CCMS | E26: CCMS​ | F26: 4 | G26: Group 2.2 | H26: Source | I26: Name helps to follow up | J26: 45287 | K26: Plan A | L26: Push | M26: 0 | N26: 0 | O26: Pending to provide | P26: Started | S26: ACN to confirm the on-prem VM's path | T26: Plan A | U26: Push File | V26: Text | W26: Control File | AG26: Pending (inquiring if credit no. can be non-encrypted)
A27: 24 | B27: Exchange Rate​ | C27: FX at booth | D27: FXB | E27: FXBOOTH​ | F27: 1 | G27: Group 2.3 | H27: 0 | I27: Fon to follow up | J27: 45287 | K27: Plan B | L27: 0 | M27: 0 | N27: ผ่านทาง DIH | O27: Pending to provide | P27: Pending | T27: Plan A | U27: Push File (DIH)
A28: 25 | B28: 0 | C28: DIH | D28: DIH | E28: DIH | F28: 1 | G28: Group 2.3 | H28: 0 | I28: 0 | J28: 0 | K28: Plan A | L28: Push | M28: 0 | N28: 0 | O28: In Progress | P28: Pending | S28: DIH to discuss internally for file push | T28: Plan A | U28: Push File (DIH)
B30: Push Cases | C30: KBMF Received 15/21
B31: Pull Cases | C31: 3/6 | D31: *KPLUS on 2024-01-16
B32: Streaming Case | C32: 1 | D32: Cardlink
B33: Pull Databases | C33: SQL Server 2016
C34: Oracle SQL 2011 | D34: *To send user request for additional source push | Q34: Cardlink, DIH | S34: Request additional users | U34: IP, Port, user, path
Q36: DIH/RDM merged | R36: using mount disk | S36: K.Yui follow up on mount disk permissions | U36: *EBAN IT setting permissions
R37: 1 file pull from DIH
D40: Sending a list of sources to be pulled, to request for firewall
D41: Files | E41: Windows/ Linux | P41: IP/port/OS | Q41: AFT: Windows must include tectia
D43: EBAN sources: mount disk | P43: *Check for each source pulling from EBAN if its disk is mounted to the on-prem VM
P44: เช็คว่าหยิบจากเครื่อง ETL รึเปล่า -> อาจจะไม่ได้อยู่ใน mount disk | U44: sync who to provide credential (EBAN/DIH)
D46: Pull DB | P46: IP, port, credentials | Q46: Titsanu to send credentials to K.Yui/K.Jay

Sheet Dev detail plan
Y1: Start SIT | AT1: Start UAT
D2: Jan | N2: Feb | AQ2: Mar
A3: Tasks | B3: Team | C3: Remark | D3: 22 | E3: 23 | F3: 24 | G3: 25 | H3: 26 | I3: 27 | J3: 28 | K3: 29 | L3: 30 | M3: 31 | N3: 1 | O3: 2 | P3: 3 | Q3: 4 | R3: 5 | S3: 6 | T3: 7 | U3: 8 | V3: 9 | W3: 10 | X3: 11 | Y3: 12 | Z3: 13 | AA3: 14 | AB3: 15 | AC3: 16 | AD3: 17 | AE3: 18 | AF3: 19 | AG3: 20 | AH3: 21 | AI3: 22 | AJ3: 23 | AK3: 24 | AL3: 25 | AM3: 26 | AN3: 27 | AO3: 28 | AP3: 29 | AQ3: 1 | AR3: 2 | AS3: 3 | AT3: 4 | AU3: 5 | AV3: 6 | AW3: 7 | AX3: 8 | AY3: 9 | AZ3: 10 | BA3: 11 | BB3: 12 | BC3: 13 | BD3: 14 | BE3: 15 | BF3: 16 | BG3: 17 | BH3: 18 | BI3: 19 | BJ3: 20 | BK3: 21 | BL3: 22 | BM3: 23 | BN3: 24 | BO3: 25 | BP3: 26 | BQ3: 27 | BR3: 28 | BS3: 29 | BT3: 30 | BU3: 31
A4: Pull data from Linux file system
A5: solution on protocol | B5: fw | C5: Request session EBAN for existing approach | G5: x | H5: x | K5: x
A6: development | B6: fw | C6: Mock up system on cloud | K6: x | L6: x | M6: x
A7: unit test | B7: fw | N7: x | O7: x
A8: Integration | B8: kbtg/infra | R8: x | S8: x | T8: x | U8: x | V8: x
A9: SIT | Z9: x | AA9: x | AB9: x
A10: UAT
A11: Pull data from EBAN
A12: solution on protocol | C12: Request session EBAN for existing approach | G12: x | H12: x | K12: x
A13: development | M13: x | N13: x | O13: x
A14: unit test | R14: x | S14: x
A15: Integration | B15: kbtg/infra | T15: x | U15: x | V15: x
A16: SIT | Z16: x | AA16: x | AB16: x | AC16: x | AD16: x
A17: UAT
A18: Pull data from SQL DB
A19: solution on protocol | C19: Request session EBAN for existing approach | L19: x | M19: x
A20: development | N20: x | O20: x | R20: x
A21: unit test | S21: x | T21: x
A22: Integration | B22: kbtg/infra | U22: x | V22: x | Z22: x | AA22: x
A23: SIT
A24: UAT
A25: Pull data from Oracle
A26: solution on protocol | C26: Request session EBAN for existing approach | N26: x | O26: x
A27: development | R27: x | S27: x | T27: x
A28: unit test | U28: x | V28: x
A29: Integration | B29: kbtg/infra | Z29: x | AA29: x | AB29: x | AC29: x | AD29: x
A30: SIT | AG30: x | AH30: x
A31: UAT
A32: Transfer data to Azure inbound
A33: development | D33: x | E33: x
A34: unit test | F34: x | G34: x
A35: Integration | B35: kbtg/infra | C35: re-use same eban migration ? | H35: x | K35: x | L35: x | M35: x
A36: SIT | N36: x | O36: x
A37: UAT
A38: Consume data from Streaming Hub
A39: solution | C39: Request session Streaming Hub
A40: development
A41: unit test
A42: Integration | B42: kbtg/infra
A43: SIT
A44: UAT
A45: Consume data from IBM-MQ
A46: solution | C46: Finalize DIH or MQ
A47: development
A48: unit test
A49: Integration | B49: kbtg/infra
A50: SIT
A51: UAT
A53: INGT: incremental load | D53: x | E53: x | F53: x | G53: x | H53: x | K53: x | L53: x | M53: x | N53: x | O53: x
A54: INGT: fixed-length | D54: x | E54: x | F54: x
A55: INGT: fixed-length + CTL footer | G55: x | H55: x
A56: INGT: fixed-length mainframe | K56: x | L56: x | M56: x
A57: INGT: CSV CTL footer | N57: x | O57: x | R57: x | S57: x
A58: INGT: CSV CTL header | R58: x | S58: x
A59: INGT: rotating encryption key | R59: x | S59: x | T59: x | U59: x | V59: x

Sheet KBMF_spec
A1: Follow KBMF
A2: Batch | B2: System | C2: Plan | D2: Extraction Cases | E2: File name/Table name | F2: Status | G2: Target
A3: Batch 2 | B3: Supply Chain | C3: Plan B (Source) | D3: Pull Database | E3: SCM_PRODUCT_MAP | F3: curated team | G3: 07-02-2024 morning
A4: Batch 2 | B4: HRIS | C4: Plan B (EBAN) | D4: Pull EBAN File | E4: VC_RC_CD | F4: Found KBMF-OUT
A7: Follow Spec
A8: Batch | B8: System | C8: Plan | D8: Extraction Cases | E8: File name/Table name | F8: Pending
A9: Batch 1 | B9: UD | C9: Plan B (EBAN) | D9: Pull EBAN File | E9: KA_FundCode.txt
A10: Batch 1 | B10: KS | C10: Plan B (EBAN) | D10: Pull EBAN File | E10: KSecFundMaster_YYYYMMDD.txt
A11: Batch 1 | B11: KS | C11: Plan B (EBAN) | D11: Pull EBAN File | E11: KSecFundPortfolio_YYYYMMDD.txt
A12: Batch 1 | B12: KS | C12: Plan B (EBAN) | D12: Pull EBAN File | E12: KSecCustProfile_YYYYMMDD.txt
A13: Batch 1 | B13: LEC​ | C13: Plan B (EBAN) | D13: Pull EBAN File | E13: LECP.LEC3D18.TXT
A14: Batch 2 | B14: Supply Chain | C14: Plan B (Source) | D14: Pull Database | E14: VW_SCT_BOOK_LOAN
A15: Batch 2 | B15: Supply Chain | C15: Plan B (Source) | D15: Pull Database | E15: VW_RDT_SCF_CL
A16: Batch 2 | B16: Supply Chain | C16: Plan B (Source) | D16: Pull Database | E16: VW_CM_FEE_STRUCTURE
A17: Batch 2 | B17: Supply Chain | C17: Plan B (Source) | D17: Pull Database | E17: VW_SCM_ACCT
A18: Batch 2 | B18: Supply Chain | C18: Plan B (Source) | D18: Pull Database | E18: SCM_TRADING
A19: Batch 2 | B19: Supply Chain | C19: Plan B (Source) | D19: Pull Database | E19: SCM_CUSTOMER
A20: Batch 2 | B20: Cardlink | C20: Plan B (EBAN) | D20: Pull EBAN File | E20: ODSCC.CCV2_JCB
... A38: Batch 2 | B38: PCB-Deposit | C38: Plan B (EBAN) | D38: Pull EBAN File | E38: PCB_DEPTXN_DB
A39: Batch 2 | B39: K PLUS | C39: Plan B (EBAN) | D39: Pull EBAN File | E39: View_JMobileActLog_Log | F39: - Record count in data file, Data with header, run cycle, holiday flag, File format, Quote Character, File Encode
A40: Batch 2 | B40: K PLUS | C40: Plan B (EBAN) | D40: Pull EBAN File | E40: View_JMobile_Log | F40: - Record count in data file, Data with header, run cycle, holiday flag, File format, Quote Character, File Encode
A41: Batch 2 | B41: K PLUS | C41: Plan B (EBAN) | D41: Pull EBAN File | E41: View_JMobileAcctCard_Log | F41: - Record count in data file, Data with header, run cycle, holiday flag, File format, Quote Character, File Encode
A42: Batch 2 | B42: K PLUS | C42: Plan B (EBAN) | D42: Pull EBAN File | E42: eMobileBatchLog.View_BalanceAlertRegLog_Log | F42: - Record count in data file, Data with header, run cycle, holiday flag, File format, Quote Character, File Encode
A43: Batch 2 | B43: K PLUS | C43: Plan B (EBAN) | D43: Pull EBAN File | E43: MBL_ACTN_LOG | F43: - Record count in data file, Data with header, run cycle, holiday flag, File format, Quote Character, File Encode
A44: Batch 2 | B44: K PLUS | C44: Plan B (EBAN) | D44: Pull EBAN File | E44: ODSMBL.MBL_FNC_TXN | F44: - Record count in data file, Data with header, run cycle, holiday flag, File format, Quote Character, File Encode
A45: Batch 2 | B45: K PLUS | C45: Plan B (EBAN) | D45: Pull EBAN File | E45: ODSMBL.MBL_NON_FNC_TXN | F45: - Record count in data file, Data with header, run cycle, holiday flag, File format, Quote Character, File Encode
A46: Batch 2 | B46: K PLUS | C46: Plan B (EBAN) | D46: Pull EBAN File | E46: View_SIMBankBankInfo_Log | F46: - Record count in data file, Data with header, run cycle, holiday flag, File format, Quote Character, File Encode
A47: Batch 2 | B47: Supply Chain | C47: Plan B (Source) | D47: Pull Database | E47: SCM_PRODUCT_MAP
A48: Batch 2 | B48: Supply Chain | C48: Plan B (Source) | D48: Pull Database | E48: VW_RDT_SCF_CL_ACCT
A49: Batch 2 | B49: Supply Chain | C49: Plan B (Source) | D49: Pull Database | E49: SCM_TRADING_ACCT
A50: Batch 2 | B50: HRIS | C50: Plan B (EBAN) | D50: Pull EBAN File | E50: VC_RC_CD

Sheet STS_ABBR
A1: Batch 1 | B1: Status | D1: Batch 2 lot 1 | E1: Status | G1: Batch 2 lot 2 | H1: Status | J1: Waiting ABBR | K1: Can Summit
A2: pcb_dep_src_pf_ar_sa_dly | B2: Waiting ABBR | D2: pcb_loan_common_limit_info | E2: Waiting ABBR | G2: gts_kbgt_cont_outstanding | H2: Waiting ABBR | J2: Done | K2: On 4-March
A3: pcb_dep_src_pf_ar_ca_dly | B3: Waiting ABBR | D3: pcb_loan_common_market_code | E3: Done | G3: gts_kbgt_loan_outstanding | H3: Waiting ABBR
A4: pcb_dep_src_pf_ar_fx_dly | B4: Waiting ABBR | D4: pcb_loan_common_rate_type | E4: Done | G4: fxb_midrate_kbank | H4: Waiting ABBR
A5: pcb_dep_src_pf_ar_sf_dly | B5: Waiting ABBR | D5: pcb_loan_common_account_tier_by_time | E5: Done | G5: lpm_as400_lpm_x_ip_rel | H5: Done
A6: pcb_dep_extrate1 | B6: Done | D6: pcb_dep_cb2d0005_odencitd_sam | E6: Waiting ABBR | G6: cardlink_kb1dh004_cpbmer | H6: Waiting ABBR
A7: pcb_dep_src_pf_txn_mis_eft_dly | B7: Waiting ABBR | D7: pcb_loan_common_product_type | E7: Done | G7: cardlink_kb1dh023_lbpttrn | H7: Waiting ABBR
A8: pcb_dep_cls500029 | B8: Waiting ABBR | D8: pcb_loan_common_sub_type | E8: Done | G8: cardlink_kb1dh039_ccnd5012 | H8: Done
A9: pcb_dep_src_pf_ar_ca_cr_inf_dly | B9: Waiting ABBR | D9: pcb_loan_common_loan_purpose_table | E9: Done | G9: cardlink_kb1dh010_oadctf | H9: Waiting ABBR
A10: fcd_ar | B10: Waiting ABBR | D10: lpm_as400_ar_wrtof_rcv | E10: Waiting ABBR | G10: cardlink_kb1dh017_cpamt | H10: Waiting ABBR
A11: lpm_as400_lmt_ar_inf_bfr_wrtof | B11: Waiting ABBR | D11: trade_na_lcr070 | E11: Waiting ABBR | G11: cardlink_kb1dh019_cc1t377 | H11: Waiting ABBR
A12: lpm_as400_ln_cntg_dmmy_clss_prvn | B12: Waiting ABBR | D12: trade_na_src_eximar | E12: Waiting ABBR | G12: cardlink_kb1dh018_cpsrptt | H12: Waiting ABBR
A13: lpm_as400_ln_card_clss_prvn | B13: Waiting ABBR | D13: scf_vw_sct_book_loan | E13: Done | G13: cardlink_kb1dh037_cpccpf | H13: Remove
A14: lpm_as400_ln_cntg_clss_prvn | B14: Waiting ABBR | D14: scf_vw_rdt_scf_cl | E14: Done | G14: cardlink_kb1dh003_cpbcus | H14: Waiting ABBR
... A53: cis_ipsegment | B53: Waiting ABBR | D53: cardlink_kb1dh045_cc1d289g | E53: Waiting ABBR | G53: rmst_customer | H53: Waiting ABBR
A54: cis_histsegm | B54: Waiting ABBR | G54: cardlink_kb1dh001_cp1t170_01 | H54: Waiting ABBR
A55: cis_addr | B55: Waiting ABBR | G55: cardlink_kb1dh001_cp1t170_02 | H55: Waiting ABBR
A56: cis_ipxaddr | B56: Waiting ABBR | G56: cardlink_kb1dh037_cpccpf_d | H56: Waiting ABBR
A57: cis_dntcnt | B57: Waiting ABBR | G57: cardlink_kb1dh037_cpccpf_p | H57: Waiting ABBR
A58: cis_othdoc | B58: Waiting ABBR | G58: cardlink_kb1dh037_cptcpf_d | H58: Waiting ABBR
A59: ud_ka_fundcode | B59: Waiting ABBR | G59: cardlink_kb1dh037_cptcpf_p | H59: Waiting ABBR
A60: ks_fundmaster | B60: Waiting ABBR
A61: ks_fundportfolio | B61: Done
A62: ks_custprofile | B62: Done
A63: ud_privatefund_balance | B63: Done
A64: hris_staff_accnt_vw | B64: Done
A65: cardlink_la10s_oatkn | B65: Waiting ABBR
A66: csm_downstreamrules | B66: Waiting ABBR
A67: csm_downstreamconfig | B67: Done
A68: csm_custxformxconsentlog | B68: Waiting ABBR
A69: csm_custxformxconsentderived | B69: Waiting ABBR
A70: csm_custxformxconsentderivedlog | B70: Waiting ABBR
A71: mx_src_murx_deal_ar | B71: Waiting ABBR
... A78: lec_lecp_lec3d18 | B78: Waiting ABBR

Sheet Ingestion Inventory
A1: No | B1: System | C1: Plan | D1: Extraction Cases | E1: File name/Table name | F1: Table name | G1: KBMF File Reference | H1: CBR EBAN File Reference | I1: File Format | J1: Extraction Method | K1: Data File with Header | L1: change column name ./- to _ | M1: src_pos_dt | N1: Control file | O1: Record count in data file | P1: Remark Label (Header/Tailor) | Q1: Input Frequency | R1: Remark | S1: Received KBMF (Y/N) | T1: Table Specification (Y/N)
A2: 1 | B2: PCB-Deposit | C2: Plan B (EBAN) | D2: Pull EBAN File | E2: src_pf_ar_sa_dly_yyyymmdd.txt | F2: pcb_dep_src_pf_ar_sa_dly | G2: W4-AMS-APIB00392-SavingArrangement_DM.xlsx | H2: CBR_V_PCB_AR_SA_DLY_v.1.13 | I2: txt | J2: Fulldump | K2: N | L2: N | M2: Y | N2: N | O2: Tailor | P2: =VLOOKUP(E2,'Dev Inventory'!T:Y,5,FALSE) -> - Have rec type (To be revised) | Q2: Daily | S2: Y | T2: Y
A3: 2 | B3: PCB-Deposit | C3: Plan B (EBAN) | D3: Pull EBAN File | E3: src_pf_ar_ca_dly_yyyymmdd.txt | F3: pcb_dep_src_pf_ar_ca_dly | G3: W4-AMS-APIB00392-CurrentArrangement_DM_V20200312.xlsx | H3: CBR_V_PCB_AR_CA_DLY_V0.17 | I3: txt | J3: Fulldump | K3: N | L3: N | M3: Y | N3: N | O3: Tailor | P3: =VLOOKUP(E3,'Dev Inventory'!T:Y,5,FALSE) -> - Have rec type (To be revised) | Q3: Daily | S3: Y | T3: Y
A4: 3 | B4: PCB-Deposit | C4: Plan B (EBAN) | D4: Pull EBAN File | E4: src_pf_ar_fx_dly_yyyymmdd.txt | F4: pcb_dep_src_pf_ar_fx_dly | G4: W4-AMS-APIB00392-FixedDepositArrangement_DM_V20200312.xlsx | H4: CBR_V_PCB_AR_FX_DLY_V0.15 | I4: txt | J4: Fulldump | K4: N | L4: N | M4: Y | N4: N | O4: Tailor | P4: =VLOOKUP(E4,'Dev Inventory'!T:Y,5,FALSE) -> - Have rec type (To be revised) | Q4: Daily | S4: Y | T4: Y
A5: 4 | B5: PCB-Deposit | C5: Plan B (EBAN) | D5: Pull EBAN File | E5: src_pf_ar_sf_dly_yyyymmdd.txt | F5: pcb_dep_src_pf_ar_sf_dly | G5: W4-AMS-APIB00392-SpecialFixedArrangement_DM_V20200312.xlsx | H5: CBR_V_PCB_AR_SF_DLY_v0.12 | I5: txt | J5: Fulldump | K5: N | L5: N | M5: Y | N5: N | O5: Tailor | P5: =VLOOKUP(E5,'Dev Inventory'!T:Y,5,FALSE) -> - Have rec type (To be revised) | Q5: Daily | S5: Y | T5: Y
A6: 5 | B6: PCB-Deposit | C6: Plan B (EBAN) | D6: Pull EBAN File | E6: PCB_DIH_ExtRATE1_YYYYMMDD.txt | F6: pcb_dep_extrate1 | G6: PCB-DIH+KBMF_PCBB00002-ExtRATE1_v1.2.xlsx | H6: CBR_FIX_DEP_RATE_TIER_BY_AMT_v0.2 | I6: txt | J6: Fulldump | K6: N | L6: N | M6: N | N6: N | O6: Tailor | P6: =VLOOKUP(E6,'Dev Inventory'!T:Y,5,FALSE) -> - Have rec type (To be revised) | Q6: Daily | S6: Y | T6: Y
A7: 6 | B7: PCB-Lending | C7: Plan B (EBAN) | D7: Pull EBAN File | E7: Common_Account_Info_YYYYMMDD.txt | F7: pcb_loan_common_account_info | G7: Common_Account_Info.xlsx | H7: CBR_V_AC_INF_V1.1 | I7: txt | J7: Fulldump | K7: N | L7: N | M7: Header | N7: N | O7: Tailor | P7: =VLOOKUP(E7,'Dev Inventory'!T:Y,5,FALSE) -> - Have rec type (To be revised) | Q7: Daily | R7: Open Platform : Var Length "|" (pipe) AS400 Platform: Fixed Length | S7: Y | T7: Y
A8: 7 | B8: PCB-Lending | C8: Plan B (EBAN) | D8: Pull EBAN File | E8: Common_Limit_Info_YYYYMMDD.txt | F8: pcb_loan_common_limit_info | G8: Common_Limit_Info_V2.0.xls | H8: CBR_VP_LMT_FNC_SVC_AR_v1.6 | I8: txt | J8: Fulldump | K8: N | L8: TBC | M8: N | N8: N | O8: Tailor | P8: =VLOOKUP(E8,'Dev Inventory'!T:Y,5,FALSE) -> - Have rec type (To be revised) - [Feb 21] Remark: File Delimiter listed as | (pipe) as per Table Spec | Q8: Daily | R8: Open Platform : Var Length "|" (pipe) AS400 Platform: Fixed Length | S8: Y | T8: Y
A9: 8 | B9: PCB-Lending | C9: Plan B (EBAN) | D9: Pull EBAN File | E9: Common_Market_Code_YYYYMMDD.txt | F9: pcb_loan_common_market_code | G9: Common_Market_Code.xlsx | H9: KBMF-718.02-DATALAKE_VIEW_VQ_MKT_CD_V0.4 CBR_VQ_MKT_CD_V0.4 | I9: txt | J9: Fulldump | K9: N | L9: TBC | M9: N | N9: N | O9: Tailor | P9: =VLOOKUP(E9,'Dev Inventory'!T:Y,5,FALSE) -> - Have rec type (To be revised) - [Feb 21] Remark: File Delimiter listed as | (pipe) as per Table Spec | Q9: Daily | R9: Open Platform : Var Length "|" (pipe) AS400 Platform: Fixed Length | S9: Y | T9: Y
A10: 9 | B10: PCB-Lending | C10: Plan B (EBAN) | D10: Pull EBAN File | E10: Common_Rate_Type.txt | F10: pcb_loan_common_rate_type | G10: Common_Rate_Type.xls | H10: CBR_718.02_VQ_INT_RATE_TP_CD_V0.4 | I10: txt | J10: Fulldump | K10: N | L10: TBC | M10: N | N10: N | O10: Tailor | P10: =VLOOKUP(E10,'Dev Inventory'!T:Y,5,FALSE) -> - Have rec type (To be revised) - [Feb 21] Remark: File Delimiter listed as | (pipe) as per Table Spec | Q10: Daily | R10: Open Platform : Var Length "|" (pipe) AS400 Platform: Fixed Length | S10: Y | T10: Y
A11: 10 | B11: PCB-Lending | C11: Plan B (EBAN) | D11: Pull EBAN File | E11: Common_Account_Tier_By_Time.txt | F11: pcb_loan_common_account_tier_by_time | G11: Common_Account_Tier_By_Time.xlsx | H11: CBR_VP_AR_RATE_TIER_BY_TM_V0.4 | I11: txt | J11: Fulldump | K11: N | L11: TBC | M11: N | N11: N | O11: Tailor | P11: =VLOOKUP(E11,'Dev Inventory'!T:Y,5,FALSE) -> - Have rec type (To be revised) '[Feb 21] Remark: File Delimiter listed as | (pipe) as per Table Spec | Q11: Daily | R11: Open Platform : Var Length "|" (pipe) AS400 Platform: Fixed Length | S11: Y | T11: Y
A12: 11 | B12: PCB-Deposit | C12: Plan B (EBAN) | D12: Pull EBAN File | E12: CISP.CB2D0005.ODENCITD.SAM_YYYYMMDD | F12: pcb_dep_cb2d0005_odencitd_sam | G12: R192-AMS-KBMFB1900176-CB2D0005-BaOdEncItdAcctBal001_DM | H12: CBR_EBAN_VP_PCB_AR_CA_OD_ENC_ITD_LMT_DLY_V0.5 | I12: txt (fix length) | J12: Fulldump | K12: N | L12: N | M12: N | N12: N | O12: Tailor | P12: =VLOOKUP(E12,'Dev Inventory'!T:Y,5,FALSE) -> - CBR missing field => อิงตามKBMF แทน | Q12: Daily | S12: Y | T12: Y
A13: 12 | B13: PCB-Deposit | C13: Plan B (EBAN) | D13: Pull EBAN File | E13: src_pf_txn_mis_eft_dly_yyyymmdd.txt | F13: pcb_dep_src_pf_txn_mis_eft_dly | G13: KBMF-(718.02)-DATALAKE_VIEW_VP_PCB_EFT_TXN_v.0.4 W4-AMS-APIB00392-ElectronicFundTransferTransaction_DM | H13: CBR_VP_PCB_EFT_TXN_v0.3.xlsx | I13: txt | J13: Fulldump | K13: N | L13: N | M13: N | N13: N | O13: Tailor | P13: =VLOOKUP(E13,'Dev Inventory'!T:Y,5,FALSE) -> Remark: '- Have rec type (To be revised) - ใน Table Spec ระบุ Tailor แต่ใน KBMF EBAN ไม่มี => Flag Tailor = Y ไว้ - TIS-620 encoding in KBMF | Q13: Daily | S13: Y | T13: Y
A14: 13 | B14: PCB-Deposit | C14: Plan B (EBAN) | D14: Pull EBAN File | E14: cls500029_yyyymmdd.txt | F14: pcb_dep_cls500029 | G14: W4-AMS-APIB00392-Classification_DM | H14: CBR_V_PCB_CL_v.0.7.xlsx | I14: txt | J14: Fulldump | K14: N | L14: N | M14: N | N14: N | O14: Tailor | P14: =VLOOKUP(E14,'Dev Inventory'!T:Y,5,FALSE) -> Remark: '- Have rec type (To be revised) - ใน Table Spec ระบุ Tailor แต่ใน KBMF EBAN ไม่มี => Flag Tailor = Y ไว้ | Q14: Daily | R14: No KBMF: Used CBR | S14: Y | T14: Y
A15: 14 | B15: PCB-Deposit | C15: Plan B (EBAN) | D15: Pull EBAN File | E15: SRC_PF_AR_CA_CR_INF_DLY_yyyymmdd.txt | F15: pcb_dep_src_pf_ar_ca_cr_inf_dly | G15: W4-AMS-APIB00075-Account Arrangement_DM.xlsx | H15: CBR_VP_PCB_AR_MSTR_DLY_v.0.3_20200124.xlsx | I15: txt (fix length) | J15: Fulldump | K15: N | L15: N | M15: N | N15: N | O15: Tailor | P15: =VLOOKUP(E15,'Dev Inventory'!T:Y,5,FALSE) -> Remark: '- Have rec type (To be revised) - ใน Table Spec ระบุ Tailor แต่ใน KBMF EBAN ไม่มี => Flag Tailor = Y ไว้ | Q15: Daily | R15: No KBMF: Used CBR | S15: Y | T15: Y
A16: 15 | B16: FCD | C16: Plan B (EBAN) | D16: Pull EBAN File | E16: FCD_AR_YYYYMMDD.txt | F16: fcd_ar | G16: KBMF_640_FCDB0001O_FCDArrangement_v1.0_20220816.xlsx | H16: CBR_VP_FCD_DEP_AR_DLY_v1.3 | I16: txt | J16: Fulldump | K16: N | L16: N | M16: Y | N16: N | O16: Tailor | P16: =VLOOKUP(E16,'Dev Inventory'!T:Y,5,FALSE) -> Remark: '- Have rec type (To be revised) - TIS-620 encoding in KBMF | Q16: Daily | S16: Y | T16: Y
A17: 16 | B17: PCB-Lending | C17: Plan B (EBAN) | D17: Pull EBAN File | E17: Common_Product_Type.txt | F17: pcb_loan_common_product_type | G17: Common_Product_Type | H17: KBMF-718.02-DATALAKE_VIEW_VQ_PD_TP_CD_V0.3 CBR_VQ_PD_TP_CD_V0.3 | I17: txt | J17: Fulldump | K17: N | L17: TBC | M17: 0 | N17: N | O17: Tailor | P17: =VLOOKUP(E17,'Dev Inventory'!T:Y,5,FALSE) -> - Have rec type (To be revised) | Q17: Daily | R17: Open Platform : Var Length "|" (pipe) AS400 Platform: Fixed Length | S17: Y | T17: Y
A18: 17 | B18: PCB-Lending | C18: Plan B (EBAN) | D18: Pull EBAN File | E18: Common_Sub_Type.txt | F18: pcb_loan_common_sub_type | G18: Common_Sub_Type | H18: KBMF-718.02-DATALAKE_VIEW_VQ_PD_SUB_TP_CD_V0.3 CBR_VQ_PD_SUB_TP_CD_V0.3 | I18: txt | J18: Fulldump | K18: N | L18: TBC | M18: 0 | N18: N | O18: Tailor | P18: =VLOOKUP(E18,'Dev Inventory'!T:Y,5,FALSE) -> - Have rec type (To be revised) | Q18: Daily | R18: Open Platform : Var Length "|" (pipe) AS400 Platform: Fixed Length | S18: Y | T18: Y
A19: 18 | B19: PCB-Lending | C19: Plan B (EBAN) | D19: Pull EBAN File | E19: Common_Loan_Purpose_Table_yyyymmdd.txt | F19: pcb_loan_common_loan_purpose_table | G19: Common-Loan purpose table | H19: KBMF-718.02-DATATANK_VIEW_VQN_AR_PPS_TP_CD_V0.1 CBR_VQ_AR_PPS_TP_CD_V0.2 | I19: txt | J19: Fulldump | K19: N | L19: TBC | M19: 0 | N19: N | O19: Tailor | P19: =VLOOKUP(E19,'Dev Inventory'!T:Y,5,FALSE) -> - Have rec type (To be revised) | Q19: Daily | R19: Open Platform : Var Length "|" (pipe) AS400 Platform: Fixed Length | S19: Y | T19: Y
A20: 19 | B20: LPM-AS/400​ | C20: Plan B (EBAN) | D20: Pull EBAN IN File | E20: DATALAKE.IN_LPM_LMT_AR_INF_BFR_WRTOF | F20: lpm_as400_lmt_ar_inf_bfr_wrtof | G20: LMD23400.xls | H20: CBR_VP_LPM_LMT_AR_INF_BFR_WRTOF_v0.5 | I20: txt | J20: Fulldump | K20: Y | L20: N | M20: N | N20: Y | O20: N | Q20: Daily | S20: Y | T20: Y
A21: 20 | B21: LPM-AS/400​ | C21: Plan B (EBAN) | D21: Pull EBAN IN File | E21: DATALAKE.IN_LPM_AR_WRTOF_RCV | F21: lpm_as400_ar_wrtof_rcv | G21: L01D070.xls | H21: CBR_V_LPM_AR_WRTOF_RCV_v0.9.xlsx | I21: txt | J21: Fulldump | K21: Y | L21: N | M21: N | N21: Y | O21: N | Q21: Monthly | S21: Y | T21: Y
A22: 21 | B22: LPM-AS/400​ | C22: Plan B (EBAN) | D22: Pull EBAN IN File | E22: DATALAKE.IN_LPM_LN_CNTG_DMMY_CLSS_PRVN | F22: lpm_as400_ln_cntg_dmmy_clss_prvn | G22: L01W769.xls | H22: CBR_VP_LPM_LN_CNTG_DMMY_CLSS_PRVN_v0.19 | I22: txt | J22: Fulldump | K22: Y | L22: N | M22: N | N22: Y | O22: N | Q22: Daily | S22: Y | T22: Y
A23: 22 | B23: LPM-AS/400​ | C23: Plan B (EBAN) | D23: Pull EBAN IN File | E23: DATALAKE.IN_LPM_LN_CARD_CLSS_PRVN | F23: lpm_as400_ln_card_clss_prvn | G23: L01W181.xls | H23: CBR_VP_LPM_LN_CARD_CLSS_PRVN_v0.18 | I23: txt | J23: Fulldump | K23: Y | L23: N | M23: N | N23: Y | O23: N | Q23: Daily | S23: Y | T23: Y
A24: 23 | B24: LPM-AS/400​ | C24: Plan B (EBAN) | D24: Pull EBAN IN File | E24: DATALAKE.IN_LPM_LN_CNTG_CLSS_PRVN | F24: lpm_as400_ln_cntg_clss_prvn | G24: L01W909.xls | H24: CBR_VP_LPM_LN_CNTG_CLSS_PRVN_v0.18 | I24: txt | J24: Fulldump | K24: Y | L24: N | M24: N | N24: Y | O24: N | Q24: Monthly | S24: Y | T24: Y
A25: 24 | B25: LPM-AS/400​ | C25: Plan B (EBAN) | D25: Pull EBAN IN File | E25: DATALAKE.IN_LPM_AR_CLSS_QLY | F25: lpm_as400_ar_clss_qly | G25: L01D027.xls | H25: CBR_VP_LPM_AR_CLSS_QLY_v.0.8 | I25: txt | J25: Fulldump | K25: Y | L25: N | M25: N | N25: Y | O25: N | Q25: Daily | S25: Y | T25: Y
A26: 25 | B26: LPM-AS/400​ | C26: Plan B (EBAN) | D26: Pull EBAN IN File | E26: DATALAKE.IN_LPM_LN_CNTG_CLSS_PRVN_BFR_WRTOF | F26: lpm_as400_ln_cntg_clss_prvn_bfr_wrtof | G26: Layout_L01W909_L01W910.xls | H26: CBR_VP_LPM_LN_CNTG_CLSS_PRVN_BFR_WRTOF.v0.4 | I26: txt | J26: Fulldump | K26: Y | L26: N | M26: N | N26: Y | O26: N | Q26: Monthly | S26: Y | T26: Y
A27: 26 | B27: LPM-AS/400​ | C27: Plan B (EBAN) | D27: Pull EBAN IN File | E27: DATALAKE.IN_LPM_LMT_INF_BFR_WRTOF | F27: lpm_as400_lmt_inf_bfr_wrtof | G27: LMD23500.xls | H27: CBR_VP_LPM_LMT_INF_BFR_WRTOF_v0.5 | I27: txt | J27: Fulldump | K27: Y | L27: N | M27: N | N27: Y | O27: N | Q27: Daily | S27: Y | T27: Y
A28: 27 | B28: CIS | C28: Plan A | D28: Source File (Push) | E28: CIS_IPXAR_YYYYMMDD.txt | F28: cis_ipxar | G28: KBMF-17601-CIS-MDF_IPXAR V0.1 | H28: CBR_V_AR_X_IP_REL_for_CIS_DECOM_0.11 | I28: txt | J28: Fulldump | K28: N | L28: N | M28: N | N28: Y | O28: N | P28: =VLOOKUP(E28,'Dev Inventory'!T:Y,5,FALSE) -> 0 | Q28: Daily | R28: Data file no header Column name | S28: Y | T28: Y
A29: 28 | B29: CIS | C29: Plan A | D29: Source File (Push) | E29: CIS_IP_YYYYMMDD.txt | F29: cis_ip | G29: KBMF-17601-CIS-MDF_IP V0.1 | H29: CBR_V_IP_for_CIS_DECOM_0.15 | I29: txt | J29: Fulldump | K29: N | L29: N | M29: N | N29: Y | O29: N | P29: =VLOOKUP(E29,'Dev Inventory'!T:Y,5,FALSE) -> 0 | Q29: Daily | R29: Data file no header Column name | S29: Y | T29: Y
A30: 29 | B30: CIS | C30: Plan A | D30: Source File (Push) | E30: CIS_AR_YYYYMMDD.txt | F30: cis_ar | G30: KBMF-17601-CIS-MDF_AR V0.2 | I30: txt | J30: Fulldump | K30: N | L30: N | M30: N | N30: Y | O30: N | P30: =VLOOKUP(E30,'Dev Inventory'!T:Y,5,FALSE) -> 0 | Q30: Daily | R30: Data file no header Column name | S30: Y | T30: Y
A31: 30 | B31: CSM | C31: Plan A | D31: Source File (Push) | E31: CSM_CUSTXFORMXCONSENT_YYYYMMDD.TXT | F31: csm_custxformxconsent | G31: KBMF-780-CSMP_V_CUSTXFORMXCONSENT_v.0.3 | H31: CBR_V_CNSNT_FORM_KBNK_V0.7.xlsx | I31: txt | J31: Fulldump | K31: Y | L31: N | M31: N | N31: Y | O31: N | P31: =VLOOKUP(E31,'Dev Inventory'!T:Y,5,FALSE) -> 0 | Q31: Daily | S31: Y | T31: Y
A32: 31 | B32: CSM | C32: Plan A | D32: Source File (Push) | E32: CSM_FORMXAPPR_YYYYMMDD.TXT | F32: csm_formxappr | G32: KBMF-780-CSMP_V_FORMXAPPR_v.0.2 | H32: CBR_VP_CNSNT_FORM_DTL_V0.1.xlsx | I32: txt | J32: Fulldump | K32: Y | L32: N | M32: N | N32: Y | O32: N | P32: =VLOOKUP(E32,'Dev Inventory'!T:Y,5,FALSE) -> 0 | Q32: Daily | S32: Y | T32: Y
A33: 32 | B33: CSM | C33: Plan A | D33: Source File (Push) | E33: CSM_CHANNEL_YYYYMMDD.TXT | F33: csm_channel | G33: KBMF-780-CSMP_V_CHANNEL_v.0.2 | H33: CBR_VP_CNSNT_CNL_CD_v.0.1.xlsx | I33: txt | J33: Fulldump | K33: Y | L33: N | M33: N | N33: Y | O33: N | P33: =VLOOKUP(E33,'Dev Inventory'!T:Y,5,FALSE) -> 0 | Q33: Daily | S33: Y | T33: Y
A34: 33 | B34: CSM | C34: Plan A | D34: Source File (Push) | E34: CSM_ORIGINATEPRODUCTCOA_YYYYMMDD.TXT | F34: csm_originateproductcoa | G34: KBMF-780-CSMP_ORIGINATEPRODUCTCOA_v.0.1 | I34: txt | J34: Fulldump | K34: Y | L34: N | M34: N | N34: Y | O34: N | P34: =VLOOKUP(E34,'Dev Inventory'!T:Y,5,FALSE) -> 0 | Q34: Daily | S34: Y | T34: Y
A35: 34 | B35: CSM | C35: Plan A | D35: Source File (Push) | E35: CSM_ORIGINATEPRODUCTNONCOA_YYYYMMDD.TXT | F35: csm_originateproductnoncoa | G35: KBMF-780-CSMP_V_ORIGINATEPRODUCTNONCOA_v.0.2 | H35: CBR_VP_CNSNT_ORIG_NON_COA_PD_CD_v.0.2.xlsx | I35: txt | J35: Fulldump | K35: Y | L35: N | M35: N | N35: Y | O35: N | P35: =VLOOKUP(E35,'Dev Inventory'!T:Y,5,FALSE) -> 0 | Q35: Daily | S35: Y | T35: Y
A36: 35 | B36: CSM | C36: Plan A | D36: Source File (Push) | E36: CSM_PURPOSE_YYYYMMDD.TXT | F36: csm_purpose | G36: KBMF-780-CSMP_V_PURPOSE_v.0.2 | H36: CBR_VP_CNSNT_PPS_CD_v.0.1.xlsx | I36: txt | J36: Fulldump | K36: Y | L36: N | M36: N | N36: Y | O36: N | P36: =VLOOKUP(E36,'Dev Inventory'!T:Y,5,FALSE) -> 0 | Q36: Daily | S36: Y | T36: Y
A37: 36 | B37: CSM | C37: Plan A | D37: Source File (Push) | E37: CSM_COMPANY_YYYYMMDD.TXT | F37: csm_company | G37: KBMF-780-CSMP_V_COMPANY_v.0.2 | H37: CBR_VP_CNSNT_CO_CD_v.0.2.xlsx | I37: txt | J37: Fulldump | K37: Y | L37: N | M37: N | N37: Y | O37: N | P37: =VLOOKUP(E37,'Dev Inventory'!T:Y,5,FALSE) -> 0 | Q37: Daily | S37: Y | T37: Y
A38: 37 | B38: CSM | C38: Plan A | D38: Source File (Push) | E38: CSM_RECEIVERTYPE_YYYYMMDD.TXT | F38: csm_receivertype | G38: KBMF-780-CSMP_V_RECEIVERTYPE_v.0.2 | H38: CBR_VP_CNSNT_RCVR_TP_CD_v.0.1 | I38: txt | J38: Fulldump | K38: Y | L38: N | M38: N | N38: Y | O38: N | P38: =VLOOKUP(E38,'Dev Inventory'!T:Y,5,FALSE) -> 0 | Q38: Daily | S38: Y | T38: Y
A39: 38 | B39: CSM | C39: Plan A | D39: Source File (Push) | E39: CSM_FORMCONSENT_YYYYMMDD.TXT | F39: csm_formconsent | G39: KBMF-780-CSMP_V_FORMCONSENT_v.0.1 | H39: CBR_VP_CNSNT_FORM_v0.1 | I39: txt | J39: Fulldump | K39: Y | L39: N | M39: N | N39: Y | O39: N | P39: =VLOOKUP(E39,'Dev Inventory'!T:Y,5,FALSE) -> 0 | Q39: Daily | S39: Y | T39: Y
A40: 39 | B40: CSM | C40: Plan A | D40: Source File (Push) | E40: CSM_FORMXCONTENT_YYYYMMDD.TXT | F40: csm_formxcontent | G40: KBMF-780-CSMP_V_FORMXCONTENT_v.0.5 | H40: CBR_VP_CNSNT_FORM_CNTNT_v.1.0 | I40: txt | J40: Fulldump | K40: Y | L40: N | M40: N | N40: Y | O40: N | P40: =VLOOKUP(E40,'Dev Inventory'!T:Y,5,FALSE) -> 0 | Q40: Daily | S40: Y | T40: Y
A41: 40 | B41: CSM | C41: Plan A | D41: Source File (Push) | E41: CSM_ACTION_YYYYMMDD.TXT | F41: csm_action | G41: KBMF-780-CSMP_V_ACTION_v.0.2 | H41: CBR_VP_CNSNT_ACTN_CD_v.0.1 | I41: txt | J41: Fulldump | K41: Y | L41: N | M41: N | N41: Y | O41: N | P41: =VLOOKUP(E41,'Dev Inventory'!T:Y,5,FALSE) -> 0 | Q41: Daily | S41: Y | T41: Y
A42: 41 | B42: CSM | C42: Plan A | D42: Source File (Push) | E42: CSM_PRODUCT_YYYYMMDD.TXT | F42: csm_product | G42: KBMF-780-CSMP_PRODUCT_v.0.1 | I42: txt | J42: Fulldump | K42: Y | L42: N | M42: N | N42: Y | O42: N | P42: =VLOOKUP(E42,'Dev Inventory'!T:Y,5,FALSE) -> 0 | Q42: Daily | S42: Y | T42: Y
A43: 42 | B43: Trade-Navigator | C43: Plan B (EBAN) | D43: Pull EBAN File | E43: LCR070_YYYYMMDD.txt | F43: trade_na_lcr070 | G43: KBMF_Batch_TF_MIS-Report_(LCR070).xlsx | H43: CBR_EBAN_V_TRD_AC_AR_v1.2 | I43: txt | J43: Fulldump | K43: N | L43: Y (header/tailor only) | M43: N | N43: N | O43: Tailor | P43: =VLOOKUP(E43,'Dev Inventory'!T:Y,5,FALSE) -> - ต้องใส่ File Delimiter ใน CBR เป็นแบบไหน KBMF ระบุเป็น (txt var length) | Q43: Daily | R43: Freq: previous business day | S43: Y | T43: Y
A44: 43 | B44: Trade-Navigator | C44: Plan B (EBAN) | D44: Pull EBAN File | E44: SRC_EXIMAR_YYYYMMDD.TXT | F44: trade_na_src_eximar | G44: KBMF_Batch_TF_MIS-Report_(ALM).xlsx | H44: CBR_EBAN_V_TRD_AC_AR_INF_v0.4 | I44: txt | J44: Fulldump | K44: N | L44: Y (header/tailor only) | M44: Y | N44: N | O44: Tailor | P44: =VLOOKUP(E44,'Dev Inventory'!T:Y,5,FALSE) -> [Feb 21]: 2 Pos dates Integer has no size in KBMF and EBAN CBR | Q44: Daily | R44: Freq: previous business day | S44: Y | T44: Y
A45: 44 | B45: New-Trade | C45: Plan B (EBAN) | D45: Pull EBAN File | E45: KBGT_CONT_OUTSTANDING_YYYYMMDD.TXT | F45: gts_kbgt_cont_outstanding | G45: KBMF-Batch_NTF_Contingent_Outstanding_DIH_v0.0.29_20200702.xlsx | H45: CBR_EBAN_VP_CNTG_TDG_AC_AR_INF_v1.4 | I45: txt | J45: Fulldump | K45: N | L45: change column name - to _ | M45: N | N45: N | O45: Tailor | P45: =VLOOKUP(E45,'Dev Inventory'!T:Y,5,FALSE) -> 0 | Q45: Daily | R45: Freq: Business Daily | S45: Y | T45: Y
A46: 45 | B46: New-Trade | C46: Plan B (EBAN) | D46: Pull EBAN File | E46: KBGT_LOAN_OUTSTANDING_YYYYMMDD.TXT | F46: gts_kbgt_loan_outstanding | G46: KBMF-Batch_NTF_Loan_Outstanding_DIH_v0.0.28_20200702.xlsx | H46: CBR_EBAN_V_TDG_AC_AR_INF_v1.2 CBR_EBAN_V_TDG_AC_AR_INF_v1.4 | I46: txt | J46: Fulldump | K46: N | L46: change column name - to _ | M46: N | N46: N | O46: Tailor | P46: =VLOOKUP(E46,'Dev Inventory'!T:Y,5,FALSE) -> 0 | Q46: Daily | R46: Freq: Business Daily | S46: Y | T46: Y
A47: 46 | B47: Supply Chain | C47: Plan B (Source) | D47: Pull Database | E47: VW_SCT_BOOK_LOAN | F47: scf_vw_sct_book_loan | G47: KBMF-(460)-SCT_BOOK_LOAN.xlsx | H47: CBR_VP_SCF_BOOK_LOAN_v0.7 | I47: txt | J47: Fulldump | K47: Y | L47: N | M47: N | N47: Y | O47: N | P47: =VLOOKUP(E47,'Dev Inventory'!T:Y,5,FALSE) -> 0 | Q47: Daily | R47: Enhance by FW | S47: Y | T47: Y
A48: 47 | B48: Supply Chain | C48: Plan B (Source) | D48: Pull Database | E48: VW_RDT_SCF_CL | F48: scf_vw_rdt_scf_cl | G48: KBMF-Batch_SCF_Credit_limit_v4.0.xlsx | H48: CBR_VP_SCF_LMT_AR_INF_v0.4 | I48: txt | J48: Fulldump | K48: Y | L48: N | M48: N | N48: Y | O48: N | P48: =VLOOKUP(E48,'Dev Inventory'!T:Y,5,FALSE) -> 0 | Q48: Daily | R48: Enhance by FW | S48: Y | T48: Y
A49: 48 | B49: Supply Chain | C49: Plan B (Source) | D49: Pull Database | E49: VW_CM_FEE_STRUCTURE | F49: scf_vw_cm_fee_structure | G49: KBMF-(460)-SCM_FEE_STRUCTURE.xlsx | H49: CBR_VP_SCF_FEE_DTL_v0.6 | I49: txt | J49: Fulldump | K49: Y | L49: N | M49: N | N49: Y | O49: N | P49: =VLOOKUP(E49,'Dev Inventory'!T:Y,5,FALSE) -> 0 | Q49: Daily | R49: Enhance by FW | S49: Y | T49: Y
A50: 49 | B50: Supply Chain | C50: Plan B (Source) | D50: Pull Database | E50: VW_SCM_ACCT | F50: scf_vw_scm_acct | G50: KBMF-(460)-SCM_ACCT.xlsx | H50: CBR_VP_SCF_CST_X_AR_REL_v0.2 | I50: txt | J50: Fulldump | K50: Y | L50: N | M50: N | N50: Y | O50: N | P50: =VLOOKUP(E50,'Dev Inventory'!T:Y,5,FALSE) -> Pending top section | Q50: Daily | R50: Enhance by FW | S50: Y | T50: Y
A51: 50 | B51: Supply Chain | C51: Plan B (Source) | D51: Pull Database | E51: SCM_TRADING | F51: scf_trading | G51: KBMF-(460)-SCM_TRADING.xlsx | H51: CBR_VP_SCF_TDG_0.4 | I51: txt | J51: Fulldump | K51: Y | L51: N | M51: N | N51: Y | O51: N | P51: =VLOOKUP(E51,'Dev Inventory'!T:Y,5,FALSE) -> - 2 column copy data from phy. Cbr eban - 2 Colunm diff kbnf | Q51: Daily | R51: Enhance by FW | S51: Y | T51: Y
A52: 51 | B52: Supply Chain | C52: Plan B (Source) | D52: Pull Database | E52: SCM_CUSTOMER | F52: scf_customer | G52: KBMF-(460)-SCM_CUSTOMER_updatefield.xlsx | H52: CBR_VP_SCF_CST_PRFL_v0.3 | I52: txt | J52: Fulldump | K52: Y | L52: N | M52: N | N52: Y | O52: N | P52: =VLOOKUP(E52,'Dev Inventory'!T:Y,5,FALSE) -> - 1 column copy data from phy. Cbr eban - 1 Colunm diff kbnf | Q52: Daily | R52: Enhance by FW | S52: Y | T52: Y
A53: 52 | B53: Murex | C53: Plan B (EBAN) | D53: Pull EBAN File | E53: MXMKTEvent_YYYYMMDD.txt | F53: mx_mktevent | G53: KBMF-Batch_MX_ADD_ON-590-XXX_MXMKTEvent_Y22M04D21_v1.0.0_WL.xls | H53: CBR_VP_CMB_MKT_EV_v0.1 | I53: txt | J53: Fulldump | K53: N | L53: N | M53: N | N53: N | O53: Tailor | P53: =VLOOKUP(E53,'Dev Inventory'!T:Y,5,FALSE) -> - Have rec type (To be revised) | Q53: Daily | S53: Y | T53: Y
A54: 53 | B54: Murex | C54: Plan B (EBAN) | D54: Pull EBAN File | E54: MMLiveMat_YYYYMMDD.txt | F54: mx_mmlivemat | G54: -(105) KBMF-Batch_MX_ADD_ON-590-048_MMLiveMat_Y22M04D21_v1.0.5_WL.xls - (105) KBMF-Batch_MX_ADD_ON-590-048_MMLiveMat_Y21M11D012_v1.0.2_PC | H54: CBR_VP_CMB_MM_DEAL_AR_v0.6 | I54: txt | J54: Fulldump | K54: N | L54: N | M54: N | N54: N | O54: Tailor | P54: =VLOOKUP(E54,'Dev Inventory'!T:Y,5,FALSE) -> - Have rec type (To be revised) | Q54: Daily | R54: KBMF มี 2 ไฟล์ | S54: Y | T54: Y
A55: 54 | B55: RDM | C55: Plan A | D55: Source File (Push) | E55: mdm.CST_IP_LGL_STC_TP_CD | F55: rdm_cst_ip_lgl_stc_tp_cd | G55: KBMF-655-FILE-RDM_CST_IP_LGL_STC_TP_CD_V.0.1 | H55: CBR_V_IP_LGL_STC_TP_CD_v.0.5 | I55: txt | J55: Fulldump | K55: Y | L55: N | M55: N | N55: Y | O55: N | P55: =VLOOKUP(E55,'Dev Inventory'!T:Y,5,FALSE) -> 0 | Q55: Daily | R55: Have Header | S55: Y | T55: Y
A56: 55 | B56: RDM | C56: Plan A | D56: Source File (Push) | E56: mdm.CST_NAT_CD | F56: rdm_cst_nat_cd | G56: KBMF-655-FILE-RDM_CST_NAT_CD_V.0.1 | H56: CBR_V_NAT_CD_v0.7 | I56: txt | J56: Fulldump | K56: Y | L56: N | M56: N | N56: Y | O56: N | P56: =VLOOKUP(E56,'Dev Inventory'!T:Y,5,FALSE) -> 0 | Q56: Daily | R56: Have Header | S56: Y | T56: Y
A57: 56 | B57: RDM | C57: Plan A | D57: Source File (Push) | E57: mdm.CST_MAR_ST_CD | F57: rdm_cst_mar_st_cd | G57: KBMF-655-FILE-RDM_CST_MAR_ST_CD_V.0.1 | H57: CBR_V_MAR_ST_CD_v0.8 | I57: txt | J57: Fulldump | K57: Y | L57: N | M57: N | N57: Y | O57: N | P57: =VLOOKUP(E57,'Dev Inventory'!T:Y,5,FALSE) -> 0 | Q57: Daily | R57: Have Header | S57: Y | T57: Y
A58: 57 | B58: RDM | C58: Plan A | D58: Source File (Push) | E58: mdm.CST_CTF_TP_CD | F58: rdm_cst_ctf_tp_cd | G58: KBMF-655-FILE-RDM_CST_CTF_TP_CD_V.0.1 | H58: CBR_V_CTF_TP_CD_v.0.7 | I58: txt | J58: Fulldump | K58: Y | L58: N | M58: N | N58: Y | O58: N | P58: =VLOOKUP(E58,'Dev Inventory'!T:Y,5,FALSE) -> 0 | Q58: Daily | R58: Have Header | S58: Y | T58: Y
A59: 58 | B59: RDM | C59: Plan A | D59: Source File (Push) | E59: mdm.CST_OCP_CD | F59: rdm_cst_ocp_cd | G59: KBMF-655-FILE-RDM_CST_OCP_CD_V.0.1 | H59: CBR_V_OCP_CD_V0.4_PRD | I59: txt | J59: Fulldump | K59: Y | L59: N | M59: N | N59: Y | O59: N | P59: =VLOOKUP(E59,'Dev Inventory'!T:Y,5,FALSE) -> 0 | Q59: Daily | R59: Have Header | S59: Y | T59: Y
A60: 59 | B60: RDM | C60: Plan A | D60: Source File (Push) | E60: mdm.CST_PROF_CD | F60: rdm_cst_prof_cd | G60: KBMF-655-FILE-RDM_CST_PROF_CD_V.0.1 | H60: CBR_EBAN_V_PROF_CD_V0.7 | I60: txt | J60: Fulldump | K60: Y | L60: N | M60: N | N60: Y | O60: N | P60: =VLOOKUP(E60,'Dev Inventory'!T:Y,5,FALSE) -> 0 | Q60: Daily | R60: Have Header | S60: Y | T60: Y
A61: 60 | B61: RDM | C61: Plan A | D61: Source File (Push) | E61: mdm.CST_IDV_INCM_SEG_CD | F61: rdm_cst_idv_incm_seg_cd | G61: KBMF-655-FILE-RDM_CST_IDV_INCM_SEG_CD_V.0.1 | H61: CBR_V_IDV_INCM_SEG_CD_v.1.0 | I61: txt | J61: Fulldump | K61: Y | L61: N | M61: N | N61: Y | O61: N | P61: =VLOOKUP(E61,'Dev Inventory'!T:Y,5,FALSE) -> 0 | Q61: Daily | R61: Have Header | S61: Y | T61: Y
A62: 61 | B62: RDM | C62: Plan A | D62: Source File (Push) | E62: mdm.CST_SEG_CD | F62: rdm_cst_seg_cd | G62: KBMF-655-FILE-RDM_CST_SEG_CD_V.0.1 | H62: CBR_V_SEG_CD_v1.2 | I62: txt | J62: Fulldump | K62: Y | L62: N | M62: N | N62: Y | O62: N | P62: =VLOOKUP(E62,'Dev Inventory'!T:Y,5,FALSE) -> 0 | Q62: Daily | R62: Have Header | S62: Y | T62: Y
A63: 62 | B63: RDM | C63: Plan A | D63: Source File (Push) | E63: mdm.CARD_TP_CD | F63: rdm_card_tp_cd | G63: KBMF-655-FILE-RDM_CARD_TP_CD_V.0.1 | H63: CBR_EBAN_V_CC_TP_CD_v1.0 | I63: txt | J63: Fulldump | K63: Y | L63: N | M63: N | N63: Y | O63: N | P63: =VLOOKUP(E63,'Dev Inventory'!T:Y,5,FALSE) -> 0 | Q63: Daily | R63: Have Header | S63: Y | T63: Y
A64: 63 | B64: RDM | C64: Plan A | D64: Source File (Push) | E64: PIM.V_COA_PD | F64: rdm_pim_coa_pd | G64: KBMF-655-FILE-RDM_PIM_COA_PD_V.0.1 | H64: CBR_V_COA_PD_v.0.5.xlsx | I64: txt | J64: Fulldump | K64: Y | L64: N | M64: N | N64: Y | O64: N | P64: =VLOOKUP(E64,'Dev Inventory'!T:Y,5,FALSE) -> 0 | Q64: Daily | R64: Have Header | S64: Y | T64: Y
A65: 64 | B65: RDM | C65: Plan A | D65: Source File (Push) | E65: IDY_CL_CD | F65: rdm_idy_cl_cd | G65: KBMF-655-FILE-RDM_IDY_CL_CD_V.0.1 | H65: CBR_EBAN_VC_REFR_IDY_CL_CD_V.2.7 | I65: txt | J65: Fulldump | K65: Y | L65: N | M65: N | N65: Y | O65: N | P65: =VLOOKUP(E65,'Dev Inventory'!T:Y,5,FALSE) -> 0 | Q65: Daily | R65: Have Header | S65: Y | T65: Y
A66: 65 | B66: RDM | C66: Plan A | D66: Source File (Push) | E66: IDY_CL_SUB_GRP_CD | F66: rdm_idy_cl_sub_grp_cd | G66: KBMF-655-FILE-RDM_IDY_CL_SUB_GRP_CD_V.0.1 | I66: txt | J66: Fulldump | K66: Y | L66: N | M66: N | N66: Y | O66: N | P66: =VLOOKUP(E66,'Dev Inventory'!T:Y,5,FALSE) -> 0 | Q66: Daily | R66: Have Header | S66: Y | T66: Y
A67: 66 | B67: FXBOOTH​ | C67: Plan B (Source) | D67: DIH Extraction File (Pull) | E67: MIDRATE_KBANK_YYYY-MM-DD.csv | F67: fxb_midrate_kbank | G67: KBMF_FXPub-761-200_KBankMidRate_Y18M07D18_V001_CS | I67: csv | J67: Delta | K67: Y | L67: change column name space to _ | M67: N | N67: N | O67: Header (Source count 1 header + #of detail + 1 trailer) | P67: =VLOOKUP(E67,'Dev Inventory'!T:Y,5,FALSE) -> 0 | Q67: Daily | R67: No Header Column name Freq: Business Daily | S67: Y | T67: Y
A68: 67 | B68: LPM-AS/400​ | C68: Plan A | D68: DIH Extraction File (Push) | E68: DIH_Composite_V_LPM_X_IP_REL lpm_x_ip_rel_yyyymmdd.txt | F68: lpm_as400_lpm_x_ip_rel | G68: KBMF-655-FILE_LPM_X_IP_REL_V0.1 | I68: txt | J68: Delta | K68: N | L68: TBC | M68: 0 | N68: Y | O68: N | P68: =VLOOKUP(E68,'Dev Inventory'!T:Y,5,FALSE) -> #N/A | Q68: Daily | R68: No Header Column name Freq: Business Date (Order Date - 1) | S68: Y | T68: Y
A69: 68 | B69: CIS | C69: Plan A | D69: Source File (Push) | E69: CIS_RELAR_YYYYMMDD.txt | F69: cis_relar | G69: KBMF-17601-CIS-MDF_RELAR V0.1 | H69: CBR_V_AR_X_IP_REL_TP_CD_for_CIS_DECOM_0.5 | I69: txt | J69: Fulldump | K69: N | L69: N | M69: N | N69: Y | O69: N | P69: =VLOOKUP(E69,'Dev Inventory'!T:Y,5,FALSE) -> 0 | Q69: Daily | R69: Data file no header Column name | S69: Y | T69: Y
A70: 69 | B70: CIS | C70: Plan A | D70: Source File (Push) | E70: CIS_DOCTP_YYYYMMDD.txt | F70: cis_doctp | G70: KBMF-17601-CIS-MDF_DOCTP V0.1 | H70: CBR_V_DOC_ITM_CD_for_CIS_DECOM_v0.3 | I70: txt | J70: Fulldump | K70: N | L70: N | M70: N | N70: Y | O70: N | P70: =VLOOKUP(E70,'Dev Inventory'!T:Y,5,FALSE) -> 0 | Q70: Daily | R70: Data file no header Column name | S70: Y | T70: Y
A71: 70 | B71: CIS | C71: Plan A | D71: Source File (Push) | E71: CIS_CNTRELTP_YYYYMMDD.txt | F71: cis_cntreltp | G71: KBMF-17601-CIS-MDF_CNTRELTP V0.1 | H71: CBR_V_ELC_ADR_LO_USE_TP_CD_for_CIS_DECOM_0.5 | I71: txt | J71: Fulldump | K71: N | L71: N | M71: N | N71: Y | O71: N | P71: =VLOOKUP(E71,'Dev Inventory'!T:Y,5,FALSE) -> 0 | Q71: Daily | R71: Data file no header Column name | S71: Y | T71: Y
A72: 71 | B72: CIS | C72: Plan A | D72: Source File (Push) | E72: CIS_IPXCONTACT_YYYYMMDD.txt | F72: cis_ipxcontact | G72: KBMF-17601-CIS-MDF_IPXCONTACT V0.1 | H72: CBR_V_IP_X_ELC_ADR_REL_for_CIS_DECOM_0.8 | I72: txt | J72: Fulldump | K72: N | L72: N | M72: N | N72: Y | O72: N | P72: =VLOOKUP(E72,'Dev Inventory'!T:Y,5,FALSE) -> 0 | Q72: Daily | R72: Data file no header Column name | S72: Y | T72: Y
A73: 72 | B73: CIS | C73: Plan A | D73: Source File (Push) | E73: CIS_CONTTP_YYYYMMDD.txt | F73: cis_conttp | G73: KBMF-17601-CIS-MDF_CONTTP V0.1 | H73: CBR_V_ELC_ADR_USE_TP_CD_for_CIS_DECOM_0.4 | I73: txt | J73: Fulldump | K73: N | L73: TBC | M73: N | N73: Y | O73: N | P73: =VLOOKUP(E73,'Dev Inventory'!T:Y,5,FALSE) -> 0 | Q73: Daily | R73: Data file no header Column name | S73: Y | T73: Y
A74: 73 | B74: CIS | C74: Plan A | D74: Source File (Push) | E74: CIS_CONTINFO_YYYYMMDD.txt | F74: cis_continfo | G74: KBMF-17601-CIS-MDF_CONTINFO V0.1 | H74: CBR_V_ELC_ADR_for_CIS_DECOM_0.12 | I74: txt | J74: Fulldump | K74: N | L74: N | M74: N | N74: Y | O74: N | P74: =VLOOKUP(E74,'Dev Inventory'!T:Y,5,FALSE) -> 0 | Q74: Daily | R74: Data file no header Column name | S74: Y | T74: Y
A75: 74 | B75: CIS | C75: Plan A | D75: Source File (Push) | E75: CIS_IDV_YYYYMMDD.txt | F75: cis_idv | G75: KBMF-17601-CIS-MDF-IDV V0.1 | H75: CBR_V_IDV_for_CIS_DECOM_v0.12 | I75: txt | J75: Fulldump | K75: N | L75: N | M75: N | N75: Y | O75: N | P75: =VLOOKUP(E75,'Dev Inventory'!T:Y,5,FALSE) -> 0 | Q75: Daily | R75: Data file no header Column name | S75: Y | T75: Y
A76: 75 | B76: CIS | C76: Plan A | D76: Source File (Push) | E76: CIS_ORG_YYYYMMDD.txt | F76: cis_org | G76: KBMF-17601-CIS-MDF_ORG V0.1 | H76: CBR_V_ORG_for_CIS_DECOM_0.11 | I76: txt | J76: Fulldump | K76: N | L76: N | M76: N | N76: Y | O76: N | P76: =VLOOKUP(E76,'Dev Inventory'!T:Y,5,FALSE) -> 0 | Q76: Daily | R76: Data file no header Column name | S76: Y | T76: Y
A77: 76 | B77: CIS | C77: Plan A | D77: Source File (Push) | E77: CIS_IPSEGMENT_YYYYMMDD.txt | F77: cis_ipsegment | G77: KBMF-17601-CIS-MDF_IPSEGMENT V0.1 | H77: CBR_V_IP_X_SEG_REL_for_CIS_DECOM_0.11 | I77: txt | J77: Fulldump | K77: N | L77: N | M77: N | N77: Y | O77: N | P77: =VLOOKUP(E77,'Dev Inventory'!T:Y,5,FALSE) -> 0 | Q77: Daily | R77: Data file no header Column name | S77: Y | T77: Y
A78: 77 | B78: CIS | C78: Plan A | D78: Source File (Push) | E78: CIS_HISTSEGM_YYYYMMDD.txt | F78: cis_histsegm | G78: KBMF-17601-CIS-MDF_HISTSEGM V0.1 | H78: CBR_V_IP_X_SEG_REL_for_CIS_DECOM_0.11 | I78: txt | J78: Fulldump | K78: N | L78: N | M78: N | N78: Y | O78: N | P78: =VLOOKUP(E78,'Dev Inventory'!T:Y,5,FALSE) -> 0 | Q78: Daily | R78: Data file no header Column name | S78: Y | T78: Y
A79: 78 | B79: CIS | C79: Plan A | D79: Source File (Push) | E79: CIS_ADDR_YYYYMMDD.txt | F79: cis_addr | G79: KBMF-17601-CIS-MDF_ADDR V0.1 | H79: CBR_V_ADR_for_CIS_DECOM_v0.10 | I79: txt | J79: Fulldump | K79: N | L79: N | M79: N | N79: Y | O79: N | P79: =VLOOKUP(E79,'Dev Inventory'!T:Y,5,FALSE) -> 0 | Q79: Daily | R79: Data file no header Column name | S79: Y | T79: Y
A80: 79 | B80: CIS | C80: Plan A | D80: Source File (Push) | E80: CIS_IPXADDR_YYYYMMDD.txt | F80: cis_ipxaddr | G80: KBMF-17601-CIS-MDF_IPXADDR V0.1 | H80: CBR_V_IP_X_ADR_REL_for_CIS_DECOM_v0.7 | I80: txt | J80: Fulldump | K80: N | L80: N | M80: N | N80: Y | O80: N | P80: =VLOOKUP(E80,'Dev Inventory'!T:Y,5,FALSE) -> 0 | Q80: Daily | R80: Data file no header Column name | S80: Y | T80: Y
... A82: 81 | B82: CIS | C82: Plan A | D82: Source File (Push) | E82: CIS_OTHDOC_YYYYMMDD.txt | F82: cis_othdoc | G82: KBMF-17601-CIS-MDF_OTHDOC V0.1 | H82: CBR_V_IP_X_DOC_ITM_REL_for_CIS_DECOM_v0.6 | I82: txt | J82: Fulldump | K82: N | L82: N | M82: N | N82: Y | O82: N | P82: =VLOOKUP(E82,'Dev Inventory'!T:Y,5,FALSE) -> 0 | Q82: Daily | R82: Data file no header Column name | S82: Y | T82: Y
A83: 82 | B83: Cardlink | C83: Plan B (EBAN/DIH) | D83: Pull EBAN/DIH file | E83: CPACP.DIH.KB1DH013.EPTRANS.Dddmmyy | F83: cardlink_kb1dh013_eptrans | G83: KBMF_KB1DH013_EPTRANS_V1.0.8.xls | I83: txt (fix length) | J83: Fulldump | K83: N | L83: change column name - to _ | M83: Header | N83: N | O83: Tailor | P83: =VLOOKUP(E83,'Dev Inventory'!T:Y,5,FALSE) -> - Have rec type (To be revised) | Q83: Daily | R83: EBCDIC (mainframe) | S83: Y | T83: Y
A84: 83 | B84: Cardlink | C84: Plan B (EBAN/DIH) | D84: Pull EBAN/DIH file | E84: CPACP.DIH.KB1DH045.CC1D289G.D%%TRANDATE.TXT | F84: cardlink_kb1dh045_cc1d289g | G84: KBMF_KB1DH045_CC1D289G_collateral_V 1.0.1_09March2022.xlsx | I84: txt | J84: Fulldump | K84: N | L84: N | M84: N | N84: N | O84: Tailor | P84: =VLOOKUP(E84,'Dev Inventory'!T:Y,5,FALSE) -> - To recheck decimal datatype (x,x) - To recheck label format in datafile | Q84: Daily | R84: Fixed Length, SAM | S84: Y | T84: Y
A85: 84 | B85: Cardlink | C85: Plan B (EBAN/DIH) | D85: Pull EBAN/DIH file | E85: CPACP.DIH.KB1DH002.CPBCRD.D%%TRANDATE | F85: cardlink_kb1dh002_cpbcrd | G85: KBMF_KB1DH002_CPBCRD V 1.0.13.xlsx | I85: txt | J85: Fulldump | K85: N | L85: Y | M85: N | N85: N | O85: Tailor | P85: =VLOOKUP(E85,'Dev Inventory'!T:Y,5,FALSE) -> [Feb 21] CBR does not extract all fields, to follow KBMF instead | Q85: Daily | S85: Y | T85: Y
A86: 85 | B86: Cardlink | C86: Plan B (EBAN/DIH) | D86: Pull EBAN/DIH file | E86: CPACP.DIH.KB1DH005.KBBCRD.D%%TRANDATE | F86: cardlink_kb1dh005_kbbcrd | G86: KBMF_KB1DH005_KBBCRD_V 1.0.8.xlsx | I86: txt | J86: Fulldump | K86: N | L86: Y | M86: N | N86: N | O86: Tailor | P86: =VLOOKUP(E86,'Dev Inventory'!T:Y,5,FALSE) -> 0 | Q86: Daily | S86: Y | T86: Y
A87: 86 | B87: Cardlink | C87: Plan B (EBAN/DIH) | D87: Pull EBAN/DIH file | E87: CPACP.DIH.KB1DH023.LBPTTRN.Dddmmyy.TXT | F87: cardlink_kb1dh023_lbpttrn | G87: 7.KBMF_KB1DH023_LBPTTRN V1.8.xls | I87: txt (fix length) | J87: Fulldump | K87: N | L87: Y | M87: N | N87: N | O87: Tailor | P87: =VLOOKUP(E87,'Dev Inventory'!T:Y,5,FALSE) -> - Have rec type (To be revised) | Q87: Daily | R87: - EBCDIC (mainframe) - Fixed Length, SAM | S87: Y | T87: Y
A88: 87 | B88: Cardlink | C88: Plan B (EBAN/DIH) | D88: Pull EBAN/DIH file | E88: CPACP.DIH.KB1DH039.CCND5012.Dddmmyy.TXT | F88: cardlink_kb1dh039_ccnd5012 | G88: KBMF_KB1DH039_CCND5012_V0.6.xls | I88: txt | J88: Fulldump | K88: N | L88: Y | M88: N | N88: N | O88: Tailor | P88: =VLOOKUP(E88,'Dev Inventory'!T:Y,5,FALSE) -> - Have rec type (To be revised) | Q88: Daily | R88: Fixed Length, SAM | S88: Y | T88: Y
A89: 88 | B89: Cardlink | C89: Plan B (EBAN/DIH) | D89: Pull EBAN/DIH file | E89: CPACP.DIH.KB1DH017.CPAMT.Dddmmyy.TXT | F89: cardlink_kb1dh017_cpamt | G89: KBMF_KB1DH017_CPAMT V1.9.xlsx | I89: txt (fix length) | J89: Fulldump | K89: N | L89: Y | M89: N | N89: N | O89: Tailor | P89: =VLOOKUP(E89,'Dev Inventory'!T:Y,5,FALSE) -> - Have rec type (To be revised) | Q89: Daily | R89: - EBCDIC (mainframe) - Fixed Length, SAM | S89: Y | T89: Y
A90: 89 | B90: Cardlink | C90: Plan B (EBAN/DIH) | D90: Pull EBAN/DIH file | E90: CPACP.DIH.KB1DH019.CC1T377.Dddmmyy.txt | F90: cardlink_kb1dh019_cc1t377 | G90: KBMF_KB1DH019_CP1T377 V2.8.xlsx | I90: txt (fix length) | J90: Fulldump | K90: N | L90: Y | M90: N | N90: N | O90: Tailor | P90: =VLOOKUP(E90,'Dev Inventory'!T:Y,5,FALSE) -> - Have rec type (To be revised) | Q90: Daily | R90: - EBCDIC (mainframe) - Fixed Length, SAM - same KBMF as CP1T377 | S90: Y | T90: Y
A91: 90 | B91: Cardlink | C91: Plan B (EBAN/DIH) | D91: Pull EBAN/DIH file | E91: CPACP.DIH.KB1DH018.CPSRPTT.Dddmmyy.TXT | F91: cardlink_kb1dh018_cpsrptt | G91: KBMF_KB1DH018_CPSRPTT V1.9.xls | I91: txt (fix length) | J91: Fulldump | K91: N | L91: Y | M91: N | N91: N | O91: Tailor | P91: =VLOOKUP(E91,'Dev Inventory'!T:Y,5,FALSE) -> - Have rec type (To be revised) | Q91: Daily | R91: - EBCDIC (mainframe) - Fixed Length, SAM | S91: Y | T91: Y
A92: 91 | B92: Cardlink | C92: Plan B (EBAN/DIH) | D92: Pull EBAN/DIH file | E92: CPACP.DIH.KB1DH037.CPCCPF.Dddmmyy.TXT (Target Table: cardlink_kb1dh037_cpccpf_p) | F92: cardlink_kb1dh037_cpccpf_p | G92: KBMF_KB1DH037_CPCCPF_CPTCPF_V0.9.xls | H92: CBR_VP_CC_MNT_LOG_v0.6 | I92: txt | J92: Fulldump | K92: N | L92: change column name - to _ | M92: N | N92: N | O92: Tailor | P92: =VLOOKUP(E92,'Dev Inventory'!T:Y,5,FALSE) -> - Have rec type (To be revised) KB1DH037.CPTCPF และ KB1DH037.CPCCPF - ใช้ KBMF/CBR เดียวกัน - ใน KBMF มีแยก detail 2 section (D and P) + datafile ข้อมูล D P ปนกันในไฟล์เดียว - CBR Foundation อิง CBR มีเฉพาะ part D | Q92: Daily | R92: Fixed Length, SAM | S92: Y | T92: Y
A93: 92 | B93: Cardlink | C93: Plan B (EBAN/DIH) | D93: Pull EBAN/DIH file | E93: CPACP.DIH.KB1DH003.CPBCUS.D%%TRANDATE | F93: cardlink_kb1dh003_cpbcus | G93: KBMF_KB1DH003_CPBCUS_V 1.0.7.xlsx | I93: txt | J93: Fulldump | K93: N | L93: N | M93: N | N93: N | O93: Tailor | P93: =VLOOKUP(E93,'Dev Inventory'!T:Y,5,FALSE) -> 0 | Q93: Daily | R93: Fixed Length, SAM | S93: Y | T93: Y
A94: 93 | B94: Cardlink | C94: Plan B (EBAN/DIH) | D94: Pull EBAN/DIH file | E94: CPACP.DIH.KB1DH006.KBBCUS.D%%TRANDATE | F94: cardlink_kb1dh006_kbbcus | G94: KBMF_KB1DH006_KBBCUS_V 1.0.8.xlsx | I94: txt | J94: Fulldump | K94: N | L94: N | M94: N | N94: N | O94: Tailor | P94: =VLOOKUP(E94,'Dev Inventory'!T:Y,5,FALSE) -> 0 | Q94: Daily | R94: Fixed Length, SAM | S94: Y | T94: Y
A95: 94 | B95: Cardlink | C95: Plan B (EBAN/DIH) | D95: Pull EBAN/DIH file | E95: CPACP.DIH.KB1DH028.CCIXPT.Dddmmyy.TXT | F95: cardlink_kb1dh028_ccixpt | G95: KBMF DIH: AMS-KBMF-655-DIH-OPEN_CARDLINK_MASTER_V5.0.xls KBMF Cardlink: KBMF_KB1DH028_CCIXPT V1.1 | H95: CBR_V_CC_MC_BIN_v.0.7 | I95: txt (fix length) | J95: Fulldump | K95: N | L95: N | M95: N | N95: N | O95: Tailor | P95: =VLOOKUP(E95,'Dev Inventory'!T:Y,5,FALSE) -> - Have rec type (To be revised) [Feb 27] Received Cardlink KBMF w Header + tailor fields [Feb 22] Flag header + tailor, but no header/tailor fields in DIH KBMF. | Q95: Daily | R95: - EBCDIC (mainframe) - Fixed Length, SAM | S95: Y | T95: Y
A96: 95 | B96: Cardlink | C96: Plan B (EBAN/DIH) | D96: Pull EBAN/DIH file | E96: CPACP.DIH.KB1DH029.CCATABLA.Dddmmyy.TXT | F96: cardlink_kb1dh029_ccatabla | G96: KBMF DIH: AMS-KBMF-655-DIH-OPEN_CARDLINK_VISA_V6.0.xls KBMF Cardlink: KBMF_KB1DH029_CCATABLA V1.1 | H96: CBR_V_CC_VS_BIN_v.0.5 | I96: txt (fix length) | J96: Fulldump | K96: N | L96: N | M96: N | N96: N | O96: Tailor | P96: =VLOOKUP(E96,'Dev Inventory'!T:Y,5,FALSE) -> - Have rec type (To be revised) [Feb 27] Received Cardlink KBMF w Header + tailor fields [Feb 22] Flag header + tailor, but no header/tailor fields in DIH KBMF. | Q96: Daily | R96: EBCDIC (mainframe) | S96: Y | T96: Y
A97: 96 | B97: Cardlink | C97: Plan B (EBAN/DIH) | D97: Pull EBAN/DIH file | E97: CPACP.DIH.KB1DH030.CUPTRAN.Dddmmyy.TXT | F97: cardlink_kb1dh030_cuptran | G97: 30.KBMF_KB1DH030_CC1DLOGC V3.0.xls | I97: txt | J97: Fulldump | K97: N | L97: Y | M97: N | N97: N | O97: Tailor | P97: =VLOOKUP(E97,'Dev Inventory'!T:Y,5,FALSE) -> - Have rec type (To be revised) | Q97: Daily | R97: Fixed Length, SAM | S97: Y | T97: Y
A98: 97 | B98: Cardlink | C98: Plan B (EBAN/DIH) | D98: Pull EBAN/DIH file | E98: CPACP.DIH.KB1DH031.CC1D583B.Dddmmyy.TXT | F98: cardlink_kb1dh031_cc1d583b | G98: 31.KBMF_KB1DH031_CC1D583B V2.0.xls | I98: txt | J98: Fulldump | K98: N | L98: change column name - to _ | M98: Y | N98: N | O98: Tailor | P98: =VLOOKUP(E98,'Dev Inventory'!T:Y,5,FALSE) -> - Have rec type (To be revised) | Q98: Daily | S98: Y | T98: Y
A99: 98 | B99: Cardlink | C99: Plan B (EBAN) | D99: Pull EBAN IN File | E99: ODSCC.CCV2_JCB | F99: cardlink_odscc_ccv2_jcb | G99: N/A | H99: CBR_V_CC_JCB_AHR_LOG_v0.5 | I99: txt | J99: Fulldump | K99: N | L99: N | M99: N | N99: Y | O99: N | Q99: Daily | R99: No KBMF: Used CBR | S99: Y | T99: Y
A100: 99 | B100: RMST | C100: Plan A | D100: Source File (Push) | E100: SalesSmart_Customer_yyyyMMdd.txt | F100: rmst_customer | G100: SalesSmart_KBMF_MDP_Customer_20240130_V7.0 | I100: txt | J100: Delta | K100: Y | L100: change column name . to _ | M100: N | N100: Y | O100: Tailor | P100: =VLOOKUP(E100,'Dev Inventory'!T:Y,5,FALSE) -> [29-Feb] account_extensions__r.createddate มี . มาในชื่อ column | Q100: Daily | R100: extract with double quote | S100: Y | T100: Y
A101: 100 | B101: LPM-WriteOff | C101: Plan B (EBAN) | D101: Pull EBAN File | E101: PSCP.WO.WO1D04H.SAM | F101: lpm_wrtoff_pscp_wo_wo1d04h_sam | G101: N/A | H101: CBR_VP_LPM_WRTOF_AR_v0.2 | I101: txt (fix length) | J101: Fulldump | K101: Y | L101: change column name - to _ | M101: N | N101: N | O101: Tailor | P101: =VLOOKUP(E101,'Dev Inventory'!T:Y,5,FALSE) -> [29-Feb] มี Header เป็น date ไม่มี total rec | Q101: Monthly | R101: No KBMF: Used CBR | S101: Y | T101: Y
...

Sheet Ingest dev Status
A1: CBR Development Status (Dev Inventory) | F1: Row Labels | G1: Count of Target Table Name (Persist) | R1: Batch | S1: Batch 1 | X1: Batch | Y1: Batch 2 | AE1: KBMF Status (Ingestion Inventory)
A2: Count Table | B2: Column Labels | F2: Plan A | G2: 52
A3: CBR Status | B3: Re-submitted | C3: Total | F3: ccms | G3: 4 | R3: Count of File name/Table name | S3: Column Labels | X3: Count of File name/Table name | Y3: Column Labels | AE3: Count of Received KBMF (Y/N) | AF3: Column Labels | AI3: Count of Received KBMF (Y/N) | AJ3: Column Labels
A4: Batch 1 | B4: 77 | C4: 77 | F4: cis | G4: 17 | R4: Row Labels | S4: Header/Tailor | T4: N/A | U4: Tailor | V4: Grand Total | X4: Row Labels | Y4: 0 | Z4: Header/Tailor | AA4: N/A | AB4: Tailor | AC4: Grand Total | AE4: Row Labels | AF4: Y | AG4: Grand Total | AI4: Row Labels | AJ4: Y | AK4: Grand Total
A5: Batch 2 | B5: 107 | C5: 107 | F5: csm | G5: 17 | R5: txt | S5: 20 | T5: 54 | U5: 3 | V5: 77 | X5: N | Y5: 55 | Z5: 12 | AC5: 67 | AE5: Plan A | AF5: 89 | AG5: 89 | AI5: Plan A | AJ5: 89 | AK5: 89
A6: Total | B6: 184 | C6: 184 | F6: lpm_as400 | G6: 1 | R6: N | S6: 20 | U6: 3 | V6: 23 | W6: Target complete dev Wed | X6: csv | Y6: 1 | AC6: 1 | AE6: Cardlink | AF6: 34 | AG6: 34 | AI6: Cardlink | AJ6: 34 | AK6: 34
F7: rdm | G7: 12 | R7: Cardlink | S7: 1 | V7: 1 | X7: FXBOOTH​ | Y7: 1 | AC7: 1 | AE7: Cardlink(TPN​) | AF7: 3 | AG7: 3 | AI7: Cardlink(TPN​) | AJ7: 3 | AK7: 3
F8: rmst | G8: 1 | R8: FCD | S8: 1 | V8: 1 | X8: Paq | Y8: 1 | AC8: 1 | AE8: CCMS​ | AF8: 4 | AG8: 4 | AI8: CCMS​ | AJ8: 4 | AK8: 4
F9: Plan B | G9: 118 | R9: HRIS | S9: 1 | V9: 1 | X9: HRIS | Y9: 1 | AC9: 1 | AE9: CIS | AF9: 17 | AG9: 17 | AI9: CIS | AJ9: 17 | AK9: 17
F10: cardlink | G10: 34 | R10: KS | S10: 3 | V10: 3 | X10: txt | Y10: 4 | AC10: 4 | AE10: CSM | AF10: 17 | AG10: 17 | AI10: CSM | AJ10: 17 | AK10: 17
F11: cardlink_acq | G11: 3 | R11: Murex | S11: 7 | V11: 7 | X11: Cardlink | Y11: 1 | AC11: 1 | AE11: DIH | AF11: 1 | AG11: 1 | AI11: DIH | AJ11: 1 | AK11: 1
A12: Batch | B12: Batch 1 | F12: dgtl_fctrng | G12: 8 | R12: PCB-Deposit | S12: 5 | U12: 3 | V12: 8 | X12: PCB-Deposit | Y12: 2 | AC12: 2 | AE12: RDM | AF12: 12 | AG12: 12 | AI12: RDM | AJ12: 12 | AK12: 12
F13: fcd | G13: 1 | R13: UD | S13: 2 | V13: 2 | X13: PCB-Lending | Y13: 1 | AC13: 1 | AE13: RMST | AF13: 1 | AG13: 1 | AI13: RMST | AJ13: 1 | AK13: 1
A14: Count Table | B14: Column Labels | F14: fxb | G14: 1 | R14: Y | T14: 54 | V14: 54 | W14: Target complete dev Fri 16-Feb-24 | X14: txt (EBCDIC) | Y14: 12 | AC14: 12 | AE14: Plan B (EBAN) | AF14: 65 | AG14: 65 | AI14: Plan B (EBAN) | AJ14: 65 | AK14: 65
A15: CBR Status | B15: Completed | C15: Total | F15: gts | G15: 6 | R15: CIS | T15: 17 | V15: 17 | X15: Cardlink | Y15: 12 | AC15: 12 | AE15: Cardlink | AF15: 1 | AG15: 1 | AI15: Cardlink | AJ15: 1 | AK15: 1
A16: Plan A | B16: 46 | C16: 46 | F16: hris | G16: 1 | R16: CSM | T16: 17 | V16: 17 | X16: txt (fix length) | Y16: 32 | AC16: 32 | AE16: Factoring | AF16: 1 | AG16: 1 | AI16: Factoring | AJ16: 1 | AK16: 1
A17: cis | B17: 17 | C17: 17 | F17: kplus | G17: 8 | R17: LEC​ | T17: 1 | V17: 1 | X17: Cardlink(TPN​) | Y17: 3 | AC17: 3 | AE17: FCD | AF17: 1 | AG17: 1 | AI17: FCD | AJ17: 1 | AK17: 1
A18: csm | B18: 17 | C18: 17 | F18: ks | G18: 3 | R18: LPM-AS/400​ | T18: 7 | V18: 7 | X18: CCMS​ | Y18: 4 | AC18: 4 | AE18: HRIS | AF18: 2 | AG18: 2 | AI18: HRIS | AJ18: 2 | AK18: 2
A19: rdm | B19: 12 | C19: 12 | F19: lec | G19: 1 | R19: RDM | T19: 12 | V19: 12 | X19: Cardlink | Y19: 21 | AC19: 21 | AE19: K PLUS | AF19: 8 | AG19: 8 | AI19: K PLUS | AJ19: 8 | AK19: 8
A20: Plan B (EBAN) | B20: 30 | C20: 30 | F20: lpm_wrtoff | G20: 1 | R20: Grand Total | S20: 20 | T20: 54 | U20: 3 | V20: 77 | X20: LPM-WriteOff | Y20: 1 | AC20: 1 | AE20: KS | AF20: 3 | AG20: 3 | AI20: KS | AJ20: 3 | AK20: 3
A21: fcd | B21: 1 | C21: 1 | F21: mx | G21: 9 | X21: New-Trade | Y21: 2 | AC21: 2 | AE21: LEC​ | AF21: 1 | AG21: 1 | AI21: LEC​ | AJ21: 1 | AK21: 1
A22: hris | B22: 1 | C22: 1 | F22: pcb_dep | G22: 11 | X22: PCB-Deposit | Y22: 1 | AC22: 1 | AE22: LPM-AS/400​ | AF22: 8 | AG22: 8 | AI22: LPM-AS/400​ | AJ22: 8 | AK22: 8
A23: ks | B23: 3 | C23: 3 | F23: pcb_loan | G23: 9 | X23: txt (var length) | Y23: 5 | Z23: 12 | AC23: 17 | AE23: LPM-WriteOff | AF23: 1 | AG23: 1 | AI23: LPM-WriteOff | AJ23: 1 | AK23: 1
A24: lec | B24: 1 | C24: 1 | F24: scf | G24: 9 | X24: Factoring | Y24: 1 | AC24: 1 | AE24: Murex | AF24: 9 | AG24: 9 | AI24: Murex | AJ24: 9 | AK24: 9
A25: lpm_as400 | B25: 7 | C25: 7 | F25: trade_na | G25: 2 | X25: Murex | Y25: 2 | AC25: 2 | AE25: New-Trade | AF25: 6 | AG25: 6 | AI25: New-Trade | AJ25: 6 | AK25: 6
A26: mx | B26: 7 | C26: 7 | F26: ud | G26: 11 | X26: New-Trade | Y26: 2 | Z26: 2 | AC26: 4 | AE26: PCB-Deposit | AF26: 11 | AG26: 11 | AI26: PCB-Deposit | AJ26: 11 | AK26: 11
A27: pcb_dep | B27: 8 | C27: 8 | F27: Plan B - EBAN IN | G27: 10 | X27: PCB-Lending | Z27: 8 | AC27: 8 | AE27: PCB-Lending | AF27: 9 | AG27: 9 | AI27: PCB-Lending | AJ27: 9 | AK27: 9
A28: ud | B28: 2 | C28: 2 | F28: cardlink | G28: 1 | X28: Trade-Navigator | Z28: 2 | AC28: 2 | AE28: Trade-Navigator | AF28: 2 | AG28: 2 | AI28: Trade-Navigator | AJ28: 2 | AK28: 2
A29: Plan B (EBAN/DIH) | B29: 1 | C29: 1 | F29: hrcrc | G29: 1 | X29: Y | Y29: 28 | AA29: 8 | AB29: 1 | AC29: 37 | AE29: UD | AF29: 2 | AG29: 2 | AI29: UD | AJ29: 2 | AK29: 2
A30: cardlink | B30: 1 | C30: 1 | F30: lpm_as400 | G30: 8 | X30: txt | Y30: 28 | AA30: 8 | AC30: 36 | AE30: Plan B (Source) | AF30: 27 | AG30: 27 | AI30: Plan B (Source) | AJ30: 27 | AK30: 27
A31: Total | B31: 77 | C31: 77 | F31: Grand Total | G31: 180 | X31: LPM-AS/400​ | Y31: 1 | AC31: 1 | AE31: Factoring | AF31: 7 | AG31: 7 | AI31: Factoring | AJ31: 7 | AK31: 7
X32: Factoring | Y32: 7 | AC32: 7 | AE32: FXBOOTH​ | AF32: 1 | AG32: 1 | AI32: FXBOOTH​ | AJ32: 1 | AK32: 1
X33: K PLUS | AA33: 8 | AC33: 8 | AE33: Supply Chain | AF33: 9 | AG33: 9 | AI33: Supply Chain | AJ33: 9 | AK33: 9
X34: RMST | Y34: 1 | AC34: 1 | AE34: UD | AF34: 10 | AG34: 10 | AI34: UD | AJ34: 10 | AK34: 10
X35: Supply Chain | Y35: 9 | AC35: 9 | AE35: Grand Total | AF35: 181 | AG35: 181 | AI35: Grand Total | AJ35: 181 | AK35: 181
X36: UD | Y36: 10 | AC36: 10
X37: txt (fix length) | AB37: 1 | AC37: 1
X38: LPM-AS/400​ | AB38: 1 | AC38: 1
X39: Grand Total | Y39: 83 | Z39: 12 | AA39: 8 | AB39: 1 | AC39: 104
A40: Unit test data file Status
A41: Batch | B41: Batch 1 | I41: Batch | J41: (All)
A43: Count Table | B43: Column Labels | I43: Count Table | J43: Column Labels
A44: Unit test data Readiness | B44: Not Started | C44: Completed | D44: Total | I44: Unit test data Readiness | J44: Not Started | K44: Completed | L44: Total | X44: Batch | Y44: Batch 2
A45: Pull EBAN File | B45: 23 | D45: 23 | I45: Plan A | J45: 5 | K45: 47 | L45: 52
A46: FCD | B46: 1 | D46: 1 | I46: Source File (Push) | J46: 1 | K46: 46 | L46: 47 | M46: manual // config transfer | X46: Count of CBR Status | Y46: Column Labels
A47: HRIS | B47: 1 | D47: 1 | I47: CIS | K47: 17 | L47: 17 | X47: Row Labels | Y47: Lot 1 | Z47: Lot 2 | AA47: Grand Total | AB47: Lot 1 = Have Control File + No delta + CBR which already started (Target Wed 21-Feb)
A48: KS | B48: 3 | D48: 3 | I48: CSM | K48: 17 | L48: 17 | X48: Auto | Y48: 23 | Z48: 29 | AA48: 52 | AB48: Lot 2 = No Control File (Target Fri 23-Feb)
A49: LEC​ | B49: 1 | D49: 1 | I49: RDM | K49: 12 | L49: 12 | X49: 45341 | Y49: 8 | AA49: 8
A50: Murex | B50: 7 | D50: 7 | I50: RMST | J50: 1 | L50: 1 | X50: 45342 | Y50: 7 | AA50: 7
A51: PCB-Deposit | B51: 8 | D51: 8 | I51: DIH Extraction File (Push) | K51: 1 | L51: 1 | M51: manual // config transfer | X51: 45343 | Y51: 8 | AA51: 8
A52: UD | B52: 2 | D52: 2 | I52: LPM-AS/400​ | K52: 1 | L52: 1 | X52: 45344 | Z52: 16 | AA52: 16
A53: Source File (Push) | C53: 46 | D53: 46 | I53: Source File (Pull) | J53: 4 | L53: 4 | M53: config control M | X53: Completed | Z53: 8 | AA53: 8
A54: CIS | C54: 17 | D54: 17 | I54: CCMS​ | J54: 4 | L54: 4 | X54: In-Progress | Z54: 3 | AA54: 3
A55: CSM | C55: 17 | D55: 17 | I55: Plan B (EBAN) | J55: 65 | L55: 65 | M55: config ready | X55: Pending Recheck | Z55: 5 | AA55: 5
A56: RDM | C56: 12 | D56: 12 | I56: Pull EBAN File | J56: 47 | L56: 47 | X56: 45345 | Z56: 13 | AA56: 13
A57: Pull EBAN IN File | B57: 7 | D57: 7 | I57: Factoring | J57: 1 | L57: 1 | X57: Completed | Z57: 3 | AA57: 3
A58: LPM-AS/400​ | B58: 7 | D58: 7 | I58: FCD | J58: 1 | L58: 1 | X58: In-Progress | Z58: 4 | AA58: 4
A59: Pull EBAN/DIH file | B59: 1 | D59: 1 | I59: HRIS | J59: 1 | L59: 1 | X59: Pending Recheck | Z59: 6 | AA59: 6
A60: Cardlink | B60: 1 | D60: 1 | I60: KS | J60: 3 | L60: 3 | X60: Kaew | Y60: 12 | Z60: 23 | AA60: 35
A61: Total | B61: 31 | C61: 46 | D61: 77 | I61: LEC​ | J61: 1 | L61: 1 | X61: 45341 | Y61: 6 | AA61: 6
I62: LPM-WriteOff | J62: 1 | L62: 1 | X62: 45343 | Y62: 6 | AA62: 6
I63: Murex | J63: 9 | L63: 9 | X63: 45344 | Z63: 10 | AA63: 10
I64: New-Trade | J64: 6 | L64: 6 | X64: Completed | Z64: 8 | AA64: 8
I65: PCB-Deposit | J65: 11 | L65: 11 | X65: In-Progress | Z65: 1 | AA65: 1
A66: Batch | B66: Batch 1 | I66: PCB-Lending | J66: 9 | L66: 9 | X66: Not Started | Z66: 1 | AA66: 1
I67: Trade-Navigator | J67: 2 | L67: 2 | X67: 45345 | Z67: 13 | AA67: 13
A68: Count Table | B68: Column Labels | I68: UD | J68: 2 | L68: 2 | X68: Completed | Z68: 5 | AA68: 5
A69: execute init | B69: Completed | C69: Not Started | D69: Re-checked | E69: Total | I69: EBAN Extraction File | J69: 8 | L69: 8 | M69: mount file | X69: In-Progress | Z69: 4 | AA69: 4
A70: Plan A | B70: 28 | D70: 18 | E70: 46 | I70: K PLUS | J70: 8 | L70: 8 | X70: Not Started | Z70: 4 | AA70: 4
A71: CIS | D71: 17 | E71: 17 | I71: Pull EBAN IN File | J71: 10 | L71: 10 | M71: config transfer | X71: Tua | Y71: 17 | AA71: 17
A72: CSM | B72: 17 | E72: 17 | I72: Cardlink | J72: 1 | L72: 1 | X72: 45341 | Y72: 9 | AA72: 9
A73: RDM | B73: 11 | D73: 1 | E73: 12 | I73: LPM-AS/400​ | J73: 8 | L73: 8 | X73: 45342 | Y73: 8 | AA73: 8
A74: Plan B (EBAN) | C74: 30 | E74: 30 | I74: HRCRC | J74: 1 | L74: 1 | X74: Grand Total | Y74: 52 | Z74: 52 | AA74: 104
A75: FCD | C75: 1 | E75: 1 | I75: Plan B (Source) | J75: 27 | L75: 27
A76: HRIS | C76: 1 | E76: 1 | I76: Pull Database | J76: 26 | L76: 26 | M76: TBC - check result EOD 27-Feb
A77: KS | C77: 3 | E77: 3 | I77: Factoring | J77: 7 | L77: 7 | M77: tmr manual
A78: LEC​ | C78: 1 | E78: 1 | I78: Supply Chain | J78: 9 | L78: 9
A79: LPM-AS/400​ | C79: 7 | E79: 7 | I79: UD | J79: 10 | L79: 10
A80: Murex | C80: 7 | E80: 7 | I80: DIH Extraction File (Pull) | J80: 1 | L80: 1 | M80: config transfer
A81: PCB-Deposit | C81: 8 | E81: 8 | I81: FXBOOTH​ | J81: 1 | L81: 1
A82: UD | C82: 2 | E82: 2 | I82: Plan B (EBAN/DIH) | J82: 37 | L82: 37
A83: Plan B (EBAN/DIH) | C83: 1 | E83: 1 | I83: Pull EBAN/DIH file | J83: 37 | L83: 37 | M83: config transfer
A84: Cardlink | C84: 1 | E84: 1 | I84: Cardlink | J84: 34 | L84: 34
A85: Total | B85: 28 | C85: 31 | D85: 18 | E85: 77 | I85: Cardlink(TPN​) | J85: 3 | L85: 3
I86: Total | J86: 134 | K86: 47 | L86: 181
A89: Batch | B89: Batch 1
A91: Count Table | B91: Column Labels
A92: execute job | B92: In-Progress | C92: Not Started | D92: Passed | E92: Total
A93: Plan A | B93: 2 | C93: 19 | D93: 25 | E93: 46
A94: CIS | C94: 17 | E94: 17
A95: CSM | B95: 2 | C95: 2 | D95: 13 | E95: 17
A96: RDM | D96: 12 | E96: 12
A97: Plan B (EBAN) | C97: 30 | E97: 30
A98: FCD | C98: 1 | E98: 1
A99: HRIS | C99: 1 | E99: 1
A100: KS | C100: 3 | E100: 3
A101: LEC​ | C101: 1 | E101: 1
A102: LPM-AS/400​ | C102: 7 | E102: 7
A103: Murex | C103: 7 | E103: 7
A104: PCB-Deposit | C104: 8 | E104: 8
...

Sheet Sheet5
A1: No | B1: src_sys | C1: Plan | D1: Target Schema Name | E1: Target Table Name (Raw+Persist) | F1: Persist View name
A2: 1 | B2: ccms | C2: Plan A | D2: persist_ccms | E2: ccms_bp772n1_cardholder_purge | F2: v_ccms_dc_prg_log
A3: 2 | B3: ccms | C3: Plan A | D3: persist_ccms | E3: ccms_bda772n5_listcardtype | F3: v_ccms_dc_tp_cl
A4: 3 | B4: cis | C4: Plan A | D4: persist_cis | E4: cis_relar | F4: v_cis_acct_rel_tp_cl
A5: 4 | B5: cis | C5: Plan A | D5: persist_cis | E5: cis_doctp | F5: v_cis_doc_tp_cl
A6: 5 | B6: cis | C6: Plan A | D6: persist_cis | E6: cis_cntreltp | F6: v_cis_ctc_rel_tp_cl
A7: 6 | B7: cis | C7: Plan A | D7: persist_cis | E7: cis_ipxcontact | F7: v_cis_cst_ctc_rel_prfl
A8: 7 | B8: cis | C8: Plan A | D8: persist_cis | E8: cis_conttp | F8: v_cis_ctc_tp_cl
A9: 8 | B9: cis | C9: Plan A | D9: persist_cis | E9: cis_org | F9: v_cis_org_dtl
A10: 9 | B10: cis | C10: Plan A | D10: persist_cis | E10: cis_ipsegment | F10: v_cis_cst_seg_rel_prfl
A11: 10 | B11: cis | C11: Plan A | D11: persist_cis | E11: cis_histsegm | F11: v_cis_cst_seg_rel_hist
A12: 11 | B12: cis | C12: Plan A | D12: persist_cis | E12: cis_ipxaddr | F12: v_cis_cst_addr_rel_prfl
A13: 12 | B13: cis | C13: Plan A | D13: persist_cis | E13: cis_dntcnt | F13: v_cis_cst_do_not_ctc_rel_prfl
... A42: 41 | B42: rdm | C42: Plan A | D42: persist_rdm | E42: rdm_idy_cl_sub_grp_cd | F42: v_rdm_indst_cl_sub_grp_cl

Sheet Dev Inventory
A1: ="Ingestion Foundation "&A2& " Tables" -> Ingestion Foundation 180 Tables | Z1: Dev Built & Test Plan | AG1: UAT Built & Test Plan
A2: =COUNTA(A4:A616) -> 180 | R2: ingest_<table name>_<frequency> | X2: QA
A3: No | B3: Batch | C3: System | D3: (Plan) | E3: src_sys | F3: Plan | G3: Extraction Cases | H3: src_sys_id | I3: Source Table Name (For Foundation naming) | J3: Target Schema Name | K3: Target Table Name (Raw+Persist) | L3: Persist View name | M3: data file name | N3: control file name | O3: for lookup | P3: frequency | Q3: freq | R3: job_name | S3: remark | T3: File name/Table name | U3: src_pos_dt | V3: change column name ./- to _ | W3: Data File with Header | X3: Remark CBR dev | Y3: Remark Label | Z3: DDL scripts | AA3: Mapping Spec | AB3: Config | AC3: execute job | AD3: Error job | AE3: DEV: Unit test | AF3: Error test | AG3: data date | AH3: UAT execute job | AI3: job error | AJ3: UAT Test | AK3: Error test | AL3: execute init table | AM3: UAM - UAT | AN3: Rec_Type | AO3: Filler | AP3: recheck script | AQ3: Data File with Header
A4: 1 | B4: Batch 1 | C4: PCB-Deposit | D4: Plan B (EBAN) | E4: =VLOOKUP(C4,'Source Inventory'!D:E,2,FALSE) -> pcb_dep | F4: Plan B | G4: Pull EBAN File | H4: 668 | I4: src_pf_ar_sa_dly | J4: ="persist_"&E4 -> persist_pcb_dep | K4: =E4&"_"&I4 -> pcb_dep_src_pf_ar_sa_dly | L4: v_pcb_dep_sa_prfl | M4: src_pf_ar_sa_dly_yyyymmdd.txt | O4: =K4 -> pcb_dep_src_pf_ar_sa_dly | P4: Daily | Q4: =IF(P4="Daily","d",IF(P4="Monthly","m",IF(P4="Yearly","y",IF(P4="Weekly","w",IF(P4="S","s",IF(P4="On-Request","o","")))))) -> d | R4: ="ingest_"&K4&"_"&Q4 -> ingest_pcb_dep_src_pf_ar_sa_dly_d | T4: src_pf_ar_sa_dly_yyyymmdd.txt | U4: Y | V4: N | X4: - Have rec type (To be revised) | Y4: Header/Tailor | Z4: Re-checked | AA4: Re-checked | AB4: Not Started | AC4: Not Started | AE4: Not Started | AH4: Passed | AJ4: Not Started | AL4: Completed | AM4: Completed | AN4: Y | AO4: N | AP4: =IF(OR(AN4="Y", AO4="Y"), "Y", "N") -> Y
A5: 2 | B5: Batch 1 | C5: PCB-Deposit | D5: Plan B (EBAN) | E5: =VLOOKUP(C5,'Source Inventory'!D:E,2,FALSE) -> pcb_dep | F5: Plan B | G5: Pull EBAN File | H5: 668 | I5: src_pf_ar_ca_dly | J5: ="persist_"&E5 -> persist_pcb_dep | K5: =E5&"_"&I5 -> pcb_dep_src_pf_ar_ca_dly | L5: v_pcb_dep_ca_prfl | M5: src_pf_ar_ca_dly_yyyymmdd.txt | O5: =K5 -> pcb_dep_src_pf_ar_ca_dly | P5: Daily | Q5: =IF(P5="Daily","d",IF(P5="Monthly","m",IF(P5="Yearly","y",IF(P5="Weekly","w",IF(P5="S","s",IF(P5="On-Request","o","")))))) -> d | R5: ="ingest_"&K5&"_"&Q5 -> ingest_pcb_dep_src_pf_ar_ca_dly_d | T5: src_pf_ar_ca_dly_yyyymmdd.txt | U5: Y | V5: N | X5: - Have rec type (To be revised) | Y5: Header/Tailor | Z5: Re-checked | AA5: Re-checked | AB5: Not Started | AC5: Not Started | AE5: Not Started | AH5: Passed | AJ5: Not Started | AL5: Completed | AM5: Completed | AN5: Y | AO5: N | AP5: =IF(OR(AN5="Y", AO5="Y"), "Y", "N") -> Y
A6: 3 | B6: Batch 1 | C6: PCB-Deposit | D6: Plan B (EBAN) | E6: =VLOOKUP(C6,'Source Inventory'!D:E,2,FALSE) -> pcb_dep | F6: Plan B | G6: Pull EBAN File | H6: 668 | I6: src_pf_ar_fx_dly | J6: ="persist_"&E6 -> persist_pcb_dep | K6: =E6&"_"&I6 -> pcb_dep_src_pf_ar_fx_dly | L6: v_pcb_dep_fd_acct_prfl | M6: src_pf_ar_fx_dly_yyyymmdd.txt | O6: =K6 -> pcb_dep_src_pf_ar_fx_dly | P6: Daily | Q6: =IF(P6="Daily","d",IF(P6="Monthly","m",IF(P6="Yearly","y",IF(P6="Weekly","w",IF(P6="S","s",IF(P6="On-Request","o","")))))) -> d | R6: ="ingest_"&K6&"_"&Q6 -> ingest_pcb_dep_src_pf_ar_fx_dly_d | T6: src_pf_ar_fx_dly_yyyymmdd.txt | U6: Y | V6: N | X6: - Have rec type (To be revised) | Y6: Header/Tailor | Z6: Re-checked | AA6: Re-checked | AB6: Not Started | AC6: Not Started | AE6: Not Started | AH6: Passed | AJ6: Not Started | AL6: Completed | AM6: Completed | AN6: Y | AO6: N | AP6: =IF(OR(AN6="Y", AO6="Y"), "Y", "N") -> Y
A7: 4 | B7: Batch 1 | C7: PCB-Deposit | D7: Plan B (EBAN) | E7: =VLOOKUP(C7,'Source Inventory'!D:E,2,FALSE) -> pcb_dep | F7: Plan B | G7: Pull EBAN File | H7: 668 | I7: src_pf_ar_sf_dly | J7: ="persist_"&E7 -> persist_pcb_dep | K7: =E7&"_"&I7 -> pcb_dep_src_pf_ar_sf_dly | L7: v_pcb_dep_sf_acct_prfl | M7: src_pf_ar_sf_dly_yyyymmdd.txt | O7: =K7 -> pcb_dep_src_pf_ar_sf_dly | P7: Daily | Q7: =IF(P7="Daily","d",IF(P7="Monthly","m",IF(P7="Yearly","y",IF(P7="Weekly","w",IF(P7="S","s",IF(P7="On-Request","o","")))))) -> d | R7: ="ingest_"&K7&"_"&Q7 -> ingest_pcb_dep_src_pf_ar_sf_dly_d | T7: src_pf_ar_sf_dly_yyyymmdd.txt | U7: Y | V7: N | X7: - Have rec type (To be revised) | Y7: Header/Tailor | Z7: Re-checked | AA7: Re-checked | AB7: Not Started | AC7: Not Started | AE7: Not Started | AH7: Passed | AJ7: Not Started | AL7: Completed | AM7: Completed | AN7: Y | AO7: N | AP7: =IF(OR(AN7="Y", AO7="Y"), "Y", "N") -> Y
A8: 5 | B8: Batch 1 | C8: PCB-Deposit | D8: Plan B (EBAN) | E8: =VLOOKUP(C8,'Source Inventory'!D:E,2,FALSE) -> pcb_dep | F8: Plan B | G8: Pull EBAN File | H8: 668 | I8: extrate1 | J8: ="persist_"&E8 -> persist_pcb_dep | K8: =E8&"_"&I8 -> pcb_dep_extrate1 | L8: v_pcb_dep_fd_int_rate_cl | M8: PCB_DIH_ExtRATE1_YYYYMMDD.txt | O8: =K8 -> pcb_dep_extrate1 | P8: Daily | Q8: =IF(P8="Daily","d",IF(P8="Monthly","m",IF(P8="Yearly","y",IF(P8="Weekly","w",IF(P8="S","s",IF(P8="On-Request","o","")))))) -> d | R8: ="ingest_"&K8&"_"&Q8 -> ingest_pcb_dep_extrate1_d | T8: PCB_DIH_ExtRATE1_YYYYMMDD.txt | U8: N | V8: N | X8: - Have rec type (To be revised) | Y8: Header/Tailor | Z8: Re-checked | AA8: Re-checked | AB8: Not Started | AC8: Not Started | AE8: Not Started | AH8: Not Started | AJ8: Not Started | AL8: Completed | AM8: Completed | AN8: Y | AO8: N | AP8: =IF(OR(AN8="Y", AO8="Y"), "Y", "N") -> Y
A9: 6 | B9: Batch 2 | C9: PCB-Lending | D9: Plan B (EBAN) | E9: =VLOOKUP(C9,'Source Inventory'!D:E,2,FALSE) -> pcb_loan | F9: Plan B | G9: Pull EBAN File | H9: 668.08 | I9: common_account_info | J9: ="persist_"&E9 -> persist_pcb_loan | K9: =E9&"_"&I9 -> pcb_loan_common_account_info | L9: v_pcb_loan_ln_acct_prfl | M9: Common_Account_Info_YYYYMMDD.txt | O9: =K9 -> pcb_loan_common_account_info | P9: Daily | Q9: =IF(P9="Daily","d",IF(P9="Monthly","m",IF(P9="Yearly","y",IF(P9="Weekly","w",IF(P9="S","s",IF(P9="On-Request","o","")))))) -> d | R9: ="ingest_"&K9&"_"&Q9 -> ingest_pcb_loan_common_account_info_d | T9: Common_Account_Info_YYYYMMDD.txt | U9: Header | V9: N | X9: - Have rec type (To be revised) | Y9: Header/Tailor | Z9: Re-checked | AA9: Re-checked | AB9: Not Started | AC9: Not Started | AE9: Not Started | AH9: Not Started | AJ9: Not Started | AL9: Completed | AM9: Completed | AN9: Y | AO9: N | AP9: =IF(OR(AN9="Y", AO9="Y"), "Y", "N") -> Y
A10: 7 | B10: Batch 2 | C10: PCB-Lending | D10: Plan B (EBAN) | E10: =VLOOKUP(C10,'Source Inventory'!D:E,2,FALSE) -> pcb_loan | F10: Plan B | G10: Pull EBAN File | H10: 668.08 | I10: common_limit_info | J10: ="persist_"&E10 -> persist_pcb_loan | K10: =E10&"_"&I10 -> pcb_loan_common_limit_info | L10: v_pcb_loan_ln_lmt_prfl | M10: Common_Limit_Info_YYYYMMDD.txt | O10: =K10 -> pcb_loan_common_limit_info | P10: Daily | Q10: =IF(P10="Daily","d",IF(P10="Monthly","m",IF(P10="Yearly","y",IF(P10="Weekly","w",IF(P10="S","s",IF(P10="On-Request","o","")))))) -> d | R10: ="ingest_"&K10&"_"&Q10 -> ingest_pcb_loan_common_limit_info_d | T10: Common_Limit_Info_YYYYMMDD.txt | U10: N | X10: - Have rec type (To be revised) - [Feb 21] Remark: File Delimiter listed as | (pipe) as per Table Spec | Y10: Header/Tailor | Z10: Re-checked | AA10: Re-checked | AB10: Not Started | AC10: Not Started | AE10: Not Started | AH10: Not Started | AJ10: Not Started | AL10: Completed | AM10: Completed | AN10: Y | AO10: Y | AP10: =IF(OR(AN10="Y", AO10="Y"), "Y", "N") -> Y
A11: 8 | B11: Batch 2 | C11: PCB-Lending | D11: Plan B (EBAN) | E11: =VLOOKUP(C11,'Source Inventory'!D:E,2,FALSE) -> pcb_loan | F11: Plan B | G11: Pull EBAN File | H11: 668.08 | I11: common_market_code | J11: ="persist_"&E11 -> persist_pcb_loan | K11: =E11&"_"&I11 -> pcb_loan_common_market_code | L11: v_pcb_loan_mkt_cd_cl | M11: Common_Market_Code_YYYYMMDD.txt | O11: =K11 -> pcb_loan_common_market_code | P11: Daily | Q11: =IF(P11="Daily","d",IF(P11="Monthly","m",IF(P11="Yearly","y",IF(P11="Weekly","w",IF(P11="S","s",IF(P11="On-Request","o","")))))) -> d | R11: ="ingest_"&K11&"_"&Q11 -> ingest_pcb_loan_common_market_code_d | T11: Common_Market_Code_YYYYMMDD.txt | U11: N | X11: - Have rec type (To be revised) - [Feb 21] Remark: File Delimiter listed as | (pipe) as per Table Spec | Y11: Header/Tailor | Z11: Re-checked | AA11: Re-checked | AB11: Not Started | AC11: Not Started | AE11: Not Started | AH11: Not Started | AJ11: Not Started | AL11: Completed | AM11: Completed | AN11: Y | AO11: N | AP11: =IF(OR(AN11="Y", AO11="Y"), "Y", "N") -> Y
A12: 9 | B12: Batch 2 | C12: PCB-Lending | D12: Plan B (EBAN) | E12: =VLOOKUP(C12,'Source Inventory'!D:E,2,FALSE) -> pcb_loan | F12: Plan B | G12: Pull EBAN File | H12: 668.08 | I12: common_rate_type | J12: ="persist_"&E12 -> persist_pcb_loan | K12: =E12&"_"&I12 -> pcb_loan_common_rate_type | L12: v_pcb_loan_rate_tp_cl | M12: Common_Rate_Type.txt | O12: =K12 -> pcb_loan_common_rate_type | P12: Daily | Q12: =IF(P12="Daily","d",IF(P12="Monthly","m",IF(P12="Yearly","y",IF(P12="Weekly","w",IF(P12="S","s",IF(P12="On-Request","o","")))))) -> d | R12: ="ingest_"&K12&"_"&Q12 -> ingest_pcb_loan_common_rate_type_d | T12: Common_Rate_Type.txt | U12: N | X12: - Have rec type (To be revised) - [Feb 21] Remark: File Delimiter listed as | (pipe) as per Table Spec | Y12: Header/Tailor | Z12: Re-checked | AA12: Re-checked | AB12: Not Started | AC12: Not Started | AE12: Not Started | AH12: Not Started | AJ12: Not Started | AL12: Completed | AM12: Completed | AN12: Y | AO12: N | AP12: =IF(OR(AN12="Y", AO12="Y"), "Y", "N") -> Y
A13: 10 | B13: Batch 2 | C13: PCB-Lending | D13: Plan B (EBAN) | E13: =VLOOKUP(C13,'Source Inventory'!D:E,2,FALSE) -> pcb_loan | F13: Plan B | G13: Pull EBAN File | H13: 668.08 | I13: common_account_tier_by_time | J13: ="persist_"&E13 -> persist_pcb_loan | K13: =E13&"_"&I13 -> pcb_loan_common_account_tier_by_time | L13: v_pcb_loan_ln_acct_tier_by_tm_prfl | M13: Common_Account_Tier_By_Time.txt | O13: =K13 -> pcb_loan_common_account_tier_by_time | P13: Daily | Q13: =IF(P13="Daily","d",IF(P13="Monthly","m",IF(P13="Yearly","y",IF(P13="Weekly","w",IF(P13="S","s",IF(P13="On-Request","o","")))))) -> d | R13: ="ingest_"&K13&"_"&Q13 -> ingest_pcb_loan_common_account_tier_by_time_d | T13: Common_Account_Tier_By_Time.txt | U13: N | X13: - Have rec type (To be revised) '[Feb 21] Remark: File Delimiter listed as | (pipe) as per Table Spec | Y13: Header/Tailor | Z13: Re-checked | AA13: Re-checked | AB13: Not Started | AC13: Not Started | AE13: Not Started | AH13: Not Started | AJ13: Not Started | AL13: Completed | AM13: Completed | AN13: Y | AO13: N | AP13: =IF(OR(AN13="Y", AO13="Y"), "Y", "N") -> Y
A14: 11 | B14: Batch 2 | C14: PCB-Deposit | D14: Plan B (EBAN) | E14: =VLOOKUP(C14,'Source Inventory'!D:E,2,FALSE) -> pcb_dep | F14: Plan B | G14: Pull EBAN File | H14: 668 | I14: cb2d0005_odencitd_sam | J14: ="persist_"&E14 -> persist_pcb_dep | K14: =E14&"_"&I14 -> pcb_dep_cb2d0005_odencitd_sam | L14: v_pcb_dep_od_enc_itd_lmt_prfl | M14: CISP.CB2D0005.ODENCITD.SAM_YYYYMMDD | O14: =K14 -> pcb_dep_cb2d0005_odencitd_sam | P14: Daily | Q14: =IF(P14="Daily","d",IF(P14="Monthly","m",IF(P14="Yearly","y",IF(P14="Weekly","w",IF(P14="S","s",IF(P14="On-Request","o","")))))) -> d | R14: ="ingest_"&K14&"_"&Q14 -> ingest_pcb_dep_cb2d0005_odencitd_sam_d | T14: CISP.CB2D0005.ODENCITD.SAM_YYYYMMDD | U14: N | V14: N | X14: - CBR missing field => อิงตามKBMF แทน | Z14: In-Progress | AA14: Not Started | AB14: Not Started | AC14: Not Started | AE14: Not Started | AH14: Failed | AI14: empty file | AJ14: Not Started | AL14: Not Started | AM14: Not Started | AN14: N | AO14: Y | AP14: =IF(OR(AN14="Y", AO14="Y"), "Y", "N") -> Y
A15: 12 | B15: Batch 1 | C15: PCB-Deposit | D15: Plan B (EBAN) | E15: =VLOOKUP(C15,'Source Inventory'!D:E,2,FALSE) -> pcb_dep | F15: Plan B | G15: Pull EBAN File | H15: 668 | I15: src_pf_txn_mis_eft_dly | J15: ="persist_"&E15 -> persist_pcb_dep | K15: =E15&"_"&I15 -> pcb_dep_src_pf_txn_mis_eft_dly | L15: v_pcb_dep_eft_txn | M15: src_pf_txn_mis_eft_dly_yyyymmdd.txt | O15: =K15 -> pcb_dep_src_pf_txn_mis_eft_dly | P15: Daily | Q15: =IF(P15="Daily","d",IF(P15="Monthly","m",IF(P15="Yearly","y",IF(P15="Weekly","w",IF(P15="S","s",IF(P15="On-Request","o","")))))) -> d | R15: ="ingest_"&K15&"_"&Q15 -> ingest_pcb_dep_src_pf_txn_mis_eft_dly_d | T15: src_pf_txn_mis_eft_dly_yyyymmdd.txt | U15: N | V15: N | X15: Remark: '- Have rec type (To be revised) - ใน Table Spec ระบุ Tailor แต่ใน KBMF EBAN ไม่มี => Flag Tailor = Y ไว้ - TIS-620 encoding in KBMF | Y15: Header/Tailor | Z15: Re-checked | AA15: Re-checked | AB15: Not Started | AC15: Not Started | AE15: Not Started | AH15: Passed | AJ15: Not Started | AL15: Completed | AM15: Completed | AN15: Y | AO15: N | AP15: =IF(OR(AN15="Y", AO15="Y"), "Y", "N") -> Y
A16: 13 | B16: Batch 1 | C16: PCB-Deposit | D16: Plan B (EBAN) | E16: =VLOOKUP(C16,'Source Inventory'!D:E,2,FALSE) -> pcb_dep | F16: Plan B | G16: Pull EBAN File | H16: 668 | I16: cls500029 | J16: ="persist_"&E16 -> persist_pcb_dep | K16: =E16&"_"&I16 -> pcb_dep_cls500029 | L16: v_pcb_dep_int_rate_tp_cl | M16: cls500029_yyyymmdd.txt | O16: =K16 -> pcb_dep_cls500029 | P16: Daily | Q16: =IF(P16="Daily","d",IF(P16="Monthly","m",IF(P16="Yearly","y",IF(P16="Weekly","w",IF(P16="S","s",IF(P16="On-Request","o","")))))) -> d | R16: ="ingest_"&K16&"_"&Q16 -> ingest_pcb_dep_cls500029_d | T16: cls500029_yyyymmdd.txt | U16: N | V16: N | X16: Remark: '- Have rec type (To be revised) - ใน Table Spec ระบุ Tailor แต่ใน KBMF EBAN ไม่มี => Flag Tailor = Y ไว้ | Y16: Header/Tailor | Z16: Re-checked | AA16: Re-checked | AB16: Not Started | AC16: Not Started | AE16: Not Started | AH16: Not Started | AJ16: Not Started | AL16: Completed | AM16: Completed | AN16: N | AO16: N | AP16: =IF(OR(AN16="Y", AO16="Y"), "Y", "N") -> N
A17: 14 | B17: Batch 1 | C17: PCB-Deposit | D17: Plan B (EBAN) | E17: =VLOOKUP(C17,'Source Inventory'!D:E,2,FALSE) -> pcb_dep | F17: Plan B | G17: Pull EBAN File | H17: 668 | I17: src_pf_ar_ca_cr_inf_dly | J17: ="persist_"&E17 -> persist_pcb_dep | K17: =E17&"_"&I17 -> pcb_dep_src_pf_ar_ca_cr_inf_dly | L17: v_pcb_dep_ca_cr_dtl | M17: SRC_PF_AR_CA_CR_INF_DLY_yyyymmdd.txt | O17: =K17 -> pcb_dep_src_pf_ar_ca_cr_inf_dly | P17: Daily | Q17: =IF(P17="Daily","d",IF(P17="Monthly","m",IF(P17="Yearly","y",IF(P17="Weekly","w",IF(P17="S","s",IF(P17="On-Request","o","")))))) -> d | R17: ="ingest_"&K17&"_"&Q17 -> ingest_pcb_dep_src_pf_ar_ca_cr_inf_dly_d | T17: SRC_PF_AR_CA_CR_INF_DLY_yyyymmdd.txt | U17: N | V17: N | X17: Remark: '- Have rec type (To be revised) - ใน Table Spec ระบุ Tailor แต่ใน KBMF EBAN ไม่มี => Flag Tailor = Y ไว้ | Y17: Header/Tailor | Z17: Re-checked | AA17: Re-checked | AB17: Not Started | AC17: Not Started | AE17: Not Started | AH17: Failed | AI17: tuple index out of range | AJ17: Not Started | AL17: Completed | AM17: Completed | AN17: Y | AO17: N | AP17: =IF(OR(AN17="Y", AO17="Y"), "Y", "N") -> Y
A18: 15 | B18: Batch 1 | C18: FCD | D18: Plan B (EBAN) | E18: =VLOOKUP(C18,'Source Inventory'!D:E,2,FALSE) -> fcd | F18: Plan B | G18: Pull EBAN File | H18: 640 | I18: ar | J18: ="persist_"&E18 -> persist_fcd | K18: =E18&"_"&I18 -> fcd_ar | L18: v_fcd_fcd_acct_prfl | M18: FCD_AR_YYYYMMDD.txt | O18: =K18 -> fcd_ar | P18: Daily | Q18: =IF(P18="Daily","d",IF(P18="Monthly","m",IF(P18="Yearly","y",IF(P18="Weekly","w",IF(P18="S","s",IF(P18="On-Request","o","")))))) -> d | R18: ="ingest_"&K18&"_"&Q18 -> ingest_fcd_ar_d | T18: FCD_AR_YYYYMMDD.txt | U18: Y | V18: N | X18: Remark: '- Have rec type (To be revised) - TIS-620 encoding in KBMF | Y18: Header/Tailor | Z18: Re-checked | AA18: Re-checked | AB18: Not Started | AC18: Not Started | AE18: Not Started | AH18: Failed | AI18: raw : rec_type | AJ18: Not Started | AL18: Completed | AM18: Completed | AN18: Y | AO18: N | AP18: =IF(OR(AN18="Y", AO18="Y"), "Y", "N") -> Y
A19: 16 | B19: Batch 2 | C19: PCB-Lending | D19: Plan B (EBAN) | E19: =VLOOKUP(C19,'Source Inventory'!D:E,2,FALSE) -> pcb_loan | F19: Plan B | G19: Pull EBAN File | H19: 668.08 | I19: common_product_type | J19: ="persist_"&E19 -> persist_pcb_loan | K19: =E19&"_"&I19 -> pcb_loan_common_product_type | L19: v_pcb_loan_pd_tp_cl | M19: Common_Product_Type.txt | O19: =K19 -> pcb_loan_common_product_type | P19: Daily | Q19: =IF(P19="Daily","d",IF(P19="Monthly","m",IF(P19="Yearly","y",IF(P19="Weekly","w",IF(P19="S","s",IF(P19="On-Request","o","")))))) -> d | R19: ="ingest_"&K19&"_"&Q19 -> ingest_pcb_loan_common_product_type_d | T19: Common_Product_Type.txt | X19: - Have rec type (To be revised) | Y19: Header/Tailor | Z19: Re-checked | AA19: Re-checked | AB19: Not Started | AC19: Not Started | AE19: Not Started | AH19: Not Started | AJ19: Not Started | AL19: Completed | AM19: Completed | AN19: Y | AO19: N | AP19: =IF(OR(AN19="Y", AO19="Y"), "Y", "N") -> Y
A20: 17 | B20: Batch 2 | C20: PCB-Lending | D20: Plan B (EBAN) | E20: =VLOOKUP(C20,'Source Inventory'!D:E,2,FALSE) -> pcb_loan | F20: Plan B | G20: Pull EBAN File | H20: 668.08 | I20: common_sub_type | J20: ="persist_"&E20 -> persist_pcb_loan | K20: =E20&"_"&I20 -> pcb_loan_common_sub_type | L20: v_pcb_loan_pd_subtp_cl | M20: Common_Sub_Type.txt | O20: =K20 -> pcb_loan_common_sub_type | P20: Daily | Q20: =IF(P20="Daily","d",IF(P20="Monthly","m",IF(P20="Yearly","y",IF(P20="Weekly","w",IF(P20="S","s",IF(P20="On-Request","o","")))))) -> d | R20: ="ingest_"&K20&"_"&Q20 -> ingest_pcb_loan_common_sub_type_d | T20: Common_Sub_Type.txt | X20: - Have rec type (To be revised) | Y20: Header/Tailor | Z20: Re-checked | AA20: Re-checked | AB20: Not Started | AC20: Not Started | AE20: Not Started | AH20: Not Started | AJ20: Not Started | AL20: Completed | AM20: Completed | AN20: Y | AO20: N | AP20: =IF(OR(AN20="Y", AO20="Y"), "Y", "N") -> Y
A21: 18 | B21: Batch 2 | C21: PCB-Lending | D21: Plan B (EBAN) | E21: =VLOOKUP(C21,'Source Inventory'!D:E,2,FALSE) -> pcb_loan | F21: Plan B | G21: Pull EBAN File | H21: 668.08 | I21: common_loan_purpose_table | J21: ="persist_"&E21 -> persist_pcb_loan | K21: =E21&"_"&I21 -> pcb_loan_common_loan_purpose_table | L21: v_pcb_loan_ln_pps_cl | M21: Common_Loan_Purpose_Table_yyyymmdd.txt | O21: =K21 -> pcb_loan_common_loan_purpose_table | P21: Daily | Q21: =IF(P21="Daily","d",IF(P21="Monthly","m",IF(P21="Yearly","y",IF(P21="Weekly","w",IF(P21="S","s",IF(P21="On-Request","o","")))))) -> d | R21: ="ingest_"&K21&"_"&Q21 -> ingest_pcb_loan_common_loan_purpose_table_d | T21: Common_Loan_Purpose_Table_yyyymmdd.txt | X21: - Have rec type (To be revised) | Y21: Header/Tailor | Z21: Re-checked | AA21: Re-checked | AB21: Not Started | AC21: Not Started | AE21: Not Started | AH21: Not Started | AJ21: Not Started | AL21: Completed | AM21: Completed | AN21: Y | AO21: N | AP21: =IF(OR(AN21="Y", AO21="Y"), "Y", "N") -> Y
A22: 19 | B22: Batch 1 | C22: LPM-AS/400​ | D22: Plan B (EBAN) | E22: =VLOOKUP(C22,'Source Inventory'!D:E,2,FALSE) -> lpm_as400 | F22: Plan B - EBAN IN | G22: Pull EBAN IN File | H22: 75 | I22: lmt_ar_inf_bfr_wrtof | J22: ="persist_"&E22 -> persist_lpm_as400 | K22: =E22&"_"&I22 -> lpm_as400_lmt_ar_inf_bfr_wrtof | L22: v_lpm_as400_lmt_info_bfr_wrtoff_prfl | M22: in_lpm_lmt_ar_inf_bfr_wrtof_yyyy-mm-dd.txt | N22: in_lpm_lmt_ar_inf_bfr_wrtof_yyyymmdd.ctl | O22: =K22 -> lpm_as400_lmt_ar_inf_bfr_wrtof | P22: Daily | Q22: =IF(P22="Daily","d",IF(P22="Monthly","m",IF(P22="Yearly","y",IF(P22="Weekly","w",IF(P22="S","s",IF(P22="On-Request","o","")))))) -> d | R22: ="ingest_"&K22&"_"&Q22 -> ingest_lpm_as400_lmt_ar_inf_bfr_wrtof_d | T22: DATALAKE.IN_LPM_LMT_AR_INF_BFR_WRTOF | U22: N | V22: N | Y22: N/A | Z22: Not Started | AA22: Not Started | AB22: Not Started | AC22: Not Started | AE22: Not Started | AH22: Not Started | AJ22: Not Started | AL22: Not Started | AM22: Not Started | AN22: N | AO22: N | AP22: =IF(OR(AN22="Y", AO22="Y"), "Y", "N") -> N
A23: 20 | B23: Batch 2 | C23: LPM-AS/400​ | D23: Plan B (EBAN) | E23: =VLOOKUP(C23,'Source Inventory'!D:E,2,FALSE) -> lpm_as400 | F23: Plan B - EBAN IN | G23: Pull EBAN IN File | H23: 75 | I23: ar_wrtof_rcv | J23: ="persist_"&E23 -> persist_lpm_as400 | K23: =E23&"_"&I23 -> lpm_as400_ar_wrtof_rcv | L23: v_lpm_as400_wrtoff_acct_dtl | M23: in_lpm_ar_wrtof_dtl_yyyy-mm-dd.txt | N23: in_lpm_ar_wrtof_dtl_yyyymmdd.ctl | O23: =K23 -> lpm_as400_ar_wrtof_rcv | P23: Monthly | Q23: =IF(P23="Daily","d",IF(P23="Monthly","m",IF(P23="Yearly","y",IF(P23="Weekly","w",IF(P23="S","s",IF(P23="On-Request","o","")))))) -> m | R23: ="ingest_"&K23&"_"&Q23 -> ingest_lpm_as400_ar_wrtof_rcv_m | T23: DATALAKE.IN_LPM_AR_WRTOF_RCV | U23: N | V23: N | Y23: Tailor | Z23: Not Started | AA23: Not Started | AB23: Not Started | AC23: Not Started | AE23: Not Started | AH23: Not Started | AJ23: Not Started | AL23: Not Started | AM23: Not Started | AN23: N | AO23: N | AP23: =IF(OR(AN23="Y", AO23="Y"), "Y", "N") -> N
A24: 21 | B24: Batch 1 | C24: LPM-AS/400​ | D24: Plan B (EBAN) | E24: =VLOOKUP(C24,'Source Inventory'!D:E,2,FALSE) -> lpm_as400 | F24: Plan B - EBAN IN | G24: Pull EBAN IN File | H24: 75 | I24: ln_cntg_dmmy_clss_prvn | J24: ="persist_"&E24 -> persist_lpm_as400 | K24: =E24&"_"&I24 -> lpm_as400_ln_cntg_dmmy_clss_prvn | L24: v_lpm_as400_ln_cntg_dmmy_acct_cl_prvsn_prfl | M24: in_lpm_ln_cntg_dmmy_clss_prvn_yyyy-mm-dd.txt | N24: in_lpm_ln_cntg_dmmy_clss_prvn_yyyymmdd.ctl | O24: =K24 -> lpm_as400_ln_cntg_dmmy_clss_prvn | P24: Daily | Q24: =IF(P24="Daily","d",IF(P24="Monthly","m",IF(P24="Yearly","y",IF(P24="Weekly","w",IF(P24="S","s",IF(P24="On-Request","o","")))))) -> d | R24: ="ingest_"&K24&"_"&Q24 -> ingest_lpm_as400_ln_cntg_dmmy_clss_prvn_d | T24: DATALAKE.IN_LPM_LN_CNTG_DMMY_CLSS_PRVN | U24: N | V24: N | Y24: N/A | Z24: Not Started | AA24: Not Started | AB24: Not Started | AC24: Not Started | AE24: Not Started | AH24: Not Started | AJ24: Not Started | AL24: Not Started | AM24: Not Started | AN24: N | AO24: Y | AP24: =IF(OR(AN24="Y", AO24="Y"), "Y", "N") -> Y
A25: 22 | B25: Batch 1 | C25: LPM-AS/400​ | D25: Plan B (EBAN) | E25: =VLOOKUP(C25,'Source Inventory'!D:E,2,FALSE) -> lpm_as400 | F25: Plan B - EBAN IN | G25: Pull EBAN IN File | H25: 75 | I25: ln_card_clss_prvn | J25: ="persist_"&E25 -> persist_lpm_as400 | K25: =E25&"_"&I25 -> lpm_as400_ln_card_clss_prvn | L25: v_lpm_as400_ln_card_acct_cl_prvsn_prfl | M25: in_lpm_ln_card_clss_prvn_yyyy-mm-dd_*.txt | N25: in_lpm_ln_card_clss_prvn_yyyymmdd.ctl | O25: =K25 -> lpm_as400_ln_card_clss_prvn | P25: Daily | Q25: =IF(P25="Daily","d",IF(P25="Monthly","m",IF(P25="Yearly","y",IF(P25="Weekly","w",IF(P25="S","s",IF(P25="On-Request","o","")))))) -> d | R25: ="ingest_"&K25&"_"&Q25 -> ingest_lpm_as400_ln_card_clss_prvn_d | T25: DATALAKE.IN_LPM_LN_CARD_CLSS_PRVN | U25: N | V25: N | X25: Remark [Feb 12]: - No tailor confirmed by EBAN | Y25: N/A | Z25: Not Started | AA25: Not Started | AB25: Not Started | AC25: Not Started | AE25: Not Started | AH25: Not Started | AJ25: Not Started | AL25: Not Started | AM25: Not Started | AN25: N | AO25: Y | AP25: =IF(OR(AN25="Y", AO25="Y"), "Y", "N") -> Y
A26: 23 | B26: Batch 1 | C26: LPM-AS/400​ | D26: Plan B (EBAN) | E26: =VLOOKUP(C26,'Source Inventory'!D:E,2,FALSE) -> lpm_as400 | F26: Plan B - EBAN IN | G26: Pull EBAN IN File | H26: 75 | I26: ln_cntg_clss_prvn | J26: ="persist_"&E26 -> persist_lpm_as400 | K26: =E26&"_"&I26 -> lpm_as400_ln_cntg_clss_prvn | L26: v_lpm_as400_ln_cntg_acct_cl_prvsn_prfl | M26: in_lpm_ln_cntg_clss_prvn_yyyy-mm-dd.txt | N26: in_lpm_ln_cntg_clss_prvn_yyyymmdd.ctl | O26: =K26 -> lpm_as400_ln_cntg_clss_prvn | P26: Monthly | Q26: =IF(P26="Daily","d",IF(P26="Monthly","m",IF(P26="Yearly","y",IF(P26="Weekly","w",IF(P26="S","s",IF(P26="On-Request","o","")))))) -> m | R26: ="ingest_"&K26&"_"&Q26 -> ingest_lpm_as400_ln_cntg_clss_prvn_m | T26: DATALAKE.IN_LPM_LN_CNTG_CLSS_PRVN | U26: N | V26: N | X26: Remark [Feb 12]: - No tailor confirmed by EBAN | Y26: N/A | Z26: Not Started | AA26: Not Started | AB26: Not Started | AC26: Not Started | AE26: Not Started | AH26: Not Started | AJ26: Not Started | AL26: Not Started | AM26: Not Started | AN26: N | AO26: Y | AP26: =IF(OR(AN26="Y", AO26="Y"), "Y", "N") -> Y
A27: 24 | B27: Batch 1 | C27: LPM-AS/400​ | D27: Plan B (EBAN) | E27: =VLOOKUP(C27,'Source Inventory'!D:E,2,FALSE) -> lpm_as400 | F27: Plan B - EBAN IN | G27: Pull EBAN IN File | H27: 75 | I27: ar_clss_qly | J27: ="persist_"&E27 -> persist_lpm_as400 | K27: =E27&"_"&I27 -> lpm_as400_ar_clss_qly | L27: v_lpm_as400_acct_cl_dpd_prfl | M27: in_lpm_ar_clss_qly_yyyy-mm-dd.txt | N27: in_lpm_ar_clss_qly_yyyymmdd.ctl | O27: =K27 -> lpm_as400_ar_clss_qly | P27: Daily | Q27: =IF(P27="Daily","d",IF(P27="Monthly","m",IF(P27="Yearly","y",IF(P27="Weekly","w",IF(P27="S","s",IF(P27="On-Request","o","")))))) -> d | R27: ="ingest_"&K27&"_"&Q27 -> ingest_lpm_as400_ar_clss_qly_d | T27: DATALAKE.IN_LPM_AR_CLSS_QLY | U27: N | V27: N | Y27: N/A | Z27: Not Started | AA27: Not Started | AB27: Not Started | AC27: Not Started | AE27: Not Started | AH27: Not Started | AJ27: Not Started | AL27: Not Started | AM27: Not Started | AN27: N | AO27: N | AP27: =IF(OR(AN27="Y", AO27="Y"), "Y", "N") -> N
A28: 25 | B28: Batch 1 | C28: LPM-AS/400​ | D28: Plan B (EBAN) | E28: =VLOOKUP(C28,'Source Inventory'!D:E,2,FALSE) -> lpm_as400 | F28: Plan B - EBAN IN | G28: Pull EBAN IN File | H28: 75 | I28: ln_cntg_clss_prvn_bfr_wrtof | J28: ="persist_"&E28 -> persist_lpm_as400 | K28: =E28&"_"&I28 -> lpm_as400_ln_cntg_clss_prvn_bfr_wrtof | L28: v_lpm_as400_ln_cntg_acct_bfr_wrtoff_prfl | M28: in_lpm_ln_cntg_clss_prvn_bfr_wrtof_yyyy-mm-dd.txt | N28: in_lpm_ln_cntg_clss_prvn_bfr_wrtof_yyyymmdd.ctl | O28: =K28 -> lpm_as400_ln_cntg_clss_prvn_bfr_wrtof | P28: Monthly | Q28: =IF(P28="Daily","d",IF(P28="Monthly","m",IF(P28="Yearly","y",IF(P28="Weekly","w",IF(P28="S","s",IF(P28="On-Request","o","")))))) -> m | R28: ="ingest_"&K28&"_"&Q28 -> ingest_lpm_as400_ln_cntg_clss_prvn_bfr_wrtof_m | T28: DATALAKE.IN_LPM_LN_CNTG_CLSS_PRVN_BFR_WRTOF | U28: N | V28: N | X28: Remark [Feb 12]: - No tailor confirmed by EBAN | Y28: N/A | Z28: Not Started | AA28: Not Started | AB28: Not Started | AC28: Not Started | AE28: Not Started | AH28: Not Started | AJ28: Not Started | AL28: Not Started | AM28: Not Started | AN28: N | AO28: Y | AP28: =IF(OR(AN28="Y", AO28="Y"), "Y", "N") -> Y
A29: 26 | B29: Batch 1 | C29: LPM-AS/400​ | D29: Plan B (EBAN) | E29: =VLOOKUP(C29,'Source Inventory'!D:E,2,FALSE) -> lpm_as400 | F29: Plan B - EBAN IN | G29: Pull EBAN IN File | H29: 75 | I29: lmt_inf_bfr_wrtof | J29: ="persist_"&E29 -> persist_lpm_as400 | K29: =E29&"_"&I29 -> lpm_as400_lmt_inf_bfr_wrtof | L29: v_lpm_as400_sub_lmt_info_bfr_wrtoff_prfl | M29: in_lpm_lmt_inf_bfr_wrtof_yyyy-mm-dd.txt | N29: in_lpm_lmt_inf_bfr_wrtof_yyyymmdd.ctl | O29: =K29 -> lpm_as400_lmt_inf_bfr_wrtof | P29: Daily | Q29: =IF(P29="Daily","d",IF(P29="Monthly","m",IF(P29="Yearly","y",IF(P29="Weekly","w",IF(P29="S","s",IF(P29="On-Request","o","")))))) -> d | R29: ="ingest_"&K29&"_"&Q29 -> ingest_lpm_as400_lmt_inf_bfr_wrtof_d | T29: DATALAKE.IN_LPM_LMT_INF_BFR_WRTOF | U29: N | V29: N | Y29: N/A | Z29: Not Started | AA29: Not Started | AB29: Not Started | AC29: Not Started | AE29: Not Started | AH29: Not Started | AJ29: Not Started | AL29: Not Started | AM29: Not Started | AN29: N | AO29: N | AP29: =IF(OR(AN29="Y", AO29="Y"), "Y", "N") -> N
A30: 27 | B30: Batch 1 | C30: CIS | D30: Plan A | E30: =VLOOKUP(C30,'Source Inventory'!D:E,2,FALSE) -> cis | F30: Plan A | G30: Source File (Push) | H30: 176 | I30: ipxar | J30: ="persist_"&E30 -> persist_cis | K30: =E30&"_"&I30 -> cis_ipxar | L30: v_cis_cst_acct_rel_prfl | M30: cis_ipxar_YYYYMMDD.txt | N30: =E30&"_"&I30&"_YYYYMMDD.ctl" -> cis_ipxar_YYYYMMDD.ctl | O30: =K30 -> cis_ipxar | P30: Daily | Q30: =IF(P30="Daily","d",IF(P30="Monthly","m",IF(P30="Yearly","y",IF(P30="Weekly","w",IF(P30="S","s",IF(P30="On-Request","o","")))))) -> d | R30: ="ingest_"&K30&"_"&Q30 -> ingest_cis_ipxar_d | S30: account number | T30: CIS_IPXAR_YYYYMMDD.txt | U30: N | V30: N | Y30: N/A | Z30: In-Progress | AA30: In-Progress | AB30: Completed | AC30: Passed | AE30: Completed | AG30: 2024-03-14 | AH30: Passed | AJ30: Passed | AL30: Completed | AM30: Completed | AN30: N | AO30: N | AP30: =IF(OR(AN30="Y", AO30="Y"), "Y", "N") -> N
A31: 28 | B31: Batch 1 | C31: CIS | D31: Plan A | E31: =VLOOKUP(C31,'Source Inventory'!D:E,2,FALSE) -> cis | F31: Plan A | G31: Source File (Push) | H31: 176 | I31: ip | J31: ="persist_"&E31 -> persist_cis | K31: =E31&"_"&I31 -> cis_ip | L31: v_cis_cst_prfl | M31: cis_ip_YYYYMMDD.txt | N31: =E31&"_"&I31&"_YYYYMMDD.ctl" -> cis_ip_YYYYMMDD.ctl | O31: =K31 -> cis_ip | P31: Daily | Q31: =IF(P31="Daily","d",IF(P31="Monthly","m",IF(P31="Yearly","y",IF(P31="Weekly","w",IF(P31="S","s",IF(P31="On-Request","o","")))))) -> d | R31: ="ingest_"&K31&"_"&Q31 -> ingest_cis_ip_d | T31: CIS_IP_YYYYMMDD.txt | U31: N | V31: N | Y31: N/A | Z31: In-Progress | AA31: In-Progress | AB31: Completed | AC31: Passed | AE31: Failed | AF31: Mandatory null | AG31: 2024-03-14 | AH31: Passed | AJ31: Passed | AK31: - Ingest error (delimiter) - mandatory null | AL31: Completed | AM31: Completed | AN31: N | AO31: N | AP31: =IF(OR(AN31="Y", AO31="Y"), "Y", "N") -> N
A32: 29 | B32: Batch 1 | C32: CIS | D32: Plan A | E32: =VLOOKUP(C32,'Source Inventory'!D:E,2,FALSE) -> cis | F32: Plan A | G32: Source File (Push) | H32: 176 | I32: ar | J32: ="persist_"&E32 -> persist_cis | K32: =E32&"_"&I32 -> cis_ar | L32: v_cis_cst_acct_ownr_prfl | M32: cis_ar_YYYYMMDD.txt | N32: =E32&"_"&I32&"_YYYYMMDD.ctl" -> cis_ar_YYYYMMDD.ctl | O32: =K32 -> cis_ar | P32: Daily | Q32: =IF(P32="Daily","d",IF(P32="Monthly","m",IF(P32="Yearly","y",IF(P32="Weekly","w",IF(P32="S","s",IF(P32="On-Request","o","")))))) -> d | R32: ="ingest_"&K32&"_"&Q32 -> ingest_cis_ar_d | T32: CIS_AR_YYYYMMDD.txt | U32: N | V32: N | Y32: N/A | Z32: In-Progress | AA32: In-Progress | AB32: Completed | AC32: Passed | AD32: 26GB (17 columns) | AE32: Failed | AF32: TS11: sum numeric mismatch | AG32: 2024-03-14 | AH32: Passed | AJ32: Passed | AK32: (FW) mandatory null To remove ar_src_stm_no_3 from mandatory (ar_src_stm_no_1 and ar_src_stm_no_2 still null) | AL32: Completed | AM32: Completed | AN32: N | AO32: N | AP32: =IF(OR(AN32="Y", AO32="Y"), "Y", "N") -> N
A33: 30 | B33: Batch 1 | C33: CSM | D33: Plan A | E33: =VLOOKUP(C33,'Source Inventory'!D:E,2,FALSE) -> csm | F33: Plan A | G33: Source File (Push) | H33: 780 | I33: action | J33: ="persist_"&E33 -> persist_csm | K33: =E33&"_"&I33 -> csm_action | L33: v_csm_actn_cl | M33: csm_action_YYYYMMDD.txt | N33: =E33&"_"&I33&"_YYYYMMDD.ctl" -> csm_action_YYYYMMDD.ctl | O33: =K33 -> csm_action | P33: Daily | Q33: =IF(P33="Daily","d",IF(P33="Monthly","m",IF(P33="Yearly","y",IF(P33="Weekly","w",IF(P33="S","s",IF(P33="On-Request","o","")))))) -> d | R33: ="ingest_"&K33&"_"&Q33 -> ingest_csm_action_d | T33: CSM_ACTION_YYYYMMDD.TXT | U33: N | V33: N | Y33: N/A | Z33: In-Progress | AA33: In-Progress | AB33: Completed | AC33: Passed | AE33: Completed | AH33: Passed | AJ33: Passed | AL33: Completed | AM33: Completed | AN33: N | AO33: N | AP33: =IF(OR(AN33="Y", AO33="Y"), "Y", "N") -> N
A34: 31 | B34: Batch 1 | C34: CSM | D34: Plan A | E34: =VLOOKUP(C34,'Source Inventory'!D:E,2,FALSE) -> csm | F34: Plan A | G34: Source File (Push) | H34: 780 | I34: channel | J34: ="persist_"&E34 -> persist_csm | K34: =E34&"_"&I34 -> csm_channel | L34: v_csm_chnl_cl | M34: csm_channel_YYYYMMDD.txt | N34: =E34&"_"&I34&"_YYYYMMDD.ctl" -> csm_channel_YYYYMMDD.ctl | O34: =K34 -> csm_channel | P34: Daily | Q34: =IF(P34="Daily","d",IF(P34="Monthly","m",IF(P34="Yearly","y",IF(P34="Weekly","w",IF(P34="S","s",IF(P34="On-Request","o","")))))) -> d | R34: ="ingest_"&K34&"_"&Q34 -> ingest_csm_channel_d | T34: CSM_CHANNEL_YYYYMMDD.TXT | U34: N | V34: N | Y34: N/A | Z34: In-Progress | AA34: In-Progress | AB34: Completed | AC34: Passed | AE34: Completed | AH34: Passed | AJ34: Passed | AL34: Completed | AM34: Completed | AN34: N | AO34: N | AP34: =IF(OR(AN34="Y", AO34="Y"), "Y", "N") -> N
A35: 32 | B35: Batch 1 | C35: CSM | D35: Plan A | E35: =VLOOKUP(C35,'Source Inventory'!D:E,2,FALSE) -> csm | F35: Plan A | G35: Source File (Push) | H35: 780 | I35: company | J35: ="persist_"&E35 -> persist_csm | K35: =E35&"_"&I35 -> csm_company | L35: v_csm_co_cl | M35: csm_company_YYYYMMDD.txt | N35: =E35&"_"&I35&"_YYYYMMDD.ctl" -> csm_company_YYYYMMDD.ctl | O35: =K35 -> csm_company | P35: Daily | Q35: =IF(P35="Daily","d",IF(P35="Monthly","m",IF(P35="Yearly","y",IF(P35="Weekly","w",IF(P35="S","s",IF(P35="On-Request","o","")))))) -> d | R35: ="ingest_"&K35&"_"&Q35 -> ingest_csm_company_d | T35: CSM_COMPANY_YYYYMMDD.TXT | U35: N | V35: N | Y35: N/A | Z35: In-Progress | AA35: In-Progress | AB35: Completed | AC35: Passed | AE35: Completed | AH35: Passed | AJ35: Passed | AL35: Completed | AM35: Completed | AN35: N | AO35: N | AP35: =IF(OR(AN35="Y", AO35="Y"), "Y", "N") -> N
A36: 33 | B36: Batch 1 | C36: CSM | D36: Plan A | E36: =VLOOKUP(C36,'Source Inventory'!D:E,2,FALSE) -> csm | F36: Plan A | G36: Source File (Push) | H36: 780 | I36: custxformxconsent | J36: ="persist_"&E36 -> persist_csm | K36: =E36&"_"&I36 -> csm_custxformxconsent | L36: v_csm_cst_form_cnsnt_prfl | M36: csm_custxformxconsent_YYYYMMDD.txt | N36: =E36&"_"&I36&"_YYYYMMDD.ctl" -> csm_custxformxconsent_YYYYMMDD.ctl | O36: =K36 -> csm_custxformxconsent | P36: Daily | Q36: =IF(P36="Daily","d",IF(P36="Monthly","m",IF(P36="Yearly","y",IF(P36="Weekly","w",IF(P36="S","s",IF(P36="On-Request","o","")))))) -> d | R36: ="ingest_"&K36&"_"&Q36 -> ingest_csm_custxformxconsent_d | T36: CSM_CUSTXFORMXCONSENT_YYYYMMDD.TXT | U36: N | V36: N | Y36: N/A | Z36: In-Progress | AA36: In-Progress | AB36: Completed | AC36: Passed | AD36: Data file 4 GB (cannot manual upload to Volumns) | AE36: Completed | AH36: Passed | AJ36: Passed | AL36: Completed | AM36: Completed | AN36: N | AO36: N | AP36: =IF(OR(AN36="Y", AO36="Y"), "Y", "N") -> N
